Workbook
Name Scenario: Cover!$C$6
Name Students_S: Assumptions!$G$6
Name Students_M: Assumptions!$G$7
Name Students_L: Assumptions!$G$8
Name Fee_S: Assumptions!$G$9
Name Fee_M: Assumptions!$G$10
Name Fee_L: Assumptions!$G$11
Name OnboardMult_S: Assumptions!$G$12
Name OnboardMult_M: Assumptions!$G$13
Name OnboardMult_L: Assumptions!$G$14
Name DropoutRate: Assumptions!$G$16
Name UpfrontShare: Assumptions!$G$17
Name NInstalments: Assumptions!$G$18
Name RefundEnforced: Assumptions!$G$19
Name CourseMonths: Assumptions!$G$20
Name BlindMonths: Assumptions!$G$21
Name Preventable: Assumptions!$G$22
Name MinorShare: Assumptions!$G$23
Name Recall_Minor: Assumptions!$G$24
Name Recall_Adult: Assumptions!$G$25
Name Precision: Assumptions!$G$26
Name ActionRate: Assumptions!$G$27
Name InterventionSuccess: Assumptions!$G$28
Name AdmissionUplift: Assumptions!$G$29
Name MarginExtraAdmission: Assumptions!$G$30
Name StaffHoursSaved: Assumptions!$G$31
Name StaffHourCost: Assumptions!$G$32
Name InterventionMinutes: Assumptions!$G$33
Name MentorHourCost: Assumptions!$G$34
Name GST: Assumptions!$G$35
Name ITCShare: Assumptions!$G$36
Name ListPrice: Assumptions!$G$38
Name CompetitorAnchor: Assumptions!$G$39
Name CompetitorAnchorHigh: Assumptions!$G$40
Name MinFee: Assumptions!$G$41
Name NegotiationDisc: Assumptions!$G$42
Name PrepayUptake: Assumptions!$G$43
Name PrepayDisc: Assumptions!$G$44
Name BadDebt: Assumptions!$G$45
Name GatewayFee: Assumptions!$G$46
Name ReportsPerStudentMonth: Assumptions!$G$48
Name TokensInPerReport: Assumptions!$G$49
Name TokensOutPerReport: Assumptions!$G$50
Name LLMPriceIn: Assumptions!$G$51
Name LLMPriceOut: Assumptions!$G$52
Name WAMsgsPerStudentMonth: Assumptions!$G$53
Name WAPricePerMsg: Assumptions!$G$54
Name ComputePerStudentMonth: Assumptions!$G$55
Name ConsentCostPerStudentYear: Assumptions!$G$56
Name ServerCostMonth: Assumptions!$G$57
Name BSPFeeMonth: Assumptions!$G$58
Name InstPerStack: Assumptions!$G$59
Name CompliancePerInstMonth: Assumptions!$G$60
Name CSM_CTC: Assumptions!$G$62
Name InstPerCSM: Assumptions!$G$63
Name RepCTC: Assumptions!$G$64
Name RepTravel: Assumptions!$G$65
Name PilotsPerRepMonth: Assumptions!$G$66
Name PilotConv: Assumptions!$G$67
Name PilotMonths: Assumptions!$G$68

Sheet Cover
A1: The Data Moat — Financial Model
A2: Institute Intelligence Platform · Nextute × Finance Club IIT Patna, Case B · R1-v1.0 · 2026-10-20
B6: SCENARIO (1 = Bear, 2 = Base, 3 = Bull) → | C6: 2 | D6: =CHOOSE(Scenario,"Bear","Base","Bull")
B7: Model checks | C7: =IF(ErrorCount=0,"ALL CHECKS PASS","ERRORS: "&ErrorCount) | D7: ="Warnings to discuss: "&WarningCount
B9: Headline (Mid institute, 400 students, live scenario) | C9: Our model | D9: Guide (naive)
B10: Effective dropout reduction | C10: =Institute_ROI!E37 | D10: =G_Prevent
B11: Dropouts prevented per year | C11: =Institute_ROI!E38 | D11: =Institute_ROI!$E$65
B12: Institute ROI (all benefits) | C12: =Institute_ROI!E53 | D12: =Institute_ROI!$E$68
B13: Institute ROI (fees only) | C13: =Institute_ROI!E54 | D13: =Institute_ROI!$E$68
B14: Break-even: students to save per year | C14: =Institute_ROI!E55 | D14: =Institute_ROI!$E$69
B15: Extra admissions needed to break even (after fees + staff time) | C15: =Institute_ROI!E58 | D15: n/a
B16: Platform cost as % of a student's fee | C16: =Institute_ROI!E60 | D16: =G_Price*G_Months/Fee_M
B17: Avg monthly revenue per institute | C17: =Unit_Econ!E30 | D17: =Unit_Econ!$I$5
B18: Contribution margin | C18: =Unit_Econ!E35 | D18: =Unit_Econ!$I$6/Unit_Econ!$I$5
B19: Fully loaded acquisition cost | C19: =Unit_Econ!E41 | D19: =Unit_Econ!$I$7
B20: LTV | C20: =Unit_Econ!E48 | D20: =Unit_Econ!$I$9
B21: LTV ÷ acquisition cost | C21: =Unit_Econ!E49 | D21: =Unit_Econ!$I$10
B22: Payback (months) | C22: =Unit_Econ!E50 | D22: =Unit_Econ!$I$8
B23: Institutes needed to cover fixed team cost | C23: =Unit_Econ!I16 | D23: n/a
B25: Colour code
B26: Blue text | C26: Input — edit only these (Assumptions D:F, Seasonality, grid points, Scenario)
B27: Black text | C27: Formula
B28: Green text | C28: Link from another sheet
B29: Yellow fill | C29: Key lever / live value
B30: Green fill | C30: Key output
B32: How to use
B33: 1 | C33: Pick a scenario in C6. Everything recalculates; Scenarios and Sensitivity always show all three.
B34: 2 | C34: Change an input on Assumptions (Bear/Base/Bull) — never type over a formula.
B35: 3 | C35: Cover C7 must say ALL CHECKS PASS before you quote any number.
B36: 4 | C36: To rebuild from the CSVs: python build_model.py (Financial_Model folder).
B38: Evidence labels | C38: Researched/Public = sourced (see Sources) · Guide = case brief · Assumption = unverified · Structural = modelling convention
B39: Scope | C39: Round 1: Pricing, COGS, Institute ROI, Unit economics, Scenarios, Sensitivity. Round 2 adds cohorts, hiring plan, 3-year P&L, cash and funding need.

Sheet Assumptions
A1: Assumptions — every input in the model lives here
A2: Blue = input you may edit (Bear / Base / Bull). Live = CHOOSE(Scenario, Bear, Base, Bull). Bear = worst case for OUR business. Type: Researched/Public = sourced · Guide = case brief · Assumption = unverified · Structural = modelling convention.
A4: Name (named range → Live) | B4: Input | C4: Unit | D4: Bear | E4: Base | F4: Bull | G4: LIVE | H4: Type | I4: Confidence | J4: Source | K4: Note | L4: Pct out of [0,1] | M4: Live outside Bear–Bull
A5: Segments
A6: Students_S | B6: Students per institute - Small | C6: students | D6: 180 | E6: 180 | F6: 180 | G6: =CHOOSE(Scenario,D6,E6,F6) | H6: Assumption | I6: M | J6: Case brief range 150-2000; our cut <250 | K6: Segment midpoint | L6: 0 | M6: =IF(AND(G6>=MIN(D6,F6),G6<=MAX(D6,F6)),0,1)
A7: Students_M | B7: Students per institute - Mid | C7: students | D7: 400 | E7: 400 | F7: 400 | G7: =CHOOSE(Scenario,D7,E7,F7) | H7: Guide | I7: M | J7: Case brief baseline 400 | L7: 0 | M7: =IF(AND(G7>=MIN(D7,F7),G7<=MAX(D7,F7)),0,1)
A8: Students_L | B8: Students per institute - Large | C8: students | D8: 1200 | E8: 1200 | F8: 1200 | G8: =CHOOSE(Scenario,D8,E8,F8) | H8: Assumption | I8: M | J8: Case brief range 150-2000; our cut >800 | L8: 0 | M8: =IF(AND(G8>=MIN(D8,F8),G8<=MAX(D8,F8)),0,1)
A9: Fee_S | B9: Annual fee per student - Small | C9: Rs/yr | D9: 50000 | E9: 65000 | F9: 80000 | G9: =CHOOSE(Scenario,D9,E9,F9) | H9: Researched | I9: L | J9: R2: Vedantu Gaya 1-yr Rs50-56k; Rupantri Muzaffarpur Rs55-60k; GOAL Patna Rs51-99k (research/R2_R3) | K9: Size-to-fee mapping is our assumption | L9: 0 | M9: =IF(AND(G9>=MIN(D9,F9),G9<=MAX(D9,F9)),0,1)
A10: Fee_M | B10: Annual fee per student - Mid | C10: Rs/yr | D10: 70000 | E10: 95000 | F10: 120000 | G10: =CHOOSE(Scenario,D10,E10,F10) | H10: Researched | I10: L | J10: R2: GOAL Patna 1-yr Rs1.2L; Vedantu Patna Rs95k; Pathshala Lucknow ~Rs82.5k; Vedantu Indore Rs67k | K10: Case brief used Rs60k | L10: 0 | M10: =IF(AND(G10>=MIN(D10,F10),G10<=MAX(D10,F10)),0,1)
A11: Fee_L | B11: Annual fee per student - Large | C11: Rs/yr | D11: 100000 | E11: 125000 | F11: 150000 | G11: =CHOOSE(Scenario,D11,E11,F11) | H11: Researched | I11: M | J11: R2: Udaan Patna Rs1.15-1.25L/yr (own site 2025-27); chains Rs1.1-1.4L (Motion/Allen/Vedantu) | L11: 0 | M11: =IF(AND(G11>=MIN(D11,F11),G11<=MAX(D11,F11)),0,1)
A12: OnboardMult_S | B12: Onboarding cost multiplier - Small | C12: x | D12: 0.8 | E12: 0.8 | F12: 0.8 | G12: =CHOOSE(Scenario,D12,E12,F12) | H12: Assumption | I12: L | J12: Fewer batches to migrate | L12: 0 | M12: =IF(AND(G12>=MIN(D12,F12),G12<=MAX(D12,F12)),0,1)
A13: OnboardMult_M | B13: Onboarding cost multiplier - Mid | C13: x | D13: 1 | E13: 1 | F13: 1 | G13: =CHOOSE(Scenario,D13,E13,F13) | H13: Structural | I13: H | J13: Reference segment | L13: 0 | M13: =IF(AND(G13>=MIN(D13,F13),G13<=MAX(D13,F13)),0,1)
A14: OnboardMult_L | B14: Onboarding cost multiplier - Large | C14: x | D14: 1.6 | E14: 1.6 | F14: 1.6 | G14: =CHOOSE(Scenario,D14,E14,F14) | H14: Assumption | I14: L | J14: More batches and staff to train | L14: 0 | M14: =IF(AND(G14>=MIN(D14,F14),G14<=MAX(D14,F14)),0,1)
A15: Institute
A16: DropoutRate | B16: Mid-session dropout/default rate | C16: % of students/yr | D16: 0.06 | E16: 0.1 | F16: 0.18 | G16: =CHOOSE(Scenario,D16,E16,F16) | H16: Researched | I16: L | J16: R3: Coaching Federation of India 'at least 10 per cent of students in every batch' (ThePrint 31-Jul-2025); YourStory May-2026 ~20% offline (unattributed); analogue UDISE+ Cl.9-10 11.5% | K16: Higher = more value to protect (Bull); case brief 8-15% | L16: =IF(OR(G16<0,G16>1),1,0) | M16: =IF(AND(G16>=MIN(D16,F16),G16<=MAX(D16,F16)),0,1)
A17: UpfrontShare | B17: Share of students paying full fee upfront | C17: % | D17: 0.4 | E17: 0.25 | F17: 0.15 | G17: =CHOOSE(Scenario,D17,E17,F17) | H17: Assumption | I17: L | J17: R2: not found. Instalments are the norm (Allen 2; PW 3; Aakash several; Rajasthan Act s.6(2)(d) >=4 option) | K17: TECH_PLAN's 35% had no source | L17: =IF(OR(G17<0,G17>1),1,0) | M17: =IF(AND(G17>=MIN(D17,F17),G17<=MAX(D17,F17)),0,1)
A18: NInstalments | B18: Instalments per year for non-upfront payers | C18: count | D18: 2 | E18: 3 | F18: 4 | G18: =CHOOSE(Scenario,D18,E18,F18) | H18: Researched | I18: M | J18: R2: Allen 2 (2nd within 45 days); PW 3; Rajasthan Act 16/2025 s.6(2)(d) min. 4 equal | K18: Fewer instalments = cash collected early = less at risk | L18: 0 | M18: =IF(AND(G18>=MIN(D18,F18),G18<=MAX(D18,F18)),0,1)
A19: RefundEnforced | B19: Share of upfront leavers actually refunded pro-rata | C19: % | D19: 0.1 | E19: 0.3 | F19: 0.6 | G19: =CHOOSE(Scenario,D19,E19,F19) | H19: Assumption | I19: L | J19: R2: MoE Guidelines 2024 cl.8(iv) and Rajasthan s.13(4) require pro-rata refund within 10 days; MoE is advisory and Allen/Aakash/PW practice is cut-off or no refund | K19: Refunded upfront leavers = fee at risk | L19: =IF(OR(G19<0,G19>1),1,0) | M19: =IF(AND(G19>=MIN(D19,F19),G19<=MAX(D19,F19)),0,1)
A20: CourseMonths | B20: Course length | C20: months | D20: 10 | E20: 10 | F20: 10 | G20: =CHOOSE(Scenario,D20,E20,F20) | H20: Guide | I20: H | J20: Case brief ~10 months | L20: 0 | M20: =IF(AND(G20>=MIN(D20,F20),G20<=MAX(D20,F20)),0,1)
A21: BlindMonths | B21: Months before the model can flag (no test data yet) | C21: months | D21: 2 | E21: 1 | F21: 0 | G21: =CHOOSE(Scenario,D21,E21,F21) | H21: Assumption | I21: M | J21: Model needs >=1-2 tests; R2: refund windows weeks 1-4 mean early exits are fast | K21: Dropouts in these months cannot be caught | L21: 0 | M21: =IF(AND(G21>=MIN(D21,F21),G21<=MAX(D21,F21)),0,1)
A22: Preventable | B22: Share of dropouts that are preventable (check only) | C22: % | D22: 0.3 | E22: 0.45 | F22: 0.6 | G22: =CHOOSE(Scenario,D22,E22,F22) | H22: Assumption | I22: L | J22: R3: reasons listed without shares (interest; family; health; dissatisfaction - ThePrint/CFI) | K22: Upper bound for the RCT effect | L22: =IF(OR(G22<0,G22>1),1,0) | M22: =IF(AND(G22>=MIN(D22,F22),G22<=MAX(D22,F22)),0,1)
A23: MinorShare | B23: Share of students under 18 | C23: % | D23: 0.85 | E23: 0.75 | F23: 0.6 | G23: =CHOOSE(Scenario,D23,E23,F23) | H23: Assumption | I23: M | J23: JEE/NEET Class 11-12 are 16-17; droppers 18+ | K23: DPDP s.9(3): minors get academic-support model + rules only | L23: =IF(OR(G23<0,G23>1),1,0) | M23: =IF(AND(G23>=MIN(D23,F23),G23<=MAX(D23,F23)),0,1)
A24: Recall_Minor | B24: Model recall on minors (academic-support + rules) | C24: % | D24: 0.4 | E24: 0.55 | F24: 0.7 | G24: =CHOOSE(Scenario,D24,E24,F24) | H24: Assumption | I24: L | J24: TECH_PLAN NB04 rules-only vs ML; replace with metrics.json | K24: At mentor-capacity threshold | L24: =IF(OR(G24<0,G24>1),1,0) | M24: =IF(AND(G24>=MIN(D24,F24),G24<=MAX(D24,F24)),0,1)
A25: Recall_Adult | B25: Model recall on 18+ (full ML) | C25: % | D25: 0.5 | E25: 0.65 | F25: 0.8 | G25: =CHOOSE(Scenario,D25,E25,F25) | H25: Public | I25: M | J25: OULAD withdrawal AUC 0.727-0.794 (TECH_PLAN s.24); replace with metrics.json | K25: At mentor-capacity threshold | L25: =IF(OR(G25<0,G25>1),1,0) | M25: =IF(AND(G25>=MIN(D25,F25),G25<=MAX(D25,F25)),0,1)
A26: Precision | B26: Precision of at-risk flag | C26: % | D26: 0.25 | E26: 0.35 | F26: 0.5 | G26: =CHOOSE(Scenario,D26,E26,F26) | H26: Assumption | I26: L | J26: Replace with metrics.json | K26: Drives wasted mentor time | L26: =IF(OR(G26<0,G26>1),1,0) | M26: =IF(AND(G26>=MIN(D26,F26),G26<=MAX(D26,F26)),0,1)
A27: ActionRate | B27: Share of flags the institute assigns to outreach | C27: % | D27: 0.7 | E27: 0.9 | F27: 1 | G27: =CHOOSE(Scenario,D27,E27,F27) | H27: Assumption | I27: L | J27: Mentor capacity; the RCT effect below is already intention-to-treat | K27: Primary research needed | L27: =IF(OR(G27<0,G27>1),1,0) | M27: =IF(AND(G27>=MIN(D27,F27),G27<=MAX(D27,F27)),0,1)
A28: InterventionSuccess | B28: Dropout reduction among flagged students given outreach (RCT) | C28: relative % | D28: 0.05 | E28: 0.15 | F28: 0.3 | G28: =CHOOSE(Scenario,D28,E28,F28) | H28: Researched | I28: M | J28: R4: mean 15.8% / median 12.5% over 8 RCTs - OU outreach RCT 2020 -19%/-35%; Room to Read India -30%; Bergman parent texts; MAAPS/Samata/Oreopoulos nulls (research/R4_R5) | K28: Borrowed from other settings - not our measured effect | L28: =IF(OR(G28<0,G28>1),1,0) | M28: =IF(AND(G28>=MIN(D28,F28),G28<=MAX(D28,F28)),0,1)
A29: AdmissionUplift | B29: Admissions uplift next session from results/parent trust | C29: % of students | D29: 0 | E29: 0.01 | F29: 0.03 | G29: =CHOOSE(Scenario,D29,E29,F29) | H29: Assumption | I29: L | J29: No evidence - Bear = 0 | L29: =IF(OR(G29<0,G29>1),1,0) | M29: =IF(AND(G29>=MIN(D29,F29),G29<=MAX(D29,F29)),0,1)
A30: MarginExtraAdmission | B30: Institute margin on one extra admission | C30: % | D30: 0.4 | E30: 0.6 | F30: 0.8 | G30: =CHOOSE(Scenario,D30,E30,F30) | H30: Assumption | I30: L | J30: Marginal seat in an existing batch | L30: =IF(OR(G30<0,G30>1),1,0) | M30: =IF(AND(G30>=MIN(D30,F30),G30<=MAX(D30,F30)),0,1)
A31: StaffHoursSaved | B31: Staff hours saved per month | C31: hours/month | D31: 10 | E31: 25 | F31: 50 | G31: =CHOOSE(Scenario,D31,E31,F31) | H31: Guide | I31: L | J31: Case brief value lever; primary research needed | L31: 0 | M31: =IF(AND(G31>=MIN(D31,F31),G31<=MAX(D31,F31)),0,1)
A32: StaffHourCost | B32: Cost of one admin staff hour | C32: Rs/hour | D32: 75 | E32: 100 | F32: 150 | G32: =CHOOSE(Scenario,D32,E32,F32) | H32: Researched | I32: M | J32: R5: Tier-2 executive pay Rs18-25k/month (Payscale/Indeed Patna) / ~200 h | L32: 0 | M32: =IF(AND(G32>=MIN(D32,F32),G32<=MAX(D32,F32)),0,1)
A33: InterventionMinutes | B33: Mentor minutes per intervention | C33: minutes | D33: 45 | E33: 30 | F33: 20 | G33: =CHOOSE(Scenario,D33,E33,F33) | H33: Assumption | I33: L | J33: Call + meeting with parent | L33: 0 | M33: =IF(AND(G33>=MIN(D33,F33),G33<=MAX(D33,F33)),0,1)
A34: MentorHourCost | B34: Cost of one mentor hour | C34: Rs/hour | D34: 250 | E34: 200 | F34: 150 | G34: =CHOOSE(Scenario,D34,E34,F34) | H34: Assumption | I34: M | J34: Teacher pay ~Rs30-50k/month / ~200 h | L34: 0 | M34: =IF(AND(G34>=MIN(D34,F34),G34<=MAX(D34,F34)),0,1)
A35: GST | B35: GST on SaaS | C35: % | D35: 0.18 | E35: 0.18 | F35: 0.18 | G35: =CHOOSE(Scenario,D35,E35,F35) | H35: Researched | I35: M | J35: R6: 18% (heading 9983 residual entry; Notif. 11/2017-CTR as amended by 15/2025-CTR) | K35: SAC code 9983 vs 9984 unconfirmed - ask a CA | L35: =IF(OR(G35<0,G35>1),1,0) | M35: =IF(AND(G35>=MIN(D35,F35),G35<=MAX(D35,F35)),0,1)
A36: ITCShare | B36: Share of institutes that reclaim our GST as input credit | C36: % | D36: 0.3 | E36: 0.6 | F36: 0.9 | G36: =CHOOSE(Scenario,D36,E36,F36) | H36: Assumption | I36: L | J36: R6: coaching is taxable at 18%; registration mandatory above Rs20L turnover; CGST s.16(1) gives ITC to registered persons. A 180-student institute turns over ~Rs1 Cr, so legally registered - but cash/informal practice in Tier-3 | K36: Was 'all unregistered' in the naive view | L36: =IF(OR(G36<0,G36>1),1,0) | M36: =IF(AND(G36>=MIN(D36,F36),G36<=MAX(D36,F36)),0,1)
A37: Pricing
A38: ListPrice | B38: List price per active student per month | C38: Rs/student/month | D38: 20 | E38: 30 | F38: 40 | G38: =CHOOSE(Scenario,D38,E38,F38) | H38: Assumption | I38: L | J38: R1: ERP/LMS anchors Rs4-21/student/month at 400 students (Classplus/Fedena/Graphy); no competitor bundles OMR + topic analytics + Hindi WhatsApp | K38: Decision lever - test in interviews (Van Westendorp) | L38: 0 | M38: =IF(AND(G38>=MIN(D38,F38),G38<=MAX(D38,F38)),0,1)
A39: CompetitorAnchor | B39: What institutes already pay for an ERP/LMS | C39: Rs/student/month | D39: 4.17 | E39: 10.42 | F39: 20.83 | G39: =CHOOSE(Scenario,D39,E39,F39) | H39: Researched | I39: M | J39: R1: Classplus Starter Rs19999/yr (Capterra); Fedena Standard / Graphy Grow Rs50k/yr; Fedena Ultimate Rs1L/yr - all at 400 students | K39: Reference only - not used in revenue | L39: 0 | M39: =IF(AND(G39>=MIN(D39,F39),G39<=MAX(D39,F39)),0,1)
A40: CompetitorAnchorHigh | B40: Highest priced ERP/LMS anchor found | C40: Rs/student/month | D40: 20.83 | E40: 20.83 | F40: 20.83 | G40: =CHOOSE(Scenario,D40,E40,F40) | H40: Researched | I40: M | J40: R1: Fedena Ultimate / Graphy Rise Rs1L/yr at 400 students | K40: Used in a warning check | L40: 0 | M40: =IF(AND(G40>=MIN(D40,F40),G40<=MAX(D40,F40)),0,1)
A41: MinFee | B41: Minimum monthly fee per institute | C41: Rs/month | D41: 2000 | E41: 3000 | F41: 4000 | G41: =CHOOSE(Scenario,D41,E41,F41) | H41: Assumption | I41: L | J41: FINANCE_PLAN s.3.2 | L41: 0 | M41: =IF(AND(G41>=MIN(D41,F41),G41<=MAX(D41,F41)),0,1)
A42: NegotiationDisc | B42: Average negotiated discount off list | C42: % | D42: 0.2 | E42: 0.1 | F42: 0.05 | G42: =CHOOSE(Scenario,D42,E42,F42) | H42: Assumption | I42: L | J42: Primary research needed | L42: =IF(OR(G42<0,G42>1),1,0) | M42: =IF(AND(G42>=MIN(D42,F42),G42<=MAX(D42,F42)),0,1)
A43: PrepayUptake | B43: Share of institutes choosing annual prepay | C43: % | D43: 0.2 | E43: 0.4 | F43: 0.6 | G43: =CHOOSE(Scenario,D43,E43,F43) | H43: Assumption | I43: L | J43: Coaching institutes are cash-rich in Apr-Jun (admission season) | K43: Prepaid institutes cannot churn mid-session | L43: =IF(OR(G43<0,G43>1),1,0) | M43: =IF(AND(G43>=MIN(D43,F43),G43<=MAX(D43,F43)),0,1)
A44: PrepayDisc | B44: Annual prepay discount | C44: % | D44: 0.15 | E44: 0.15 | F44: 0.15 | G44: =CHOOSE(Scenario,D44,E44,F44) | H44: Assumption | I44: M | J44: FINANCE_PLAN s.3.2; R2 shows institutes give 4-6% for upfront fees | L44: =IF(OR(G44<0,G44>1),1,0) | M44: =IF(AND(G44>=MIN(D44,F44),G44<=MAX(D44,F44)),0,1)
A45: BadDebt | B45: Bad debt / uncollected billing | C45: % | D45: 0.08 | E45: 0.03 | F45: 0.01 | G45: =CHOOSE(Scenario,D45,E45,F45) | H45: Assumption | I45: M | J45: FINANCE_PLAN s.3.2 | L45: =IF(OR(G45<0,G45>1),1,0) | M45: =IF(AND(G45>=MIN(D45,F45),G45<=MAX(D45,F45)),0,1)
A46: GatewayFee | B46: Payment collection cost (blended) | C46: % of revenue | D46: 0.0236 | E46: 0.012 | F46: 0.004 | G46: =CHOOSE(Scenario,D46,E46,F46) | H46: Researched | I46: M | J46: R6: Razorpay 2% + 18% GST = 2.36%; UPI MDR 0.4% on P2M >Rs2000 from 15-Oct-2026; NEFT ~0 | K46: Base assumes half paid by bank transfer | L46: =IF(OR(G46<0,G46>1),1,0) | M46: =IF(AND(G46>=MIN(D46,F46),G46<=MAX(D46,F46)),0,1)
A47: COGS
A48: ReportsPerStudentMonth | B48: AI parent reports per student per month | C48: reports | D48: 6 | E48: 4 | F48: 4 | G48: =CHOOSE(Scenario,D48,E48,F48) | H48: Assumption | I48: M | J48: TECH_PLAN s.11 weekly report; Bear adds alerts | L48: 0 | M48: =IF(AND(G48>=MIN(D48,F48),G48<=MAX(D48,F48)),0,1)
A49: TokensInPerReport | B49: LLM input tokens per report | C49: tokens | D49: 2500 | E49: 1500 | F49: 1000 | G49: =CHOOSE(Scenario,D49,E49,F49) | H49: Assumption | I49: M | J49: TECH_PLAN GenAI design (numbers_json + template) | L49: 0 | M49: =IF(AND(G49>=MIN(D49,F49),G49<=MAX(D49,F49)),0,1)
A50: TokensOutPerReport | B50: LLM output tokens per report | C50: tokens | D50: 1200 | E50: 1000 | F50: 600 | G50: =CHOOSE(Scenario,D50,E50,F50) | H50: Assumption | I50: M | J50: Bilingual report ~400-600 words | L50: 0 | M50: =IF(AND(G50>=MIN(D50,F50),G50<=MAX(D50,F50)),0,1)
A51: LLMPriceIn | B51: LLM input price (hosted) | C51: Rs per 1M tokens | D51: 142.58 | E51: 23.76 | F51: 9.51 | G51: =CHOOSE(Scenario,D51,E51,F51) | H51: Researched | I51: H | J51: R6: Gemini 3.8 Flash from 1-Jan-2027 / Gemini 3.1 Flash-Lite / Claude Haiku 5.5 at Rs95.05/USD (official pricing pages 20-Oct-2026) | K51: Local Ollama = ~0 (prototype) | L51: 0 | M51: =IF(AND(G51>=MIN(D51,F51),G51<=MAX(D51,F51)),0,1)
A52: LLMPriceOut | B52: LLM output price (hosted) | C52: Rs per 1M tokens | D52: 712.88 | E52: 142.58 | F52: 47.53 | G52: =CHOOSE(Scenario,D52,E52,F52) | H52: Researched | I52: H | J52: R6: same models as input price | L52: 0 | M52: =IF(AND(G52>=MIN(D52,F52),G52<=MAX(D52,F52)),0,1)
A53: WAMsgsPerStudentMonth | B53: WhatsApp utility messages per student per month | C53: messages | D53: 10 | E53: 6 | F53: 4 | G53: =CHOOSE(Scenario,D53,E53,F53) | H53: Assumption | I53: M | J53: Weekly report + alerts + fee reminders | L53: 0 | M53: =IF(AND(G53>=MIN(D53,F53),G53<=MAX(D53,F53)),0,1)
A54: WAPricePerMsg | B54: WhatsApp utility message price (India) | C54: Rs/message | D54: 0.145 | E54: 0.1323 | F54: 0.115 | G54: =CHOOSE(Scenario,D54,E54,F54) | H54: Researched | I54: H | J54: R6: Meta list Rs0.115 (eff. 1-Oct-2026); Gallabox Rs0.1323; AiSensy Rs0.145. Utility replies in window charged again from 1-Oct-2026 | L54: 0 | M54: =IF(AND(G54>=MIN(D54,F54),G54<=MAX(D54,F54)),0,1)
A55: ComputePerStudentMonth | B55: Compute + storage + backups per student | C55: Rs/student/month | D55: 1.5 | E55: 0.8 | F55: 0.4 | G55: =CHOOSE(Scenario,D55,E55,F55) | H55: Assumption | I55: L | J55: TECH_PLAN s.16 cost model (NB09 pending); OMR images auto-deleted after 7 days | L55: 0 | M55: =IF(AND(G55>=MIN(D55,F55),G55<=MAX(D55,F55)),0,1)
A56: ConsentCostPerStudentYear | B56: Consent OTP + verification per student | C56: Rs/student/yr | D56: 3 | E56: 1.5 | F56: 0.5 | G56: =CHOOSE(Scenario,D56,E56,F56) | H56: Assumption | I56: L | J56: TECH_PLAN consent design (OTP) | L56: 0 | M56: =IF(AND(G56>=MIN(D56,F56),G56<=MAX(D56,F56)),0,1)
A57: ServerCostMonth | B57: App server + managed Postgres + backups per stack | C57: Rs/month | D57: 9000 | E57: 4000 | F57: 3000 | G57: =CHOOSE(Scenario,D57,E57,F57) | H57: Researched | I57: M | J57: R6: AWS t3.medium Rs3108 + DO PG 2vCPU Rs5789 / Lightsail-DO Rs2281 + DO PG Rs1440 / t4g Rs1554 + Lightsail DB Rs1426 | K57: Base adds ~Rs300 backups | L57: 0 | M57: =IF(AND(G57>=MIN(D57,F57),G57<=MAX(D57,F57)),0,1)
A58: BSPFeeMonth | B58: WhatsApp BSP platform fee per stack | C58: Rs/month | D58: 3200 | E58: 1500 | F58: 0 | G58: =CHOOSE(Scenario,D58,E58,F58) | H58: Researched | I58: M | J58: R6: AiSensy Pro Rs3200 / Basic Rs1500 / Gupshup self-serve Rs0 + per-msg | L58: 0 | M58: =IF(AND(G58>=MIN(D58,F58),G58<=MAX(D58,F58)),0,1)
A59: InstPerStack | B59: Institutes sharing one server stack | C59: institutes | D59: 10 | E59: 20 | F59: 40 | G59: =CHOOSE(Scenario,D59,E59,F59) | H59: Assumption | I59: L | J59: Depends on load test (NB09) | L59: 0 | M59: =IF(AND(G59>=MIN(D59,F59),G59<=MAX(D59,F59)),0,1)
A60: CompliancePerInstMonth | B60: DPDP compliance cost per institute | C60: Rs/month | D60: 400 | E60: 200 | F60: 100 | G60: =CHOOSE(Scenario,D60,E60,F60) | H60: Assumption | I60: L | J60: Audits / consent management / DPO time | L60: 0 | M60: =IF(AND(G60>=MIN(D60,F60),G60<=MAX(D60,F60)),0,1)
A61: GTM
A62: CSM_CTC | B62: Customer-success / onboarding exec monthly CTC | C62: Rs/month | D62: 45000 | E62: 35000 | F62: 25000 | G62: =CHOOSE(Scenario,D62,E62,F62) | H62: Researched | I62: L | J62: R5: Tier-2 remote CS median Rs33-42k (Frontlines 2026); Payscale Jaipur CSM-manager Rs58k | L62: 0 | M62: =IF(AND(G62>=MIN(D62,F62),G62<=MAX(D62,F62)),0,1)
A63: InstPerCSM | B63: Institutes per CSM | C63: institutes | D63: 40 | E63: 80 | F63: 120 | G63: =CHOOSE(Scenario,D63,E63,F63) | H63: Researched | I63: L | J63: R5: Gainsight SMB 100-250 accounts per CSM - cut for high-touch Tier-2 onboarding | L63: 0 | M63: =IF(AND(G63>=MIN(D63,F63),G63<=MAX(D63,F63)),0,1)
A64: RepCTC | B64: Field sales rep monthly CTC (incl. fuel) | C64: Rs/month | D64: 30000 | E64: 24000 | F64: 19000 | G64: =CHOOSE(Scenario,D64,E64,F64) | H64: Researched | I64: M | J64: R5: Payscale Patna field sales ~Rs20k base; PhonePe postings Rs18-25k + Rs4-4.5k fuel | L64: 0 | M64: =IF(AND(G64>=MIN(D64,F64),G64<=MAX(D64,F64)),0,1)
A65: RepTravel | B65: Rep intercity travel + demo material per month | C65: Rs/month | D65: 8000 | E65: 5000 | F65: 3000 | G65: =CHOOSE(Scenario,D65,E65,F65) | H65: Assumption | I65: L | J65: R5: per-km allowance not found | L65: 0 | M65: =IF(AND(G65>=MIN(D65,F65),G65<=MAX(D65,F65)),0,1)
A66: PilotsPerRepMonth | B66: Pilots started per rep per month (yearly avg) | C66: pilots | D66: 6 | E66: 10 | F66: 14 | G66: =CHOOSE(Scenario,D66,E66,F66) | H66: Assumption | I66: L | J66: R5: SaaStr 20-50 deals/month is inside sales; cut for in-person Tier-2 demos; peak Mar-Jun | L66: 0 | M66: =IF(AND(G66>=MIN(D66,F66),G66<=MAX(D66,F66)),0,1)
A67: PilotConv | B67: Pilot-to-paid conversion | C67: % | D67: 0.15 | E67: 0.3 | F67: 0.5 | G67: =CHOOSE(Scenario,D67,E67,F67) | H67: Researched | I67: L | J67: R5: trial-to-paid 8% median / 18.2% opt-in / 48.8% opt-out (Userpilot 2026); assisted-pilot benchmark not found | L67: =IF(OR(G67<0,G67>1),1,0) | M67: =IF(AND(G67>=MIN(D67,F67),G67<=MAX(D67,F67)),0,1)
A68: PilotMonths | B68: Free pilot length | C68: months | D68: 2 | E68: 1 | F68: 1 | G68: =CHOOSE(Scenario,D68,E68,F68) | H68: Assumption | I68: M | J68: FINANCE_PLAN s.3.2 | L68: 0 | M68: =IF(AND(G68>=MIN(D68,F68),G68<=MAX(D68,F68)),0,1)
A69: PilotSetupCost | B69: Retro-pilot setup (import last year's Excel; show who left) | C69: Rs per pilot | D69: 5000 | E69: 3000 | F69: 1500 | G69: =CHOOSE(Scenario,D69,E69,F69) | H69: Assumption | I69: L | J69: GTM design: light pilot; full onboarding only after conversion | K69: Primary research needed | L69: 0 | M69: =IF(AND(G69>=MIN(D69,F69),G69<=MAX(D69,F69)),0,1)
A70: OnboardBase | B70: Onboarding cost per institute (mid) | C70: Rs | D70: 15000 | E70: 8000 | F70: 5000 | G70: =CHOOSE(Scenario,D70,E70,F70) | H70: Guide | I70: L | J70: Case brief Rs5-10k; low-tech institutes higher | L70: 0 | M70: =IF(AND(G70>=MIN(D70,F70),G70<=MAX(D70,F70)),0,1)
A71: MarketingPerPaid | B71: Marketing spend per paid institute | C71: Rs | D71: 6000 | E71: 3000 | F71: 1000 | G71: =CHOOSE(Scenario,D71,E71,F71) | H71: Assumption | I71: L | L71: 0 | M71: =IF(AND(G71>=MIN(D71,F71),G71<=MAX(D71,F71)),0,1)
A72: ChurnInSeason | B72: Monthly logo churn for monthly payers | C72: %/month | D72: 0.05 | E72: 0.03 | F72: 0.015 | G72: =CHOOSE(Scenario,D72,E72,F72) | H72: Researched | I72: L | J72: R5: ChartMogul 6.1%/month at ARPA <$25 (2022); eChai India SMB 3-5%; SaaS Capital 2025 GRR 90%/yr | K72: Applied only to institutes not on annual prepay | L72: =IF(OR(G72<0,G72>1),1,0) | M72: =IF(AND(G72>=MIN(D72,F72),G72<=MAX(D72,F72)),0,1)
A73: RenewalSpike | B73: Non-renewal at session end (annual) | C73: % of logos | D73: 0.3 | E73: 0.2 | F73: 0.1 | G73: =CHOOSE(Scenario,D73,E73,F73) | H73: Assumption | I73: L | J73: R5: no benchmark found - answers the judges' post-exam churn question | K73: Spread over renewal months | L73: =IF(OR(G73<0,G73>1),1,0) | M73: =IF(AND(G73>=MIN(D73,F73),G73<=MAX(D73,F73)),0,1)
A74: DiscountRate | B74: Discount rate for LTV | C74: %/yr | D74: 0.2 | E74: 0.2 | F74: 0.2 | G74: =CHOOSE(Scenario,D74,E74,F74) | H74: Structural | I74: M | J74: Early-stage cost of capital convention | L74: =IF(OR(G74<0,G74>1),1,0) | M74: =IF(AND(G74>=MIN(D74,F74),G74<=MAX(D74,F74)),0,1)
A75: StartMonth | B75: Paid start month (1 = April) | C75: month # | D75: 2 | E75: 2 | F75: 2 | G75: =CHOOSE(Scenario,D75,E75,F75) | H75: Structural | I75: M | J75: Sales peak Mar-Jun; paid from May after a 1-month pilot | L75: 0 | M75: =IF(AND(G75>=MIN(D75,F75),G75<=MAX(D75,F75)),0,1)
A76: Team
A77: Founders | B77: Founders drawing a stipend | C77: people | D77: 3 | E77: 3 | F77: 3 | G77: =CHOOSE(Scenario,D77,E77,F77) | H77: Assumption | I77: M | J77: Owner decision | L77: 0 | M77: =IF(AND(G77>=MIN(D77,F77),G77<=MAX(D77,F77)),0,1)
A78: FounderStipend | B78: Founder stipend per month | C78: Rs/month | D78: 30000 | E78: 20000 | F78: 15000 | G78: =CHOOSE(Scenario,D78,E78,F78) | H78: Assumption | I78: M | J78: Owner decision | L78: 0 | M78: =IF(AND(G78>=MIN(D78,F78),G78<=MAX(D78,F78)),0,1)
A79: Engineers | B79: Engineers hired | C79: people | D79: 2 | E79: 1 | F79: 1 | G79: =CHOOSE(Scenario,D79,E79,F79) | H79: Assumption | I79: M | L79: 0 | M79: =IF(AND(G79>=MIN(D79,F79),G79<=MAX(D79,F79)),0,1)
A80: EngineerCTC | B80: Engineer monthly CTC | C80: Rs/month | D80: 67000 | E80: 50000 | F80: 35000 | G80: =CHOOSE(Scenario,D80,E80,F80) | H80: Researched | I80: L | J80: R5: Glassdoor Jaipur Rs6L/yr; Indore Rs6-8L/yr (1-3 yrs) | L80: 0 | M80: =IF(AND(G80>=MIN(D80,F80),G80<=MAX(D80,F80)),0,1)
A81: ToolsOpex | B81: Tools / office / legal per month | C81: Rs/month | D81: 20000 | E81: 12000 | F81: 8000 | G81: =CHOOSE(Scenario,D81,E81,F81) | H81: Assumption | I81: L | L81: 0 | M81: =IF(AND(G81>=MIN(D81,F81),G81<=MAX(D81,F81)),0,1)
A82: Guide
A83: G_Students | B83: Guide: students | C83: students | D83: 400 | E83: 400 | F83: 400 | G83: =CHOOSE(Scenario,D83,E83,F83) | H83: Guide | I83: H | J83: Case brief | L83: 0 | M83: =IF(AND(G83>=MIN(D83,F83),G83<=MAX(D83,F83)),0,1)
A84: G_Dropout | B84: Guide: dropout rate | C84: % | D84: 0.12 | E84: 0.12 | F84: 0.12 | G84: =CHOOSE(Scenario,D84,E84,F84) | H84: Guide | I84: H | J84: Case brief | L84: =IF(OR(G84<0,G84>1),1,0) | M84: =IF(AND(G84>=MIN(D84,F84),G84<=MAX(D84,F84)),0,1)
A85: G_RemainingFee | B85: Guide: remaining fee per dropout | C85: Rs | D85: 36000 | E85: 36000 | F85: 36000 | G85: =CHOOSE(Scenario,D85,E85,F85) | H85: Guide | I85: H | J85: Case brief | L85: 0 | M85: =IF(AND(G85>=MIN(D85,F85),G85<=MAX(D85,F85)),0,1)
A86: G_Prevent | B86: Guide: share of dropouts prevented | C86: % | D86: 0.25 | E86: 0.25 | F86: 0.25 | G86: =CHOOSE(Scenario,D86,E86,F86) | H86: Guide | I86: H | J86: Case brief | L86: =IF(OR(G86<0,G86>1),1,0) | M86: =IF(AND(G86>=MIN(D86,F86),G86<=MAX(D86,F86)),0,1)
A87: G_Price | B87: Guide: price per student per month | C87: Rs | D87: 40 | E87: 40 | F87: 40 | G87: =CHOOSE(Scenario,D87,E87,F87) | H87: Guide | I87: H | J87: Case brief | L87: 0 | M87: =IF(AND(G87>=MIN(D87,F87),G87<=MAX(D87,F87)),0,1)
A88: G_Months | B88: Guide: billing months per year | C88: months | D88: 12 | E88: 12 | F88: 12 | G88: =CHOOSE(Scenario,D88,E88,F88) | H88: Guide | I88: H | J88: Case brief | L88: 0 | M88: =IF(AND(G88>=MIN(D88,F88),G88<=MAX(D88,F88)),0,1)
A89: G_Infra | B89: Guide: infra + AI per student per month | C89: Rs | D89: 6 | E89: 6 | F89: 6 | G89: =CHOOSE(Scenario,D89,E89,F89) | H89: Guide | I89: H | J89: Case brief | L89: 0 | M89: =IF(AND(G89>=MIN(D89,F89),G89<=MAX(D89,F89)),0,1)
A90: G_Support | B90: Guide: support per institute per month | C90: Rs | D90: 3000 | E90: 3000 | F90: 3000 | G90: =CHOOSE(Scenario,D90,E90,F90) | H90: Guide | I90: H | J90: Case brief | L90: 0 | M90: =IF(AND(G90>=MIN(D90,F90),G90<=MAX(D90,F90)),0,1)
A91: G_CAC | B91: Guide: CAC | C91: Rs | D91: 25000 | E91: 25000 | F91: 25000 | G91: =CHOOSE(Scenario,D91,E91,F91) | H91: Guide | I91: H | J91: Case brief | L91: 0 | M91: =IF(AND(G91>=MIN(D91,F91),G91<=MAX(D91,F91)),0,1)
A92: G_Onboard | B92: Guide: onboarding | C92: Rs | D92: 8000 | E92: 8000 | F92: 8000 | G92: =CHOOSE(Scenario,D92,E92,F92) | H92: Guide | I92: H | J92: Case brief | L92: 0 | M92: =IF(AND(G92>=MIN(D92,F92),G92<=MAX(D92,F92)),0,1)
A93: G_Churn | B93: Guide: monthly churn | C93: % | D93: 0.03 | E93: 0.03 | F93: 0.03 | G93: =CHOOSE(Scenario,D93,E93,F93) | H93: Guide | I93: H | J93: Case brief | L93: =IF(OR(G93<0,G93>1),1,0) | M93: =IF(AND(G93>=MIN(D93,F93),G93<=MAX(D93,F93)),0,1)

Sheet Seasonality
A1: Seasonality, dropout timing and the 60-month timeline
A2: Session month 1 = April. Blue cells are inputs (currently assumptions, see Source).
A3: A. Active-student index and renewal (churn) months
A4: No. | B4: Month | C4: Active-student index | D4: Renewal month (1/0) | E4: Source
A5: 1 | B5: Apr | C5: 0.85 | D5: 1 | E5: Assumption (L): new session starts; admissions still coming in | flag: Assumption: renewal decision for the new session
A6: 2 | B6: May | C6: 0.95 | D6: 1 | E6: Assumption (L) | flag: Assumption
A7: 3 | B7: Jun | C7: 1 | D7: 0 | E7: Assumption (L)
A8: 4 | B8: Jul | C8: 1 | D8: 0 | E8: Assumption (L)
A9: 5 | B9: Aug | C9: 1 | D9: 0 | E9: Assumption (L)
A10: 6 | B10: Sep | C10: 1 | D10: 0 | E10: Assumption (L)
A11: 7 | B11: Oct | C11: 0.98 | D11: 0 | E11: Assumption (L): dropouts start reducing roster
A12: 8 | B12: Nov | C12: 0.96 | D12: 0 | E12: Assumption (L)
A13: 9 | B13: Dec | C13: 0.93 | D13: 0 | E13: Assumption (L)
A14: 10 | B14: Jan | C14: 0.85 | D14: 0 | E14: Assumption (L): JEE Main Jan; 12th students thin out
A15: 11 | B15: Feb | C15: 0.6 | D15: 0 | E15: Assumption (L): board exams
A16: 12 | B16: Mar | C16: 0.45 | D16: 1 | E16: Assumption (L): boards end; session over for 12th | flag: Assumption: post-exam churn window
B18: Renewal months per year | C18: =SUM(Season_Flag)
A20: B. When in the course students drop out
A21: Course month | C21: Share of dropouts | D21: Share of course left | E21: Source
A22: 1 | B22: Course month 1 | C22: 0.15 | D22: =MAX(0,(CourseMonths-A22)/CourseMonths) | E22: Assumption (L): R3 found no monthly data; front-loaded shape from refund windows (weeks 1-4) and case exits at months 2-4 (ThePrint 2025)
A23: 2 | B23: Course month 2 | C23: 0.15 | D23: =MAX(0,(CourseMonths-A23)/CourseMonths) | E23: Assumption (L): R3 base curve
A24: 3 | B24: Course month 3 | C24: 0.14 | D24: =MAX(0,(CourseMonths-A24)/CourseMonths) | E24: Assumption (L): R3 base curve
A25: 4 | B25: Course month 4 | C25: 0.12 | D25: =MAX(0,(CourseMonths-A25)/CourseMonths) | E25: Assumption (L): R3 base curve
A26: 5 | B26: Course month 5 | C26: 0.1 | D26: =MAX(0,(CourseMonths-A26)/CourseMonths) | E26: Assumption (L): R3 base curve
A27: 6 | B27: Course month 6 | C27: 0.09 | D27: =MAX(0,(CourseMonths-A27)/CourseMonths) | E27: Assumption (L): R3 base curve
A28: 7 | B28: Course month 7 | C28: 0.08 | D28: =MAX(0,(CourseMonths-A28)/CourseMonths) | E28: Assumption (L): R3 base curve
A29: 8 | B29: Course month 8 | C29: 0.07 | D29: =MAX(0,(CourseMonths-A29)/CourseMonths) | E29: Assumption (L): R3 base curve
A30: 9 | B30: Course month 9 | C30: 0.06 | D30: =MAX(0,(CourseMonths-A30)/CourseMonths) | E30: Assumption (L): R3 base curve
A31: 10 | B31: Course month 10 | C31: 0.04 | D31: =MAX(0,(CourseMonths-A31)/CourseMonths) | E31: Assumption (L): R3 base curve
B32: Total (must be 100%) | C32: =SUM(DropTiming)
A34: C. Timeline for LTV: paid month t → calendar month, student index, renewal flag, discount factor
A36: t (paid month) | B36: Calendar month # | C36: Active-student index | D36: Renewal flag | E36: Discount factor
A37: 1 | B37: =MOD(StartMonth+A37-2,12)+1 | C37: =INDEX(Season_Idx,B37) | D37: =INDEX(Season_Flag,B37) | E37: =1/(1+DiscountRate)^(A37/12)
A38: 2 | B38: =MOD(StartMonth+A38-2,12)+1 | C38: =INDEX(Season_Idx,B38) | D38: =INDEX(Season_Flag,B38) | E38: =1/(1+DiscountRate)^(A38/12)
A39: 3 | B39: =MOD(StartMonth+A39-2,12)+1 | C39: =INDEX(Season_Idx,B39) | D39: =INDEX(Season_Flag,B39) | E39: =1/(1+DiscountRate)^(A39/12)
A40: 4 | B40: =MOD(StartMonth+A40-2,12)+1 | C40: =INDEX(Season_Idx,B40) | D40: =INDEX(Season_Flag,B40) | E40: =1/(1+DiscountRate)^(A40/12)
A41: 5 | B41: =MOD(StartMonth+A41-2,12)+1 | C41: =INDEX(Season_Idx,B41) | D41: =INDEX(Season_Flag,B41) | E41: =1/(1+DiscountRate)^(A41/12)
A42: 6 | B42: =MOD(StartMonth+A42-2,12)+1 | C42: =INDEX(Season_Idx,B42) | D42: =INDEX(Season_Flag,B42) | E42: =1/(1+DiscountRate)^(A42/12)
A43: 7 | B43: =MOD(StartMonth+A43-2,12)+1 | C43: =INDEX(Season_Idx,B43) | D43: =INDEX(Season_Flag,B43) | E43: =1/(1+DiscountRate)^(A43/12)
A44: 8 | B44: =MOD(StartMonth+A44-2,12)+1 | C44: =INDEX(Season_Idx,B44) | D44: =INDEX(Season_Flag,B44) | E44: =1/(1+DiscountRate)^(A44/12)
A45: 9 | B45: =MOD(StartMonth+A45-2,12)+1 | C45: =INDEX(Season_Idx,B45) | D45: =INDEX(Season_Flag,B45) | E45: =1/(1+DiscountRate)^(A45/12)
A46: 10 | B46: =MOD(StartMonth+A46-2,12)+1 | C46: =INDEX(Season_Idx,B46) | D46: =INDEX(Season_Flag,B46) | E46: =1/(1+DiscountRate)^(A46/12)
A47: 11 | B47: =MOD(StartMonth+A47-2,12)+1 | C47: =INDEX(Season_Idx,B47) | D47: =INDEX(Season_Flag,B47) | E47: =1/(1+DiscountRate)^(A47/12)
A48: 12 | B48: =MOD(StartMonth+A48-2,12)+1 | C48: =INDEX(Season_Idx,B48) | D48: =INDEX(Season_Flag,B48) | E48: =1/(1+DiscountRate)^(A48/12)
... A96: 60 | B96: =MOD(StartMonth+A96-2,12)+1 | C96: =INDEX(Season_Idx,B96) | D96: =INDEX(Season_Flag,B96) | E96: =1/(1+DiscountRate)^(A96/12)

Sheet Pricing
A1: Pricing — list price, discounts, realised price
A2: Green = linked input · black = formula · green fill = output used elsewhere
B4: Item | C4: Unit | D4: LIVE
B5: Inputs (from Assumptions)
B6: List price per active student per month | C6: Rs/student/month | D6: =ListPrice
B7: Minimum monthly fee per institute | C7: Rs/month | D7: =MinFee
B8: Average negotiated discount off list | C8: % | D8: =NegotiationDisc
B9: Share of institutes choosing annual prepay | C9: % | D9: =PrepayUptake
B10: Annual prepay discount | C10: % | D10: =PrepayDisc
B11: GST on SaaS | C11: % | D11: =GST
B12: Realised price
B13: Effective discount = negotiation + prepay uptake × prepay discount | C13: % | D13: =D8+D9*D10
B14: Realised price per student-month (ex-GST) | C14: ₹/student/month | D14: =D6*(1-D13)
B15: Price the owner feels (incl. GST) | C15: ₹/student/month | D15: =D14*(1+D11)
B16: What institutes already pay for an ERP/LMS | C16: Rs/student/month | D16: =CompetitorAnchor
B17: Our realised price ÷ what institutes already pay for an ERP/LMS | C17: x | D17: =IF(D16>0,D14/D16,0)
A20: Packaging (for the deck; Pro price is the model's list price)
A21: Tier | B21: Contents | C21: Price | D21: Role
A22: Starter | B22: CSV / OMR upload, test-level reports, 1 batch | C22: 0 | D22: Free — lead generation, data on-ramp
A23: Pro (core) | B23: Topic heatmap, at-risk list with reasons, template parent reports | C23: =ListPrice | D23: Core paid plan, ₹/active student/month, min fee applies
A24: Premium (AI) | B24: GenAI Hindi/English parent reports on WhatsApp, percentile band, study plans | C24: Pro + add-on | D24: Upsell — NOT in base revenue until priced by research
A25: Annual plan | B25: Pro billed yearly upfront | C25: =ListPrice*(1-PrepayDisc) | D25: Cash up front, lower churn at renewal

Sheet COGS_Build
A1: COGS build-up — cost to serve one student (must match TECH_PLAN §16 / NB09)
A2: Mid-segment size used for the all-in figure. Tech plan target band: ₹3–10 per student-month.
B4: Item | C4: Unit | D4: LIVE
B5: Inputs (from Assumptions)
B6: AI parent reports per student per month | C6: reports | D6: =ReportsPerStudentMonth
B7: LLM input tokens per report | C7: tokens | D7: =TokensInPerReport
B8: LLM output tokens per report | C8: tokens | D8: =TokensOutPerReport
B9: LLM input price (hosted) | C9: Rs per 1M tokens | D9: =LLMPriceIn
B10: LLM output price (hosted) | C10: Rs per 1M tokens | D10: =LLMPriceOut
B11: WhatsApp utility messages per student per month | C11: messages | D11: =WAMsgsPerStudentMonth
B12: WhatsApp utility message price (India) | C12: Rs/message | D12: =WAPricePerMsg
B13: Compute + storage + backups per student | C13: Rs/student/month | D13: =ComputePerStudentMonth
B14: Consent OTP + verification per student | C14: Rs/student/yr | D14: =ConsentCostPerStudentYear
B15: App server + managed Postgres + backups per stack | C15: Rs/month | D15: =ServerCostMonth
B16: WhatsApp BSP platform fee per stack | C16: Rs/month | D16: =BSPFeeMonth
B17: Institutes sharing one server stack | C17: institutes | D17: =InstPerStack
B18: DPDP compliance cost per institute | C18: Rs/month | D18: =CompliancePerInstMonth
B19: Students per institute | C19: students | D19: =Students_M
B20: Variable cost per active student per month
B21: LLM (AI parent reports, hosted model) | C21: ₹/student/month | D21: =D6*(D7*D9+D8*D10)/1000000
B22: WhatsApp utility messages | C22: ₹/student/month | D22: =D11*D12
B23: Compute + storage + backups | C23: ₹/student/month | D23: =D13
B24: Consent OTP / verification (annual ÷ 12) | C24: ₹/student/month | D24: =D14/12
B25: Total variable COGS per student-month | C25: ₹/student/month | D25: =SUM(D21:D24)
B26: Fixed cost per institute per month
B27: Hosting share = (server + DB + WhatsApp BSP fee) ÷ institutes per stack | C27: ₹/institute/month | D27: =(D15+D16)/D17
B28: Hosting share + DPDP compliance | C28: ₹/institute/month | D28: =D27+D18
B29: All-in COGS per student-month at this size | C29: ₹/student/month | D29: =D25+D28/D19

Sheet Institute_ROI
A1: Institute ROI — does it pay for the owner? (per segment, live scenario)
A2: Same price and same dropout funnel as Unit_Econ. Green fill = key outputs.
B4: Line | C4: Unit | D4: Small (<250) | E4: Mid (250-800) | F4: Large (>800)
B5: Inputs (from Assumptions / Pricing)
B6: Students per institute | C6: students | D6: =Students_S | E6: =Students_M | F6: =Students_L
B7: Annual fee per student | C7: Rs/yr | D7: =Fee_S | E7: =Fee_M | F7: =Fee_L
B8: Mid-session dropout/default rate | C8: % of students/yr | D8: =DropoutRate | E8: =DropoutRate | F8: =DropoutRate
B9: Share of students paying full fee upfront | C9: % | D9: =UpfrontShare | E9: =UpfrontShare | F9: =UpfrontShare
B10: Instalments per year for non-upfront payers | C10: count | D10: =NInstalments | E10: =NInstalments | F10: =NInstalments
B11: Share of upfront leavers actually refunded pro-rata | C11: % | D11: =RefundEnforced | E11: =RefundEnforced | F11: =RefundEnforced
B12: Months before the model can flag (no test data yet) | C12: months | D12: =BlindMonths | E12: =BlindMonths | F12: =BlindMonths
B13: Share of students under 18 | C13: % | D13: =MinorShare | E13: =MinorShare | F13: =MinorShare
B14: Model recall on minors (academic-support + rules) | C14: % | D14: =Recall_Minor | E14: =Recall_Minor | F14: =Recall_Minor
B15: Model recall on 18+ (full ML) | C15: % | D15: =Recall_Adult | E15: =Recall_Adult | F15: =Recall_Adult
B16: Precision of at-risk flag | C16: % | D16: =Precision | E16: =Precision | F16: =Precision
B17: Share of flags the institute assigns to outreach | C17: % | D17: =ActionRate | E17: =ActionRate | F17: =ActionRate
B18: Dropout reduction among flagged students given outreach (RCT) | C18: relative % | D18: =InterventionSuccess | E18: =InterventionSuccess | F18: =InterventionSuccess
B19: Admissions uplift next session from results/parent trust | C19: % of students | D19: =AdmissionUplift | E19: =AdmissionUplift | F19: =AdmissionUplift
B20: Institute margin on one extra admission | C20: % | D20: =MarginExtraAdmission | E20: =MarginExtraAdmission | F20: =MarginExtraAdmission
B21: Staff hours saved per month | C21: hours/month | D21: =StaffHoursSaved | E21: =StaffHoursSaved | F21: =StaffHoursSaved
B22: Cost of one admin staff hour | C22: Rs/hour | D22: =StaffHourCost | E22: =StaffHourCost | F22: =StaffHourCost
B23: Mentor minutes per intervention | C23: minutes | D23: =InterventionMinutes | E23: =InterventionMinutes | F23: =InterventionMinutes
B24: Cost of one mentor hour | C24: Rs/hour | D24: =MentorHourCost | E24: =MentorHourCost | F24: =MentorHourCost
B25: List price per active student per month | C25: Rs/student/month | D25: =ListPrice | E25: =ListPrice | F25: =ListPrice
B26: Minimum monthly fee per institute | C26: Rs/month | D26: =MinFee | E26: =MinFee | F26: =MinFee
B27: GST on SaaS | C27: % | D27: =GST | E27: =GST | F27: =GST
B28: Share of institutes that reclaim our GST as input credit | C28: % | D28: =ITCShare | E28: =ITCShare | F28: =ITCShare
B29: Effective discount (Pricing) | C29: % | D29: =EffDisc | E29: =EffDisc | F29: =EffDisc
B30: 1. What a dropout actually costs (unpaid instalments + refunds to full payers)
B31: Dropouts per year | C31: students/yr | D31: =D6*D8 | E31: =E6*E8 | F31: =F6*F8
B32: Avg fee lost per dropout (timing curve × unpaid instalments / pro-rata refund) | C32: ₹/dropout | D32: =SUMPRODUCT(DropTiming,D7*((1-D9)*(1-(INT((DropMonth-1)*D10/CourseMonths)+1)/D10)+D9*D11*DropRemain)) | E32: =SUMPRODUCT(DropTiming,E7*((1-E9)*(1-(INT((DropMonth-1)*E10/CourseMonths)+1)/E10)+E9*E11*DropRemain)) | F32: =SUMPRODUCT(DropTiming,F7*((1-F9)*(1-(INT((DropMonth-1)*F10/CourseMonths)+1)/F10)+F9*F11*DropRemain))
B33: Fee lost to dropouts per year (no platform) | C33: ₹/yr | D33: =D31*D32 | E33: =E31*E32 | F33: =F31*F32
B34: 2. Prevention funnel (replaces the guide's flat 25%)
B35: Blended recall (minors: academic model + rules; 18+: full ML) | C35: % | D35: =D13*D14+(1-D13)*D15 | E35: =E13*E14+(1-E13)*E15 | F35: =F13*F14+(1-F13)*F15
B36: Share of dropouts after the 'blind' months (enough test data to flag) | C36: % | D36: =SUMPRODUCT(DropTiming*(DropMonth>D12)) | E36: =SUMPRODUCT(DropTiming*(DropMonth>E12)) | F36: =SUMPRODUCT(DropTiming*(DropMonth>F12))
B37: Effective dropout reduction = recall × action × RCT effect × catchable | C37: % | D37: =D35*D17*D18*D36 | E37: =E35*E17*E18*E36 | F37: =F35*F17*F18*F36
B38: Dropouts prevented per year | C38: students/yr | D38: =D31*D37 | E38: =E31*E37 | F38: =F31*F37
B39: Fee saved per prevented dropout (catchable months only) | C39: ₹/student | D39: =IF(D36>0,SUMPRODUCT(DropTiming*(DropMonth>D12)*D7*((1-D9)*(1-(INT((DropMonth-1)*D10/CourseMonths)+1)/D10)+D9*D11*DropRemain))/D36,0) | E39: =IF(E36>0,SUMPRODUCT(DropTiming*(DropMonth>E12)*E7*((1-E9)*(1-(INT((DropMonth-1)*E10/CourseMonths)+1)/E10)+E9*E11*DropRemain))/E36,0) | F39: =IF(F36>0,SUMPRODUCT(DropTiming*(DropMonth>F12)*F7*((1-F9)*(1-(INT((DropMonth-1)*F10/CourseMonths)+1)/F10)+F9*F11*DropRemain))/F36,0)
B40: 3. Value to the institute (₹/yr)
B41: Fees retained | C41: ₹/yr | D41: =D38*D39 | E41: =E38*E39 | F41: =F38*F39
B42: Margin on extra admissions (results / parent trust) | C42: ₹/yr | D42: =D6*D19*D7*D20 | E42: =E6*E19*E7*E20 | F42: =F6*F19*F7*F20
B43: Staff time saved | C43: ₹/yr | D43: =D21*D22*12 | E43: =E21*E22*12 | F43: =F21*F22*12
B44: Total value | C44: ₹/yr | D44: =D41+D42+D43 | E44: =E41+E42+E43 | F44: =F41+F42+F43
B45: 4. Cost to the institute (₹/yr)
B46: Platform fee (seasonal active students, min fee, discounts; ex-GST) | C46: ₹/yr | D46: =SUMPRODUCT((D6*Season_Idx*D25>D26)*(D6*Season_Idx*D25)+(D6*Season_Idx*D25<=D26)*D26)*(1-D29) | E46: =SUMPRODUCT((E6*Season_Idx*E25>E26)*(E6*Season_Idx*E25)+(E6*Season_Idx*E25<=E26)*E26)*(1-E29) | F46: =SUMPRODUCT((F6*Season_Idx*F25>F26)*(F6*Season_Idx*F25)+(F6*Season_Idx*F25<=F26)*F26)*(1-F29)
B47: GST the institute cannot reclaim | C47: ₹/yr | D47: =D46*D27*(1-D28) | E47: =E46*E27*(1-E28) | F47: =F46*F27*(1-F28)
B48: Students flagged per year (true + false alarms) | C48: students/yr | D48: =IF(D16>0,D31*D35/D16,0) | E48: =IF(E16>0,E31*E35/E16,0) | F48: =IF(F16>0,F31*F35/F16,0)
B49: Mentor time spent acting on flags | C49: ₹/yr | D49: =D48*D17*D23/60*D24 | E49: =E48*E17*E23/60*E24 | F49: =F48*F17*F23/60*F24
B50: Total cost | C50: ₹/yr | D50: =D46+D47+D49 | E50: =E46+E47+E49 | F50: =F46+F47+F49
B51: 5. Result
B52: Net benefit to institute | C52: ₹/yr | D52: =D44-D50 | E52: =E44-E50 | F52: =F44-F50
B53: Institute ROI (value ÷ cost) | C53: x | D53: =IF(D50>0,D44/D50,0) | E53: =IF(E50>0,E44/E50,0) | F53: =IF(F50>0,F44/F50,0)
B54: Fees-only ROI (no soft benefits) | C54: x | D54: =IF(D50>0,D41/D50,0) | E54: =IF(E50>0,E41/E50,0) | F54: =IF(F50>0,F41/F50,0)
B55: Break-even: students to save per year (fees only) | C55: students/yr | D55: =IF(D39>0,D50/D39,0) | E55: =IF(E39>0,E50/E39,0) | F55: =IF(F39>0,F50/F39,0)
B56: Break-even dropout reduction needed | C56: % | D56: =IF(D31>0,D55/D31,0) | E56: =IF(E31>0,E55/E31,0) | F56: =IF(F31>0,F55/F31,0)
B57: Admissions uplift needed to break even, after fees + staff time | C57: % of students | D57: =IF(D6*D7*D20>0,MAX(0,D50-D41-D43)/(D6*D7*D20),0) | E57: =IF(E6*E7*E20>0,MAX(0,E50-E41-E43)/(E6*E7*E20),0) | F57: =IF(F6*F7*F20>0,MAX(0,F50-F41-F43)/(F6*F7*F20),0)
B58: …in extra admissions per year | C58: students/yr | D58: =D57*D6 | E58: =E57*E6 | F58: =F57*F6
B59: Platform cost per student per year (incl. unreclaimed GST) | C59: ₹/student/yr | D59: =(D46+D47)/D6 | E59: =(E46+E47)/E6 | F59: =(F46+F47)/F6
B60: Platform cost as % of the student's fee | C60: % | D60: =D59/D7 | E60: =E59/E7 | F60: =F59/F7
A63: The guide's naive model (for contrast — all inputs from the Guide block on Assumptions)
B64: Dropouts per year | E64: =G_Students*G_Dropout
B65: Dropouts prevented (flat 25%) | E65: =G_Students*G_Dropout*G_Prevent
B66: Fees saved | E66: =G_Students*G_Dropout*G_Prevent*G_RemainingFee
B67: Platform cost (12 months, no GST, no seasonality) | E67: =G_Students*G_Price*G_Months
B68: Guide ROI | E68: =IF(ROUND(G_Students*G_Price*G_Months,6)>0,G_Students*G_Dropout*G_Prevent*G_RemainingFee/(G_Students*G_Price*G_Months),0)
B69: Guide break-even students | E69: =G_Students*G_Price*G_Months/G_RemainingFee

Sheet Unit_Econ
A1: Unit economics per institute (live scenario)
A2: LTV uses a seasonal survival curve (monthly churn + renewal spike), discounted, capped at 60 months. Payback = 61 means 'not within 60 months'.
B4: Line | C4: Unit | D4: Small (<250) | E4: Mid (250-800) | F4: Large (>800) | H4: Guide's naive unit economics | I4: Value
B5: Inputs (from Assumptions / Pricing / COGS_Build) | H5: Revenue per institute per month | I5: =G_Students*G_Price
B6: Students per institute | C6: students | D6: =Students_S | E6: =Students_M | F6: =Students_L | H6: Contribution per month | I6: =G_Students*G_Price-G_Students*G_Infra-G_Support
B7: List price per active student per month | C7: Rs/student/month | D7: =ListPrice | E7: =ListPrice | F7: =ListPrice | H7: CAC + onboarding | I7: =G_CAC+G_Onboard
B8: Minimum monthly fee per institute | C8: Rs/month | D8: =MinFee | E8: =MinFee | F8: =MinFee | H8: Payback (months) | I8: =(G_CAC+G_Onboard)/(G_Students*G_Price-G_Students*G_Infra-G_Support)
B9: Bad debt / uncollected billing | C9: % | D9: =BadDebt | E9: =BadDebt | F9: =BadDebt | H9: LTV = contribution ÷ churn | I9: =(G_Students*G_Price-G_Students*G_Infra-G_Support)/G_Churn
B10: Payment collection cost (blended) | C10: % of revenue | D10: =GatewayFee | E10: =GatewayFee | F10: =GatewayFee | H10: LTV ÷ (CAC + onboarding) | I10: =((G_Students*G_Price-G_Students*G_Infra-G_Support)/G_Churn)/(G_CAC+G_Onboard)
B11: Monthly logo churn for monthly payers | C11: %/month | D11: =ChurnInSeason | E11: =ChurnInSeason | F11: =ChurnInSeason
B12: Share of institutes choosing annual prepay | C12: % | D12: =PrepayUptake | E12: =PrepayUptake | F12: =PrepayUptake
B13: Non-renewal at session end (annual) | C13: % of logos | D13: =RenewalSpike | E13: =RenewalSpike | F13: =RenewalSpike | H13: Break-even scale (fixed team cost ÷ Mid contribution) | I13: Value
B14: Customer-success / onboarding exec monthly CTC | C14: Rs/month | D14: =CSM_CTC | E14: =CSM_CTC | F14: =CSM_CTC | H14: Fixed team + tools cost per month | I14: =Founders*FounderStipend+Engineers*EngineerCTC+ToolsOpex
B15: Institutes per CSM | C15: institutes | D15: =InstPerCSM | E15: =InstPerCSM | F15: =InstPerCSM | H15: Mid-institute avg monthly contribution | I15: =E34
B16: Field sales rep monthly CTC (incl. fuel) | C16: Rs/month | D16: =RepCTC | E16: =RepCTC | F16: =RepCTC | H16: Institutes needed to cover fixed cost | I16: =IF(I15>0,I14/I15,0)
B17: Rep intercity travel + demo material per month | C17: Rs/month | D17: =RepTravel | E17: =RepTravel | F17: =RepTravel | H17: …equivalent active students | I17: =I16*Students_M
B18: Pilots started per rep per month (yearly avg) | C18: pilots | D18: =PilotsPerRepMonth | E18: =PilotsPerRepMonth | F18: =PilotsPerRepMonth | H18: Paid institutes one rep adds per month | I18: =PilotsPerRepMonth*PilotConv
B19: Pilot-to-paid conversion | C19: % | D19: =PilotConv | E19: =PilotConv | F19: =PilotConv
B20: Free pilot length | C20: months | D20: =PilotMonths | E20: =PilotMonths | F20: =PilotMonths | H20: Full hiring plan, cohorts, cash and funding need: Round 2 sheets.
B21: Retro-pilot setup (import last year's Excel; show who left) | C21: Rs per pilot | D21: =PilotSetupCost | E21: =PilotSetupCost | F21: =PilotSetupCost
B22: Onboarding cost per institute (mid) | C22: Rs | D22: =OnboardBase | E22: =OnboardBase | F22: =OnboardBase
B23: Onboarding cost multiplier | C23: x | D23: =OnboardMult_S | E23: =OnboardMult_M | F23: =OnboardMult_L
B24: Marketing spend per paid institute | C24: Rs | D24: =MarketingPerPaid | E24: =MarketingPerPaid | F24: =MarketingPerPaid
B25: Effective discount (Pricing) | C25: % | D25: =EffDisc | E25: =EffDisc | F25: =EffDisc
B26: Variable COGS per student-month (COGS_Build) | C26: ₹/student/month | D26: =COGS_PerStudent | E26: =COGS_PerStudent | F26: =COGS_PerStudent
B27: Fixed COGS per institute-month (COGS_Build) | C27: ₹/month | D27: =COGS_FixedInst | E27: =COGS_FixedInst | F27: =COGS_FixedInst
B28: 1. Year-1 economics per institute (before churn)
B29: Collected revenue, first 12 paid months (ex-GST, after bad debt) | C29: ₹/yr | D29: =SUM(D52:D63) | E29: =SUM(E52:E63) | F29: =SUM(F52:F63)
B30: Average monthly revenue | C30: ₹/month | D30: =D29/12 | E30: =E29/12 | F30: =F29/12
B31: COGS, first 12 months (students × seasonality × COGS + fixed + gateway) | C31: ₹/yr | D31: =D6*D26*SUM(Seasonality!$C$37:$C$48)+12*D27+D10*D29 | E31: =E6*E26*SUM(Seasonality!$C$37:$C$48)+12*E27+E10*E29 | F31: =F6*F26*SUM(Seasonality!$C$37:$C$48)+12*F27+F10*F29
B32: Gross margin | C32: % | D32: =IF(D29>0,(D29-D31)/D29,0) | E32: =IF(E29>0,(E29-E31)/E29,0) | F32: =IF(F29>0,(F29-F31)/F29,0)
B33: Customer-success cost per institute | C33: ₹/month | D33: =D14/D15 | E33: =E14/E15 | F33: =F14/F15
B34: Average monthly contribution (after COGS + support) | C34: ₹/month | D34: =SUM(D112:D123)/12 | E34: =SUM(E112:E123)/12 | F34: =SUM(F112:F123)/12
B35: Contribution margin | C35: % | D35: =IF(D30>0,D34/D30,0) | E35: =IF(E30>0,E34/E30,0) | F35: =IF(F30>0,F34/F30,0)
B36: 2. Cost to acquire one paying institute
B37: Sales cost per pilot started (rep CTC + travel ÷ pilots) | C37: ₹ | D37: =(D16+D17)/D18 | E37: =(E16+E17)/E18 | F37: =(F16+F17)/F18
B38: Onboarding cost (data migration + training) | C38: ₹ | D38: =D22*D23 | E38: =E22*E23 | F38: =F22*F23
B39: Cost of serving the free pilot | C39: ₹ | D39: =D20*(D6*D26+D27) | E39: =E20*(E6*E26+E27) | F39: =F20*(F6*F26+F27)
B40: CAC: sales + marketing per paid institute (failed pilots included) | C40: ₹ | D40: =D37/D19+D24 | E40: =E37/E19+E24 | F40: =F37/F19+F24
B41: Fully loaded acquisition cost = (sales + pilot setup + pilot COGS) ÷ conversion + onboarding (paid only) + marketing | C41: ₹ | D41: =(D37+D21+D39)/D19+D38+D24 | E41: =(E37+E21+E39)/E19+E38+E24 | F41: =(F37+F21+F39)/F19+F38+F24
B42: 3. Retention (seasonal, not 1/churn)
B43: In-season churn, monthly payers only (prepaid annual plans cannot leave mid-year) | C43: %/month | D43: =D11*(1-D12) | E43: =E11*(1-E12) | F43: =F11*(1-F12)
B44: Extra churn per renewal month | C44: %/month | D44: =1-(1-D13)^(1/NRenew) | E44: =1-(1-E13)^(1/NRenew) | F44: =1-(1-F13)^(1/NRenew)
B45: Annual logo retention | C45: % | D45: =(1-D43)^12*(1-D13) | E45: =(1-E43)^12*(1-E13) | F45: =(1-F43)^12*(1-F13)
B46: Expected paid lifetime within horizon | C46: months | D46: =SUM(D172:D231) | E46: =SUM(E172:E231) | F46: =SUM(F172:F231)
B47: 4. Lifetime value (60-month horizon, survival-weighted, discounted)
B48: LTV (contribution) | C48: ₹ | D48: =D291 | E48: =E291 | F48: =F291
B49: LTV ÷ fully loaded acquisition cost | C49: x | D49: =IF(D41>0,D48/D41,0) | E49: =IF(E41>0,E48/E41,0) | F49: =IF(F41>0,F48/F41,0)
B50: Payback (months of paid life, discounted) | C50: months | D50: =IF(D291<D41,61,COUNTIF(D232:D291,"<"&D41)+1) | E50: =IF(E291<E41,61,COUNTIF(E232:E291,"<"&E41)+1) | F50: =IF(F291<F41,61,COUNTIF(F232:F291,"<"&F41)+1)
B51: 5. Month-by-month engine (t = paid month; calendar from Seasonality timeline)
B52: Revenue collected · month 1 | C52: ₹ | D52: =MAX(D8,D6*Seasonality!$C$37*D7)*(1-D25)*(1-D9) | E52: =MAX(E8,E6*Seasonality!$C$37*E7)*(1-E25)*(1-E9) | F52: =MAX(F8,F6*Seasonality!$C$37*F7)*(1-F25)*(1-F9)
B53: Revenue collected · month 2 | C53: ₹ | D53: =MAX(D8,D6*Seasonality!$C$38*D7)*(1-D25)*(1-D9) | E53: =MAX(E8,E6*Seasonality!$C$38*E7)*(1-E25)*(1-E9) | F53: =MAX(F8,F6*Seasonality!$C$38*F7)*(1-F25)*(1-F9)
B54: Revenue collected · month 3 | C54: ₹ | D54: =MAX(D8,D6*Seasonality!$C$39*D7)*(1-D25)*(1-D9) | E54: =MAX(E8,E6*Seasonality!$C$39*E7)*(1-E25)*(1-E9) | F54: =MAX(F8,F6*Seasonality!$C$39*F7)*(1-F25)*(1-F9)
B55: Revenue collected · month 4 | C55: ₹ | D55: =MAX(D8,D6*Seasonality!$C$40*D7)*(1-D25)*(1-D9) | E55: =MAX(E8,E6*Seasonality!$C$40*E7)*(1-E25)*(1-E9) | F55: =MAX(F8,F6*Seasonality!$C$40*F7)*(1-F25)*(1-F9)
B56: Revenue collected · month 5 | C56: ₹ | D56: =MAX(D8,D6*Seasonality!$C$41*D7)*(1-D25)*(1-D9) | E56: =MAX(E8,E6*Seasonality!$C$41*E7)*(1-E25)*(1-E9) | F56: =MAX(F8,F6*Seasonality!$C$41*F7)*(1-F25)*(1-F9)
B57: Revenue collected · month 6 | C57: ₹ | D57: =MAX(D8,D6*Seasonality!$C$42*D7)*(1-D25)*(1-D9) | E57: =MAX(E8,E6*Seasonality!$C$42*E7)*(1-E25)*(1-E9) | F57: =MAX(F8,F6*Seasonality!$C$42*F7)*(1-F25)*(1-F9)
B58: Revenue collected · month 7 | C58: ₹ | D58: =MAX(D8,D6*Seasonality!$C$43*D7)*(1-D25)*(1-D9) | E58: =MAX(E8,E6*Seasonality!$C$43*E7)*(1-E25)*(1-E9) | F58: =MAX(F8,F6*Seasonality!$C$43*F7)*(1-F25)*(1-F9)
B59: Revenue collected · month 8 | C59: ₹ | D59: =MAX(D8,D6*Seasonality!$C$44*D7)*(1-D25)*(1-D9) | E59: =MAX(E8,E6*Seasonality!$C$44*E7)*(1-E25)*(1-E9) | F59: =MAX(F8,F6*Seasonality!$C$44*F7)*(1-F25)*(1-F9)
B60: Revenue collected · month 9 | C60: ₹ | D60: =MAX(D8,D6*Seasonality!$C$45*D7)*(1-D25)*(1-D9) | E60: =MAX(E8,E6*Seasonality!$C$45*E7)*(1-E25)*(1-E9) | F60: =MAX(F8,F6*Seasonality!$C$45*F7)*(1-F25)*(1-F9)
B61: Revenue collected · month 10 | C61: ₹ | D61: =MAX(D8,D6*Seasonality!$C$46*D7)*(1-D25)*(1-D9) | E61: =MAX(E8,E6*Seasonality!$C$46*E7)*(1-E25)*(1-E9) | F61: =MAX(F8,F6*Seasonality!$C$46*F7)*(1-F25)*(1-F9)
B62: Revenue collected · month 11 | C62: ₹ | D62: =MAX(D8,D6*Seasonality!$C$47*D7)*(1-D25)*(1-D9) | E62: =MAX(E8,E6*Seasonality!$C$47*E7)*(1-E25)*(1-E9) | F62: =MAX(F8,F6*Seasonality!$C$47*F7)*(1-F25)*(1-F9)
B63: Revenue collected · month 12 | C63: ₹ | D63: =MAX(D8,D6*Seasonality!$C$48*D7)*(1-D25)*(1-D9) | E63: =MAX(E8,E6*Seasonality!$C$48*E7)*(1-E25)*(1-E9) | F63: =MAX(F8,F6*Seasonality!$C$48*F7)*(1-F25)*(1-F9)
B64: Revenue collected · month 13 | C64: ₹ | D64: =MAX(D8,D6*Seasonality!$C$49*D7)*(1-D25)*(1-D9) | E64: =MAX(E8,E6*Seasonality!$C$49*E7)*(1-E25)*(1-E9) | F64: =MAX(F8,F6*Seasonality!$C$49*F7)*(1-F25)*(1-F9)
B65: Revenue collected · month 14 | C65: ₹ | D65: =MAX(D8,D6*Seasonality!$C$50*D7)*(1-D25)*(1-D9) | E65: =MAX(E8,E6*Seasonality!$C$50*E7)*(1-E25)*(1-E9) | F65: =MAX(F8,F6*Seasonality!$C$50*F7)*(1-F25)*(1-F9)
B66: Revenue collected · month 15 | C66: ₹ | D66: =MAX(D8,D6*Seasonality!$C$51*D7)*(1-D25)*(1-D9) | E66: =MAX(E8,E6*Seasonality!$C$51*E7)*(1-E25)*(1-E9) | F66: =MAX(F8,F6*Seasonality!$C$51*F7)*(1-F25)*(1-F9)
B67: Revenue collected · month 16 | C67: ₹ | D67: =MAX(D8,D6*Seasonality!$C$52*D7)*(1-D25)*(1-D9) | E67: =MAX(E8,E6*Seasonality!$C$52*E7)*(1-E25)*(1-E9) | F67: =MAX(F8,F6*Seasonality!$C$52*F7)*(1-F25)*(1-F9)
B68: Revenue collected · month 17 | C68: ₹ | D68: =MAX(D8,D6*Seasonality!$C$53*D7)*(1-D25)*(1-D9) | E68: =MAX(E8,E6*Seasonality!$C$53*E7)*(1-E25)*(1-E9) | F68: =MAX(F8,F6*Seasonality!$C$53*F7)*(1-F25)*(1-F9)
B69: Revenue collected · month 18 | C69: ₹ | D69: =MAX(D8,D6*Seasonality!$C$54*D7)*(1-D25)*(1-D9) | E69: =MAX(E8,E6*Seasonality!$C$54*E7)*(1-E25)*(1-E9) | F69: =MAX(F8,F6*Seasonality!$C$54*F7)*(1-F25)*(1-F9)
B70: Revenue collected · month 19 | C70: ₹ | D70: =MAX(D8,D6*Seasonality!$C$55*D7)*(1-D25)*(1-D9) | E70: =MAX(E8,E6*Seasonality!$C$55*E7)*(1-E25)*(1-E9) | F70: =MAX(F8,F6*Seasonality!$C$55*F7)*(1-F25)*(1-F9)
B71: Revenue collected · month 20 | C71: ₹ | D71: =MAX(D8,D6*Seasonality!$C$56*D7)*(1-D25)*(1-D9) | E71: =MAX(E8,E6*Seasonality!$C$56*E7)*(1-E25)*(1-E9) | F71: =MAX(F8,F6*Seasonality!$C$56*F7)*(1-F25)*(1-F9)
B72: Revenue collected · month 21 | C72: ₹ | D72: =MAX(D8,D6*Seasonality!$C$57*D7)*(1-D25)*(1-D9) | E72: =MAX(E8,E6*Seasonality!$C$57*E7)*(1-E25)*(1-E9) | F72: =MAX(F8,F6*Seasonality!$C$57*F7)*(1-F25)*(1-F9)
B73: Revenue collected · month 22 | C73: ₹ | D73: =MAX(D8,D6*Seasonality!$C$58*D7)*(1-D25)*(1-D9) | E73: =MAX(E8,E6*Seasonality!$C$58*E7)*(1-E25)*(1-E9) | F73: =MAX(F8,F6*Seasonality!$C$58*F7)*(1-F25)*(1-F9)
B74: Revenue collected · month 23 | C74: ₹ | D74: =MAX(D8,D6*Seasonality!$C$59*D7)*(1-D25)*(1-D9) | E74: =MAX(E8,E6*Seasonality!$C$59*E7)*(1-E25)*(1-E9) | F74: =MAX(F8,F6*Seasonality!$C$59*F7)*(1-F25)*(1-F9)
B75: Revenue collected · month 24 | C75: ₹ | D75: =MAX(D8,D6*Seasonality!$C$60*D7)*(1-D25)*(1-D9) | E75: =MAX(E8,E6*Seasonality!$C$60*E7)*(1-E25)*(1-E9) | F75: =MAX(F8,F6*Seasonality!$C$60*F7)*(1-F25)*(1-F9)
B76: Revenue collected · month 25 | C76: ₹ | D76: =MAX(D8,D6*Seasonality!$C$61*D7)*(1-D25)*(1-D9) | E76: =MAX(E8,E6*Seasonality!$C$61*E7)*(1-E25)*(1-E9) | F76: =MAX(F8,F6*Seasonality!$C$61*F7)*(1-F25)*(1-F9)
B77: Revenue collected · month 26 | C77: ₹ | D77: =MAX(D8,D6*Seasonality!$C$62*D7)*(1-D25)*(1-D9) | E77: =MAX(E8,E6*Seasonality!$C$62*E7)*(1-E25)*(1-E9) | F77: =MAX(F8,F6*Seasonality!$C$62*F7)*(1-F25)*(1-F9)
B78: Revenue collected · month 27 | C78: ₹ | D78: =MAX(D8,D6*Seasonality!$C$63*D7)*(1-D25)*(1-D9) | E78: =MAX(E8,E6*Seasonality!$C$63*E7)*(1-E25)*(1-E9) | F78: =MAX(F8,F6*Seasonality!$C$63*F7)*(1-F25)*(1-F9)
B79: Revenue collected · month 28 | C79: ₹ | D79: =MAX(D8,D6*Seasonality!$C$64*D7)*(1-D25)*(1-D9) | E79: =MAX(E8,E6*Seasonality!$C$64*E7)*(1-E25)*(1-E9) | F79: =MAX(F8,F6*Seasonality!$C$64*F7)*(1-F25)*(1-F9)
B80: Revenue collected · month 29 | C80: ₹ | D80: =MAX(D8,D6*Seasonality!$C$65*D7)*(1-D25)*(1-D9) | E80: =MAX(E8,E6*Seasonality!$C$65*E7)*(1-E25)*(1-E9) | F80: =MAX(F8,F6*Seasonality!$C$65*F7)*(1-F25)*(1-F9)
B81: Revenue collected · month 30 | C81: ₹ | D81: =MAX(D8,D6*Seasonality!$C$66*D7)*(1-D25)*(1-D9) | E81: =MAX(E8,E6*Seasonality!$C$66*E7)*(1-E25)*(1-E9) | F81: =MAX(F8,F6*Seasonality!$C$66*F7)*(1-F25)*(1-F9)
B82: Revenue collected · month 31 | C82: ₹ | D82: =MAX(D8,D6*Seasonality!$C$67*D7)*(1-D25)*(1-D9) | E82: =MAX(E8,E6*Seasonality!$C$67*E7)*(1-E25)*(1-E9) | F82: =MAX(F8,F6*Seasonality!$C$67*F7)*(1-F25)*(1-F9)
B83: Revenue collected · month 32 | C83: ₹ | D83: =MAX(D8,D6*Seasonality!$C$68*D7)*(1-D25)*(1-D9) | E83: =MAX(E8,E6*Seasonality!$C$68*E7)*(1-E25)*(1-E9) | F83: =MAX(F8,F6*Seasonality!$C$68*F7)*(1-F25)*(1-F9)
B84: Revenue collected · month 33 | C84: ₹ | D84: =MAX(D8,D6*Seasonality!$C$69*D7)*(1-D25)*(1-D9) | E84: =MAX(E8,E6*Seasonality!$C$69*E7)*(1-E25)*(1-E9) | F84: =MAX(F8,F6*Seasonality!$C$69*F7)*(1-F25)*(1-F9)
B85: Revenue collected · month 34 | C85: ₹ | D85: =MAX(D8,D6*Seasonality!$C$70*D7)*(1-D25)*(1-D9) | E85: =MAX(E8,E6*Seasonality!$C$70*E7)*(1-E25)*(1-E9) | F85: =MAX(F8,F6*Seasonality!$C$70*F7)*(1-F25)*(1-F9)
B86: Revenue collected · month 35 | C86: ₹ | D86: =MAX(D8,D6*Seasonality!$C$71*D7)*(1-D25)*(1-D9) | E86: =MAX(E8,E6*Seasonality!$C$71*E7)*(1-E25)*(1-E9) | F86: =MAX(F8,F6*Seasonality!$C$71*F7)*(1-F25)*(1-F9)
B87: Revenue collected · month 36 | C87: ₹ | D87: =MAX(D8,D6*Seasonality!$C$72*D7)*(1-D25)*(1-D9) | E87: =MAX(E8,E6*Seasonality!$C$72*E7)*(1-E25)*(1-E9) | F87: =MAX(F8,F6*Seasonality!$C$72*F7)*(1-F25)*(1-F9)
B88: Revenue collected · month 37 | C88: ₹ | D88: =MAX(D8,D6*Seasonality!$C$73*D7)*(1-D25)*(1-D9) | E88: =MAX(E8,E6*Seasonality!$C$73*E7)*(1-E25)*(1-E9) | F88: =MAX(F8,F6*Seasonality!$C$73*F7)*(1-F25)*(1-F9)
B89: Revenue collected · month 38 | C89: ₹ | D89: =MAX(D8,D6*Seasonality!$C$74*D7)*(1-D25)*(1-D9) | E89: =MAX(E8,E6*Seasonality!$C$74*E7)*(1-E25)*(1-E9) | F89: =MAX(F8,F6*Seasonality!$C$74*F7)*(1-F25)*(1-F9)
B90: Revenue collected · month 39 | C90: ₹ | D90: =MAX(D8,D6*Seasonality!$C$75*D7)*(1-D25)*(1-D9) | E90: =MAX(E8,E6*Seasonality!$C$75*E7)*(1-E25)*(1-E9) | F90: =MAX(F8,F6*Seasonality!$C$75*F7)*(1-F25)*(1-F9)
B91: Revenue collected · month 40 | C91: ₹ | D91: =MAX(D8,D6*Seasonality!$C$76*D7)*(1-D25)*(1-D9) | E91: =MAX(E8,E6*Seasonality!$C$76*E7)*(1-E25)*(1-E9) | F91: =MAX(F8,F6*Seasonality!$C$76*F7)*(1-F25)*(1-F9)
B92: Revenue collected · month 41 | C92: ₹ | D92: =MAX(D8,D6*Seasonality!$C$77*D7)*(1-D25)*(1-D9) | E92: =MAX(E8,E6*Seasonality!$C$77*E7)*(1-E25)*(1-E9) | F92: =MAX(F8,F6*Seasonality!$C$77*F7)*(1-F25)*(1-F9)
B93: Revenue collected · month 42 | C93: ₹ | D93: =MAX(D8,D6*Seasonality!$C$78*D7)*(1-D25)*(1-D9) | E93: =MAX(E8,E6*Seasonality!$C$78*E7)*(1-E25)*(1-E9) | F93: =MAX(F8,F6*Seasonality!$C$78*F7)*(1-F25)*(1-F9)
B94: Revenue collected · month 43 | C94: ₹ | D94: =MAX(D8,D6*Seasonality!$C$79*D7)*(1-D25)*(1-D9) | E94: =MAX(E8,E6*Seasonality!$C$79*E7)*(1-E25)*(1-E9) | F94: =MAX(F8,F6*Seasonality!$C$79*F7)*(1-F25)*(1-F9)
B95: Revenue collected · month 44 | C95: ₹ | D95: =MAX(D8,D6*Seasonality!$C$80*D7)*(1-D25)*(1-D9) | E95: =MAX(E8,E6*Seasonality!$C$80*E7)*(1-E25)*(1-E9) | F95: =MAX(F8,F6*Seasonality!$C$80*F7)*(1-F25)*(1-F9)
B96: Revenue collected · month 45 | C96: ₹ | D96: =MAX(D8,D6*Seasonality!$C$81*D7)*(1-D25)*(1-D9) | E96: =MAX(E8,E6*Seasonality!$C$81*E7)*(1-E25)*(1-E9) | F96: =MAX(F8,F6*Seasonality!$C$81*F7)*(1-F25)*(1-F9)
B97: Revenue collected · month 46 | C97: ₹ | D97: =MAX(D8,D6*Seasonality!$C$82*D7)*(1-D25)*(1-D9) | E97: =MAX(E8,E6*Seasonality!$C$82*E7)*(1-E25)*(1-E9) | F97: =MAX(F8,F6*Seasonality!$C$82*F7)*(1-F25)*(1-F9)
B98: Revenue collected · month 47 | C98: ₹ | D98: =MAX(D8,D6*Seasonality!$C$83*D7)*(1-D25)*(1-D9) | E98: =MAX(E8,E6*Seasonality!$C$83*E7)*(1-E25)*(1-E9) | F98: =MAX(F8,F6*Seasonality!$C$83*F7)*(1-F25)*(1-F9)
B99: Revenue collected · month 48 | C99: ₹ | D99: =MAX(D8,D6*Seasonality!$C$84*D7)*(1-D25)*(1-D9) | E99: =MAX(E8,E6*Seasonality!$C$84*E7)*(1-E25)*(1-E9) | F99: =MAX(F8,F6*Seasonality!$C$84*F7)*(1-F25)*(1-F9)
B100: Revenue collected · month 49 | C100: ₹ | D100: =MAX(D8,D6*Seasonality!$C$85*D7)*(1-D25)*(1-D9) | E100: =MAX(E8,E6*Seasonality!$C$85*E7)*(1-E25)*(1-E9) | F100: =MAX(F8,F6*Seasonality!$C$85*F7)*(1-F25)*(1-F9)
B101: Revenue collected · month 50 | C101: ₹ | D101: =MAX(D8,D6*Seasonality!$C$86*D7)*(1-D25)*(1-D9) | E101: =MAX(E8,E6*Seasonality!$C$86*E7)*(1-E25)*(1-E9) | F101: =MAX(F8,F6*Seasonality!$C$86*F7)*(1-F25)*(1-F9)
...

Sheet Scenarios
A1: Scenarios — honest model vs the guide's naive model
A2: Bear / Base / Bull are always shown side by side, whatever the Cover selector says. Mid institute = 400 students (the guide's example).
A4: Metric (Mid institute) | B4: Unit | C4: Guide (naive) | D4: Bear | E4: Base | F4: Bull
A5: Effective dropout reduction | B5: % | C5: =Assumptions!$E$86 | D5: =Engine!$H$81 | E5: =Engine!$K$81 | F5: =Engine!$N$81
A6: Dropouts prevented per year | B6: students | C6: =Institute_ROI!$E$65 | D6: =Engine!$H$82 | E6: =Engine!$K$82 | F6: =Engine!$N$82
A7: Fee lost per dropout | B7: ₹ | C7: =G_RemainingFee | D7: =Engine!$H$77 | E7: =Engine!$K$77 | F7: =Engine!$N$77
A8: Fees retained per year | B8: ₹/yr | C8: =Institute_ROI!$E$66 | D8: =Engine!$H$84 | E8: =Engine!$K$84 | F8: =Engine!$N$84
A9: Total value to institute | B9: ₹/yr | C9: =Institute_ROI!$E$66 | D9: =Engine!$H$87 | E9: =Engine!$K$87 | F9: =Engine!$N$87
A10: Total cost to institute (fee + GST + mentor time) | B10: ₹/yr | C10: =Institute_ROI!$E$67 | D10: =Engine!$H$92 | E10: =Engine!$K$92 | F10: =Engine!$N$92
A11: Institute ROI | B11: x | C11: =Institute_ROI!$E$68 | D11: =Engine!$H$94 | E11: =Engine!$K$94 | F11: =Engine!$N$94
A12: Fees-only ROI | B12: x | C12: =Institute_ROI!$E$68 | D12: =Engine!$H$95 | E12: =Engine!$K$95 | F12: =Engine!$N$95
A13: Break-even students saved per year | B13: students | C13: =Institute_ROI!$E$69 | D13: =Engine!$H$96 | E13: =Engine!$K$96 | F13: =Engine!$N$96
A14: Avg monthly revenue per institute | B14: ₹/month | C14: =Unit_Econ!$I$5 | D14: =Engine!$H$103 | E14: =Engine!$K$103 | F14: =Engine!$N$103
A15: Avg monthly contribution | B15: ₹/month | C15: =Unit_Econ!$I$6 | D15: =Engine!$H$107 | E15: =Engine!$K$107 | F15: =Engine!$N$107
A16: Fully loaded acquisition cost | B16: ₹ | C16: =Unit_Econ!$I$7 | D16: =Engine!$H$113 | E16: =Engine!$K$113 | F16: =Engine!$N$113
A17: Annual logo retention | B17: % | C17: =(1-G_Churn)^12 | D17: =Engine!$H$116 | E17: =Engine!$K$116 | F17: =Engine!$N$116
A18: LTV | B18: ₹ | C18: =Unit_Econ!$I$9 | D18: =Engine!$H$118 | E18: =Engine!$K$118 | F18: =Engine!$N$118
A19: LTV ÷ acquisition cost | B19: x | C19: =Unit_Econ!$I$10 | D19: =Engine!$H$119 | E19: =Engine!$K$119 | F19: =Engine!$N$119
A20: Payback | B20: months | C20: =Unit_Econ!$I$8 | D20: =Engine!$H$120 | E20: =Engine!$K$120 | F20: =Engine!$N$120
A23: By segment
A24: Institute ROI | D24: Bear | E24: Base | F24: Bull
A25: Small (<250) | D25: =Engine!$G$94 | E25: =Engine!$J$94 | F25: =Engine!$M$94
A26: Mid (250-800) | D26: =Engine!$H$94 | E26: =Engine!$K$94 | F26: =Engine!$N$94
A27: Large (>800) | D27: =Engine!$I$94 | E27: =Engine!$L$94 | F27: =Engine!$O$94
A30: LTV ÷ acquisition cost | D30: Bear | E30: Base | F30: Bull
A31: Small (<250) | D31: =Engine!$G$119 | E31: =Engine!$J$119 | F31: =Engine!$M$119
A32: Mid (250-800) | D32: =Engine!$H$119 | E32: =Engine!$K$119 | F32: =Engine!$N$119
A33: Large (>800) | D33: =Engine!$I$119 | E33: =Engine!$L$119 | F33: =Engine!$O$119
A36: Payback (months) | D36: Bear | E36: Base | F36: Bull
A37: Small (<250) | D37: =Engine!$G$120 | E37: =Engine!$J$120 | F37: =Engine!$M$120
A38: Mid (250-800) | D38: =Engine!$H$120 | E38: =Engine!$K$120 | F38: =Engine!$N$120
A39: Large (>800) | D39: =Engine!$I$120 | E39: =Engine!$L$120 | F39: =Engine!$O$120

Sheet Sensitivity
A1: Sensitivity — what actually moves the answer
A2: Tornado: one input at a time moved to its Bear / Bull value, all else Base (Mid institute). Grids follow the live scenario.
A4: Input | B4: Bear value | C4: Bull value | D4: ROI @ Bear | E4: ROI @ Bull | F4: ROI swing | G4: LTV/CAC @ Bear | H4: LTV/CAC @ Bull | I4: LTV/CAC swing
A5: BASE (all inputs Base) | D5: =Engine!$K$94 | E5: =Engine!$K$94 | G5: =Engine!$K$119 | H5: =Engine!$K$119
A6: List price per active student per month | B6: =Assumptions!$D$38 | C6: =Assumptions!$F$38 | D6: =Engine!$P$94 | E6: =Engine!$Q$94 | F6: =ABS(E6-D6) | G6: =Engine!$P$119 | H6: =Engine!$Q$119 | I6: =ABS(H6-G6)
A7: Annual fee per student - Mid | B7: =Assumptions!$D$10 | C7: =Assumptions!$F$10 | D7: =Engine!$R$94 | E7: =Engine!$S$94 | F7: =ABS(E7-D7) | G7: =Engine!$R$119 | H7: =Engine!$S$119 | I7: =ABS(H7-G7)
A8: Mid-session dropout/default rate | B8: =Assumptions!$D$16 | C8: =Assumptions!$F$16 | D8: =Engine!$T$94 | E8: =Engine!$U$94 | F8: =ABS(E8-D8) | G8: =Engine!$T$119 | H8: =Engine!$U$119 | I8: =ABS(H8-G8)
A9: Share of students paying full fee upfront | B9: =Assumptions!$D$17 | C9: =Assumptions!$F$17 | D9: =Engine!$V$94 | E9: =Engine!$W$94 | F9: =ABS(E9-D9) | G9: =Engine!$V$119 | H9: =Engine!$W$119 | I9: =ABS(H9-G9)
A10: Instalments per year for non-upfront payers | B10: =Assumptions!$D$18 | C10: =Assumptions!$F$18 | D10: =Engine!$X$94 | E10: =Engine!$Y$94 | F10: =ABS(E10-D10) | G10: =Engine!$X$119 | H10: =Engine!$Y$119 | I10: =ABS(H10-G10)
A11: Dropout reduction among flagged students given outreach (RCT) | B11: =Assumptions!$D$28 | C11: =Assumptions!$F$28 | D11: =Engine!$Z$94 | E11: =Engine!$AA$94 | F11: =ABS(E11-D11) | G11: =Engine!$Z$119 | H11: =Engine!$AA$119 | I11: =ABS(H11-G11)
A12: Model recall on minors (academic-support + rules) | B12: =Assumptions!$D$24 | C12: =Assumptions!$F$24 | D12: =Engine!$AB$94 | E12: =Engine!$AC$94 | F12: =ABS(E12-D12) | G12: =Engine!$AB$119 | H12: =Engine!$AC$119 | I12: =ABS(H12-G12)
A13: Months before the model can flag (no test data yet) | B13: =Assumptions!$D$21 | C13: =Assumptions!$F$21 | D13: =Engine!$AD$94 | E13: =Engine!$AE$94 | F13: =ABS(E13-D13) | G13: =Engine!$AD$119 | H13: =Engine!$AE$119 | I13: =ABS(H13-G13)
A14: Admissions uplift next session from results/parent trust | B14: =Assumptions!$D$29 | C14: =Assumptions!$F$29 | D14: =Engine!$AF$94 | E14: =Engine!$AG$94 | F14: =ABS(E14-D14) | G14: =Engine!$AF$119 | H14: =Engine!$AG$119 | I14: =ABS(H14-G14)
A15: Share of institutes that reclaim our GST as input credit | B15: =Assumptions!$D$36 | C15: =Assumptions!$F$36 | D15: =Engine!$AH$94 | E15: =Engine!$AI$94 | F15: =ABS(E15-D15) | G15: =Engine!$AH$119 | H15: =Engine!$AI$119 | I15: =ABS(H15-G15)
A16: Monthly logo churn for monthly payers | B16: =Assumptions!$D$72 | C16: =Assumptions!$F$72 | D16: =Engine!$AJ$94 | E16: =Engine!$AK$94 | F16: =ABS(E16-D16) | G16: =Engine!$AJ$119 | H16: =Engine!$AK$119 | I16: =ABS(H16-G16)
A17: Non-renewal at session end (annual) | B17: =Assumptions!$D$73 | C17: =Assumptions!$F$73 | D17: =Engine!$AL$94 | E17: =Engine!$AM$94 | F17: =ABS(E17-D17) | G17: =Engine!$AL$119 | H17: =Engine!$AM$119 | I17: =ABS(H17-G17)
A18: Pilot-to-paid conversion | B18: =Assumptions!$D$67 | C18: =Assumptions!$F$67 | D18: =Engine!$AN$94 | E18: =Engine!$AO$94 | F18: =ABS(E18-D18) | G18: =Engine!$AN$119 | H18: =Engine!$AO$119 | I18: =ABS(H18-G18)
A19: Pilots started per rep per month (yearly avg) | B19: =Assumptions!$D$66 | C19: =Assumptions!$F$66 | D19: =Engine!$AP$94 | E19: =Engine!$AQ$94 | F19: =ABS(E19-D19) | G19: =Engine!$AP$119 | H19: =Engine!$AQ$119 | I19: =ABS(H19-G19)
A22: Grid 1 — Institute ROI (Mid, live scenario): list price × effective dropout reduction
A23: Rows: effective reduction · Columns: list price ₹/student/month (blue = grid points)
B24: 20 | C24: 30 | D24: 40 | E24: 50 | F24: 60 | G24: 80
A25: 0.05 | B25: =(Institute_ROI!$E$31*Institute_ROI!$E$39*$A25+Institute_ROI!$E$42+Institute_ROI!$E$43)/(SUMPRODUCT((Institute_ROI!$E$6*Season_Idx*B$24>Institute_ROI!$E$26)*(Institute_ROI!$E$6*Season_Idx*B$24)+(Institute_ROI!$E$6*Season_Idx*B$24<=Institute_ROI!$E$26)*Institute_ROI!$E$26)*(1-Institute_ROI!$E$29)*(1+GST*(1-ITCShare))+Institute_ROI!$E$49) | C25: =(Institute_ROI!$E$31*Institute_ROI!$E$39*$A25+Institute_ROI!$E$42+Institute_ROI!$E$43)/(SUMPRODUCT((Institute_ROI!$E$6*Season_Idx*C$24>Institute_ROI!$E$26)*(Institute_ROI!$E$6*Season_Idx*C$24)+(Institute_ROI!$E$6*Season_Idx*C$24<=Institute_ROI!$E$26)*Institute_ROI!$E$26)*(1-Institute_ROI!$E$29)*(1+GST*(1-ITCShare))+Institute_ROI!$E$49) | D25: =(Institute_ROI!$E$31*Institute_ROI!$E$39*$A25+Institute_ROI!$E$42+Institute_ROI!$E$43)/(SUMPRODUCT((Institute_ROI!$E$6*Season_Idx*D$24>Institute_ROI!$E$26)*(Institute_ROI!$E$6*Season_Idx*D$24)+(Institute_ROI!$E$6*Season_Idx*D$24<=Institute_ROI!$E$26)*Institute_ROI!$E$26)*(1-Institute_ROI!$E$29)*(1+GST*(1-ITCShare))+Institute_ROI!$E$49) | E25: =(Institute_ROI!$E$31*Institute_ROI!$E$39*$A25+Institute_ROI!$E$42+Institute_ROI!$E$43)/(SUMPRODUCT((Institute_ROI!$E$6*Season_Idx*E$24>Institute_ROI!$E$26)*(Institute_ROI!$E$6*Season_Idx*E$24)+(Institute_ROI!$E$6*Season_Idx*E$24<=Institute_ROI!$E$26)*Institute_ROI!$E$26)*(1-Institute_ROI!$E$29)*(1+GST*(1-ITCShare))+Institute_ROI!$E$49) | F25: =(Institute_ROI!$E$31*Institute_ROI!$E$39*$A25+Institute_ROI!$E$42+Institute_ROI!$E$43)/(SUMPRODUCT((Institute_ROI!$E$6*Season_Idx*F$24>Institute_ROI!$E$26)*(Institute_ROI!$E$6*Season_Idx*F$24)+(Institute_ROI!$E$6*Season_Idx*F$24<=Institute_ROI!$E$26)*Institute_ROI!$E$26)*(1-Institute_ROI!$E$29)*(1+GST*(1-ITCShare))+Institute_ROI!$E$49) | G25: =(Institute_ROI!$E$31*Institute_ROI!$E$39*$A25+Institute_ROI!$E$42+Institute_ROI!$E$43)/(SUMPRODUCT((Institute_ROI!$E$6*Season_Idx*G$24>Institute_ROI!$E$26)*(Institute_ROI!$E$6*Season_Idx*G$24)+(Institute_ROI!$E$6*Season_Idx*G$24<=Institute_ROI!$E$26)*Institute_ROI!$E$26)*(1-Institute_ROI!$E$29)*(1+GST*(1-ITCShare))+Institute_ROI!$E$49)
A26: 0.08 | B26: =(Institute_ROI!$E$31*Institute_ROI!$E$39*$A26+Institute_ROI!$E$42+Institute_ROI!$E$43)/(SUMPRODUCT((Institute_ROI!$E$6*Season_Idx*B$24>Institute_ROI!$E$26)*(Institute_ROI!$E$6*Season_Idx*B$24)+(Institute_ROI!$E$6*Season_Idx*B$24<=Institute_ROI!$E$26)*Institute_ROI!$E$26)*(1-Institute_ROI!$E$29)*(1+GST*(1-ITCShare))+Institute_ROI!$E$49) | C26: =(Institute_ROI!$E$31*Institute_ROI!$E$39*$A26+Institute_ROI!$E$42+Institute_ROI!$E$43)/(SUMPRODUCT((Institute_ROI!$E$6*Season_Idx*C$24>Institute_ROI!$E$26)*(Institute_ROI!$E$6*Season_Idx*C$24)+(Institute_ROI!$E$6*Season_Idx*C$24<=Institute_ROI!$E$26)*Institute_ROI!$E$26)*(1-Institute_ROI!$E$29)*(1+GST*(1-ITCShare))+Institute_ROI!$E$49) | D26: =(Institute_ROI!$E$31*Institute_ROI!$E$39*$A26+Institute_ROI!$E$42+Institute_ROI!$E$43)/(SUMPRODUCT((Institute_ROI!$E$6*Season_Idx*D$24>Institute_ROI!$E$26)*(Institute_ROI!$E$6*Season_Idx*D$24)+(Institute_ROI!$E$6*Season_Idx*D$24<=Institute_ROI!$E$26)*Institute_ROI!$E$26)*(1-Institute_ROI!$E$29)*(1+GST*(1-ITCShare))+Institute_ROI!$E$49) | E26: =(Institute_ROI!$E$31*Institute_ROI!$E$39*$A26+Institute_ROI!$E$42+Institute_ROI!$E$43)/(SUMPRODUCT((Institute_ROI!$E$6*Season_Idx*E$24>Institute_ROI!$E$26)*(Institute_ROI!$E$6*Season_Idx*E$24)+(Institute_ROI!$E$6*Season_Idx*E$24<=Institute_ROI!$E$26)*Institute_ROI!$E$26)*(1-Institute_ROI!$E$29)*(1+GST*(1-ITCShare))+Institute_ROI!$E$49) | F26: =(Institute_ROI!$E$31*Institute_ROI!$E$39*$A26+Institute_ROI!$E$42+Institute_ROI!$E$43)/(SUMPRODUCT((Institute_ROI!$E$6*Season_Idx*F$24>Institute_ROI!$E$26)*(Institute_ROI!$E$6*Season_Idx*F$24)+(Institute_ROI!$E$6*Season_Idx*F$24<=Institute_ROI!$E$26)*Institute_ROI!$E$26)*(1-Institute_ROI!$E$29)*(1+GST*(1-ITCShare))+Institute_ROI!$E$49) | G26: =(Institute_ROI!$E$31*Institute_ROI!$E$39*$A26+Institute_ROI!$E$42+Institute_ROI!$E$43)/(SUMPRODUCT((Institute_ROI!$E$6*Season_Idx*G$24>Institute_ROI!$E$26)*(Institute_ROI!$E$6*Season_Idx*G$24)+(Institute_ROI!$E$6*Season_Idx*G$24<=Institute_ROI!$E$26)*Institute_ROI!$E$26)*(1-Institute_ROI!$E$29)*(1+GST*(1-ITCShare))+Institute_ROI!$E$49)
A27: 0.11 | B27: =(Institute_ROI!$E$31*Institute_ROI!$E$39*$A27+Institute_ROI!$E$42+Institute_ROI!$E$43)/(SUMPRODUCT((Institute_ROI!$E$6*Season_Idx*B$24>Institute_ROI!$E$26)*(Institute_ROI!$E$6*Season_Idx*B$24)+(Institute_ROI!$E$6*Season_Idx*B$24<=Institute_ROI!$E$26)*Institute_ROI!$E$26)*(1-Institute_ROI!$E$29)*(1+GST*(1-ITCShare))+Institute_ROI!$E$49) | C27: =(Institute_ROI!$E$31*Institute_ROI!$E$39*$A27+Institute_ROI!$E$42+Institute_ROI!$E$43)/(SUMPRODUCT((Institute_ROI!$E$6*Season_Idx*C$24>Institute_ROI!$E$26)*(Institute_ROI!$E$6*Season_Idx*C$24)+(Institute_ROI!$E$6*Season_Idx*C$24<=Institute_ROI!$E$26)*Institute_ROI!$E$26)*(1-Institute_ROI!$E$29)*(1+GST*(1-ITCShare))+Institute_ROI!$E$49) | D27: =(Institute_ROI!$E$31*Institute_ROI!$E$39*$A27+Institute_ROI!$E$42+Institute_ROI!$E$43)/(SUMPRODUCT((Institute_ROI!$E$6*Season_Idx*D$24>Institute_ROI!$E$26)*(Institute_ROI!$E$6*Season_Idx*D$24)+(Institute_ROI!$E$6*Season_Idx*D$24<=Institute_ROI!$E$26)*Institute_ROI!$E$26)*(1-Institute_ROI!$E$29)*(1+GST*(1-ITCShare))+Institute_ROI!$E$49) | E27: =(Institute_ROI!$E$31*Institute_ROI!$E$39*$A27+Institute_ROI!$E$42+Institute_ROI!$E$43)/(SUMPRODUCT((Institute_ROI!$E$6*Season_Idx*E$24>Institute_ROI!$E$26)*(Institute_ROI!$E$6*Season_Idx*E$24)+(Institute_ROI!$E$6*Season_Idx*E$24<=Institute_ROI!$E$26)*Institute_ROI!$E$26)*(1-Institute_ROI!$E$29)*(1+GST*(1-ITCShare))+Institute_ROI!$E$49) | F27: =(Institute_ROI!$E$31*Institute_ROI!$E$39*$A27+Institute_ROI!$E$42+Institute_ROI!$E$43)/(SUMPRODUCT((Institute_ROI!$E$6*Season_Idx*F$24>Institute_ROI!$E$26)*(Institute_ROI!$E$6*Season_Idx*F$24)+(Institute_ROI!$E$6*Season_Idx*F$24<=Institute_ROI!$E$26)*Institute_ROI!$E$26)*(1-Institute_ROI!$E$29)*(1+GST*(1-ITCShare))+Institute_ROI!$E$49) | G27: =(Institute_ROI!$E$31*Institute_ROI!$E$39*$A27+Institute_ROI!$E$42+Institute_ROI!$E$43)/(SUMPRODUCT((Institute_ROI!$E$6*Season_Idx*G$24>Institute_ROI!$E$26)*(Institute_ROI!$E$6*Season_Idx*G$24)+(Institute_ROI!$E$6*Season_Idx*G$24<=Institute_ROI!$E$26)*Institute_ROI!$E$26)*(1-Institute_ROI!$E$29)*(1+GST*(1-ITCShare))+Institute_ROI!$E$49)
A28: 0.15 | B28: =(Institute_ROI!$E$31*Institute_ROI!$E$39*$A28+Institute_ROI!$E$42+Institute_ROI!$E$43)/(SUMPRODUCT((Institute_ROI!$E$6*Season_Idx*B$24>Institute_ROI!$E$26)*(Institute_ROI!$E$6*Season_Idx*B$24)+(Institute_ROI!$E$6*Season_Idx*B$24<=Institute_ROI!$E$26)*Institute_ROI!$E$26)*(1-Institute_ROI!$E$29)*(1+GST*(1-ITCShare))+Institute_ROI!$E$49) | C28: =(Institute_ROI!$E$31*Institute_ROI!$E$39*$A28+Institute_ROI!$E$42+Institute_ROI!$E$43)/(SUMPRODUCT((Institute_ROI!$E$6*Season_Idx*C$24>Institute_ROI!$E$26)*(Institute_ROI!$E$6*Season_Idx*C$24)+(Institute_ROI!$E$6*Season_Idx*C$24<=Institute_ROI!$E$26)*Institute_ROI!$E$26)*(1-Institute_ROI!$E$29)*(1+GST*(1-ITCShare))+Institute_ROI!$E$49) | D28: =(Institute_ROI!$E$31*Institute_ROI!$E$39*$A28+Institute_ROI!$E$42+Institute_ROI!$E$43)/(SUMPRODUCT((Institute_ROI!$E$6*Season_Idx*D$24>Institute_ROI!$E$26)*(Institute_ROI!$E$6*Season_Idx*D$24)+(Institute_ROI!$E$6*Season_Idx*D$24<=Institute_ROI!$E$26)*Institute_ROI!$E$26)*(1-Institute_ROI!$E$29)*(1+GST*(1-ITCShare))+Institute_ROI!$E$49) | E28: =(Institute_ROI!$E$31*Institute_ROI!$E$39*$A28+Institute_ROI!$E$42+Institute_ROI!$E$43)/(SUMPRODUCT((Institute_ROI!$E$6*Season_Idx*E$24>Institute_ROI!$E$26)*(Institute_ROI!$E$6*Season_Idx*E$24)+(Institute_ROI!$E$6*Season_Idx*E$24<=Institute_ROI!$E$26)*Institute_ROI!$E$26)*(1-Institute_ROI!$E$29)*(1+GST*(1-ITCShare))+Institute_ROI!$E$49) | F28: =(Institute_ROI!$E$31*Institute_ROI!$E$39*$A28+Institute_ROI!$E$42+Institute_ROI!$E$43)/(SUMPRODUCT((Institute_ROI!$E$6*Season_Idx*F$24>Institute_ROI!$E$26)*(Institute_ROI!$E$6*Season_Idx*F$24)+(Institute_ROI!$E$6*Season_Idx*F$24<=Institute_ROI!$E$26)*Institute_ROI!$E$26)*(1-Institute_ROI!$E$29)*(1+GST*(1-ITCShare))+Institute_ROI!$E$49) | G28: =(Institute_ROI!$E$31*Institute_ROI!$E$39*$A28+Institute_ROI!$E$42+Institute_ROI!$E$43)/(SUMPRODUCT((Institute_ROI!$E$6*Season_Idx*G$24>Institute_ROI!$E$26)*(Institute_ROI!$E$6*Season_Idx*G$24)+(Institute_ROI!$E$6*Season_Idx*G$24<=Institute_ROI!$E$26)*Institute_ROI!$E$26)*(1-Institute_ROI!$E$29)*(1+GST*(1-ITCShare))+Institute_ROI!$E$49)
A29: 0.2 | B29: =(Institute_ROI!$E$31*Institute_ROI!$E$39*$A29+Institute_ROI!$E$42+Institute_ROI!$E$43)/(SUMPRODUCT((Institute_ROI!$E$6*Season_Idx*B$24>Institute_ROI!$E$26)*(Institute_ROI!$E$6*Season_Idx*B$24)+(Institute_ROI!$E$6*Season_Idx*B$24<=Institute_ROI!$E$26)*Institute_ROI!$E$26)*(1-Institute_ROI!$E$29)*(1+GST*(1-ITCShare))+Institute_ROI!$E$49) | C29: =(Institute_ROI!$E$31*Institute_ROI!$E$39*$A29+Institute_ROI!$E$42+Institute_ROI!$E$43)/(SUMPRODUCT((Institute_ROI!$E$6*Season_Idx*C$24>Institute_ROI!$E$26)*(Institute_ROI!$E$6*Season_Idx*C$24)+(Institute_ROI!$E$6*Season_Idx*C$24<=Institute_ROI!$E$26)*Institute_ROI!$E$26)*(1-Institute_ROI!$E$29)*(1+GST*(1-ITCShare))+Institute_ROI!$E$49) | D29: =(Institute_ROI!$E$31*Institute_ROI!$E$39*$A29+Institute_ROI!$E$42+Institute_ROI!$E$43)/(SUMPRODUCT((Institute_ROI!$E$6*Season_Idx*D$24>Institute_ROI!$E$26)*(Institute_ROI!$E$6*Season_Idx*D$24)+(Institute_ROI!$E$6*Season_Idx*D$24<=Institute_ROI!$E$26)*Institute_ROI!$E$26)*(1-Institute_ROI!$E$29)*(1+GST*(1-ITCShare))+Institute_ROI!$E$49) | E29: =(Institute_ROI!$E$31*Institute_ROI!$E$39*$A29+Institute_ROI!$E$42+Institute_ROI!$E$43)/(SUMPRODUCT((Institute_ROI!$E$6*Season_Idx*E$24>Institute_ROI!$E$26)*(Institute_ROI!$E$6*Season_Idx*E$24)+(Institute_ROI!$E$6*Season_Idx*E$24<=Institute_ROI!$E$26)*Institute_ROI!$E$26)*(1-Institute_ROI!$E$29)*(1+GST*(1-ITCShare))+Institute_ROI!$E$49) | F29: =(Institute_ROI!$E$31*Institute_ROI!$E$39*$A29+Institute_ROI!$E$42+Institute_ROI!$E$43)/(SUMPRODUCT((Institute_ROI!$E$6*Season_Idx*F$24>Institute_ROI!$E$26)*(Institute_ROI!$E$6*Season_Idx*F$24)+(Institute_ROI!$E$6*Season_Idx*F$24<=Institute_ROI!$E$26)*Institute_ROI!$E$26)*(1-Institute_ROI!$E$29)*(1+GST*(1-ITCShare))+Institute_ROI!$E$49) | G29: =(Institute_ROI!$E$31*Institute_ROI!$E$39*$A29+Institute_ROI!$E$42+Institute_ROI!$E$43)/(SUMPRODUCT((Institute_ROI!$E$6*Season_Idx*G$24>Institute_ROI!$E$26)*(Institute_ROI!$E$6*Season_Idx*G$24)+(Institute_ROI!$E$6*Season_Idx*G$24<=Institute_ROI!$E$26)*Institute_ROI!$E$26)*(1-Institute_ROI!$E$29)*(1+GST*(1-ITCShare))+Institute_ROI!$E$49)
A30: 0.25 | B30: =(Institute_ROI!$E$31*Institute_ROI!$E$39*$A30+Institute_ROI!$E$42+Institute_ROI!$E$43)/(SUMPRODUCT((Institute_ROI!$E$6*Season_Idx*B$24>Institute_ROI!$E$26)*(Institute_ROI!$E$6*Season_Idx*B$24)+(Institute_ROI!$E$6*Season_Idx*B$24<=Institute_ROI!$E$26)*Institute_ROI!$E$26)*(1-Institute_ROI!$E$29)*(1+GST*(1-ITCShare))+Institute_ROI!$E$49) | C30: =(Institute_ROI!$E$31*Institute_ROI!$E$39*$A30+Institute_ROI!$E$42+Institute_ROI!$E$43)/(SUMPRODUCT((Institute_ROI!$E$6*Season_Idx*C$24>Institute_ROI!$E$26)*(Institute_ROI!$E$6*Season_Idx*C$24)+(Institute_ROI!$E$6*Season_Idx*C$24<=Institute_ROI!$E$26)*Institute_ROI!$E$26)*(1-Institute_ROI!$E$29)*(1+GST*(1-ITCShare))+Institute_ROI!$E$49) | D30: =(Institute_ROI!$E$31*Institute_ROI!$E$39*$A30+Institute_ROI!$E$42+Institute_ROI!$E$43)/(SUMPRODUCT((Institute_ROI!$E$6*Season_Idx*D$24>Institute_ROI!$E$26)*(Institute_ROI!$E$6*Season_Idx*D$24)+(Institute_ROI!$E$6*Season_Idx*D$24<=Institute_ROI!$E$26)*Institute_ROI!$E$26)*(1-Institute_ROI!$E$29)*(1+GST*(1-ITCShare))+Institute_ROI!$E$49) | E30: =(Institute_ROI!$E$31*Institute_ROI!$E$39*$A30+Institute_ROI!$E$42+Institute_ROI!$E$43)/(SUMPRODUCT((Institute_ROI!$E$6*Season_Idx*E$24>Institute_ROI!$E$26)*(Institute_ROI!$E$6*Season_Idx*E$24)+(Institute_ROI!$E$6*Season_Idx*E$24<=Institute_ROI!$E$26)*Institute_ROI!$E$26)*(1-Institute_ROI!$E$29)*(1+GST*(1-ITCShare))+Institute_ROI!$E$49) | F30: =(Institute_ROI!$E$31*Institute_ROI!$E$39*$A30+Institute_ROI!$E$42+Institute_ROI!$E$43)/(SUMPRODUCT((Institute_ROI!$E$6*Season_Idx*F$24>Institute_ROI!$E$26)*(Institute_ROI!$E$6*Season_Idx*F$24)+(Institute_ROI!$E$6*Season_Idx*F$24<=Institute_ROI!$E$26)*Institute_ROI!$E$26)*(1-Institute_ROI!$E$29)*(1+GST*(1-ITCShare))+Institute_ROI!$E$49) | G30: =(Institute_ROI!$E$31*Institute_ROI!$E$39*$A30+Institute_ROI!$E$42+Institute_ROI!$E$43)/(SUMPRODUCT((Institute_ROI!$E$6*Season_Idx*G$24>Institute_ROI!$E$26)*(Institute_ROI!$E$6*Season_Idx*G$24)+(Institute_ROI!$E$6*Season_Idx*G$24<=Institute_ROI!$E$26)*Institute_ROI!$E$26)*(1-Institute_ROI!$E$29)*(1+GST*(1-ITCShare))+Institute_ROI!$E$49)
A33: Grid 2 — LTV ÷ acquisition cost (Mid, live scenario): monthly churn × acquisition cost
A34: Monthly in-season churn (blue) → LTV from Engine | B34: 0.01 | C34: 0.02 | D34: 0.03 | E34: 0.04 | F34: 0.05
A35: LTV at that churn (₹) | B35: =Engine!$AR$118 | C35: =Engine!$AS$118 | D35: =Engine!$AT$118 | E35: =Engine!$AU$118 | F35: =Engine!$AV$118
A36: Acquisition cost ₹ ↓
A37: 15000 | B37: =B$35/$A37 | C37: =C$35/$A37 | D37: =D$35/$A37 | E37: =E$35/$A37 | F37: =F$35/$A37
A38: 25000 | B38: =B$35/$A38 | C38: =C$35/$A38 | D38: =D$35/$A38 | E38: =E$35/$A38 | F38: =F$35/$A38
A39: 35000 | B39: =B$35/$A39 | C39: =C$35/$A39 | D39: =D$35/$A39 | E39: =E$35/$A39 | F39: =F$35/$A39
A40: 50000 | B40: =B$35/$A40 | C40: =C$35/$A40 | D40: =D$35/$A40 | E40: =E$35/$A40 | F40: =F$35/$A40
A41: 75000 | B41: =B$35/$A41 | C41: =C$35/$A41 | D41: =D$35/$A41 | E41: =E$35/$A41 | F41: =F$35/$A41
A43: Reading: ROI < 1.0x red, 1–2x amber, ≥ 2x green. LTV/CAC < 3x red.

Sheet Checks
A1: Checks — any red flag means the model is not safe to quote
A3: Check | B3: Type | C3: Value | D3: Flag (1 = fail)
A4: Scenario selector is 1, 2 or 3 | B4: Error | C4: =Scenario | D4: =IF(OR(Scenario=1,Scenario=2,Scenario=3),0,1)
A5: Dropout timing curve sums to 100% | B5: Error | C5: =SUM(DropTiming) | D5: =IF(ABS(C5-1)<0.0001,0,1)
A6: Percent inputs within 0–100% | B6: Error | C6: =SUM(Assumptions!L5:L93) | D6: =IF(C6=0,0,1)
A7: Live values within Bear–Bull range | B7: Error | C7: =SUM(Assumptions!M5:M93) | D7: =IF(C7=0,0,1)
A8: At least one renewal month (avoids ÷0) | B8: Error | C8: =NRenew | D8: =IF(C8>=1,0,1)
A9: Active-student index between 0 and 1.2 | B9: Error | C9: =SUMPRODUCT((Season_Idx<0)+(Season_Idx>1.2)) | D9: =IF(C9=0,0,1)
A10: Effective reduction ≤ RCT effect (Mid) | B10: Error | C10: =Institute_ROI!E37-InterventionSuccess | D10: =IF(C10<=0.000001,0,1)
A11: Instalments ≥ 1 and ≤ course months | B11: Error | C11: =NInstalments | D11: =IF(AND(C11>=1,C11<=CourseMonths,C11=INT(C11)),0,1)
A12: Engine reproduces Institute_ROI ROI (S) | B12: Error | C12: =ABS(Institute_ROI!D53-Engine!$D$94) | D12: =IF(C12<0.000001,0,1)
A13: Engine reproduces Unit_Econ LTV (S) | B13: Error | C13: =ABS(Unit_Econ!D48-Engine!$D$118) | D13: =IF(C13<0.000001,0,1)
A14: Engine reproduces Institute_ROI ROI (M) | B14: Error | C14: =ABS(Institute_ROI!E53-Engine!$E$94) | D14: =IF(C14<0.000001,0,1)
A15: Engine reproduces Unit_Econ LTV (M) | B15: Error | C15: =ABS(Unit_Econ!E48-Engine!$E$118) | D15: =IF(C15<0.000001,0,1)
A16: Engine reproduces Institute_ROI ROI (L) | B16: Error | C16: =ABS(Institute_ROI!F53-Engine!$F$94) | D16: =IF(C16<0.000001,0,1)
A17: Engine reproduces Unit_Econ LTV (L) | B17: Error | C17: =ABS(Unit_Econ!F48-Engine!$F$118) | D17: =IF(C17<0.000001,0,1)
A18: Survival curve stays within 0–1 (Mid) | B18: Error | C18: =IF(AND(MIN(Unit_Econ!E172:E231)>=0,MAX(Unit_Econ!E172:E231)<=1),0,1) | D18: =C18
A19: Guide ROI reproduces the brief's 2.25x | B19: Error | C19: =Institute_ROI!$E$68 | D19: =IF(ABS(C19-2.25)<0.01,0,1)
A20: WARNING: RCT effect exceeds share of dropouts that are preventable | B20: Warning | C20: =InterventionSuccess-Preventable | D20: =IF(C20<=0,0,1)
A21: WARNING: list price above the highest ERP/LMS anchor found (₹21/student/month) | B21: Warning | C21: =ListPrice | D21: =IF(C21<=CompetitorAnchorHigh,0,1)
A22: WARNING: months with negative contribution (Mid) | B22: Warning | C22: =COUNTIF(Unit_Econ!E112:E171,"<0") | D22: =IF(C22=0,0,1)
A23: WARNING: all-in COGS outside tech band ₹3–10 per student-month | B23: Warning | C23: =COGS_AllIn | D23: =IF(AND(C23>=3,C23<=10),0,1)
A24: WARNING: Mid institute ROI below 1.0x | B24: Warning | C24: =Institute_ROI!E53 | D24: =IF(C24>=1,0,1)
A25: WARNING: Mid LTV/CAC below 3x | B25: Warning | C25: =Unit_Econ!E49 | D25: =IF(C25>=3,0,1)
A26: WARNING: Mid payback above 24 months | B26: Warning | C26: =Unit_Econ!E50 | D26: =IF(C26<=24,0,1)
A28: ERRORS | D28: =SUMIF(B4:B26,"Error",D4:D26)
A29: WARNINGS (honest red flags to discuss, not bugs) | D29: =SUMIF(B4:B26,"Warning",D4:D26)

Sheet Sources
A1: Sources & evidence register
A2: Raw research is in Financial_Model/research/*.md. Anything typed 'Assumption' is unverified — say so on the slide.
A4: Name | B4: Input | C4: Type | D4: Confidence | E4: Source | F4: Note
A5: Students_S | B5: Students per institute - Small | C5: Assumption | D5: M | E5: Case brief range 150-2000; our cut <250 | F5: Segment midpoint
A6: Students_M | B6: Students per institute - Mid | C6: Guide | D6: M | E6: Case brief baseline 400
A7: Students_L | B7: Students per institute - Large | C7: Assumption | D7: M | E7: Case brief range 150-2000; our cut >800
A8: Fee_S | B8: Annual fee per student - Small | C8: Researched | D8: L | E8: R2: Vedantu Gaya 1-yr Rs50-56k; Rupantri Muzaffarpur Rs55-60k; GOAL Patna Rs51-99k (research/R2_R3) | F8: Size-to-fee mapping is our assumption
A9: Fee_M | B9: Annual fee per student - Mid | C9: Researched | D9: L | E9: R2: GOAL Patna 1-yr Rs1.2L; Vedantu Patna Rs95k; Pathshala Lucknow ~Rs82.5k; Vedantu Indore Rs67k | F9: Case brief used Rs60k
A10: Fee_L | B10: Annual fee per student - Large | C10: Researched | D10: M | E10: R2: Udaan Patna Rs1.15-1.25L/yr (own site 2025-27); chains Rs1.1-1.4L (Motion/Allen/Vedantu)
A11: OnboardMult_S | B11: Onboarding cost multiplier - Small | C11: Assumption | D11: L | E11: Fewer batches to migrate
A12: OnboardMult_M | B12: Onboarding cost multiplier - Mid | C12: Structural | D12: H | E12: Reference segment
A13: OnboardMult_L | B13: Onboarding cost multiplier - Large | C13: Assumption | D13: L | E13: More batches and staff to train
A14: DropoutRate | B14: Mid-session dropout/default rate | C14: Researched | D14: L | E14: R3: Coaching Federation of India 'at least 10 per cent of students in every batch' (ThePrint 31-Jul-2025); YourStory May-2026 ~20% offline (unattributed); analogue UDISE+ Cl.9-10 11.5% | F14: Higher = more value to protect (Bull); case brief 8-15%
A15: UpfrontShare | B15: Share of students paying full fee upfront | C15: Assumption | D15: L | E15: R2: not found. Instalments are the norm (Allen 2; PW 3; Aakash several; Rajasthan Act s.6(2)(d) >=4 option) | F15: TECH_PLAN's 35% had no source
A16: NInstalments | B16: Instalments per year for non-upfront payers | C16: Researched | D16: M | E16: R2: Allen 2 (2nd within 45 days); PW 3; Rajasthan Act 16/2025 s.6(2)(d) min. 4 equal | F16: Fewer instalments = cash collected early = less at risk
A17: RefundEnforced | B17: Share of upfront leavers actually refunded pro-rata | C17: Assumption | D17: L | E17: R2: MoE Guidelines 2024 cl.8(iv) and Rajasthan s.13(4) require pro-rata refund within 10 days; MoE is advisory and Allen/Aakash/PW practice is cut-off or no refund | F17: Refunded upfront leavers = fee at risk
A18: CourseMonths | B18: Course length | C18: Guide | D18: H | E18: Case brief ~10 months
A19: BlindMonths | B19: Months before the model can flag (no test data yet) | C19: Assumption | D19: M | E19: Model needs >=1-2 tests; R2: refund windows weeks 1-4 mean early exits are fast | F19: Dropouts in these months cannot be caught
A20: Preventable | B20: Share of dropouts that are preventable (check only) | C20: Assumption | D20: L | E20: R3: reasons listed without shares (interest; family; health; dissatisfaction - ThePrint/CFI) | F20: Upper bound for the RCT effect
A21: MinorShare | B21: Share of students under 18 | C21: Assumption | D21: M | E21: JEE/NEET Class 11-12 are 16-17; droppers 18+ | F21: DPDP s.9(3): minors get academic-support model + rules only
A22: Recall_Minor | B22: Model recall on minors (academic-support + rules) | C22: Assumption | D22: L | E22: TECH_PLAN NB04 rules-only vs ML; replace with metrics.json | F22: At mentor-capacity threshold
A23: Recall_Adult | B23: Model recall on 18+ (full ML) | C23: Public | D23: M | E23: OULAD withdrawal AUC 0.727-0.794 (TECH_PLAN s.24); replace with metrics.json | F23: At mentor-capacity threshold
A24: Precision | B24: Precision of at-risk flag | C24: Assumption | D24: L | E24: Replace with metrics.json | F24: Drives wasted mentor time
A25: ActionRate | B25: Share of flags the institute assigns to outreach | C25: Assumption | D25: L | E25: Mentor capacity; the RCT effect below is already intention-to-treat | F25: Primary research needed
A26: InterventionSuccess | B26: Dropout reduction among flagged students given outreach (RCT) | C26: Researched | D26: M | E26: R4: mean 15.8% / median 12.5% over 8 RCTs - OU outreach RCT 2020 -19%/-35%; Room to Read India -30%; Bergman parent texts; MAAPS/Samata/Oreopoulos nulls (research/R4_R5) | F26: Borrowed from other settings - not our measured effect
A27: AdmissionUplift | B27: Admissions uplift next session from results/parent trust | C27: Assumption | D27: L | E27: No evidence - Bear = 0
A28: MarginExtraAdmission | B28: Institute margin on one extra admission | C28: Assumption | D28: L | E28: Marginal seat in an existing batch
A29: StaffHoursSaved | B29: Staff hours saved per month | C29: Guide | D29: L | E29: Case brief value lever; primary research needed
A30: StaffHourCost | B30: Cost of one admin staff hour | C30: Researched | D30: M | E30: R5: Tier-2 executive pay Rs18-25k/month (Payscale/Indeed Patna) / ~200 h
A31: InterventionMinutes | B31: Mentor minutes per intervention | C31: Assumption | D31: L | E31: Call + meeting with parent
A32: MentorHourCost | B32: Cost of one mentor hour | C32: Assumption | D32: M | E32: Teacher pay ~Rs30-50k/month / ~200 h
A33: GST | B33: GST on SaaS | C33: Researched | D33: M | E33: R6: 18% (heading 9983 residual entry; Notif. 11/2017-CTR as amended by 15/2025-CTR) | F33: SAC code 9983 vs 9984 unconfirmed - ask a CA
A34: ITCShare | B34: Share of institutes that reclaim our GST as input credit | C34: Assumption | D34: L | E34: R6: coaching is taxable at 18%; registration mandatory above Rs20L turnover; CGST s.16(1) gives ITC to registered persons. A 180-student institute turns over ~Rs1 Cr, so legally registered - but cash/informal practice in Tier-3 | F34: Was 'all unregistered' in the naive view
A35: ListPrice | B35: List price per active student per month | C35: Assumption | D35: L | E35: R1: ERP/LMS anchors Rs4-21/student/month at 400 students (Classplus/Fedena/Graphy); no competitor bundles OMR + topic analytics + Hindi WhatsApp | F35: Decision lever - test in interviews (Van Westendorp)
A36: CompetitorAnchor | B36: What institutes already pay for an ERP/LMS | C36: Researched | D36: M | E36: R1: Classplus Starter Rs19999/yr (Capterra); Fedena Standard / Graphy Grow Rs50k/yr; Fedena Ultimate Rs1L/yr - all at 400 students | F36: Reference only - not used in revenue
A37: CompetitorAnchorHigh | B37: Highest priced ERP/LMS anchor found | C37: Researched | D37: M | E37: R1: Fedena Ultimate / Graphy Rise Rs1L/yr at 400 students | F37: Used in a warning check
A38: MinFee | B38: Minimum monthly fee per institute | C38: Assumption | D38: L | E38: FINANCE_PLAN s.3.2
A39: NegotiationDisc | B39: Average negotiated discount off list | C39: Assumption | D39: L | E39: Primary research needed
A40: PrepayUptake | B40: Share of institutes choosing annual prepay | C40: Assumption | D40: L | E40: Coaching institutes are cash-rich in Apr-Jun (admission season) | F40: Prepaid institutes cannot churn mid-session
A41: PrepayDisc | B41: Annual prepay discount | C41: Assumption | D41: M | E41: FINANCE_PLAN s.3.2; R2 shows institutes give 4-6% for upfront fees
A42: BadDebt | B42: Bad debt / uncollected billing | C42: Assumption | D42: M | E42: FINANCE_PLAN s.3.2
A43: GatewayFee | B43: Payment collection cost (blended) | C43: Researched | D43: M | E43: R6: Razorpay 2% + 18% GST = 2.36%; UPI MDR 0.4% on P2M >Rs2000 from 15-Oct-2026; NEFT ~0 | F43: Base assumes half paid by bank transfer
A44: ReportsPerStudentMonth | B44: AI parent reports per student per month | C44: Assumption | D44: M | E44: TECH_PLAN s.11 weekly report; Bear adds alerts
A45: TokensInPerReport | B45: LLM input tokens per report | C45: Assumption | D45: M | E45: TECH_PLAN GenAI design (numbers_json + template)
A46: TokensOutPerReport | B46: LLM output tokens per report | C46: Assumption | D46: M | E46: Bilingual report ~400-600 words
A47: LLMPriceIn | B47: LLM input price (hosted) | C47: Researched | D47: H | E47: R6: Gemini 3.8 Flash from 1-Jan-2027 / Gemini 3.1 Flash-Lite / Claude Haiku 5.5 at Rs95.05/USD (official pricing pages 20-Oct-2026) | F47: Local Ollama = ~0 (prototype)
A48: LLMPriceOut | B48: LLM output price (hosted) | C48: Researched | D48: H | E48: R6: same models as input price
A49: WAMsgsPerStudentMonth | B49: WhatsApp utility messages per student per month | C49: Assumption | D49: M | E49: Weekly report + alerts + fee reminders
A50: WAPricePerMsg | B50: WhatsApp utility message price (India) | C50: Researched | D50: H | E50: R6: Meta list Rs0.115 (eff. 1-Oct-2026); Gallabox Rs0.1323; AiSensy Rs0.145. Utility replies in window charged again from 1-Oct-2026
A51: ComputePerStudentMonth | B51: Compute + storage + backups per student | C51: Assumption | D51: L | E51: TECH_PLAN s.16 cost model (NB09 pending); OMR images auto-deleted after 7 days
A52: ConsentCostPerStudentYear | B52: Consent OTP + verification per student | C52: Assumption | D52: L | E52: TECH_PLAN consent design (OTP)
A53: ServerCostMonth | B53: App server + managed Postgres + backups per stack | C53: Researched | D53: M | E53: R6: AWS t3.medium Rs3108 + DO PG 2vCPU Rs5789 / Lightsail-DO Rs2281 + DO PG Rs1440 / t4g Rs1554 + Lightsail DB Rs1426 | F53: Base adds ~Rs300 backups
A54: BSPFeeMonth | B54: WhatsApp BSP platform fee per stack | C54: Researched | D54: M | E54: R6: AiSensy Pro Rs3200 / Basic Rs1500 / Gupshup self-serve Rs0 + per-msg
A55: InstPerStack | B55: Institutes sharing one server stack | C55: Assumption | D55: L | E55: Depends on load test (NB09)
A56: CompliancePerInstMonth | B56: DPDP compliance cost per institute | C56: Assumption | D56: L | E56: Audits / consent management / DPO time
A57: CSM_CTC | B57: Customer-success / onboarding exec monthly CTC | C57: Researched | D57: L | E57: R5: Tier-2 remote CS median Rs33-42k (Frontlines 2026); Payscale Jaipur CSM-manager Rs58k
A58: InstPerCSM | B58: Institutes per CSM | C58: Researched | D58: L | E58: R5: Gainsight SMB 100-250 accounts per CSM - cut for high-touch Tier-2 onboarding
A59: RepCTC | B59: Field sales rep monthly CTC (incl. fuel) | C59: Researched | D59: M | E59: R5: Payscale Patna field sales ~Rs20k base; PhonePe postings Rs18-25k + Rs4-4.5k fuel
A60: RepTravel | B60: Rep intercity travel + demo material per month | C60: Assumption | D60: L | E60: R5: per-km allowance not found
A61: PilotsPerRepMonth | B61: Pilots started per rep per month (yearly avg) | C61: Assumption | D61: L | E61: R5: SaaStr 20-50 deals/month is inside sales; cut for in-person Tier-2 demos; peak Mar-Jun
A62: PilotConv | B62: Pilot-to-paid conversion | C62: Researched | D62: L | E62: R5: trial-to-paid 8% median / 18.2% opt-in / 48.8% opt-out (Userpilot 2026); assisted-pilot benchmark not found
A63: PilotMonths | B63: Free pilot length | C63: Assumption | D63: M | E63: FINANCE_PLAN s.3.2
A64: PilotSetupCost | B64: Retro-pilot setup (import last year's Excel; show who left) | C64: Assumption | D64: L | E64: GTM design: light pilot; full onboarding only after conversion | F64: Primary research needed
A65: OnboardBase | B65: Onboarding cost per institute (mid) | C65: Guide | D65: L | E65: Case brief Rs5-10k; low-tech institutes higher
A66: MarketingPerPaid | B66: Marketing spend per paid institute | C66: Assumption | D66: L
A67: ChurnInSeason | B67: Monthly logo churn for monthly payers | C67: Researched | D67: L | E67: R5: ChartMogul 6.1%/month at ARPA <$25 (2022); eChai India SMB 3-5%; SaaS Capital 2025 GRR 90%/yr | F67: Applied only to institutes not on annual prepay
A68: RenewalSpike | B68: Non-renewal at session end (annual) | C68: Assumption | D68: L | E68: R5: no benchmark found - answers the judges' post-exam churn question | F68: Spread over renewal months
A69: DiscountRate | B69: Discount rate for LTV | C69: Structural | D69: M | E69: Early-stage cost of capital convention
A70: StartMonth | B70: Paid start month (1 = April) | C70: Structural | D70: M | E70: Sales peak Mar-Jun; paid from May after a 1-month pilot
A71: Founders | B71: Founders drawing a stipend | C71: Assumption | D71: M | E71: Owner decision
A72: FounderStipend | B72: Founder stipend per month | C72: Assumption | D72: M | E72: Owner decision
A73: Engineers | B73: Engineers hired | C73: Assumption | D73: M
A74: EngineerCTC | B74: Engineer monthly CTC | C74: Researched | D74: L | E74: R5: Glassdoor Jaipur Rs6L/yr; Indore Rs6-8L/yr (1-3 yrs)
A75: ToolsOpex | B75: Tools / office / legal per month | C75: Assumption | D75: L
A76: G_Students | B76: Guide: students | C76: Guide | D76: H | E76: Case brief
A77: G_Dropout | B77: Guide: dropout rate | C77: Guide | D77: H | E77: Case brief
A78: G_RemainingFee | B78: Guide: remaining fee per dropout | C78: Guide | D78: H | E78: Case brief
A79: G_Prevent | B79: Guide: share of dropouts prevented | C79: Guide | D79: H | E79: Case brief
A80: G_Price | B80: Guide: price per student per month | C80: Guide | D80: H | E80: Case brief
A81: G_Months | B81: Guide: billing months per year | C81: Guide | D81: H | E81: Case brief
A82: G_Infra | B82: Guide: infra + AI per student per month | C82: Guide | D82: H | E82: Case brief
A83: G_Support | B83: Guide: support per institute per month | C83: Guide | D83: H | E83: Case brief
A84: G_CAC | B84: Guide: CAC | C84: Guide | D84: H | E84: Case brief
A85: G_Onboard | B85: Guide: onboarding | C85: Guide | D85: H | E85: Case brief
A86: G_Churn | B86: Guide: monthly churn | C86: Guide | D86: H | E86: Case brief
A88: Evidence mix
B89: Researched | C89: =COUNTIF(C5:C86,"Researched")
B90: Public | C90: =COUNTIF(C5:C86,"Public")
B91: Guide | C91: =COUNTIF(C5:C86,"Guide")
B92: Assumption | C92: =COUNTIF(C5:C86,"Assumption")
B93: Structural | C93: =COUNTIF(C5:C86,"Structural")

Sheet Engine
A1: Engine — re-runs the full chain for scenarios, tornado and churn grid. Do not edit.
B2: Case | D2: Live S | E2: Live M | F2: Live L | G2: Bear S | H2: Bear M | I2: Bear L | J2: Base S | K2: Base M | L2: Base L | M2: Bull S | N2: Bull M | O2: Bull L | P2: T ListPrice bear | Q2: T ListPrice bull | R2: T Fee bear | S2: T Fee bull | T2: T DropoutRate bear | U2: T DropoutRate bull | V2: T UpfrontShare bear | W2: T UpfrontShare bull | X2: T NInstalments bear | Y2: T NInstalments bull | Z2: T InterventionSuccess bear | AA2: T InterventionSuccess bull | AB2: T Recall_Minor bear | AC2: T Recall_Minor bull | AD2: T BlindMonths bear | AE2: T BlindMonths bull | AF2: T AdmissionUplift bear | AG2: T AdmissionUplift bull | AH2: T ITCShare bear | AI2: T ITCShare bull | AJ2: T ChurnInSeason bear | AK2: T ChurnInSeason bull | AL2: T RenewalSpike bear | AM2: T RenewalSpike bull | AN2: T PilotConv bear | AO2: T PilotConv bull | AP2: T PilotsPerRepMonth bear | AQ2: T PilotsPerRepMonth bull | AR2: Churn grid 1 | AS2: Churn grid 2 | AT2: Churn grid 3 | AU2: Churn grid 4 | AV2: Churn grid 5
B3: Segment | D3: S | E3: M | F3: L | G3: S | H3: M | I3: L | J3: S | K3: M | L3: L | M3: S | N3: M | O3: L | P3: M | Q3: M | R3: M | S3: M | T3: M | U3: M | V3: M | W3: M | X3: M | Y3: M | Z3: M | AA3: M | AB3: M | AC3: M | AD3: M | AE3: M | AF3: M | AG3: M | AH3: M | AI3: M | AJ3: M | AK3: M | AL3: M | AM3: M | AN3: M | AO3: M | AP3: M | AQ3: M | AR3: M | AS3: M | AT3: M | AU3: M | AV3: M
B4: Scenario (1-3) | D4: =Scenario | E4: =Scenario | F4: =Scenario | G4: 1 | H4: 1 | I4: 1 | J4: 2 | K4: 2 | L4: 2 | M4: 3 | N4: 3 | O4: 3 | P4: 2 | Q4: 2 | R4: 2 | S4: 2 | T4: 2 | U4: 2 | V4: 2 | W4: 2 | X4: 2 | Y4: 2 | Z4: 2 | AA4: 2 | AB4: 2 | AC4: 2 | AD4: 2 | AE4: 2 | AF4: 2 | AG4: 2 | AH4: 2 | AI4: 2 | AJ4: 2 | AK4: 2 | AL4: 2 | AM4: 2 | AN4: 2 | AO4: 2 | AP4: 2 | AQ4: 2 | AR4: =Scenario | AS4: =Scenario | AT4: =Scenario | AU4: =Scenario | AV4: =Scenario
B5: Override input | P5: ListPrice | Q5: ListPrice | R5: Fee | S5: Fee | T5: DropoutRate | U5: DropoutRate | V5: UpfrontShare | W5: UpfrontShare | X5: NInstalments | Y5: NInstalments | Z5: InterventionSuccess | AA5: InterventionSuccess | AB5: Recall_Minor | AC5: Recall_Minor | AD5: BlindMonths | AE5: BlindMonths | AF5: AdmissionUplift | AG5: AdmissionUplift | AH5: ITCShare | AI5: ITCShare | AJ5: ChurnInSeason | AK5: ChurnInSeason | AL5: RenewalSpike | AM5: RenewalSpike | AN5: PilotConv | AO5: PilotConv | AP5: PilotsPerRepMonth | AQ5: PilotsPerRepMonth | AR5: ChurnInSeason | AS5: ChurnInSeason | AT5: ChurnInSeason | AU5: ChurnInSeason | AV5: ChurnInSeason
B6: Override value | P6: =Assumptions!$D$38 | Q6: =Assumptions!$F$38 | R6: =Assumptions!$D$10 | S6: =Assumptions!$F$10 | T6: =Assumptions!$D$16 | U6: =Assumptions!$F$16 | V6: =Assumptions!$D$17 | W6: =Assumptions!$F$17 | X6: =Assumptions!$D$18 | Y6: =Assumptions!$F$18 | Z6: =Assumptions!$D$28 | AA6: =Assumptions!$F$28 | AB6: =Assumptions!$D$24 | AC6: =Assumptions!$F$24 | AD6: =Assumptions!$D$21 | AE6: =Assumptions!$F$21 | AF6: =Assumptions!$D$29 | AG6: =Assumptions!$F$29 | AH6: =Assumptions!$D$36 | AI6: =Assumptions!$F$36 | AJ6: =Assumptions!$D$72 | AK6: =Assumptions!$F$72 | AL6: =Assumptions!$D$73 | AM6: =Assumptions!$F$73 | AN6: =Assumptions!$D$67 | AO6: =Assumptions!$F$67 | AP6: =Assumptions!$D$66 | AQ6: =Assumptions!$F$66 | AR6: =Sensitivity!B$34 | AS6: =Sensitivity!C$34 | AT6: =Sensitivity!D$34 | AU6: =Sensitivity!E$34 | AV6: =Sensitivity!F$34
B8: ReportsPerStudentMonth | D8: =IF($D$5="ReportsPerStudentMonth",$D$6,INDEX(Assumptions!$D$48:$F$48,$D$4)) | E8: =IF($E$5="ReportsPerStudentMonth",$E$6,INDEX(Assumptions!$D$48:$F$48,$E$4)) | F8: =IF($F$5="ReportsPerStudentMonth",$F$6,INDEX(Assumptions!$D$48:$F$48,$F$4)) | G8: =IF($G$5="ReportsPerStudentMonth",$G$6,INDEX(Assumptions!$D$48:$F$48,$G$4)) | H8: =IF($H$5="ReportsPerStudentMonth",$H$6,INDEX(Assumptions!$D$48:$F$48,$H$4)) | I8: =IF($I$5="ReportsPerStudentMonth",$I$6,INDEX(Assumptions!$D$48:$F$48,$I$4)) | J8: =IF($J$5="ReportsPerStudentMonth",$J$6,INDEX(Assumptions!$D$48:$F$48,$J$4)) | K8: =IF($K$5="ReportsPerStudentMonth",$K$6,INDEX(Assumptions!$D$48:$F$48,$K$4)) | L8: =IF($L$5="ReportsPerStudentMonth",$L$6,INDEX(Assumptions!$D$48:$F$48,$L$4)) | M8: =IF($M$5="ReportsPerStudentMonth",$M$6,INDEX(Assumptions!$D$48:$F$48,$M$4)) | N8: =IF($N$5="ReportsPerStudentMonth",$N$6,INDEX(Assumptions!$D$48:$F$48,$N$4)) | O8: =IF($O$5="ReportsPerStudentMonth",$O$6,INDEX(Assumptions!$D$48:$F$48,$O$4)) | P8: =IF($P$5="ReportsPerStudentMonth",$P$6,INDEX(Assumptions!$D$48:$F$48,$P$4)) | Q8: =IF($Q$5="ReportsPerStudentMonth",$Q$6,INDEX(Assumptions!$D$48:$F$48,$Q$4)) | R8: =IF($R$5="ReportsPerStudentMonth",$R$6,INDEX(Assumptions!$D$48:$F$48,$R$4)) | S8: =IF($S$5="ReportsPerStudentMonth",$S$6,INDEX(Assumptions!$D$48:$F$48,$S$4)) | T8: =IF($T$5="ReportsPerStudentMonth",$T$6,INDEX(Assumptions!$D$48:$F$48,$T$4)) | U8: =IF($U$5="ReportsPerStudentMonth",$U$6,INDEX(Assumptions!$D$48:$F$48,$U$4)) | V8: =IF($V$5="ReportsPerStudentMonth",$V$6,INDEX(Assumptions!$D$48:$F$48,$V$4)) | W8: =IF($W$5="ReportsPerStudentMonth",$W$6,INDEX(Assumptions!$D$48:$F$48,$W$4)) | X8: =IF($X$5="ReportsPerStudentMonth",$X$6,INDEX(Assumptions!$D$48:$F$48,$X$4)) | Y8: =IF($Y$5="ReportsPerStudentMonth",$Y$6,INDEX(Assumptions!$D$48:$F$48,$Y$4)) | Z8: =IF($Z$5="ReportsPerStudentMonth",$Z$6,INDEX(Assumptions!$D$48:$F$48,$Z$4)) | AA8: =IF($AA$5="ReportsPerStudentMonth",$AA$6,INDEX(Assumptions!$D$48:$F$48,$AA$4)) | AB8: =IF($AB$5="ReportsPerStudentMonth",$AB$6,INDEX(Assumptions!$D$48:$F$48,$AB$4)) | AC8: =IF($AC$5="ReportsPerStudentMonth",$AC$6,INDEX(Assumptions!$D$48:$F$48,$AC$4)) | AD8: =IF($AD$5="ReportsPerStudentMonth",$AD$6,INDEX(Assumptions!$D$48:$F$48,$AD$4)) | AE8: =IF($AE$5="ReportsPerStudentMonth",$AE$6,INDEX(Assumptions!$D$48:$F$48,$AE$4)) | AF8: =IF($AF$5="ReportsPerStudentMonth",$AF$6,INDEX(Assumptions!$D$48:$F$48,$AF$4)) | AG8: =IF($AG$5="ReportsPerStudentMonth",$AG$6,INDEX(Assumptions!$D$48:$F$48,$AG$4)) | AH8: =IF($AH$5="ReportsPerStudentMonth",$AH$6,INDEX(Assumptions!$D$48:$F$48,$AH$4)) | AI8: =IF($AI$5="ReportsPerStudentMonth",$AI$6,INDEX(Assumptions!$D$48:$F$48,$AI$4)) | AJ8: =IF($AJ$5="ReportsPerStudentMonth",$AJ$6,INDEX(Assumptions!$D$48:$F$48,$AJ$4)) | AK8: =IF($AK$5="ReportsPerStudentMonth",$AK$6,INDEX(Assumptions!$D$48:$F$48,$AK$4)) | AL8: =IF($AL$5="ReportsPerStudentMonth",$AL$6,INDEX(Assumptions!$D$48:$F$48,$AL$4)) | AM8: =IF($AM$5="ReportsPerStudentMonth",$AM$6,INDEX(Assumptions!$D$48:$F$48,$AM$4)) | AN8: =IF($AN$5="ReportsPerStudentMonth",$AN$6,INDEX(Assumptions!$D$48:$F$48,$AN$4)) | AO8: =IF($AO$5="ReportsPerStudentMonth",$AO$6,INDEX(Assumptions!$D$48:$F$48,$AO$4)) | AP8: =IF($AP$5="ReportsPerStudentMonth",$AP$6,INDEX(Assumptions!$D$48:$F$48,$AP$4)) | AQ8: =IF($AQ$5="ReportsPerStudentMonth",$AQ$6,INDEX(Assumptions!$D$48:$F$48,$AQ$4)) | AR8: =IF($AR$5="ReportsPerStudentMonth",$AR$6,INDEX(Assumptions!$D$48:$F$48,$AR$4)) | AS8: =IF($AS$5="ReportsPerStudentMonth",$AS$6,INDEX(Assumptions!$D$48:$F$48,$AS$4)) | AT8: =IF($AT$5="ReportsPerStudentMonth",$AT$6,INDEX(Assumptions!$D$48:$F$48,$AT$4)) | AU8: =IF($AU$5="ReportsPerStudentMonth",$AU$6,INDEX(Assumptions!$D$48:$F$48,$AU$4)) | AV8: =IF($AV$5="ReportsPerStudentMonth",$AV$6,INDEX(Assumptions!$D$48:$F$48,$AV$4))
B9: TokensInPerReport | D9: =IF($D$5="TokensInPerReport",$D$6,INDEX(Assumptions!$D$49:$F$49,$D$4)) | E9: =IF($E$5="TokensInPerReport",$E$6,INDEX(Assumptions!$D$49:$F$49,$E$4)) | F9: =IF($F$5="TokensInPerReport",$F$6,INDEX(Assumptions!$D$49:$F$49,$F$4)) | G9: =IF($G$5="TokensInPerReport",$G$6,INDEX(Assumptions!$D$49:$F$49,$G$4)) | H9: =IF($H$5="TokensInPerReport",$H$6,INDEX(Assumptions!$D$49:$F$49,$H$4)) | I9: =IF($I$5="TokensInPerReport",$I$6,INDEX(Assumptions!$D$49:$F$49,$I$4)) | J9: =IF($J$5="TokensInPerReport",$J$6,INDEX(Assumptions!$D$49:$F$49,$J$4)) | K9: =IF($K$5="TokensInPerReport",$K$6,INDEX(Assumptions!$D$49:$F$49,$K$4)) | L9: =IF($L$5="TokensInPerReport",$L$6,INDEX(Assumptions!$D$49:$F$49,$L$4)) | M9: =IF($M$5="TokensInPerReport",$M$6,INDEX(Assumptions!$D$49:$F$49,$M$4)) | N9: =IF($N$5="TokensInPerReport",$N$6,INDEX(Assumptions!$D$49:$F$49,$N$4)) | O9: =IF($O$5="TokensInPerReport",$O$6,INDEX(Assumptions!$D$49:$F$49,$O$4)) | P9: =IF($P$5="TokensInPerReport",$P$6,INDEX(Assumptions!$D$49:$F$49,$P$4)) | Q9: =IF($Q$5="TokensInPerReport",$Q$6,INDEX(Assumptions!$D$49:$F$49,$Q$4)) | R9: =IF($R$5="TokensInPerReport",$R$6,INDEX(Assumptions!$D$49:$F$49,$R$4)) | S9: =IF($S$5="TokensInPerReport",$S$6,INDEX(Assumptions!$D$49:$F$49,$S$4)) | T9: =IF($T$5="TokensInPerReport",$T$6,INDEX(Assumptions!$D$49:$F$49,$T$4)) | U9: =IF($U$5="TokensInPerReport",$U$6,INDEX(Assumptions!$D$49:$F$49,$U$4)) | V9: =IF($V$5="TokensInPerReport",$V$6,INDEX(Assumptions!$D$49:$F$49,$V$4)) | W9: =IF($W$5="TokensInPerReport",$W$6,INDEX(Assumptions!$D$49:$F$49,$W$4)) | X9: =IF($X$5="TokensInPerReport",$X$6,INDEX(Assumptions!$D$49:$F$49,$X$4)) | Y9: =IF($Y$5="TokensInPerReport",$Y$6,INDEX(Assumptions!$D$49:$F$49,$Y$4)) | Z9: =IF($Z$5="TokensInPerReport",$Z$6,INDEX(Assumptions!$D$49:$F$49,$Z$4)) | AA9: =IF($AA$5="TokensInPerReport",$AA$6,INDEX(Assumptions!$D$49:$F$49,$AA$4)) | AB9: =IF($AB$5="TokensInPerReport",$AB$6,INDEX(Assumptions!$D$49:$F$49,$AB$4)) | AC9: =IF($AC$5="TokensInPerReport",$AC$6,INDEX(Assumptions!$D$49:$F$49,$AC$4)) | AD9: =IF($AD$5="TokensInPerReport",$AD$6,INDEX(Assumptions!$D$49:$F$49,$AD$4)) | AE9: =IF($AE$5="TokensInPerReport",$AE$6,INDEX(Assumptions!$D$49:$F$49,$AE$4)) | AF9: =IF($AF$5="TokensInPerReport",$AF$6,INDEX(Assumptions!$D$49:$F$49,$AF$4)) | AG9: =IF($AG$5="TokensInPerReport",$AG$6,INDEX(Assumptions!$D$49:$F$49,$AG$4)) | AH9: =IF($AH$5="TokensInPerReport",$AH$6,INDEX(Assumptions!$D$49:$F$49,$AH$4)) | AI9: =IF($AI$5="TokensInPerReport",$AI$6,INDEX(Assumptions!$D$49:$F$49,$AI$4)) | AJ9: =IF($AJ$5="TokensInPerReport",$AJ$6,INDEX(Assumptions!$D$49:$F$49,$AJ$4)) | AK9: =IF($AK$5="TokensInPerReport",$AK$6,INDEX(Assumptions!$D$49:$F$49,$AK$4)) | AL9: =IF($AL$5="TokensInPerReport",$AL$6,INDEX(Assumptions!$D$49:$F$49,$AL$4)) | AM9: =IF($AM$5="TokensInPerReport",$AM$6,INDEX(Assumptions!$D$49:$F$49,$AM$4)) | AN9: =IF($AN$5="TokensInPerReport",$AN$6,INDEX(Assumptions!$D$49:$F$49,$AN$4)) | AO9: =IF($AO$5="TokensInPerReport",$AO$6,INDEX(Assumptions!$D$49:$F$49,$AO$4)) | AP9: =IF($AP$5="TokensInPerReport",$AP$6,INDEX(Assumptions!$D$49:$F$49,$AP$4)) | AQ9: =IF($AQ$5="TokensInPerReport",$AQ$6,INDEX(Assumptions!$D$49:$F$49,$AQ$4)) | AR9: =IF($AR$5="TokensInPerReport",$AR$6,INDEX(Assumptions!$D$49:$F$49,$AR$4)) | AS9: =IF($AS$5="TokensInPerReport",$AS$6,INDEX(Assumptions!$D$49:$F$49,$AS$4)) | AT9: =IF($AT$5="TokensInPerReport",$AT$6,INDEX(Assumptions!$D$49:$F$49,$AT$4)) | AU9: =IF($AU$5="TokensInPerReport",$AU$6,INDEX(Assumptions!$D$49:$F$49,$AU$4)) | AV9: =IF($AV$5="TokensInPerReport",$AV$6,INDEX(Assumptions!$D$49:$F$49,$AV$4))
B10: TokensOutPerReport | D10: =IF($D$5="TokensOutPerReport",$D$6,INDEX(Assumptions!$D$50:$F$50,$D$4)) | E10: =IF($E$5="TokensOutPerReport",$E$6,INDEX(Assumptions!$D$50:$F$50,$E$4)) | F10: =IF($F$5="TokensOutPerReport",$F$6,INDEX(Assumptions!$D$50:$F$50,$F$4)) | G10: =IF($G$5="TokensOutPerReport",$G$6,INDEX(Assumptions!$D$50:$F$50,$G$4)) | H10: =IF($H$5="TokensOutPerReport",$H$6,INDEX(Assumptions!$D$50:$F$50,$H$4)) | I10: =IF($I$5="TokensOutPerReport",$I$6,INDEX(Assumptions!$D$50:$F$50,$I$4)) | J10: =IF($J$5="TokensOutPerReport",$J$6,INDEX(Assumptions!$D$50:$F$50,$J$4)) | K10: =IF($K$5="TokensOutPerReport",$K$6,INDEX(Assumptions!$D$50:$F$50,$K$4)) | L10: =IF($L$5="TokensOutPerReport",$L$6,INDEX(Assumptions!$D$50:$F$50,$L$4)) | M10: =IF($M$5="TokensOutPerReport",$M$6,INDEX(Assumptions!$D$50:$F$50,$M$4)) | N10: =IF($N$5="TokensOutPerReport",$N$6,INDEX(Assumptions!$D$50:$F$50,$N$4)) | O10: =IF($O$5="TokensOutPerReport",$O$6,INDEX(Assumptions!$D$50:$F$50,$O$4)) | P10: =IF($P$5="TokensOutPerReport",$P$6,INDEX(Assumptions!$D$50:$F$50,$P$4)) | Q10: =IF($Q$5="TokensOutPerReport",$Q$6,INDEX(Assumptions!$D$50:$F$50,$Q$4)) | R10: =IF($R$5="TokensOutPerReport",$R$6,INDEX(Assumptions!$D$50:$F$50,$R$4)) | S10: =IF($S$5="TokensOutPerReport",$S$6,INDEX(Assumptions!$D$50:$F$50,$S$4)) | T10: =IF($T$5="TokensOutPerReport",$T$6,INDEX(Assumptions!$D$50:$F$50,$T$4)) | U10: =IF($U$5="TokensOutPerReport",$U$6,INDEX(Assumptions!$D$50:$F$50,$U$4)) | V10: =IF($V$5="TokensOutPerReport",$V$6,INDEX(Assumptions!$D$50:$F$50,$V$4)) | W10: =IF($W$5="TokensOutPerReport",$W$6,INDEX(Assumptions!$D$50:$F$50,$W$4)) | X10: =IF($X$5="TokensOutPerReport",$X$6,INDEX(Assumptions!$D$50:$F$50,$X$4)) | Y10: =IF($Y$5="TokensOutPerReport",$Y$6,INDEX(Assumptions!$D$50:$F$50,$Y$4)) | Z10: =IF($Z$5="TokensOutPerReport",$Z$6,INDEX(Assumptions!$D$50:$F$50,$Z$4)) | AA10: =IF($AA$5="TokensOutPerReport",$AA$6,INDEX(Assumptions!$D$50:$F$50,$AA$4)) | AB10: =IF($AB$5="TokensOutPerReport",$AB$6,INDEX(Assumptions!$D$50:$F$50,$AB$4)) | AC10: =IF($AC$5="TokensOutPerReport",$AC$6,INDEX(Assumptions!$D$50:$F$50,$AC$4)) | AD10: =IF($AD$5="TokensOutPerReport",$AD$6,INDEX(Assumptions!$D$50:$F$50,$AD$4)) | AE10: =IF($AE$5="TokensOutPerReport",$AE$6,INDEX(Assumptions!$D$50:$F$50,$AE$4)) | AF10: =IF($AF$5="TokensOutPerReport",$AF$6,INDEX(Assumptions!$D$50:$F$50,$AF$4)) | AG10: =IF($AG$5="TokensOutPerReport",$AG$6,INDEX(Assumptions!$D$50:$F$50,$AG$4)) | AH10: =IF($AH$5="TokensOutPerReport",$AH$6,INDEX(Assumptions!$D$50:$F$50,$AH$4)) | AI10: =IF($AI$5="TokensOutPerReport",$AI$6,INDEX(Assumptions!$D$50:$F$50,$AI$4)) | AJ10: =IF($AJ$5="TokensOutPerReport",$AJ$6,INDEX(Assumptions!$D$50:$F$50,$AJ$4)) | AK10: =IF($AK$5="TokensOutPerReport",$AK$6,INDEX(Assumptions!$D$50:$F$50,$AK$4)) | AL10: =IF($AL$5="TokensOutPerReport",$AL$6,INDEX(Assumptions!$D$50:$F$50,$AL$4)) | AM10: =IF($AM$5="TokensOutPerReport",$AM$6,INDEX(Assumptions!$D$50:$F$50,$AM$4)) | AN10: =IF($AN$5="TokensOutPerReport",$AN$6,INDEX(Assumptions!$D$50:$F$50,$AN$4)) | AO10: =IF($AO$5="TokensOutPerReport",$AO$6,INDEX(Assumptions!$D$50:$F$50,$AO$4)) | AP10: =IF($AP$5="TokensOutPerReport",$AP$6,INDEX(Assumptions!$D$50:$F$50,$AP$4)) | AQ10: =IF($AQ$5="TokensOutPerReport",$AQ$6,INDEX(Assumptions!$D$50:$F$50,$AQ$4)) | AR10: =IF($AR$5="TokensOutPerReport",$AR$6,INDEX(Assumptions!$D$50:$F$50,$AR$4)) | AS10: =IF($AS$5="TokensOutPerReport",$AS$6,INDEX(Assumptions!$D$50:$F$50,$AS$4)) | AT10: =IF($AT$5="TokensOutPerReport",$AT$6,INDEX(Assumptions!$D$50:$F$50,$AT$4)) | AU10: =IF($AU$5="TokensOutPerReport",$AU$6,INDEX(Assumptions!$D$50:$F$50,$AU$4)) | AV10: =IF($AV$5="TokensOutPerReport",$AV$6,INDEX(Assumptions!$D$50:$F$50,$AV$4))
B11: LLMPriceIn | D11: =IF($D$5="LLMPriceIn",$D$6,INDEX(Assumptions!$D$51:$F$51,$D$4)) | E11: =IF($E$5="LLMPriceIn",$E$6,INDEX(Assumptions!$D$51:$F$51,$E$4)) | F11: =IF($F$5="LLMPriceIn",$F$6,INDEX(Assumptions!$D$51:$F$51,$F$4)) | G11: =IF($G$5="LLMPriceIn",$G$6,INDEX(Assumptions!$D$51:$F$51,$G$4)) | H11: =IF($H$5="LLMPriceIn",$H$6,INDEX(Assumptions!$D$51:$F$51,$H$4)) | I11: =IF($I$5="LLMPriceIn",$I$6,INDEX(Assumptions!$D$51:$F$51,$I$4)) | J11: =IF($J$5="LLMPriceIn",$J$6,INDEX(Assumptions!$D$51:$F$51,$J$4)) | K11: =IF($K$5="LLMPriceIn",$K$6,INDEX(Assumptions!$D$51:$F$51,$K$4)) | L11: =IF($L$5="LLMPriceIn",$L$6,INDEX(Assumptions!$D$51:$F$51,$L$4)) | M11: =IF($M$5="LLMPriceIn",$M$6,INDEX(Assumptions!$D$51:$F$51,$M$4)) | N11: =IF($N$5="LLMPriceIn",$N$6,INDEX(Assumptions!$D$51:$F$51,$N$4)) | O11: =IF($O$5="LLMPriceIn",$O$6,INDEX(Assumptions!$D$51:$F$51,$O$4)) | P11: =IF($P$5="LLMPriceIn",$P$6,INDEX(Assumptions!$D$51:$F$51,$P$4)) | Q11: =IF($Q$5="LLMPriceIn",$Q$6,INDEX(Assumptions!$D$51:$F$51,$Q$4)) | R11: =IF($R$5="LLMPriceIn",$R$6,INDEX(Assumptions!$D$51:$F$51,$R$4)) | S11: =IF($S$5="LLMPriceIn",$S$6,INDEX(Assumptions!$D$51:$F$51,$S$4)) | T11: =IF($T$5="LLMPriceIn",$T$6,INDEX(Assumptions!$D$51:$F$51,$T$4)) | U11: =IF($U$5="LLMPriceIn",$U$6,INDEX(Assumptions!$D$51:$F$51,$U$4)) | V11: =IF($V$5="LLMPriceIn",$V$6,INDEX(Assumptions!$D$51:$F$51,$V$4)) | W11: =IF($W$5="LLMPriceIn",$W$6,INDEX(Assumptions!$D$51:$F$51,$W$4)) | X11: =IF($X$5="LLMPriceIn",$X$6,INDEX(Assumptions!$D$51:$F$51,$X$4)) | Y11: =IF($Y$5="LLMPriceIn",$Y$6,INDEX(Assumptions!$D$51:$F$51,$Y$4)) | Z11: =IF($Z$5="LLMPriceIn",$Z$6,INDEX(Assumptions!$D$51:$F$51,$Z$4)) | AA11: =IF($AA$5="LLMPriceIn",$AA$6,INDEX(Assumptions!$D$51:$F$51,$AA$4)) | AB11: =IF($AB$5="LLMPriceIn",$AB$6,INDEX(Assumptions!$D$51:$F$51,$AB$4)) | AC11: =IF($AC$5="LLMPriceIn",$AC$6,INDEX(Assumptions!$D$51:$F$51,$AC$4)) | AD11: =IF($AD$5="LLMPriceIn",$AD$6,INDEX(Assumptions!$D$51:$F$51,$AD$4)) | AE11: =IF($AE$5="LLMPriceIn",$AE$6,INDEX(Assumptions!$D$51:$F$51,$AE$4)) | AF11: =IF($AF$5="LLMPriceIn",$AF$6,INDEX(Assumptions!$D$51:$F$51,$AF$4)) | AG11: =IF($AG$5="LLMPriceIn",$AG$6,INDEX(Assumptions!$D$51:$F$51,$AG$4)) | AH11: =IF($AH$5="LLMPriceIn",$AH$6,INDEX(Assumptions!$D$51:$F$51,$AH$4)) | AI11: =IF($AI$5="LLMPriceIn",$AI$6,INDEX(Assumptions!$D$51:$F$51,$AI$4)) | AJ11: =IF($AJ$5="LLMPriceIn",$AJ$6,INDEX(Assumptions!$D$51:$F$51,$AJ$4)) | AK11: =IF($AK$5="LLMPriceIn",$AK$6,INDEX(Assumptions!$D$51:$F$51,$AK$4)) | AL11: =IF($AL$5="LLMPriceIn",$AL$6,INDEX(Assumptions!$D$51:$F$51,$AL$4)) | AM11: =IF($AM$5="LLMPriceIn",$AM$6,INDEX(Assumptions!$D$51:$F$51,$AM$4)) | AN11: =IF($AN$5="LLMPriceIn",$AN$6,INDEX(Assumptions!$D$51:$F$51,$AN$4)) | AO11: =IF($AO$5="LLMPriceIn",$AO$6,INDEX(Assumptions!$D$51:$F$51,$AO$4)) | AP11: =IF($AP$5="LLMPriceIn",$AP$6,INDEX(Assumptions!$D$51:$F$51,$AP$4)) | AQ11: =IF($AQ$5="LLMPriceIn",$AQ$6,INDEX(Assumptions!$D$51:$F$51,$AQ$4)) | AR11: =IF($AR$5="LLMPriceIn",$AR$6,INDEX(Assumptions!$D$51:$F$51,$AR$4)) | AS11: =IF($AS$5="LLMPriceIn",$AS$6,INDEX(Assumptions!$D$51:$F$51,$AS$4)) | AT11: =IF($AT$5="LLMPriceIn",$AT$6,INDEX(Assumptions!$D$51:$F$51,$AT$4)) | AU11: =IF($AU$5="LLMPriceIn",$AU$6,INDEX(Assumptions!$D$51:$F$51,$AU$4)) | AV11: =IF($AV$5="LLMPriceIn",$AV$6,INDEX(Assumptions!$D$51:$F$51,$AV$4))
B12: LLMPriceOut | D12: =IF($D$5="LLMPriceOut",$D$6,INDEX(Assumptions!$D$52:$F$52,$D$4)) | E12: =IF($E$5="LLMPriceOut",$E$6,INDEX(Assumptions!$D$52:$F$52,$E$4)) | F12: =IF($F$5="LLMPriceOut",$F$6,INDEX(Assumptions!$D$52:$F$52,$F$4)) | G12: =IF($G$5="LLMPriceOut",$G$6,INDEX(Assumptions!$D$52:$F$52,$G$4)) | H12: =IF($H$5="LLMPriceOut",$H$6,INDEX(Assumptions!$D$52:$F$52,$H$4)) | I12: =IF($I$5="LLMPriceOut",$I$6,INDEX(Assumptions!$D$52:$F$52,$I$4)) | J12: =IF($J$5="LLMPriceOut",$J$6,INDEX(Assumptions!$D$52:$F$52,$J$4)) | K12: =IF($K$5="LLMPriceOut",$K$6,INDEX(Assumptions!$D$52:$F$52,$K$4)) | L12: =IF($L$5="LLMPriceOut",$L$6,INDEX(Assumptions!$D$52:$F$52,$L$4)) | M12: =IF($M$5="LLMPriceOut",$M$6,INDEX(Assumptions!$D$52:$F$52,$M$4)) | N12: =IF($N$5="LLMPriceOut",$N$6,INDEX(Assumptions!$D$52:$F$52,$N$4)) | O12: =IF($O$5="LLMPriceOut",$O$6,INDEX(Assumptions!$D$52:$F$52,$O$4)) | P12: =IF($P$5="LLMPriceOut",$P$6,INDEX(Assumptions!$D$52:$F$52,$P$4)) | Q12: =IF($Q$5="LLMPriceOut",$Q$6,INDEX(Assumptions!$D$52:$F$52,$Q$4)) | R12: =IF($R$5="LLMPriceOut",$R$6,INDEX(Assumptions!$D$52:$F$52,$R$4)) | S12: =IF($S$5="LLMPriceOut",$S$6,INDEX(Assumptions!$D$52:$F$52,$S$4)) | T12: =IF($T$5="LLMPriceOut",$T$6,INDEX(Assumptions!$D$52:$F$52,$T$4)) | U12: =IF($U$5="LLMPriceOut",$U$6,INDEX(Assumptions!$D$52:$F$52,$U$4)) | V12: =IF($V$5="LLMPriceOut",$V$6,INDEX(Assumptions!$D$52:$F$52,$V$4)) | W12: =IF($W$5="LLMPriceOut",$W$6,INDEX(Assumptions!$D$52:$F$52,$W$4)) | X12: =IF($X$5="LLMPriceOut",$X$6,INDEX(Assumptions!$D$52:$F$52,$X$4)) | Y12: =IF($Y$5="LLMPriceOut",$Y$6,INDEX(Assumptions!$D$52:$F$52,$Y$4)) | Z12: =IF($Z$5="LLMPriceOut",$Z$6,INDEX(Assumptions!$D$52:$F$52,$Z$4)) | AA12: =IF($AA$5="LLMPriceOut",$AA$6,INDEX(Assumptions!$D$52:$F$52,$AA$4)) | AB12: =IF($AB$5="LLMPriceOut",$AB$6,INDEX(Assumptions!$D$52:$F$52,$AB$4)) | AC12: =IF($AC$5="LLMPriceOut",$AC$6,INDEX(Assumptions!$D$52:$F$52,$AC$4)) | AD12: =IF($AD$5="LLMPriceOut",$AD$6,INDEX(Assumptions!$D$52:$F$52,$AD$4)) | AE12: =IF($AE$5="LLMPriceOut",$AE$6,INDEX(Assumptions!$D$52:$F$52,$AE$4)) | AF12: =IF($AF$5="LLMPriceOut",$AF$6,INDEX(Assumptions!$D$52:$F$52,$AF$4)) | AG12: =IF($AG$5="LLMPriceOut",$AG$6,INDEX(Assumptions!$D$52:$F$52,$AG$4)) | AH12: =IF($AH$5="LLMPriceOut",$AH$6,INDEX(Assumptions!$D$52:$F$52,$AH$4)) | AI12: =IF($AI$5="LLMPriceOut",$AI$6,INDEX(Assumptions!$D$52:$F$52,$AI$4)) | AJ12: =IF($AJ$5="LLMPriceOut",$AJ$6,INDEX(Assumptions!$D$52:$F$52,$AJ$4)) | AK12: =IF($AK$5="LLMPriceOut",$AK$6,INDEX(Assumptions!$D$52:$F$52,$AK$4)) | AL12: =IF($AL$5="LLMPriceOut",$AL$6,INDEX(Assumptions!$D$52:$F$52,$AL$4)) | AM12: =IF($AM$5="LLMPriceOut",$AM$6,INDEX(Assumptions!$D$52:$F$52,$AM$4)) | AN12: =IF($AN$5="LLMPriceOut",$AN$6,INDEX(Assumptions!$D$52:$F$52,$AN$4)) | AO12: =IF($AO$5="LLMPriceOut",$AO$6,INDEX(Assumptions!$D$52:$F$52,$AO$4)) | AP12: =IF($AP$5="LLMPriceOut",$AP$6,INDEX(Assumptions!$D$52:$F$52,$AP$4)) | AQ12: =IF($AQ$5="LLMPriceOut",$AQ$6,INDEX(Assumptions!$D$52:$F$52,$AQ$4)) | AR12: =IF($AR$5="LLMPriceOut",$AR$6,INDEX(Assumptions!$D$52:$F$52,$AR$4)) | AS12: =IF($AS$5="LLMPriceOut",$AS$6,INDEX(Assumptions!$D$52:$F$52,$AS$4)) | AT12: =IF($AT$5="LLMPriceOut",$AT$6,INDEX(Assumptions!$D$52:$F$52,$AT$4)) | AU12: =IF($AU$5="LLMPriceOut",$AU$6,INDEX(Assumptions!$D$52:$F$52,$AU$4)) | AV12: =IF($AV$5="LLMPriceOut",$AV$6,INDEX(Assumptions!$D$52:$F$52,$AV$4))
B13: WAMsgsPerStudentMonth | D13: =IF($D$5="WAMsgsPerStudentMonth",$D$6,INDEX(Assumptions!$D$53:$F$53,$D$4)) | E13: =IF($E$5="WAMsgsPerStudentMonth",$E$6,INDEX(Assumptions!$D$53:$F$53,$E$4)) | F13: =IF($F$5="WAMsgsPerStudentMonth",$F$6,INDEX(Assumptions!$D$53:$F$53,$F$4)) | G13: =IF($G$5="WAMsgsPerStudentMonth",$G$6,INDEX(Assumptions!$D$53:$F$53,$G$4)) | H13: =IF($H$5="WAMsgsPerStudentMonth",$H$6,INDEX(Assumptions!$D$53:$F$53,$H$4)) | I13: =IF($I$5="WAMsgsPerStudentMonth",$I$6,INDEX(Assumptions!$D$53:$F$53,$I$4)) | J13: =IF($J$5="WAMsgsPerStudentMonth",$J$6,INDEX(Assumptions!$D$53:$F$53,$J$4)) | K13: =IF($K$5="WAMsgsPerStudentMonth",$K$6,INDEX(Assumptions!$D$53:$F$53,$K$4)) | L13: =IF($L$5="WAMsgsPerStudentMonth",$L$6,INDEX(Assumptions!$D$53:$F$53,$L$4)) | M13: =IF($M$5="WAMsgsPerStudentMonth",$M$6,INDEX(Assumptions!$D$53:$F$53,$M$4)) | N13: =IF($N$5="WAMsgsPerStudentMonth",$N$6,INDEX(Assumptions!$D$53:$F$53,$N$4)) | O13: =IF($O$5="WAMsgsPerStudentMonth",$O$6,INDEX(Assumptions!$D$53:$F$53,$O$4)) | P13: =IF($P$5="WAMsgsPerStudentMonth",$P$6,INDEX(Assumptions!$D$53:$F$53,$P$4)) | Q13: =IF($Q$5="WAMsgsPerStudentMonth",$Q$6,INDEX(Assumptions!$D$53:$F$53,$Q$4)) | R13: =IF($R$5="WAMsgsPerStudentMonth",$R$6,INDEX(Assumptions!$D$53:$F$53,$R$4)) | S13: =IF($S$5="WAMsgsPerStudentMonth",$S$6,INDEX(Assumptions!$D$53:$F$53,$S$4)) | T13: =IF($T$5="WAMsgsPerStudentMonth",$T$6,INDEX(Assumptions!$D$53:$F$53,$T$4)) | U13: =IF($U$5="WAMsgsPerStudentMonth",$U$6,INDEX(Assumptions!$D$53:$F$53,$U$4)) | V13: =IF($V$5="WAMsgsPerStudentMonth",$V$6,INDEX(Assumptions!$D$53:$F$53,$V$4)) | W13: =IF($W$5="WAMsgsPerStudentMonth",$W$6,INDEX(Assumptions!$D$53:$F$53,$W$4)) | X13: =IF($X$5="WAMsgsPerStudentMonth",$X$6,INDEX(Assumptions!$D$53:$F$53,$X$4)) | Y13: =IF($Y$5="WAMsgsPerStudentMonth",$Y$6,INDEX(Assumptions!$D$53:$F$53,$Y$4)) | Z13: =IF($Z$5="WAMsgsPerStudentMonth",$Z$6,INDEX(Assumptions!$D$53:$F$53,$Z$4)) | AA13: =IF($AA$5="WAMsgsPerStudentMonth",$AA$6,INDEX(Assumptions!$D$53:$F$53,$AA$4)) | AB13: =IF($AB$5="WAMsgsPerStudentMonth",$AB$6,INDEX(Assumptions!$D$53:$F$53,$AB$4)) | AC13: =IF($AC$5="WAMsgsPerStudentMonth",$AC$6,INDEX(Assumptions!$D$53:$F$53,$AC$4)) | AD13: =IF($AD$5="WAMsgsPerStudentMonth",$AD$6,INDEX(Assumptions!$D$53:$F$53,$AD$4)) | AE13: =IF($AE$5="WAMsgsPerStudentMonth",$AE$6,INDEX(Assumptions!$D$53:$F$53,$AE$4)) | AF13: =IF($AF$5="WAMsgsPerStudentMonth",$AF$6,INDEX(Assumptions!$D$53:$F$53,$AF$4)) | AG13: =IF($AG$5="WAMsgsPerStudentMonth",$AG$6,INDEX(Assumptions!$D$53:$F$53,$AG$4)) | AH13: =IF($AH$5="WAMsgsPerStudentMonth",$AH$6,INDEX(Assumptions!$D$53:$F$53,$AH$4)) | AI13: =IF($AI$5="WAMsgsPerStudentMonth",$AI$6,INDEX(Assumptions!$D$53:$F$53,$AI$4)) | AJ13: =IF($AJ$5="WAMsgsPerStudentMonth",$AJ$6,INDEX(Assumptions!$D$53:$F$53,$AJ$4)) | AK13: =IF($AK$5="WAMsgsPerStudentMonth",$AK$6,INDEX(Assumptions!$D$53:$F$53,$AK$4)) | AL13: =IF($AL$5="WAMsgsPerStudentMonth",$AL$6,INDEX(Assumptions!$D$53:$F$53,$AL$4)) | AM13: =IF($AM$5="WAMsgsPerStudentMonth",$AM$6,INDEX(Assumptions!$D$53:$F$53,$AM$4)) | AN13: =IF($AN$5="WAMsgsPerStudentMonth",$AN$6,INDEX(Assumptions!$D$53:$F$53,$AN$4)) | AO13: =IF($AO$5="WAMsgsPerStudentMonth",$AO$6,INDEX(Assumptions!$D$53:$F$53,$AO$4)) | AP13: =IF($AP$5="WAMsgsPerStudentMonth",$AP$6,INDEX(Assumptions!$D$53:$F$53,$AP$4)) | AQ13: =IF($AQ$5="WAMsgsPerStudentMonth",$AQ$6,INDEX(Assumptions!$D$53:$F$53,$AQ$4)) | AR13: =IF($AR$5="WAMsgsPerStudentMonth",$AR$6,INDEX(Assumptions!$D$53:$F$53,$AR$4)) | AS13: =IF($AS$5="WAMsgsPerStudentMonth",$AS$6,INDEX(Assumptions!$D$53:$F$53,$AS$4)) | AT13: =IF($AT$5="WAMsgsPerStudentMonth",$AT$6,INDEX(Assumptions!$D$53:$F$53,$AT$4)) | AU13: =IF($AU$5="WAMsgsPerStudentMonth",$AU$6,INDEX(Assumptions!$D$53:$F$53,$AU$4)) | AV13: =IF($AV$5="WAMsgsPerStudentMonth",$AV$6,INDEX(Assumptions!$D$53:$F$53,$AV$4))
B14: WAPricePerMsg | D14: =IF($D$5="WAPricePerMsg",$D$6,INDEX(Assumptions!$D$54:$F$54,$D$4)) | E14: =IF($E$5="WAPricePerMsg",$E$6,INDEX(Assumptions!$D$54:$F$54,$E$4)) | F14: =IF($F$5="WAPricePerMsg",$F$6,INDEX(Assumptions!$D$54:$F$54,$F$4)) | G14: =IF($G$5="WAPricePerMsg",$G$6,INDEX(Assumptions!$D$54:$F$54,$G$4)) | H14: =IF($H$5="WAPricePerMsg",$H$6,INDEX(Assumptions!$D$54:$F$54,$H$4)) | I14: =IF($I$5="WAPricePerMsg",$I$6,INDEX(Assumptions!$D$54:$F$54,$I$4)) | J14: =IF($J$5="WAPricePerMsg",$J$6,INDEX(Assumptions!$D$54:$F$54,$J$4)) | K14: =IF($K$5="WAPricePerMsg",$K$6,INDEX(Assumptions!$D$54:$F$54,$K$4)) | L14: =IF($L$5="WAPricePerMsg",$L$6,INDEX(Assumptions!$D$54:$F$54,$L$4)) | M14: =IF($M$5="WAPricePerMsg",$M$6,INDEX(Assumptions!$D$54:$F$54,$M$4)) | N14: =IF($N$5="WAPricePerMsg",$N$6,INDEX(Assumptions!$D$54:$F$54,$N$4)) | O14: =IF($O$5="WAPricePerMsg",$O$6,INDEX(Assumptions!$D$54:$F$54,$O$4)) | P14: =IF($P$5="WAPricePerMsg",$P$6,INDEX(Assumptions!$D$54:$F$54,$P$4)) | Q14: =IF($Q$5="WAPricePerMsg",$Q$6,INDEX(Assumptions!$D$54:$F$54,$Q$4)) | R14: =IF($R$5="WAPricePerMsg",$R$6,INDEX(Assumptions!$D$54:$F$54,$R$4)) | S14: =IF($S$5="WAPricePerMsg",$S$6,INDEX(Assumptions!$D$54:$F$54,$S$4)) | T14: =IF($T$5="WAPricePerMsg",$T$6,INDEX(Assumptions!$D$54:$F$54,$T$4)) | U14: =IF($U$5="WAPricePerMsg",$U$6,INDEX(Assumptions!$D$54:$F$54,$U$4)) | V14: =IF($V$5="WAPricePerMsg",$V$6,INDEX(Assumptions!$D$54:$F$54,$V$4)) | W14: =IF($W$5="WAPricePerMsg",$W$6,INDEX(Assumptions!$D$54:$F$54,$W$4)) | X14: =IF($X$5="WAPricePerMsg",$X$6,INDEX(Assumptions!$D$54:$F$54,$X$4)) | Y14: =IF($Y$5="WAPricePerMsg",$Y$6,INDEX(Assumptions!$D$54:$F$54,$Y$4)) | Z14: =IF($Z$5="WAPricePerMsg",$Z$6,INDEX(Assumptions!$D$54:$F$54,$Z$4)) | AA14: =IF($AA$5="WAPricePerMsg",$AA$6,INDEX(Assumptions!$D$54:$F$54,$AA$4)) | AB14: =IF($AB$5="WAPricePerMsg",$AB$6,INDEX(Assumptions!$D$54:$F$54,$AB$4)) | AC14: =IF($AC$5="WAPricePerMsg",$AC$6,INDEX(Assumptions!$D$54:$F$54,$AC$4)) | AD14: =IF($AD$5="WAPricePerMsg",$AD$6,INDEX(Assumptions!$D$54:$F$54,$AD$4)) | AE14: =IF($AE$5="WAPricePerMsg",$AE$6,INDEX(Assumptions!$D$54:$F$54,$AE$4)) | AF14: =IF($AF$5="WAPricePerMsg",$AF$6,INDEX(Assumptions!$D$54:$F$54,$AF$4)) | AG14: =IF($AG$5="WAPricePerMsg",$AG$6,INDEX(Assumptions!$D$54:$F$54,$AG$4)) | AH14: =IF($AH$5="WAPricePerMsg",$AH$6,INDEX(Assumptions!$D$54:$F$54,$AH$4)) | AI14: =IF($AI$5="WAPricePerMsg",$AI$6,INDEX(Assumptions!$D$54:$F$54,$AI$4)) | AJ14: =IF($AJ$5="WAPricePerMsg",$AJ$6,INDEX(Assumptions!$D$54:$F$54,$AJ$4)) | AK14: =IF($AK$5="WAPricePerMsg",$AK$6,INDEX(Assumptions!$D$54:$F$54,$AK$4)) | AL14: =IF($AL$5="WAPricePerMsg",$AL$6,INDEX(Assumptions!$D$54:$F$54,$AL$4)) | AM14: =IF($AM$5="WAPricePerMsg",$AM$6,INDEX(Assumptions!$D$54:$F$54,$AM$4)) | AN14: =IF($AN$5="WAPricePerMsg",$AN$6,INDEX(Assumptions!$D$54:$F$54,$AN$4)) | AO14: =IF($AO$5="WAPricePerMsg",$AO$6,INDEX(Assumptions!$D$54:$F$54,$AO$4)) | AP14: =IF($AP$5="WAPricePerMsg",$AP$6,INDEX(Assumptions!$D$54:$F$54,$AP$4)) | AQ14: =IF($AQ$5="WAPricePerMsg",$AQ$6,INDEX(Assumptions!$D$54:$F$54,$AQ$4)) | AR14: =IF($AR$5="WAPricePerMsg",$AR$6,INDEX(Assumptions!$D$54:$F$54,$AR$4)) | AS14: =IF($AS$5="WAPricePerMsg",$AS$6,INDEX(Assumptions!$D$54:$F$54,$AS$4)) | AT14: =IF($AT$5="WAPricePerMsg",$AT$6,INDEX(Assumptions!$D$54:$F$54,$AT$4)) | AU14: =IF($AU$5="WAPricePerMsg",$AU$6,INDEX(Assumptions!$D$54:$F$54,$AU$4)) | AV14: =IF($AV$5="WAPricePerMsg",$AV$6,INDEX(Assumptions!$D$54:$F$54,$AV$4))
B15: ComputePerStudentMonth | D15: =IF($D$5="ComputePerStudentMonth",$D$6,INDEX(Assumptions!$D$55:$F$55,$D$4)) | E15: =IF($E$5="ComputePerStudentMonth",$E$6,INDEX(Assumptions!$D$55:$F$55,$E$4)) | F15: =IF($F$5="ComputePerStudentMonth",$F$6,INDEX(Assumptions!$D$55:$F$55,$F$4)) | G15: =IF($G$5="ComputePerStudentMonth",$G$6,INDEX(Assumptions!$D$55:$F$55,$G$4)) | H15: =IF($H$5="ComputePerStudentMonth",$H$6,INDEX(Assumptions!$D$55:$F$55,$H$4)) | I15: =IF($I$5="ComputePerStudentMonth",$I$6,INDEX(Assumptions!$D$55:$F$55,$I$4)) | J15: =IF($J$5="ComputePerStudentMonth",$J$6,INDEX(Assumptions!$D$55:$F$55,$J$4)) | K15: =IF($K$5="ComputePerStudentMonth",$K$6,INDEX(Assumptions!$D$55:$F$55,$K$4)) | L15: =IF($L$5="ComputePerStudentMonth",$L$6,INDEX(Assumptions!$D$55:$F$55,$L$4)) | M15: =IF($M$5="ComputePerStudentMonth",$M$6,INDEX(Assumptions!$D$55:$F$55,$M$4)) | N15: =IF($N$5="ComputePerStudentMonth",$N$6,INDEX(Assumptions!$D$55:$F$55,$N$4)) | O15: =IF($O$5="ComputePerStudentMonth",$O$6,INDEX(Assumptions!$D$55:$F$55,$O$4)) | P15: =IF($P$5="ComputePerStudentMonth",$P$6,INDEX(Assumptions!$D$55:$F$55,$P$4)) | Q15: =IF($Q$5="ComputePerStudentMonth",$Q$6,INDEX(Assumptions!$D$55:$F$55,$Q$4)) | R15: =IF($R$5="ComputePerStudentMonth",$R$6,INDEX(Assumptions!$D$55:$F$55,$R$4)) | S15: =IF($S$5="ComputePerStudentMonth",$S$6,INDEX(Assumptions!$D$55:$F$55,$S$4)) | T15: =IF($T$5="ComputePerStudentMonth",$T$6,INDEX(Assumptions!$D$55:$F$55,$T$4)) | U15: =IF($U$5="ComputePerStudentMonth",$U$6,INDEX(Assumptions!$D$55:$F$55,$U$4)) | V15: =IF($V$5="ComputePerStudentMonth",$V$6,INDEX(Assumptions!$D$55:$F$55,$V$4)) | W15: =IF($W$5="ComputePerStudentMonth",$W$6,INDEX(Assumptions!$D$55:$F$55,$W$4)) | X15: =IF($X$5="ComputePerStudentMonth",$X$6,INDEX(Assumptions!$D$55:$F$55,$X$4)) | Y15: =IF($Y$5="ComputePerStudentMonth",$Y$6,INDEX(Assumptions!$D$55:$F$55,$Y$4)) | Z15: =IF($Z$5="ComputePerStudentMonth",$Z$6,INDEX(Assumptions!$D$55:$F$55,$Z$4)) | AA15: =IF($AA$5="ComputePerStudentMonth",$AA$6,INDEX(Assumptions!$D$55:$F$55,$AA$4)) | AB15: =IF($AB$5="ComputePerStudentMonth",$AB$6,INDEX(Assumptions!$D$55:$F$55,$AB$4)) | AC15: =IF($AC$5="ComputePerStudentMonth",$AC$6,INDEX(Assumptions!$D$55:$F$55,$AC$4)) | AD15: =IF($AD$5="ComputePerStudentMonth",$AD$6,INDEX(Assumptions!$D$55:$F$55,$AD$4)) | AE15: =IF($AE$5="ComputePerStudentMonth",$AE$6,INDEX(Assumptions!$D$55:$F$55,$AE$4)) | AF15: =IF($AF$5="ComputePerStudentMonth",$AF$6,INDEX(Assumptions!$D$55:$F$55,$AF$4)) | AG15: =IF($AG$5="ComputePerStudentMonth",$AG$6,INDEX(Assumptions!$D$55:$F$55,$AG$4)) | AH15: =IF($AH$5="ComputePerStudentMonth",$AH$6,INDEX(Assumptions!$D$55:$F$55,$AH$4)) | AI15: =IF($AI$5="ComputePerStudentMonth",$AI$6,INDEX(Assumptions!$D$55:$F$55,$AI$4)) | AJ15: =IF($AJ$5="ComputePerStudentMonth",$AJ$6,INDEX(Assumptions!$D$55:$F$55,$AJ$4)) | AK15: =IF($AK$5="ComputePerStudentMonth",$AK$6,INDEX(Assumptions!$D$55:$F$55,$AK$4)) | AL15: =IF($AL$5="ComputePerStudentMonth",$AL$6,INDEX(Assumptions!$D$55:$F$55,$AL$4)) | AM15: =IF($AM$5="ComputePerStudentMonth",$AM$6,INDEX(Assumptions!$D$55:$F$55,$AM$4)) | AN15: =IF($AN$5="ComputePerStudentMonth",$AN$6,INDEX(Assumptions!$D$55:$F$55,$AN$4)) | AO15: =IF($AO$5="ComputePerStudentMonth",$AO$6,INDEX(Assumptions!$D$55:$F$55,$AO$4)) | AP15: =IF($AP$5="ComputePerStudentMonth",$AP$6,INDEX(Assumptions!$D$55:$F$55,$AP$4)) | AQ15: =IF($AQ$5="ComputePerStudentMonth",$AQ$6,INDEX(Assumptions!$D$55:$F$55,$AQ$4)) | AR15: =IF($AR$5="ComputePerStudentMonth",$AR$6,INDEX(Assumptions!$D$55:$F$55,$AR$4)) | AS15: =IF($AS$5="ComputePerStudentMonth",$AS$6,INDEX(Assumptions!$D$55:$F$55,$AS$4)) | AT15: =IF($AT$5="ComputePerStudentMonth",$AT$6,INDEX(Assumptions!$D$55:$F$55,$AT$4)) | AU15: =IF($AU$5="ComputePerStudentMonth",$AU$6,INDEX(Assumptions!$D$55:$F$55,$AU$4)) | AV15: =IF($AV$5="ComputePerStudentMonth",$AV$6,INDEX(Assumptions!$D$55:$F$55,$AV$4))
B16: ConsentCostPerStudentYear | D16: =IF($D$5="ConsentCostPerStudentYear",$D$6,INDEX(Assumptions!$D$56:$F$56,$D$4)) | E16: =IF($E$5="ConsentCostPerStudentYear",$E$6,INDEX(Assumptions!$D$56:$F$56,$E$4)) | F16: =IF($F$5="ConsentCostPerStudentYear",$F$6,INDEX(Assumptions!$D$56:$F$56,$F$4)) | G16: =IF($G$5="ConsentCostPerStudentYear",$G$6,INDEX(Assumptions!$D$56:$F$56,$G$4)) | H16: =IF($H$5="ConsentCostPerStudentYear",$H$6,INDEX(Assumptions!$D$56:$F$56,$H$4)) | I16: =IF($I$5="ConsentCostPerStudentYear",$I$6,INDEX(Assumptions!$D$56:$F$56,$I$4)) | J16: =IF($J$5="ConsentCostPerStudentYear",$J$6,INDEX(Assumptions!$D$56:$F$56,$J$4)) | K16: =IF($K$5="ConsentCostPerStudentYear",$K$6,INDEX(Assumptions!$D$56:$F$56,$K$4)) | L16: =IF($L$5="ConsentCostPerStudentYear",$L$6,INDEX(Assumptions!$D$56:$F$56,$L$4)) | M16: =IF($M$5="ConsentCostPerStudentYear",$M$6,INDEX(Assumptions!$D$56:$F$56,$M$4)) | N16: =IF($N$5="ConsentCostPerStudentYear",$N$6,INDEX(Assumptions!$D$56:$F$56,$N$4)) | O16: =IF($O$5="ConsentCostPerStudentYear",$O$6,INDEX(Assumptions!$D$56:$F$56,$O$4)) | P16: =IF($P$5="ConsentCostPerStudentYear",$P$6,INDEX(Assumptions!$D$56:$F$56,$P$4)) | Q16: =IF($Q$5="ConsentCostPerStudentYear",$Q$6,INDEX(Assumptions!$D$56:$F$56,$Q$4)) | R16: =IF($R$5="ConsentCostPerStudentYear",$R$6,INDEX(Assumptions!$D$56:$F$56,$R$4)) | S16: =IF($S$5="ConsentCostPerStudentYear",$S$6,INDEX(Assumptions!$D$56:$F$56,$S$4)) | T16: =IF($T$5="ConsentCostPerStudentYear",$T$6,INDEX(Assumptions!$D$56:$F$56,$T$4)) | U16: =IF($U$5="ConsentCostPerStudentYear",$U$6,INDEX(Assumptions!$D$56:$F$56,$U$4)) | V16: =IF($V$5="ConsentCostPerStudentYear",$V$6,INDEX(Assumptions!$D$56:$F$56,$V$4)) | W16: =IF($W$5="ConsentCostPerStudentYear",$W$6,INDEX(Assumptions!$D$56:$F$56,$W$4)) | X16: =IF($X$5="ConsentCostPerStudentYear",$X$6,INDEX(Assumptions!$D$56:$F$56,$X$4)) | Y16: =IF($Y$5="ConsentCostPerStudentYear",$Y$6,INDEX(Assumptions!$D$56:$F$56,$Y$4)) | Z16: =IF($Z$5="ConsentCostPerStudentYear",$Z$6,INDEX(Assumptions!$D$56:$F$56,$Z$4)) | AA16: =IF($AA$5="ConsentCostPerStudentYear",$AA$6,INDEX(Assumptions!$D$56:$F$56,$AA$4)) | AB16: =IF($AB$5="ConsentCostPerStudentYear",$AB$6,INDEX(Assumptions!$D$56:$F$56,$AB$4)) | AC16: =IF($AC$5="ConsentCostPerStudentYear",$AC$6,INDEX(Assumptions!$D$56:$F$56,$AC$4)) | AD16: =IF($AD$5="ConsentCostPerStudentYear",$AD$6,INDEX(Assumptions!$D$56:$F$56,$AD$4)) | AE16: =IF($AE$5="ConsentCostPerStudentYear",$AE$6,INDEX(Assumptions!$D$56:$F$56,$AE$4)) | AF16: =IF($AF$5="ConsentCostPerStudentYear",$AF$6,INDEX(Assumptions!$D$56:$F$56,$AF$4)) | AG16: =IF($AG$5="ConsentCostPerStudentYear",$AG$6,INDEX(Assumptions!$D$56:$F$56,$AG$4)) | AH16: =IF($AH$5="ConsentCostPerStudentYear",$AH$6,INDEX(Assumptions!$D$56:$F$56,$AH$4)) | AI16: =IF($AI$5="ConsentCostPerStudentYear",$AI$6,INDEX(Assumptions!$D$56:$F$56,$AI$4)) | AJ16: =IF($AJ$5="ConsentCostPerStudentYear",$AJ$6,INDEX(Assumptions!$D$56:$F$56,$AJ$4)) | AK16: =IF($AK$5="ConsentCostPerStudentYear",$AK$6,INDEX(Assumptions!$D$56:$F$56,$AK$4)) | AL16: =IF($AL$5="ConsentCostPerStudentYear",$AL$6,INDEX(Assumptions!$D$56:$F$56,$AL$4)) | AM16: =IF($AM$5="ConsentCostPerStudentYear",$AM$6,INDEX(Assumptions!$D$56:$F$56,$AM$4)) | AN16: =IF($AN$5="ConsentCostPerStudentYear",$AN$6,INDEX(Assumptions!$D$56:$F$56,$AN$4)) | AO16: =IF($AO$5="ConsentCostPerStudentYear",$AO$6,INDEX(Assumptions!$D$56:$F$56,$AO$4)) | AP16: =IF($AP$5="ConsentCostPerStudentYear",$AP$6,INDEX(Assumptions!$D$56:$F$56,$AP$4)) | AQ16: =IF($AQ$5="ConsentCostPerStudentYear",$AQ$6,INDEX(Assumptions!$D$56:$F$56,$AQ$4)) | AR16: =IF($AR$5="ConsentCostPerStudentYear",$AR$6,INDEX(Assumptions!$D$56:$F$56,$AR$4)) | AS16: =IF($AS$5="ConsentCostPerStudentYear",$AS$6,INDEX(Assumptions!$D$56:$F$56,$AS$4)) | AT16: =IF($AT$5="ConsentCostPerStudentYear",$AT$6,INDEX(Assumptions!$D$56:$F$56,$AT$4)) | AU16: =IF($AU$5="ConsentCostPerStudentYear",$AU$6,INDEX(Assumptions!$D$56:$F$56,$AU$4)) | AV16: =IF($AV$5="ConsentCostPerStudentYear",$AV$6,INDEX(Assumptions!$D$56:$F$56,$AV$4))
B17: ServerCostMonth | D17: =IF($D$5="ServerCostMonth",$D$6,INDEX(Assumptions!$D$57:$F$57,$D$4)) | E17: =IF($E$5="ServerCostMonth",$E$6,INDEX(Assumptions!$D$57:$F$57,$E$4)) | F17: =IF($F$5="ServerCostMonth",$F$6,INDEX(Assumptions!$D$57:$F$57,$F$4)) | G17: =IF($G$5="ServerCostMonth",$G$6,INDEX(Assumptions!$D$57:$F$57,$G$4)) | H17: =IF($H$5="ServerCostMonth",$H$6,INDEX(Assumptions!$D$57:$F$57,$H$4)) | I17: =IF($I$5="ServerCostMonth",$I$6,INDEX(Assumptions!$D$57:$F$57,$I$4)) | J17: =IF($J$5="ServerCostMonth",$J$6,INDEX(Assumptions!$D$57:$F$57,$J$4)) | K17: =IF($K$5="ServerCostMonth",$K$6,INDEX(Assumptions!$D$57:$F$57,$K$4)) | L17: =IF($L$5="ServerCostMonth",$L$6,INDEX(Assumptions!$D$57:$F$57,$L$4)) | M17: =IF($M$5="ServerCostMonth",$M$6,INDEX(Assumptions!$D$57:$F$57,$M$4)) | N17: =IF($N$5="ServerCostMonth",$N$6,INDEX(Assumptions!$D$57:$F$57,$N$4)) | O17: =IF($O$5="ServerCostMonth",$O$6,INDEX(Assumptions!$D$57:$F$57,$O$4)) | P17: =IF($P$5="ServerCostMonth",$P$6,INDEX(Assumptions!$D$57:$F$57,$P$4)) | Q17: =IF($Q$5="ServerCostMonth",$Q$6,INDEX(Assumptions!$D$57:$F$57,$Q$4)) | R17: =IF($R$5="ServerCostMonth",$R$6,INDEX(Assumptions!$D$57:$F$57,$R$4)) | S17: =IF($S$5="ServerCostMonth",$S$6,INDEX(Assumptions!$D$57:$F$57,$S$4)) | T17: =IF($T$5="ServerCostMonth",$T$6,INDEX(Assumptions!$D$57:$F$57,$T$4)) | U17: =IF($U$5="ServerCostMonth",$U$6,INDEX(Assumptions!$D$57:$F$57,$U$4)) | V17: =IF($V$5="ServerCostMonth",$V$6,INDEX(Assumptions!$D$57:$F$57,$V$4)) | W17: =IF($W$5="ServerCostMonth",$W$6,INDEX(Assumptions!$D$57:$F$57,$W$4)) | X17: =IF($X$5="ServerCostMonth",$X$6,INDEX(Assumptions!$D$57:$F$57,$X$4)) | Y17: =IF($Y$5="ServerCostMonth",$Y$6,INDEX(Assumptions!$D$57:$F$57,$Y$4)) | Z17: =IF($Z$5="ServerCostMonth",$Z$6,INDEX(Assumptions!$D$57:$F$57,$Z$4)) | AA17: =IF($AA$5="ServerCostMonth",$AA$6,INDEX(Assumptions!$D$57:$F$57,$AA$4)) | AB17: =IF($AB$5="ServerCostMonth",$AB$6,INDEX(Assumptions!$D$57:$F$57,$AB$4)) | AC17: =IF($AC$5="ServerCostMonth",$AC$6,INDEX(Assumptions!$D$57:$F$57,$AC$4)) | AD17: =IF($AD$5="ServerCostMonth",$AD$6,INDEX(Assumptions!$D$57:$F$57,$AD$4)) | AE17: =IF($AE$5="ServerCostMonth",$AE$6,INDEX(Assumptions!$D$57:$F$57,$AE$4)) | AF17: =IF($AF$5="ServerCostMonth",$AF$6,INDEX(Assumptions!$D$57:$F$57,$AF$4)) | AG17: =IF($AG$5="ServerCostMonth",$AG$6,INDEX(Assumptions!$D$57:$F$57,$AG$4)) | AH17: =IF($AH$5="ServerCostMonth",$AH$6,INDEX(Assumptions!$D$57:$F$57,$AH$4)) | AI17: =IF($AI$5="ServerCostMonth",$AI$6,INDEX(Assumptions!$D$57:$F$57,$AI$4)) | AJ17: =IF($AJ$5="ServerCostMonth",$AJ$6,INDEX(Assumptions!$D$57:$F$57,$AJ$4)) | AK17: =IF($AK$5="ServerCostMonth",$AK$6,INDEX(Assumptions!$D$57:$F$57,$AK$4)) | AL17: =IF($AL$5="ServerCostMonth",$AL$6,INDEX(Assumptions!$D$57:$F$57,$AL$4)) | AM17: =IF($AM$5="ServerCostMonth",$AM$6,INDEX(Assumptions!$D$57:$F$57,$AM$4)) | AN17: =IF($AN$5="ServerCostMonth",$AN$6,INDEX(Assumptions!$D$57:$F$57,$AN$4)) | AO17: =IF($AO$5="ServerCostMonth",$AO$6,INDEX(Assumptions!$D$57:$F$57,$AO$4)) | AP17: =IF($AP$5="ServerCostMonth",$AP$6,INDEX(Assumptions!$D$57:$F$57,$AP$4)) | AQ17: =IF($AQ$5="ServerCostMonth",$AQ$6,INDEX(Assumptions!$D$57:$F$57,$AQ$4)) | AR17: =IF($AR$5="ServerCostMonth",$AR$6,INDEX(Assumptions!$D$57:$F$57,$AR$4)) | AS17: =IF($AS$5="ServerCostMonth",$AS$6,INDEX(Assumptions!$D$57:$F$57,$AS$4)) | AT17: =IF($AT$5="ServerCostMonth",$AT$6,INDEX(Assumptions!$D$57:$F$57,$AT$4)) | AU17: =IF($AU$5="ServerCostMonth",$AU$6,INDEX(Assumptions!$D$57:$F$57,$AU$4)) | AV17: =IF($AV$5="ServerCostMonth",$AV$6,INDEX(Assumptions!$D$57:$F$57,$AV$4))
B18: BSPFeeMonth | D18: =IF($D$5="BSPFeeMonth",$D$6,INDEX(Assumptions!$D$58:$F$58,$D$4)) | E18: =IF($E$5="BSPFeeMonth",$E$6,INDEX(Assumptions!$D$58:$F$58,$E$4)) | F18: =IF($F$5="BSPFeeMonth",$F$6,INDEX(Assumptions!$D$58:$F$58,$F$4)) | G18: =IF($G$5="BSPFeeMonth",$G$6,INDEX(Assumptions!$D$58:$F$58,$G$4)) | H18: =IF($H$5="BSPFeeMonth",$H$6,INDEX(Assumptions!$D$58:$F$58,$H$4)) | I18: =IF($I$5="BSPFeeMonth",$I$6,INDEX(Assumptions!$D$58:$F$58,$I$4)) | J18: =IF($J$5="BSPFeeMonth",$J$6,INDEX(Assumptions!$D$58:$F$58,$J$4)) | K18: =IF($K$5="BSPFeeMonth",$K$6,INDEX(Assumptions!$D$58:$F$58,$K$4)) | L18: =IF($L$5="BSPFeeMonth",$L$6,INDEX(Assumptions!$D$58:$F$58,$L$4)) | M18: =IF($M$5="BSPFeeMonth",$M$6,INDEX(Assumptions!$D$58:$F$58,$M$4)) | N18: =IF($N$5="BSPFeeMonth",$N$6,INDEX(Assumptions!$D$58:$F$58,$N$4)) | O18: =IF($O$5="BSPFeeMonth",$O$6,INDEX(Assumptions!$D$58:$F$58,$O$4)) | P18: =IF($P$5="BSPFeeMonth",$P$6,INDEX(Assumptions!$D$58:$F$58,$P$4)) | Q18: =IF($Q$5="BSPFeeMonth",$Q$6,INDEX(Assumptions!$D$58:$F$58,$Q$4)) | R18: =IF($R$5="BSPFeeMonth",$R$6,INDEX(Assumptions!$D$58:$F$58,$R$4)) | S18: =IF($S$5="BSPFeeMonth",$S$6,INDEX(Assumptions!$D$58:$F$58,$S$4)) | T18: =IF($T$5="BSPFeeMonth",$T$6,INDEX(Assumptions!$D$58:$F$58,$T$4)) | U18: =IF($U$5="BSPFeeMonth",$U$6,INDEX(Assumptions!$D$58:$F$58,$U$4)) | V18: =IF($V$5="BSPFeeMonth",$V$6,INDEX(Assumptions!$D$58:$F$58,$V$4)) | W18: =IF($W$5="BSPFeeMonth",$W$6,INDEX(Assumptions!$D$58:$F$58,$W$4)) | X18: =IF($X$5="BSPFeeMonth",$X$6,INDEX(Assumptions!$D$58:$F$58,$X$4)) | Y18: =IF($Y$5="BSPFeeMonth",$Y$6,INDEX(Assumptions!$D$58:$F$58,$Y$4)) | Z18: =IF($Z$5="BSPFeeMonth",$Z$6,INDEX(Assumptions!$D$58:$F$58,$Z$4)) | AA18: =IF($AA$5="BSPFeeMonth",$AA$6,INDEX(Assumptions!$D$58:$F$58,$AA$4)) | AB18: =IF($AB$5="BSPFeeMonth",$AB$6,INDEX(Assumptions!$D$58:$F$58,$AB$4)) | AC18: =IF($AC$5="BSPFeeMonth",$AC$6,INDEX(Assumptions!$D$58:$F$58,$AC$4)) | AD18: =IF($AD$5="BSPFeeMonth",$AD$6,INDEX(Assumptions!$D$58:$F$58,$AD$4)) | AE18: =IF($AE$5="BSPFeeMonth",$AE$6,INDEX(Assumptions!$D$58:$F$58,$AE$4)) | AF18: =IF($AF$5="BSPFeeMonth",$AF$6,INDEX(Assumptions!$D$58:$F$58,$AF$4)) | AG18: =IF($AG$5="BSPFeeMonth",$AG$6,INDEX(Assumptions!$D$58:$F$58,$AG$4)) | AH18: =IF($AH$5="BSPFeeMonth",$AH$6,INDEX(Assumptions!$D$58:$F$58,$AH$4)) | AI18: =IF($AI$5="BSPFeeMonth",$AI$6,INDEX(Assumptions!$D$58:$F$58,$AI$4)) | AJ18: =IF($AJ$5="BSPFeeMonth",$AJ$6,INDEX(Assumptions!$D$58:$F$58,$AJ$4)) | AK18: =IF($AK$5="BSPFeeMonth",$AK$6,INDEX(Assumptions!$D$58:$F$58,$AK$4)) | AL18: =IF($AL$5="BSPFeeMonth",$AL$6,INDEX(Assumptions!$D$58:$F$58,$AL$4)) | AM18: =IF($AM$5="BSPFeeMonth",$AM$6,INDEX(Assumptions!$D$58:$F$58,$AM$4)) | AN18: =IF($AN$5="BSPFeeMonth",$AN$6,INDEX(Assumptions!$D$58:$F$58,$AN$4)) | AO18: =IF($AO$5="BSPFeeMonth",$AO$6,INDEX(Assumptions!$D$58:$F$58,$AO$4)) | AP18: =IF($AP$5="BSPFeeMonth",$AP$6,INDEX(Assumptions!$D$58:$F$58,$AP$4)) | AQ18: =IF($AQ$5="BSPFeeMonth",$AQ$6,INDEX(Assumptions!$D$58:$F$58,$AQ$4)) | AR18: =IF($AR$5="BSPFeeMonth",$AR$6,INDEX(Assumptions!$D$58:$F$58,$AR$4)) | AS18: =IF($AS$5="BSPFeeMonth",$AS$6,INDEX(Assumptions!$D$58:$F$58,$AS$4)) | AT18: =IF($AT$5="BSPFeeMonth",$AT$6,INDEX(Assumptions!$D$58:$F$58,$AT$4)) | AU18: =IF($AU$5="BSPFeeMonth",$AU$6,INDEX(Assumptions!$D$58:$F$58,$AU$4)) | AV18: =IF($AV$5="BSPFeeMonth",$AV$6,INDEX(Assumptions!$D$58:$F$58,$AV$4))
B19: InstPerStack | D19: =IF($D$5="InstPerStack",$D$6,INDEX(Assumptions!$D$59:$F$59,$D$4)) | E19: =IF($E$5="InstPerStack",$E$6,INDEX(Assumptions!$D$59:$F$59,$E$4)) | F19: =IF($F$5="InstPerStack",$F$6,INDEX(Assumptions!$D$59:$F$59,$F$4)) | G19: =IF($G$5="InstPerStack",$G$6,INDEX(Assumptions!$D$59:$F$59,$G$4)) | H19: =IF($H$5="InstPerStack",$H$6,INDEX(Assumptions!$D$59:$F$59,$H$4)) | I19: =IF($I$5="InstPerStack",$I$6,INDEX(Assumptions!$D$59:$F$59,$I$4)) | J19: =IF($J$5="InstPerStack",$J$6,INDEX(Assumptions!$D$59:$F$59,$J$4)) | K19: =IF($K$5="InstPerStack",$K$6,INDEX(Assumptions!$D$59:$F$59,$K$4)) | L19: =IF($L$5="InstPerStack",$L$6,INDEX(Assumptions!$D$59:$F$59,$L$4)) | M19: =IF($M$5="InstPerStack",$M$6,INDEX(Assumptions!$D$59:$F$59,$M$4)) | N19: =IF($N$5="InstPerStack",$N$6,INDEX(Assumptions!$D$59:$F$59,$N$4)) | O19: =IF($O$5="InstPerStack",$O$6,INDEX(Assumptions!$D$59:$F$59,$O$4)) | P19: =IF($P$5="InstPerStack",$P$6,INDEX(Assumptions!$D$59:$F$59,$P$4)) | Q19: =IF($Q$5="InstPerStack",$Q$6,INDEX(Assumptions!$D$59:$F$59,$Q$4)) | R19: =IF($R$5="InstPerStack",$R$6,INDEX(Assumptions!$D$59:$F$59,$R$4)) | S19: =IF($S$5="InstPerStack",$S$6,INDEX(Assumptions!$D$59:$F$59,$S$4)) | T19: =IF($T$5="InstPerStack",$T$6,INDEX(Assumptions!$D$59:$F$59,$T$4)) | U19: =IF($U$5="InstPerStack",$U$6,INDEX(Assumptions!$D$59:$F$59,$U$4)) | V19: =IF($V$5="InstPerStack",$V$6,INDEX(Assumptions!$D$59:$F$59,$V$4)) | W19: =IF($W$5="InstPerStack",$W$6,INDEX(Assumptions!$D$59:$F$59,$W$4)) | X19: =IF($X$5="InstPerStack",$X$6,INDEX(Assumptions!$D$59:$F$59,$X$4)) | Y19: =IF($Y$5="InstPerStack",$Y$6,INDEX(Assumptions!$D$59:$F$59,$Y$4)) | Z19: =IF($Z$5="InstPerStack",$Z$6,INDEX(Assumptions!$D$59:$F$59,$Z$4)) | AA19: =IF($AA$5="InstPerStack",$AA$6,INDEX(Assumptions!$D$59:$F$59,$AA$4)) | AB19: =IF($AB$5="InstPerStack",$AB$6,INDEX(Assumptions!$D$59:$F$59,$AB$4)) | AC19: =IF($AC$5="InstPerStack",$AC$6,INDEX(Assumptions!$D$59:$F$59,$AC$4)) | AD19: =IF($AD$5="InstPerStack",$AD$6,INDEX(Assumptions!$D$59:$F$59,$AD$4)) | AE19: =IF($AE$5="InstPerStack",$AE$6,INDEX(Assumptions!$D$59:$F$59,$AE$4)) | AF19: =IF($AF$5="InstPerStack",$AF$6,INDEX(Assumptions!$D$59:$F$59,$AF$4)) | AG19: =IF($AG$5="InstPerStack",$AG$6,INDEX(Assumptions!$D$59:$F$59,$AG$4)) | AH19: =IF($AH$5="InstPerStack",$AH$6,INDEX(Assumptions!$D$59:$F$59,$AH$4)) | AI19: =IF($AI$5="InstPerStack",$AI$6,INDEX(Assumptions!$D$59:$F$59,$AI$4)) | AJ19: =IF($AJ$5="InstPerStack",$AJ$6,INDEX(Assumptions!$D$59:$F$59,$AJ$4)) | AK19: =IF($AK$5="InstPerStack",$AK$6,INDEX(Assumptions!$D$59:$F$59,$AK$4)) | AL19: =IF($AL$5="InstPerStack",$AL$6,INDEX(Assumptions!$D$59:$F$59,$AL$4)) | AM19: =IF($AM$5="InstPerStack",$AM$6,INDEX(Assumptions!$D$59:$F$59,$AM$4)) | AN19: =IF($AN$5="InstPerStack",$AN$6,INDEX(Assumptions!$D$59:$F$59,$AN$4)) | AO19: =IF($AO$5="InstPerStack",$AO$6,INDEX(Assumptions!$D$59:$F$59,$AO$4)) | AP19: =IF($AP$5="InstPerStack",$AP$6,INDEX(Assumptions!$D$59:$F$59,$AP$4)) | AQ19: =IF($AQ$5="InstPerStack",$AQ$6,INDEX(Assumptions!$D$59:$F$59,$AQ$4)) | AR19: =IF($AR$5="InstPerStack",$AR$6,INDEX(Assumptions!$D$59:$F$59,$AR$4)) | AS19: =IF($AS$5="InstPerStack",$AS$6,INDEX(Assumptions!$D$59:$F$59,$AS$4)) | AT19: =IF($AT$5="InstPerStack",$AT$6,INDEX(Assumptions!$D$59:$F$59,$AT$4)) | AU19: =IF($AU$5="InstPerStack",$AU$6,INDEX(Assumptions!$D$59:$F$59,$AU$4)) | AV19: =IF($AV$5="InstPerStack",$AV$6,INDEX(Assumptions!$D$59:$F$59,$AV$4))
B20: CompliancePerInstMonth | D20: =IF($D$5="CompliancePerInstMonth",$D$6,INDEX(Assumptions!$D$60:$F$60,$D$4)) | E20: =IF($E$5="CompliancePerInstMonth",$E$6,INDEX(Assumptions!$D$60:$F$60,$E$4)) | F20: =IF($F$5="CompliancePerInstMonth",$F$6,INDEX(Assumptions!$D$60:$F$60,$F$4)) | G20: =IF($G$5="CompliancePerInstMonth",$G$6,INDEX(Assumptions!$D$60:$F$60,$G$4)) | H20: =IF($H$5="CompliancePerInstMonth",$H$6,INDEX(Assumptions!$D$60:$F$60,$H$4)) | I20: =IF($I$5="CompliancePerInstMonth",$I$6,INDEX(Assumptions!$D$60:$F$60,$I$4)) | J20: =IF($J$5="CompliancePerInstMonth",$J$6,INDEX(Assumptions!$D$60:$F$60,$J$4)) | K20: =IF($K$5="CompliancePerInstMonth",$K$6,INDEX(Assumptions!$D$60:$F$60,$K$4)) | L20: =IF($L$5="CompliancePerInstMonth",$L$6,INDEX(Assumptions!$D$60:$F$60,$L$4)) | M20: =IF($M$5="CompliancePerInstMonth",$M$6,INDEX(Assumptions!$D$60:$F$60,$M$4)) | N20: =IF($N$5="CompliancePerInstMonth",$N$6,INDEX(Assumptions!$D$60:$F$60,$N$4)) | O20: =IF($O$5="CompliancePerInstMonth",$O$6,INDEX(Assumptions!$D$60:$F$60,$O$4)) | P20: =IF($P$5="CompliancePerInstMonth",$P$6,INDEX(Assumptions!$D$60:$F$60,$P$4)) | Q20: =IF($Q$5="CompliancePerInstMonth",$Q$6,INDEX(Assumptions!$D$60:$F$60,$Q$4)) | R20: =IF($R$5="CompliancePerInstMonth",$R$6,INDEX(Assumptions!$D$60:$F$60,$R$4)) | S20: =IF($S$5="CompliancePerInstMonth",$S$6,INDEX(Assumptions!$D$60:$F$60,$S$4)) | T20: =IF($T$5="CompliancePerInstMonth",$T$6,INDEX(Assumptions!$D$60:$F$60,$T$4)) | U20: =IF($U$5="CompliancePerInstMonth",$U$6,INDEX(Assumptions!$D$60:$F$60,$U$4)) | V20: =IF($V$5="CompliancePerInstMonth",$V$6,INDEX(Assumptions!$D$60:$F$60,$V$4)) | W20: =IF($W$5="CompliancePerInstMonth",$W$6,INDEX(Assumptions!$D$60:$F$60,$W$4)) | X20: =IF($X$5="CompliancePerInstMonth",$X$6,INDEX(Assumptions!$D$60:$F$60,$X$4)) | Y20: =IF($Y$5="CompliancePerInstMonth",$Y$6,INDEX(Assumptions!$D$60:$F$60,$Y$4)) | Z20: =IF($Z$5="CompliancePerInstMonth",$Z$6,INDEX(Assumptions!$D$60:$F$60,$Z$4)) | AA20: =IF($AA$5="CompliancePerInstMonth",$AA$6,INDEX(Assumptions!$D$60:$F$60,$AA$4)) | AB20: =IF($AB$5="CompliancePerInstMonth",$AB$6,INDEX(Assumptions!$D$60:$F$60,$AB$4)) | AC20: =IF($AC$5="CompliancePerInstMonth",$AC$6,INDEX(Assumptions!$D$60:$F$60,$AC$4)) | AD20: =IF($AD$5="CompliancePerInstMonth",$AD$6,INDEX(Assumptions!$D$60:$F$60,$AD$4)) | AE20: =IF($AE$5="CompliancePerInstMonth",$AE$6,INDEX(Assumptions!$D$60:$F$60,$AE$4)) | AF20: =IF($AF$5="CompliancePerInstMonth",$AF$6,INDEX(Assumptions!$D$60:$F$60,$AF$4)) | AG20: =IF($AG$5="CompliancePerInstMonth",$AG$6,INDEX(Assumptions!$D$60:$F$60,$AG$4)) | AH20: =IF($AH$5="CompliancePerInstMonth",$AH$6,INDEX(Assumptions!$D$60:$F$60,$AH$4)) | AI20: =IF($AI$5="CompliancePerInstMonth",$AI$6,INDEX(Assumptions!$D$60:$F$60,$AI$4)) | AJ20: =IF($AJ$5="CompliancePerInstMonth",$AJ$6,INDEX(Assumptions!$D$60:$F$60,$AJ$4)) | AK20: =IF($AK$5="CompliancePerInstMonth",$AK$6,INDEX(Assumptions!$D$60:$F$60,$AK$4)) | AL20: =IF($AL$5="CompliancePerInstMonth",$AL$6,INDEX(Assumptions!$D$60:$F$60,$AL$4)) | AM20: =IF($AM$5="CompliancePerInstMonth",$AM$6,INDEX(Assumptions!$D$60:$F$60,$AM$4)) | AN20: =IF($AN$5="CompliancePerInstMonth",$AN$6,INDEX(Assumptions!$D$60:$F$60,$AN$4)) | AO20: =IF($AO$5="CompliancePerInstMonth",$AO$6,INDEX(Assumptions!$D$60:$F$60,$AO$4)) | AP20: =IF($AP$5="CompliancePerInstMonth",$AP$6,INDEX(Assumptions!$D$60:$F$60,$AP$4)) | AQ20: =IF($AQ$5="CompliancePerInstMonth",$AQ$6,INDEX(Assumptions!$D$60:$F$60,$AQ$4)) | AR20: =IF($AR$5="CompliancePerInstMonth",$AR$6,INDEX(Assumptions!$D$60:$F$60,$AR$4)) | AS20: =IF($AS$5="CompliancePerInstMonth",$AS$6,INDEX(Assumptions!$D$60:$F$60,$AS$4)) | AT20: =IF($AT$5="CompliancePerInstMonth",$AT$6,INDEX(Assumptions!$D$60:$F$60,$AT$4)) | AU20: =IF($AU$5="CompliancePerInstMonth",$AU$6,INDEX(Assumptions!$D$60:$F$60,$AU$4)) | AV20: =IF($AV$5="CompliancePerInstMonth",$AV$6,INDEX(Assumptions!$D$60:$F$60,$AV$4))
B21: Students | D21: =IF($D$5="Students",$D$6,INDEX(Assumptions!$D$6:$F$6,$D$4)) | E21: =IF($E$5="Students",$E$6,INDEX(Assumptions!$D$7:$F$7,$E$4)) | F21: =IF($F$5="Students",$F$6,INDEX(Assumptions!$D$8:$F$8,$F$4)) | G21: =IF($G$5="Students",$G$6,INDEX(Assumptions!$D$6:$F$6,$G$4)) | H21: =IF($H$5="Students",$H$6,INDEX(Assumptions!$D$7:$F$7,$H$4)) | I21: =IF($I$5="Students",$I$6,INDEX(Assumptions!$D$8:$F$8,$I$4)) | J21: =IF($J$5="Students",$J$6,INDEX(Assumptions!$D$6:$F$6,$J$4)) | K21: =IF($K$5="Students",$K$6,INDEX(Assumptions!$D$7:$F$7,$K$4)) | L21: =IF($L$5="Students",$L$6,INDEX(Assumptions!$D$8:$F$8,$L$4)) | M21: =IF($M$5="Students",$M$6,INDEX(Assumptions!$D$6:$F$6,$M$4)) | N21: =IF($N$5="Students",$N$6,INDEX(Assumptions!$D$7:$F$7,$N$4)) | O21: =IF($O$5="Students",$O$6,INDEX(Assumptions!$D$8:$F$8,$O$4)) | P21: =IF($P$5="Students",$P$6,INDEX(Assumptions!$D$7:$F$7,$P$4)) | Q21: =IF($Q$5="Students",$Q$6,INDEX(Assumptions!$D$7:$F$7,$Q$4)) | R21: =IF($R$5="Students",$R$6,INDEX(Assumptions!$D$7:$F$7,$R$4)) | S21: =IF($S$5="Students",$S$6,INDEX(Assumptions!$D$7:$F$7,$S$4)) | T21: =IF($T$5="Students",$T$6,INDEX(Assumptions!$D$7:$F$7,$T$4)) | U21: =IF($U$5="Students",$U$6,INDEX(Assumptions!$D$7:$F$7,$U$4)) | V21: =IF($V$5="Students",$V$6,INDEX(Assumptions!$D$7:$F$7,$V$4)) | W21: =IF($W$5="Students",$W$6,INDEX(Assumptions!$D$7:$F$7,$W$4)) | X21: =IF($X$5="Students",$X$6,INDEX(Assumptions!$D$7:$F$7,$X$4)) | Y21: =IF($Y$5="Students",$Y$6,INDEX(Assumptions!$D$7:$F$7,$Y$4)) | Z21: =IF($Z$5="Students",$Z$6,INDEX(Assumptions!$D$7:$F$7,$Z$4)) | AA21: =IF($AA$5="Students",$AA$6,INDEX(Assumptions!$D$7:$F$7,$AA$4)) | AB21: =IF($AB$5="Students",$AB$6,INDEX(Assumptions!$D$7:$F$7,$AB$4)) | AC21: =IF($AC$5="Students",$AC$6,INDEX(Assumptions!$D$7:$F$7,$AC$4)) | AD21: =IF($AD$5="Students",$AD$6,INDEX(Assumptions!$D$7:$F$7,$AD$4)) | AE21: =IF($AE$5="Students",$AE$6,INDEX(Assumptions!$D$7:$F$7,$AE$4)) | AF21: =IF($AF$5="Students",$AF$6,INDEX(Assumptions!$D$7:$F$7,$AF$4)) | AG21: =IF($AG$5="Students",$AG$6,INDEX(Assumptions!$D$7:$F$7,$AG$4)) | AH21: =IF($AH$5="Students",$AH$6,INDEX(Assumptions!$D$7:$F$7,$AH$4)) | AI21: =IF($AI$5="Students",$AI$6,INDEX(Assumptions!$D$7:$F$7,$AI$4)) | AJ21: =IF($AJ$5="Students",$AJ$6,INDEX(Assumptions!$D$7:$F$7,$AJ$4)) | AK21: =IF($AK$5="Students",$AK$6,INDEX(Assumptions!$D$7:$F$7,$AK$4)) | AL21: =IF($AL$5="Students",$AL$6,INDEX(Assumptions!$D$7:$F$7,$AL$4)) | AM21: =IF($AM$5="Students",$AM$6,INDEX(Assumptions!$D$7:$F$7,$AM$4)) | AN21: =IF($AN$5="Students",$AN$6,INDEX(Assumptions!$D$7:$F$7,$AN$4)) | AO21: =IF($AO$5="Students",$AO$6,INDEX(Assumptions!$D$7:$F$7,$AO$4)) | AP21: =IF($AP$5="Students",$AP$6,INDEX(Assumptions!$D$7:$F$7,$AP$4)) | AQ21: =IF($AQ$5="Students",$AQ$6,INDEX(Assumptions!$D$7:$F$7,$AQ$4)) | AR21: =IF($AR$5="Students",$AR$6,INDEX(Assumptions!$D$7:$F$7,$AR$4)) | AS21: =IF($AS$5="Students",$AS$6,INDEX(Assumptions!$D$7:$F$7,$AS$4)) | AT21: =IF($AT$5="Students",$AT$6,INDEX(Assumptions!$D$7:$F$7,$AT$4)) | AU21: =IF($AU$5="Students",$AU$6,INDEX(Assumptions!$D$7:$F$7,$AU$4)) | AV21: =IF($AV$5="Students",$AV$6,INDEX(Assumptions!$D$7:$F$7,$AV$4))
B22: ListPrice | D22: =IF($D$5="ListPrice",$D$6,INDEX(Assumptions!$D$38:$F$38,$D$4)) | E22: =IF($E$5="ListPrice",$E$6,INDEX(Assumptions!$D$38:$F$38,$E$4)) | F22: =IF($F$5="ListPrice",$F$6,INDEX(Assumptions!$D$38:$F$38,$F$4)) | G22: =IF($G$5="ListPrice",$G$6,INDEX(Assumptions!$D$38:$F$38,$G$4)) | H22: =IF($H$5="ListPrice",$H$6,INDEX(Assumptions!$D$38:$F$38,$H$4)) | I22: =IF($I$5="ListPrice",$I$6,INDEX(Assumptions!$D$38:$F$38,$I$4)) | J22: =IF($J$5="ListPrice",$J$6,INDEX(Assumptions!$D$38:$F$38,$J$4)) | K22: =IF($K$5="ListPrice",$K$6,INDEX(Assumptions!$D$38:$F$38,$K$4)) | L22: =IF($L$5="ListPrice",$L$6,INDEX(Assumptions!$D$38:$F$38,$L$4)) | M22: =IF($M$5="ListPrice",$M$6,INDEX(Assumptions!$D$38:$F$38,$M$4)) | N22: =IF($N$5="ListPrice",$N$6,INDEX(Assumptions!$D$38:$F$38,$N$4)) | O22: =IF($O$5="ListPrice",$O$6,INDEX(Assumptions!$D$38:$F$38,$O$4)) | P22: =IF($P$5="ListPrice",$P$6,INDEX(Assumptions!$D$38:$F$38,$P$4)) | Q22: =IF($Q$5="ListPrice",$Q$6,INDEX(Assumptions!$D$38:$F$38,$Q$4)) | R22: =IF($R$5="ListPrice",$R$6,INDEX(Assumptions!$D$38:$F$38,$R$4)) | S22: =IF($S$5="ListPrice",$S$6,INDEX(Assumptions!$D$38:$F$38,$S$4)) | T22: =IF($T$5="ListPrice",$T$6,INDEX(Assumptions!$D$38:$F$38,$T$4)) | U22: =IF($U$5="ListPrice",$U$6,INDEX(Assumptions!$D$38:$F$38,$U$4)) | V22: =IF($V$5="ListPrice",$V$6,INDEX(Assumptions!$D$38:$F$38,$V$4)) | W22: =IF($W$5="ListPrice",$W$6,INDEX(Assumptions!$D$38:$F$38,$W$4)) | X22: =IF($X$5="ListPrice",$X$6,INDEX(Assumptions!$D$38:$F$38,$X$4)) | Y22: =IF($Y$5="ListPrice",$Y$6,INDEX(Assumptions!$D$38:$F$38,$Y$4)) | Z22: =IF($Z$5="ListPrice",$Z$6,INDEX(Assumptions!$D$38:$F$38,$Z$4)) | AA22: =IF($AA$5="ListPrice",$AA$6,INDEX(Assumptions!$D$38:$F$38,$AA$4)) | AB22: =IF($AB$5="ListPrice",$AB$6,INDEX(Assumptions!$D$38:$F$38,$AB$4)) | AC22: =IF($AC$5="ListPrice",$AC$6,INDEX(Assumptions!$D$38:$F$38,$AC$4)) | AD22: =IF($AD$5="ListPrice",$AD$6,INDEX(Assumptions!$D$38:$F$38,$AD$4)) | AE22: =IF($AE$5="ListPrice",$AE$6,INDEX(Assumptions!$D$38:$F$38,$AE$4)) | AF22: =IF($AF$5="ListPrice",$AF$6,INDEX(Assumptions!$D$38:$F$38,$AF$4)) | AG22: =IF($AG$5="ListPrice",$AG$6,INDEX(Assumptions!$D$38:$F$38,$AG$4)) | AH22: =IF($AH$5="ListPrice",$AH$6,INDEX(Assumptions!$D$38:$F$38,$AH$4)) | AI22: =IF($AI$5="ListPrice",$AI$6,INDEX(Assumptions!$D$38:$F$38,$AI$4)) | AJ22: =IF($AJ$5="ListPrice",$AJ$6,INDEX(Assumptions!$D$38:$F$38,$AJ$4)) | AK22: =IF($AK$5="ListPrice",$AK$6,INDEX(Assumptions!$D$38:$F$38,$AK$4)) | AL22: =IF($AL$5="ListPrice",$AL$6,INDEX(Assumptions!$D$38:$F$38,$AL$4)) | AM22: =IF($AM$5="ListPrice",$AM$6,INDEX(Assumptions!$D$38:$F$38,$AM$4)) | AN22: =IF($AN$5="ListPrice",$AN$6,INDEX(Assumptions!$D$38:$F$38,$AN$4)) | AO22: =IF($AO$5="ListPrice",$AO$6,INDEX(Assumptions!$D$38:$F$38,$AO$4)) | AP22: =IF($AP$5="ListPrice",$AP$6,INDEX(Assumptions!$D$38:$F$38,$AP$4)) | AQ22: =IF($AQ$5="ListPrice",$AQ$6,INDEX(Assumptions!$D$38:$F$38,$AQ$4)) | AR22: =IF($AR$5="ListPrice",$AR$6,INDEX(Assumptions!$D$38:$F$38,$AR$4)) | AS22: =IF($AS$5="ListPrice",$AS$6,INDEX(Assumptions!$D$38:$F$38,$AS$4)) | AT22: =IF($AT$5="ListPrice",$AT$6,INDEX(Assumptions!$D$38:$F$38,$AT$4)) | AU22: =IF($AU$5="ListPrice",$AU$6,INDEX(Assumptions!$D$38:$F$38,$AU$4)) | AV22: =IF($AV$5="ListPrice",$AV$6,INDEX(Assumptions!$D$38:$F$38,$AV$4))
B23: MinFee | D23: =IF($D$5="MinFee",$D$6,INDEX(Assumptions!$D$41:$F$41,$D$4)) | E23: =IF($E$5="MinFee",$E$6,INDEX(Assumptions!$D$41:$F$41,$E$4)) | F23: =IF($F$5="MinFee",$F$6,INDEX(Assumptions!$D$41:$F$41,$F$4)) | G23: =IF($G$5="MinFee",$G$6,INDEX(Assumptions!$D$41:$F$41,$G$4)) | H23: =IF($H$5="MinFee",$H$6,INDEX(Assumptions!$D$41:$F$41,$H$4)) | I23: =IF($I$5="MinFee",$I$6,INDEX(Assumptions!$D$41:$F$41,$I$4)) | J23: =IF($J$5="MinFee",$J$6,INDEX(Assumptions!$D$41:$F$41,$J$4)) | K23: =IF($K$5="MinFee",$K$6,INDEX(Assumptions!$D$41:$F$41,$K$4)) | L23: =IF($L$5="MinFee",$L$6,INDEX(Assumptions!$D$41:$F$41,$L$4)) | M23: =IF($M$5="MinFee",$M$6,INDEX(Assumptions!$D$41:$F$41,$M$4)) | N23: =IF($N$5="MinFee",$N$6,INDEX(Assumptions!$D$41:$F$41,$N$4)) | O23: =IF($O$5="MinFee",$O$6,INDEX(Assumptions!$D$41:$F$41,$O$4)) | P23: =IF($P$5="MinFee",$P$6,INDEX(Assumptions!$D$41:$F$41,$P$4)) | Q23: =IF($Q$5="MinFee",$Q$6,INDEX(Assumptions!$D$41:$F$41,$Q$4)) | R23: =IF($R$5="MinFee",$R$6,INDEX(Assumptions!$D$41:$F$41,$R$4)) | S23: =IF($S$5="MinFee",$S$6,INDEX(Assumptions!$D$41:$F$41,$S$4)) | T23: =IF($T$5="MinFee",$T$6,INDEX(Assumptions!$D$41:$F$41,$T$4)) | U23: =IF($U$5="MinFee",$U$6,INDEX(Assumptions!$D$41:$F$41,$U$4)) | V23: =IF($V$5="MinFee",$V$6,INDEX(Assumptions!$D$41:$F$41,$V$4)) | W23: =IF($W$5="MinFee",$W$6,INDEX(Assumptions!$D$41:$F$41,$W$4)) | X23: =IF($X$5="MinFee",$X$6,INDEX(Assumptions!$D$41:$F$41,$X$4)) | Y23: =IF($Y$5="MinFee",$Y$6,INDEX(Assumptions!$D$41:$F$41,$Y$4)) | Z23: =IF($Z$5="MinFee",$Z$6,INDEX(Assumptions!$D$41:$F$41,$Z$4)) | AA23: =IF($AA$5="MinFee",$AA$6,INDEX(Assumptions!$D$41:$F$41,$AA$4)) | AB23: =IF($AB$5="MinFee",$AB$6,INDEX(Assumptions!$D$41:$F$41,$AB$4)) | AC23: =IF($AC$5="MinFee",$AC$6,INDEX(Assumptions!$D$41:$F$41,$AC$4)) | AD23: =IF($AD$5="MinFee",$AD$6,INDEX(Assumptions!$D$41:$F$41,$AD$4)) | AE23: =IF($AE$5="MinFee",$AE$6,INDEX(Assumptions!$D$41:$F$41,$AE$4)) | AF23: =IF($AF$5="MinFee",$AF$6,INDEX(Assumptions!$D$41:$F$41,$AF$4)) | AG23: =IF($AG$5="MinFee",$AG$6,INDEX(Assumptions!$D$41:$F$41,$AG$4)) | AH23: =IF($AH$5="MinFee",$AH$6,INDEX(Assumptions!$D$41:$F$41,$AH$4)) | AI23: =IF($AI$5="MinFee",$AI$6,INDEX(Assumptions!$D$41:$F$41,$AI$4)) | AJ23: =IF($AJ$5="MinFee",$AJ$6,INDEX(Assumptions!$D$41:$F$41,$AJ$4)) | AK23: =IF($AK$5="MinFee",$AK$6,INDEX(Assumptions!$D$41:$F$41,$AK$4)) | AL23: =IF($AL$5="MinFee",$AL$6,INDEX(Assumptions!$D$41:$F$41,$AL$4)) | AM23: =IF($AM$5="MinFee",$AM$6,INDEX(Assumptions!$D$41:$F$41,$AM$4)) | AN23: =IF($AN$5="MinFee",$AN$6,INDEX(Assumptions!$D$41:$F$41,$AN$4)) | AO23: =IF($AO$5="MinFee",$AO$6,INDEX(Assumptions!$D$41:$F$41,$AO$4)) | AP23: =IF($AP$5="MinFee",$AP$6,INDEX(Assumptions!$D$41:$F$41,$AP$4)) | AQ23: =IF($AQ$5="MinFee",$AQ$6,INDEX(Assumptions!$D$41:$F$41,$AQ$4)) | AR23: =IF($AR$5="MinFee",$AR$6,INDEX(Assumptions!$D$41:$F$41,$AR$4)) | AS23: =IF($AS$5="MinFee",$AS$6,INDEX(Assumptions!$D$41:$F$41,$AS$4)) | AT23: =IF($AT$5="MinFee",$AT$6,INDEX(Assumptions!$D$41:$F$41,$AT$4)) | AU23: =IF($AU$5="MinFee",$AU$6,INDEX(Assumptions!$D$41:$F$41,$AU$4)) | AV23: =IF($AV$5="MinFee",$AV$6,INDEX(Assumptions!$D$41:$F$41,$AV$4))
B24: NegotiationDisc | D24: =IF($D$5="NegotiationDisc",$D$6,INDEX(Assumptions!$D$42:$F$42,$D$4)) | E24: =IF($E$5="NegotiationDisc",$E$6,INDEX(Assumptions!$D$42:$F$42,$E$4)) | F24: =IF($F$5="NegotiationDisc",$F$6,INDEX(Assumptions!$D$42:$F$42,$F$4)) | G24: =IF($G$5="NegotiationDisc",$G$6,INDEX(Assumptions!$D$42:$F$42,$G$4)) | H24: =IF($H$5="NegotiationDisc",$H$6,INDEX(Assumptions!$D$42:$F$42,$H$4)) | I24: =IF($I$5="NegotiationDisc",$I$6,INDEX(Assumptions!$D$42:$F$42,$I$4)) | J24: =IF($J$5="NegotiationDisc",$J$6,INDEX(Assumptions!$D$42:$F$42,$J$4)) | K24: =IF($K$5="NegotiationDisc",$K$6,INDEX(Assumptions!$D$42:$F$42,$K$4)) | L24: =IF($L$5="NegotiationDisc",$L$6,INDEX(Assumptions!$D$42:$F$42,$L$4)) | M24: =IF($M$5="NegotiationDisc",$M$6,INDEX(Assumptions!$D$42:$F$42,$M$4)) | N24: =IF($N$5="NegotiationDisc",$N$6,INDEX(Assumptions!$D$42:$F$42,$N$4)) | O24: =IF($O$5="NegotiationDisc",$O$6,INDEX(Assumptions!$D$42:$F$42,$O$4)) | P24: =IF($P$5="NegotiationDisc",$P$6,INDEX(Assumptions!$D$42:$F$42,$P$4)) | Q24: =IF($Q$5="NegotiationDisc",$Q$6,INDEX(Assumptions!$D$42:$F$42,$Q$4)) | R24: =IF($R$5="NegotiationDisc",$R$6,INDEX(Assumptions!$D$42:$F$42,$R$4)) | S24: =IF($S$5="NegotiationDisc",$S$6,INDEX(Assumptions!$D$42:$F$42,$S$4)) | T24: =IF($T$5="NegotiationDisc",$T$6,INDEX(Assumptions!$D$42:$F$42,$T$4)) | U24: =IF($U$5="NegotiationDisc",$U$6,INDEX(Assumptions!$D$42:$F$42,$U$4)) | V24: =IF($V$5="NegotiationDisc",$V$6,INDEX(Assumptions!$D$42:$F$42,$V$4)) | W24: =IF($W$5="NegotiationDisc",$W$6,INDEX(Assumptions!$D$42:$F$42,$W$4)) | X24: =IF($X$5="NegotiationDisc",$X$6,INDEX(Assumptions!$D$42:$F$42,$X$4)) | Y24: =IF($Y$5="NegotiationDisc",$Y$6,INDEX(Assumptions!$D$42:$F$42,$Y$4)) | Z24: =IF($Z$5="NegotiationDisc",$Z$6,INDEX(Assumptions!$D$42:$F$42,$Z$4)) | AA24: =IF($AA$5="NegotiationDisc",$AA$6,INDEX(Assumptions!$D$42:$F$42,$AA$4)) | AB24: =IF($AB$5="NegotiationDisc",$AB$6,INDEX(Assumptions!$D$42:$F$42,$AB$4)) | AC24: =IF($AC$5="NegotiationDisc",$AC$6,INDEX(Assumptions!$D$42:$F$42,$AC$4)) | AD24: =IF($AD$5="NegotiationDisc",$AD$6,INDEX(Assumptions!$D$42:$F$42,$AD$4)) | AE24: =IF($AE$5="NegotiationDisc",$AE$6,INDEX(Assumptions!$D$42:$F$42,$AE$4)) | AF24: =IF($AF$5="NegotiationDisc",$AF$6,INDEX(Assumptions!$D$42:$F$42,$AF$4)) | AG24: =IF($AG$5="NegotiationDisc",$AG$6,INDEX(Assumptions!$D$42:$F$42,$AG$4)) | AH24: =IF($AH$5="NegotiationDisc",$AH$6,INDEX(Assumptions!$D$42:$F$42,$AH$4)) | AI24: =IF($AI$5="NegotiationDisc",$AI$6,INDEX(Assumptions!$D$42:$F$42,$AI$4)) | AJ24: =IF($AJ$5="NegotiationDisc",$AJ$6,INDEX(Assumptions!$D$42:$F$42,$AJ$4)) | AK24: =IF($AK$5="NegotiationDisc",$AK$6,INDEX(Assumptions!$D$42:$F$42,$AK$4)) | AL24: =IF($AL$5="NegotiationDisc",$AL$6,INDEX(Assumptions!$D$42:$F$42,$AL$4)) | AM24: =IF($AM$5="NegotiationDisc",$AM$6,INDEX(Assumptions!$D$42:$F$42,$AM$4)) | AN24: =IF($AN$5="NegotiationDisc",$AN$6,INDEX(Assumptions!$D$42:$F$42,$AN$4)) | AO24: =IF($AO$5="NegotiationDisc",$AO$6,INDEX(Assumptions!$D$42:$F$42,$AO$4)) | AP24: =IF($AP$5="NegotiationDisc",$AP$6,INDEX(Assumptions!$D$42:$F$42,$AP$4)) | AQ24: =IF($AQ$5="NegotiationDisc",$AQ$6,INDEX(Assumptions!$D$42:$F$42,$AQ$4)) | AR24: =IF($AR$5="NegotiationDisc",$AR$6,INDEX(Assumptions!$D$42:$F$42,$AR$4)) | AS24: =IF($AS$5="NegotiationDisc",$AS$6,INDEX(Assumptions!$D$42:$F$42,$AS$4)) | AT24: =IF($AT$5="NegotiationDisc",$AT$6,INDEX(Assumptions!$D$42:$F$42,$AT$4)) | AU24: =IF($AU$5="NegotiationDisc",$AU$6,INDEX(Assumptions!$D$42:$F$42,$AU$4)) | AV24: =IF($AV$5="NegotiationDisc",$AV$6,INDEX(Assumptions!$D$42:$F$42,$AV$4))
B25: PrepayUptake | D25: =IF($D$5="PrepayUptake",$D$6,INDEX(Assumptions!$D$43:$F$43,$D$4)) | E25: =IF($E$5="PrepayUptake",$E$6,INDEX(Assumptions!$D$43:$F$43,$E$4)) | F25: =IF($F$5="PrepayUptake",$F$6,INDEX(Assumptions!$D$43:$F$43,$F$4)) | G25: =IF($G$5="PrepayUptake",$G$6,INDEX(Assumptions!$D$43:$F$43,$G$4)) | H25: =IF($H$5="PrepayUptake",$H$6,INDEX(Assumptions!$D$43:$F$43,$H$4)) | I25: =IF($I$5="PrepayUptake",$I$6,INDEX(Assumptions!$D$43:$F$43,$I$4)) | J25: =IF($J$5="PrepayUptake",$J$6,INDEX(Assumptions!$D$43:$F$43,$J$4)) | K25: =IF($K$5="PrepayUptake",$K$6,INDEX(Assumptions!$D$43:$F$43,$K$4)) | L25: =IF($L$5="PrepayUptake",$L$6,INDEX(Assumptions!$D$43:$F$43,$L$4)) | M25: =IF($M$5="PrepayUptake",$M$6,INDEX(Assumptions!$D$43:$F$43,$M$4)) | N25: =IF($N$5="PrepayUptake",$N$6,INDEX(Assumptions!$D$43:$F$43,$N$4)) | O25: =IF($O$5="PrepayUptake",$O$6,INDEX(Assumptions!$D$43:$F$43,$O$4)) | P25: =IF($P$5="PrepayUptake",$P$6,INDEX(Assumptions!$D$43:$F$43,$P$4)) | Q25: =IF($Q$5="PrepayUptake",$Q$6,INDEX(Assumptions!$D$43:$F$43,$Q$4)) | R25: =IF($R$5="PrepayUptake",$R$6,INDEX(Assumptions!$D$43:$F$43,$R$4)) | S25: =IF($S$5="PrepayUptake",$S$6,INDEX(Assumptions!$D$43:$F$43,$S$4)) | T25: =IF($T$5="PrepayUptake",$T$6,INDEX(Assumptions!$D$43:$F$43,$T$4)) | U25: =IF($U$5="PrepayUptake",$U$6,INDEX(Assumptions!$D$43:$F$43,$U$4)) | V25: =IF($V$5="PrepayUptake",$V$6,INDEX(Assumptions!$D$43:$F$43,$V$4)) | W25: =IF($W$5="PrepayUptake",$W$6,INDEX(Assumptions!$D$43:$F$43,$W$4)) | X25: =IF($X$5="PrepayUptake",$X$6,INDEX(Assumptions!$D$43:$F$43,$X$4)) | Y25: =IF($Y$5="PrepayUptake",$Y$6,INDEX(Assumptions!$D$43:$F$43,$Y$4)) | Z25: =IF($Z$5="PrepayUptake",$Z$6,INDEX(Assumptions!$D$43:$F$43,$Z$4)) | AA25: =IF($AA$5="PrepayUptake",$AA$6,INDEX(Assumptions!$D$43:$F$43,$AA$4)) | AB25: =IF($AB$5="PrepayUptake",$AB$6,INDEX(Assumptions!$D$43:$F$43,$AB$4)) | AC25: =IF($AC$5="PrepayUptake",$AC$6,INDEX(Assumptions!$D$43:$F$43,$AC$4)) | AD25: =IF($AD$5="PrepayUptake",$AD$6,INDEX(Assumptions!$D$43:$F$43,$AD$4)) | AE25: =IF($AE$5="PrepayUptake",$AE$6,INDEX(Assumptions!$D$43:$F$43,$AE$4)) | AF25: =IF($AF$5="PrepayUptake",$AF$6,INDEX(Assumptions!$D$43:$F$43,$AF$4)) | AG25: =IF($AG$5="PrepayUptake",$AG$6,INDEX(Assumptions!$D$43:$F$43,$AG$4)) | AH25: =IF($AH$5="PrepayUptake",$AH$6,INDEX(Assumptions!$D$43:$F$43,$AH$4)) | AI25: =IF($AI$5="PrepayUptake",$AI$6,INDEX(Assumptions!$D$43:$F$43,$AI$4)) | AJ25: =IF($AJ$5="PrepayUptake",$AJ$6,INDEX(Assumptions!$D$43:$F$43,$AJ$4)) | AK25: =IF($AK$5="PrepayUptake",$AK$6,INDEX(Assumptions!$D$43:$F$43,$AK$4)) | AL25: =IF($AL$5="PrepayUptake",$AL$6,INDEX(Assumptions!$D$43:$F$43,$AL$4)) | AM25: =IF($AM$5="PrepayUptake",$AM$6,INDEX(Assumptions!$D$43:$F$43,$AM$4)) | AN25: =IF($AN$5="PrepayUptake",$AN$6,INDEX(Assumptions!$D$43:$F$43,$AN$4)) | AO25: =IF($AO$5="PrepayUptake",$AO$6,INDEX(Assumptions!$D$43:$F$43,$AO$4)) | AP25: =IF($AP$5="PrepayUptake",$AP$6,INDEX(Assumptions!$D$43:$F$43,$AP$4)) | AQ25: =IF($AQ$5="PrepayUptake",$AQ$6,INDEX(Assumptions!$D$43:$F$43,$AQ$4)) | AR25: =IF($AR$5="PrepayUptake",$AR$6,INDEX(Assumptions!$D$43:$F$43,$AR$4)) | AS25: =IF($AS$5="PrepayUptake",$AS$6,INDEX(Assumptions!$D$43:$F$43,$AS$4)) | AT25: =IF($AT$5="PrepayUptake",$AT$6,INDEX(Assumptions!$D$43:$F$43,$AT$4)) | AU25: =IF($AU$5="PrepayUptake",$AU$6,INDEX(Assumptions!$D$43:$F$43,$AU$4)) | AV25: =IF($AV$5="PrepayUptake",$AV$6,INDEX(Assumptions!$D$43:$F$43,$AV$4))
B26: PrepayDisc | D26: =IF($D$5="PrepayDisc",$D$6,INDEX(Assumptions!$D$44:$F$44,$D$4)) | E26: =IF($E$5="PrepayDisc",$E$6,INDEX(Assumptions!$D$44:$F$44,$E$4)) | F26: =IF($F$5="PrepayDisc",$F$6,INDEX(Assumptions!$D$44:$F$44,$F$4)) | G26: =IF($G$5="PrepayDisc",$G$6,INDEX(Assumptions!$D$44:$F$44,$G$4)) | H26: =IF($H$5="PrepayDisc",$H$6,INDEX(Assumptions!$D$44:$F$44,$H$4)) | I26: =IF($I$5="PrepayDisc",$I$6,INDEX(Assumptions!$D$44:$F$44,$I$4)) | J26: =IF($J$5="PrepayDisc",$J$6,INDEX(Assumptions!$D$44:$F$44,$J$4)) | K26: =IF($K$5="PrepayDisc",$K$6,INDEX(Assumptions!$D$44:$F$44,$K$4)) | L26: =IF($L$5="PrepayDisc",$L$6,INDEX(Assumptions!$D$44:$F$44,$L$4)) | M26: =IF($M$5="PrepayDisc",$M$6,INDEX(Assumptions!$D$44:$F$44,$M$4)) | N26: =IF($N$5="PrepayDisc",$N$6,INDEX(Assumptions!$D$44:$F$44,$N$4)) | O26: =IF($O$5="PrepayDisc",$O$6,INDEX(Assumptions!$D$44:$F$44,$O$4)) | P26: =IF($P$5="PrepayDisc",$P$6,INDEX(Assumptions!$D$44:$F$44,$P$4)) | Q26: =IF($Q$5="PrepayDisc",$Q$6,INDEX(Assumptions!$D$44:$F$44,$Q$4)) | R26: =IF($R$5="PrepayDisc",$R$6,INDEX(Assumptions!$D$44:$F$44,$R$4)) | S26: =IF($S$5="PrepayDisc",$S$6,INDEX(Assumptions!$D$44:$F$44,$S$4)) | T26: =IF($T$5="PrepayDisc",$T$6,INDEX(Assumptions!$D$44:$F$44,$T$4)) | U26: =IF($U$5="PrepayDisc",$U$6,INDEX(Assumptions!$D$44:$F$44,$U$4)) | V26: =IF($V$5="PrepayDisc",$V$6,INDEX(Assumptions!$D$44:$F$44,$V$4)) | W26: =IF($W$5="PrepayDisc",$W$6,INDEX(Assumptions!$D$44:$F$44,$W$4)) | X26: =IF($X$5="PrepayDisc",$X$6,INDEX(Assumptions!$D$44:$F$44,$X$4)) | Y26: =IF($Y$5="PrepayDisc",$Y$6,INDEX(Assumptions!$D$44:$F$44,$Y$4)) | Z26: =IF($Z$5="PrepayDisc",$Z$6,INDEX(Assumptions!$D$44:$F$44,$Z$4)) | AA26: =IF($AA$5="PrepayDisc",$AA$6,INDEX(Assumptions!$D$44:$F$44,$AA$4)) | AB26: =IF($AB$5="PrepayDisc",$AB$6,INDEX(Assumptions!$D$44:$F$44,$AB$4)) | AC26: =IF($AC$5="PrepayDisc",$AC$6,INDEX(Assumptions!$D$44:$F$44,$AC$4)) | AD26: =IF($AD$5="PrepayDisc",$AD$6,INDEX(Assumptions!$D$44:$F$44,$AD$4)) | AE26: =IF($AE$5="PrepayDisc",$AE$6,INDEX(Assumptions!$D$44:$F$44,$AE$4)) | AF26: =IF($AF$5="PrepayDisc",$AF$6,INDEX(Assumptions!$D$44:$F$44,$AF$4)) | AG26: =IF($AG$5="PrepayDisc",$AG$6,INDEX(Assumptions!$D$44:$F$44,$AG$4)) | AH26: =IF($AH$5="PrepayDisc",$AH$6,INDEX(Assumptions!$D$44:$F$44,$AH$4)) | AI26: =IF($AI$5="PrepayDisc",$AI$6,INDEX(Assumptions!$D$44:$F$44,$AI$4)) | AJ26: =IF($AJ$5="PrepayDisc",$AJ$6,INDEX(Assumptions!$D$44:$F$44,$AJ$4)) | AK26: =IF($AK$5="PrepayDisc",$AK$6,INDEX(Assumptions!$D$44:$F$44,$AK$4)) | AL26: =IF($AL$5="PrepayDisc",$AL$6,INDEX(Assumptions!$D$44:$F$44,$AL$4)) | AM26: =IF($AM$5="PrepayDisc",$AM$6,INDEX(Assumptions!$D$44:$F$44,$AM$4)) | AN26: =IF($AN$5="PrepayDisc",$AN$6,INDEX(Assumptions!$D$44:$F$44,$AN$4)) | AO26: =IF($AO$5="PrepayDisc",$AO$6,INDEX(Assumptions!$D$44:$F$44,$AO$4)) | AP26: =IF($AP$5="PrepayDisc",$AP$6,INDEX(Assumptions!$D$44:$F$44,$AP$4)) | AQ26: =IF($AQ$5="PrepayDisc",$AQ$6,INDEX(Assumptions!$D$44:$F$44,$AQ$4)) | AR26: =IF($AR$5="PrepayDisc",$AR$6,INDEX(Assumptions!$D$44:$F$44,$AR$4)) | AS26: =IF($AS$5="PrepayDisc",$AS$6,INDEX(Assumptions!$D$44:$F$44,$AS$4)) | AT26: =IF($AT$5="PrepayDisc",$AT$6,INDEX(Assumptions!$D$44:$F$44,$AT$4)) | AU26: =IF($AU$5="PrepayDisc",$AU$6,INDEX(Assumptions!$D$44:$F$44,$AU$4)) | AV26: =IF($AV$5="PrepayDisc",$AV$6,INDEX(Assumptions!$D$44:$F$44,$AV$4))
B27: GST | D27: =IF($D$5="GST",$D$6,INDEX(Assumptions!$D$35:$F$35,$D$4)) | E27: =IF($E$5="GST",$E$6,INDEX(Assumptions!$D$35:$F$35,$E$4)) | F27: =IF($F$5="GST",$F$6,INDEX(Assumptions!$D$35:$F$35,$F$4)) | G27: =IF($G$5="GST",$G$6,INDEX(Assumptions!$D$35:$F$35,$G$4)) | H27: =IF($H$5="GST",$H$6,INDEX(Assumptions!$D$35:$F$35,$H$4)) | I27: =IF($I$5="GST",$I$6,INDEX(Assumptions!$D$35:$F$35,$I$4)) | J27: =IF($J$5="GST",$J$6,INDEX(Assumptions!$D$35:$F$35,$J$4)) | K27: =IF($K$5="GST",$K$6,INDEX(Assumptions!$D$35:$F$35,$K$4)) | L27: =IF($L$5="GST",$L$6,INDEX(Assumptions!$D$35:$F$35,$L$4)) | M27: =IF($M$5="GST",$M$6,INDEX(Assumptions!$D$35:$F$35,$M$4)) | N27: =IF($N$5="GST",$N$6,INDEX(Assumptions!$D$35:$F$35,$N$4)) | O27: =IF($O$5="GST",$O$6,INDEX(Assumptions!$D$35:$F$35,$O$4)) | P27: =IF($P$5="GST",$P$6,INDEX(Assumptions!$D$35:$F$35,$P$4)) | Q27: =IF($Q$5="GST",$Q$6,INDEX(Assumptions!$D$35:$F$35,$Q$4)) | R27: =IF($R$5="GST",$R$6,INDEX(Assumptions!$D$35:$F$35,$R$4)) | S27: =IF($S$5="GST",$S$6,INDEX(Assumptions!$D$35:$F$35,$S$4)) | T27: =IF($T$5="GST",$T$6,INDEX(Assumptions!$D$35:$F$35,$T$4)) | U27: =IF($U$5="GST",$U$6,INDEX(Assumptions!$D$35:$F$35,$U$4)) | V27: =IF($V$5="GST",$V$6,INDEX(Assumptions!$D$35:$F$35,$V$4)) | W27: =IF($W$5="GST",$W$6,INDEX(Assumptions!$D$35:$F$35,$W$4)) | X27: =IF($X$5="GST",$X$6,INDEX(Assumptions!$D$35:$F$35,$X$4)) | Y27: =IF($Y$5="GST",$Y$6,INDEX(Assumptions!$D$35:$F$35,$Y$4)) | Z27: =IF($Z$5="GST",$Z$6,INDEX(Assumptions!$D$35:$F$35,$Z$4)) | AA27: =IF($AA$5="GST",$AA$6,INDEX(Assumptions!$D$35:$F$35,$AA$4)) | AB27: =IF($AB$5="GST",$AB$6,INDEX(Assumptions!$D$35:$F$35,$AB$4)) | AC27: =IF($AC$5="GST",$AC$6,INDEX(Assumptions!$D$35:$F$35,$AC$4)) | AD27: =IF($AD$5="GST",$AD$6,INDEX(Assumptions!$D$35:$F$35,$AD$4)) | AE27: =IF($AE$5="GST",$AE$6,INDEX(Assumptions!$D$35:$F$35,$AE$4)) | AF27: =IF($AF$5="GST",$AF$6,INDEX(Assumptions!$D$35:$F$35,$AF$4)) | AG27: =IF($AG$5="GST",$AG$6,INDEX(Assumptions!$D$35:$F$35,$AG$4)) | AH27: =IF($AH$5="GST",$AH$6,INDEX(Assumptions!$D$35:$F$35,$AH$4)) | AI27: =IF($AI$5="GST",$AI$6,INDEX(Assumptions!$D$35:$F$35,$AI$4)) | AJ27: =IF($AJ$5="GST",$AJ$6,INDEX(Assumptions!$D$35:$F$35,$AJ$4)) | AK27: =IF($AK$5="GST",$AK$6,INDEX(Assumptions!$D$35:$F$35,$AK$4)) | AL27: =IF($AL$5="GST",$AL$6,INDEX(Assumptions!$D$35:$F$35,$AL$4)) | AM27: =IF($AM$5="GST",$AM$6,INDEX(Assumptions!$D$35:$F$35,$AM$4)) | AN27: =IF($AN$5="GST",$AN$6,INDEX(Assumptions!$D$35:$F$35,$AN$4)) | AO27: =IF($AO$5="GST",$AO$6,INDEX(Assumptions!$D$35:$F$35,$AO$4)) | AP27: =IF($AP$5="GST",$AP$6,INDEX(Assumptions!$D$35:$F$35,$AP$4)) | AQ27: =IF($AQ$5="GST",$AQ$6,INDEX(Assumptions!$D$35:$F$35,$AQ$4)) | AR27: =IF($AR$5="GST",$AR$6,INDEX(Assumptions!$D$35:$F$35,$AR$4)) | AS27: =IF($AS$5="GST",$AS$6,INDEX(Assumptions!$D$35:$F$35,$AS$4)) | AT27: =IF($AT$5="GST",$AT$6,INDEX(Assumptions!$D$35:$F$35,$AT$4)) | AU27: =IF($AU$5="GST",$AU$6,INDEX(Assumptions!$D$35:$F$35,$AU$4)) | AV27: =IF($AV$5="GST",$AV$6,INDEX(Assumptions!$D$35:$F$35,$AV$4))
B28: CompetitorAnchor | D28: =IF($D$5="CompetitorAnchor",$D$6,INDEX(Assumptions!$D$39:$F$39,$D$4)) | E28: =IF($E$5="CompetitorAnchor",$E$6,INDEX(Assumptions!$D$39:$F$39,$E$4)) | F28: =IF($F$5="CompetitorAnchor",$F$6,INDEX(Assumptions!$D$39:$F$39,$F$4)) | G28: =IF($G$5="CompetitorAnchor",$G$6,INDEX(Assumptions!$D$39:$F$39,$G$4)) | H28: =IF($H$5="CompetitorAnchor",$H$6,INDEX(Assumptions!$D$39:$F$39,$H$4)) | I28: =IF($I$5="CompetitorAnchor",$I$6,INDEX(Assumptions!$D$39:$F$39,$I$4)) | J28: =IF($J$5="CompetitorAnchor",$J$6,INDEX(Assumptions!$D$39:$F$39,$J$4)) | K28: =IF($K$5="CompetitorAnchor",$K$6,INDEX(Assumptions!$D$39:$F$39,$K$4)) | L28: =IF($L$5="CompetitorAnchor",$L$6,INDEX(Assumptions!$D$39:$F$39,$L$4)) | M28: =IF($M$5="CompetitorAnchor",$M$6,INDEX(Assumptions!$D$39:$F$39,$M$4)) | N28: =IF($N$5="CompetitorAnchor",$N$6,INDEX(Assumptions!$D$39:$F$39,$N$4)) | O28: =IF($O$5="CompetitorAnchor",$O$6,INDEX(Assumptions!$D$39:$F$39,$O$4)) | P28: =IF($P$5="CompetitorAnchor",$P$6,INDEX(Assumptions!$D$39:$F$39,$P$4)) | Q28: =IF($Q$5="CompetitorAnchor",$Q$6,INDEX(Assumptions!$D$39:$F$39,$Q$4)) | R28: =IF($R$5="CompetitorAnchor",$R$6,INDEX(Assumptions!$D$39:$F$39,$R$4)) | S28: =IF($S$5="CompetitorAnchor",$S$6,INDEX(Assumptions!$D$39:$F$39,$S$4)) | T28: =IF($T$5="CompetitorAnchor",$T$6,INDEX(Assumptions!$D$39:$F$39,$T$4)) | U28: =IF($U$5="CompetitorAnchor",$U$6,INDEX(Assumptions!$D$39:$F$39,$U$4)) | V28: =IF($V$5="CompetitorAnchor",$V$6,INDEX(Assumptions!$D$39:$F$39,$V$4)) | W28: =IF($W$5="CompetitorAnchor",$W$6,INDEX(Assumptions!$D$39:$F$39,$W$4)) | X28: =IF($X$5="CompetitorAnchor",$X$6,INDEX(Assumptions!$D$39:$F$39,$X$4)) | Y28: =IF($Y$5="CompetitorAnchor",$Y$6,INDEX(Assumptions!$D$39:$F$39,$Y$4)) | Z28: =IF($Z$5="CompetitorAnchor",$Z$6,INDEX(Assumptions!$D$39:$F$39,$Z$4)) | AA28: =IF($AA$5="CompetitorAnchor",$AA$6,INDEX(Assumptions!$D$39:$F$39,$AA$4)) | AB28: =IF($AB$5="CompetitorAnchor",$AB$6,INDEX(Assumptions!$D$39:$F$39,$AB$4)) | AC28: =IF($AC$5="CompetitorAnchor",$AC$6,INDEX(Assumptions!$D$39:$F$39,$AC$4)) | AD28: =IF($AD$5="CompetitorAnchor",$AD$6,INDEX(Assumptions!$D$39:$F$39,$AD$4)) | AE28: =IF($AE$5="CompetitorAnchor",$AE$6,INDEX(Assumptions!$D$39:$F$39,$AE$4)) | AF28: =IF($AF$5="CompetitorAnchor",$AF$6,INDEX(Assumptions!$D$39:$F$39,$AF$4)) | AG28: =IF($AG$5="CompetitorAnchor",$AG$6,INDEX(Assumptions!$D$39:$F$39,$AG$4)) | AH28: =IF($AH$5="CompetitorAnchor",$AH$6,INDEX(Assumptions!$D$39:$F$39,$AH$4)) | AI28: =IF($AI$5="CompetitorAnchor",$AI$6,INDEX(Assumptions!$D$39:$F$39,$AI$4)) | AJ28: =IF($AJ$5="CompetitorAnchor",$AJ$6,INDEX(Assumptions!$D$39:$F$39,$AJ$4)) | AK28: =IF($AK$5="CompetitorAnchor",$AK$6,INDEX(Assumptions!$D$39:$F$39,$AK$4)) | AL28: =IF($AL$5="CompetitorAnchor",$AL$6,INDEX(Assumptions!$D$39:$F$39,$AL$4)) | AM28: =IF($AM$5="CompetitorAnchor",$AM$6,INDEX(Assumptions!$D$39:$F$39,$AM$4)) | AN28: =IF($AN$5="CompetitorAnchor",$AN$6,INDEX(Assumptions!$D$39:$F$39,$AN$4)) | AO28: =IF($AO$5="CompetitorAnchor",$AO$6,INDEX(Assumptions!$D$39:$F$39,$AO$4)) | AP28: =IF($AP$5="CompetitorAnchor",$AP$6,INDEX(Assumptions!$D$39:$F$39,$AP$4)) | AQ28: =IF($AQ$5="CompetitorAnchor",$AQ$6,INDEX(Assumptions!$D$39:$F$39,$AQ$4)) | AR28: =IF($AR$5="CompetitorAnchor",$AR$6,INDEX(Assumptions!$D$39:$F$39,$AR$4)) | AS28: =IF($AS$5="CompetitorAnchor",$AS$6,INDEX(Assumptions!$D$39:$F$39,$AS$4)) | AT28: =IF($AT$5="CompetitorAnchor",$AT$6,INDEX(Assumptions!$D$39:$F$39,$AT$4)) | AU28: =IF($AU$5="CompetitorAnchor",$AU$6,INDEX(Assumptions!$D$39:$F$39,$AU$4)) | AV28: =IF($AV$5="CompetitorAnchor",$AV$6,INDEX(Assumptions!$D$39:$F$39,$AV$4))
B29: Fee | D29: =IF($D$5="Fee",$D$6,INDEX(Assumptions!$D$9:$F$9,$D$4)) | E29: =IF($E$5="Fee",$E$6,INDEX(Assumptions!$D$10:$F$10,$E$4)) | F29: =IF($F$5="Fee",$F$6,INDEX(Assumptions!$D$11:$F$11,$F$4)) | G29: =IF($G$5="Fee",$G$6,INDEX(Assumptions!$D$9:$F$9,$G$4)) | H29: =IF($H$5="Fee",$H$6,INDEX(Assumptions!$D$10:$F$10,$H$4)) | I29: =IF($I$5="Fee",$I$6,INDEX(Assumptions!$D$11:$F$11,$I$4)) | J29: =IF($J$5="Fee",$J$6,INDEX(Assumptions!$D$9:$F$9,$J$4)) | K29: =IF($K$5="Fee",$K$6,INDEX(Assumptions!$D$10:$F$10,$K$4)) | L29: =IF($L$5="Fee",$L$6,INDEX(Assumptions!$D$11:$F$11,$L$4)) | M29: =IF($M$5="Fee",$M$6,INDEX(Assumptions!$D$9:$F$9,$M$4)) | N29: =IF($N$5="Fee",$N$6,INDEX(Assumptions!$D$10:$F$10,$N$4)) | O29: =IF($O$5="Fee",$O$6,INDEX(Assumptions!$D$11:$F$11,$O$4)) | P29: =IF($P$5="Fee",$P$6,INDEX(Assumptions!$D$10:$F$10,$P$4)) | Q29: =IF($Q$5="Fee",$Q$6,INDEX(Assumptions!$D$10:$F$10,$Q$4)) | R29: =IF($R$5="Fee",$R$6,INDEX(Assumptions!$D$10:$F$10,$R$4)) | S29: =IF($S$5="Fee",$S$6,INDEX(Assumptions!$D$10:$F$10,$S$4)) | T29: =IF($T$5="Fee",$T$6,INDEX(Assumptions!$D$10:$F$10,$T$4)) | U29: =IF($U$5="Fee",$U$6,INDEX(Assumptions!$D$10:$F$10,$U$4)) | V29: =IF($V$5="Fee",$V$6,INDEX(Assumptions!$D$10:$F$10,$V$4)) | W29: =IF($W$5="Fee",$W$6,INDEX(Assumptions!$D$10:$F$10,$W$4)) | X29: =IF($X$5="Fee",$X$6,INDEX(Assumptions!$D$10:$F$10,$X$4)) | Y29: =IF($Y$5="Fee",$Y$6,INDEX(Assumptions!$D$10:$F$10,$Y$4)) | Z29: =IF($Z$5="Fee",$Z$6,INDEX(Assumptions!$D$10:$F$10,$Z$4)) | AA29: =IF($AA$5="Fee",$AA$6,INDEX(Assumptions!$D$10:$F$10,$AA$4)) | AB29: =IF($AB$5="Fee",$AB$6,INDEX(Assumptions!$D$10:$F$10,$AB$4)) | AC29: =IF($AC$5="Fee",$AC$6,INDEX(Assumptions!$D$10:$F$10,$AC$4)) | AD29: =IF($AD$5="Fee",$AD$6,INDEX(Assumptions!$D$10:$F$10,$AD$4)) | AE29: =IF($AE$5="Fee",$AE$6,INDEX(Assumptions!$D$10:$F$10,$AE$4)) | AF29: =IF($AF$5="Fee",$AF$6,INDEX(Assumptions!$D$10:$F$10,$AF$4)) | AG29: =IF($AG$5="Fee",$AG$6,INDEX(Assumptions!$D$10:$F$10,$AG$4)) | AH29: =IF($AH$5="Fee",$AH$6,INDEX(Assumptions!$D$10:$F$10,$AH$4)) | AI29: =IF($AI$5="Fee",$AI$6,INDEX(Assumptions!$D$10:$F$10,$AI$4)) | AJ29: =IF($AJ$5="Fee",$AJ$6,INDEX(Assumptions!$D$10:$F$10,$AJ$4)) | AK29: =IF($AK$5="Fee",$AK$6,INDEX(Assumptions!$D$10:$F$10,$AK$4)) | AL29: =IF($AL$5="Fee",$AL$6,INDEX(Assumptions!$D$10:$F$10,$AL$4)) | AM29: =IF($AM$5="Fee",$AM$6,INDEX(Assumptions!$D$10:$F$10,$AM$4)) | AN29: =IF($AN$5="Fee",$AN$6,INDEX(Assumptions!$D$10:$F$10,$AN$4)) | AO29: =IF($AO$5="Fee",$AO$6,INDEX(Assumptions!$D$10:$F$10,$AO$4)) | AP29: =IF($AP$5="Fee",$AP$6,INDEX(Assumptions!$D$10:$F$10,$AP$4)) | AQ29: =IF($AQ$5="Fee",$AQ$6,INDEX(Assumptions!$D$10:$F$10,$AQ$4)) | AR29: =IF($AR$5="Fee",$AR$6,INDEX(Assumptions!$D$10:$F$10,$AR$4)) | AS29: =IF($AS$5="Fee",$AS$6,INDEX(Assumptions!$D$10:$F$10,$AS$4)) | AT29: =IF($AT$5="Fee",$AT$6,INDEX(Assumptions!$D$10:$F$10,$AT$4)) | AU29: =IF($AU$5="Fee",$AU$6,INDEX(Assumptions!$D$10:$F$10,$AU$4)) | AV29: =IF($AV$5="Fee",$AV$6,INDEX(Assumptions!$D$10:$F$10,$AV$4))
B30: DropoutRate | D30: =IF($D$5="DropoutRate",$D$6,INDEX(Assumptions!$D$16:$F$16,$D$4)) | E30: =IF($E$5="DropoutRate",$E$6,INDEX(Assumptions!$D$16:$F$16,$E$4)) | F30: =IF($F$5="DropoutRate",$F$6,INDEX(Assumptions!$D$16:$F$16,$F$4)) | G30: =IF($G$5="DropoutRate",$G$6,INDEX(Assumptions!$D$16:$F$16,$G$4)) | H30: =IF($H$5="DropoutRate",$H$6,INDEX(Assumptions!$D$16:$F$16,$H$4)) | I30: =IF($I$5="DropoutRate",$I$6,INDEX(Assumptions!$D$16:$F$16,$I$4)) | J30: =IF($J$5="DropoutRate",$J$6,INDEX(Assumptions!$D$16:$F$16,$J$4)) | K30: =IF($K$5="DropoutRate",$K$6,INDEX(Assumptions!$D$16:$F$16,$K$4)) | L30: =IF($L$5="DropoutRate",$L$6,INDEX(Assumptions!$D$16:$F$16,$L$4)) | M30: =IF($M$5="DropoutRate",$M$6,INDEX(Assumptions!$D$16:$F$16,$M$4)) | N30: =IF($N$5="DropoutRate",$N$6,INDEX(Assumptions!$D$16:$F$16,$N$4)) | O30: =IF($O$5="DropoutRate",$O$6,INDEX(Assumptions!$D$16:$F$16,$O$4)) | P30: =IF($P$5="DropoutRate",$P$6,INDEX(Assumptions!$D$16:$F$16,$P$4)) | Q30: =IF($Q$5="DropoutRate",$Q$6,INDEX(Assumptions!$D$16:$F$16,$Q$4)) | R30: =IF($R$5="DropoutRate",$R$6,INDEX(Assumptions!$D$16:$F$16,$R$4)) | S30: =IF($S$5="DropoutRate",$S$6,INDEX(Assumptions!$D$16:$F$16,$S$4)) | T30: =IF($T$5="DropoutRate",$T$6,INDEX(Assumptions!$D$16:$F$16,$T$4)) | U30: =IF($U$5="DropoutRate",$U$6,INDEX(Assumptions!$D$16:$F$16,$U$4)) | V30: =IF($V$5="DropoutRate",$V$6,INDEX(Assumptions!$D$16:$F$16,$V$4)) | W30: =IF($W$5="DropoutRate",$W$6,INDEX(Assumptions!$D$16:$F$16,$W$4)) | X30: =IF($X$5="DropoutRate",$X$6,INDEX(Assumptions!$D$16:$F$16,$X$4)) | Y30: =IF($Y$5="DropoutRate",$Y$6,INDEX(Assumptions!$D$16:$F$16,$Y$4)) | Z30: =IF($Z$5="DropoutRate",$Z$6,INDEX(Assumptions!$D$16:$F$16,$Z$4)) | AA30: =IF($AA$5="DropoutRate",$AA$6,INDEX(Assumptions!$D$16:$F$16,$AA$4)) | AB30: =IF($AB$5="DropoutRate",$AB$6,INDEX(Assumptions!$D$16:$F$16,$AB$4)) | AC30: =IF($AC$5="DropoutRate",$AC$6,INDEX(Assumptions!$D$16:$F$16,$AC$4)) | AD30: =IF($AD$5="DropoutRate",$AD$6,INDEX(Assumptions!$D$16:$F$16,$AD$4)) | AE30: =IF($AE$5="DropoutRate",$AE$6,INDEX(Assumptions!$D$16:$F$16,$AE$4)) | AF30: =IF($AF$5="DropoutRate",$AF$6,INDEX(Assumptions!$D$16:$F$16,$AF$4)) | AG30: =IF($AG$5="DropoutRate",$AG$6,INDEX(Assumptions!$D$16:$F$16,$AG$4)) | AH30: =IF($AH$5="DropoutRate",$AH$6,INDEX(Assumptions!$D$16:$F$16,$AH$4)) | AI30: =IF($AI$5="DropoutRate",$AI$6,INDEX(Assumptions!$D$16:$F$16,$AI$4)) | AJ30: =IF($AJ$5="DropoutRate",$AJ$6,INDEX(Assumptions!$D$16:$F$16,$AJ$4)) | AK30: =IF($AK$5="DropoutRate",$AK$6,INDEX(Assumptions!$D$16:$F$16,$AK$4)) | AL30: =IF($AL$5="DropoutRate",$AL$6,INDEX(Assumptions!$D$16:$F$16,$AL$4)) | AM30: =IF($AM$5="DropoutRate",$AM$6,INDEX(Assumptions!$D$16:$F$16,$AM$4)) | AN30: =IF($AN$5="DropoutRate",$AN$6,INDEX(Assumptions!$D$16:$F$16,$AN$4)) | AO30: =IF($AO$5="DropoutRate",$AO$6,INDEX(Assumptions!$D$16:$F$16,$AO$4)) | AP30: =IF($AP$5="DropoutRate",$AP$6,INDEX(Assumptions!$D$16:$F$16,$AP$4)) | AQ30: =IF($AQ$5="DropoutRate",$AQ$6,INDEX(Assumptions!$D$16:$F$16,$AQ$4)) | AR30: =IF($AR$5="DropoutRate",$AR$6,INDEX(Assumptions!$D$16:$F$16,$AR$4)) | AS30: =IF($AS$5="DropoutRate",$AS$6,INDEX(Assumptions!$D$16:$F$16,$AS$4)) | AT30: =IF($AT$5="DropoutRate",$AT$6,INDEX(Assumptions!$D$16:$F$16,$AT$4)) | AU30: =IF($AU$5="DropoutRate",$AU$6,INDEX(Assumptions!$D$16:$F$16,$AU$4)) | AV30: =IF($AV$5="DropoutRate",$AV$6,INDEX(Assumptions!$D$16:$F$16,$AV$4))
B31: UpfrontShare | D31: =IF($D$5="UpfrontShare",$D$6,INDEX(Assumptions!$D$17:$F$17,$D$4)) | E31: =IF($E$5="UpfrontShare",$E$6,INDEX(Assumptions!$D$17:$F$17,$E$4)) | F31: =IF($F$5="UpfrontShare",$F$6,INDEX(Assumptions!$D$17:$F$17,$F$4)) | G31: =IF($G$5="UpfrontShare",$G$6,INDEX(Assumptions!$D$17:$F$17,$G$4)) | H31: =IF($H$5="UpfrontShare",$H$6,INDEX(Assumptions!$D$17:$F$17,$H$4)) | I31: =IF($I$5="UpfrontShare",$I$6,INDEX(Assumptions!$D$17:$F$17,$I$4)) | J31: =IF($J$5="UpfrontShare",$J$6,INDEX(Assumptions!$D$17:$F$17,$J$4)) | K31: =IF($K$5="UpfrontShare",$K$6,INDEX(Assumptions!$D$17:$F$17,$K$4)) | L31: =IF($L$5="UpfrontShare",$L$6,INDEX(Assumptions!$D$17:$F$17,$L$4)) | M31: =IF($M$5="UpfrontShare",$M$6,INDEX(Assumptions!$D$17:$F$17,$M$4)) | N31: =IF($N$5="UpfrontShare",$N$6,INDEX(Assumptions!$D$17:$F$17,$N$4)) | O31: =IF($O$5="UpfrontShare",$O$6,INDEX(Assumptions!$D$17:$F$17,$O$4)) | P31: =IF($P$5="UpfrontShare",$P$6,INDEX(Assumptions!$D$17:$F$17,$P$4)) | Q31: =IF($Q$5="UpfrontShare",$Q$6,INDEX(Assumptions!$D$17:$F$17,$Q$4)) | R31: =IF($R$5="UpfrontShare",$R$6,INDEX(Assumptions!$D$17:$F$17,$R$4)) | S31: =IF($S$5="UpfrontShare",$S$6,INDEX(Assumptions!$D$17:$F$17,$S$4)) | T31: =IF($T$5="UpfrontShare",$T$6,INDEX(Assumptions!$D$17:$F$17,$T$4)) | U31: =IF($U$5="UpfrontShare",$U$6,INDEX(Assumptions!$D$17:$F$17,$U$4)) | V31: =IF($V$5="UpfrontShare",$V$6,INDEX(Assumptions!$D$17:$F$17,$V$4)) | W31: =IF($W$5="UpfrontShare",$W$6,INDEX(Assumptions!$D$17:$F$17,$W$4)) | X31: =IF($X$5="UpfrontShare",$X$6,INDEX(Assumptions!$D$17:$F$17,$X$4)) | Y31: =IF($Y$5="UpfrontShare",$Y$6,INDEX(Assumptions!$D$17:$F$17,$Y$4)) | Z31: =IF($Z$5="UpfrontShare",$Z$6,INDEX(Assumptions!$D$17:$F$17,$Z$4)) | AA31: =IF($AA$5="UpfrontShare",$AA$6,INDEX(Assumptions!$D$17:$F$17,$AA$4)) | AB31: =IF($AB$5="UpfrontShare",$AB$6,INDEX(Assumptions!$D$17:$F$17,$AB$4)) | AC31: =IF($AC$5="UpfrontShare",$AC$6,INDEX(Assumptions!$D$17:$F$17,$AC$4)) | AD31: =IF($AD$5="UpfrontShare",$AD$6,INDEX(Assumptions!$D$17:$F$17,$AD$4)) | AE31: =IF($AE$5="UpfrontShare",$AE$6,INDEX(Assumptions!$D$17:$F$17,$AE$4)) | AF31: =IF($AF$5="UpfrontShare",$AF$6,INDEX(Assumptions!$D$17:$F$17,$AF$4)) | AG31: =IF($AG$5="UpfrontShare",$AG$6,INDEX(Assumptions!$D$17:$F$17,$AG$4)) | AH31: =IF($AH$5="UpfrontShare",$AH$6,INDEX(Assumptions!$D$17:$F$17,$AH$4)) | AI31: =IF($AI$5="UpfrontShare",$AI$6,INDEX(Assumptions!$D$17:$F$17,$AI$4)) | AJ31: =IF($AJ$5="UpfrontShare",$AJ$6,INDEX(Assumptions!$D$17:$F$17,$AJ$4)) | AK31: =IF($AK$5="UpfrontShare",$AK$6,INDEX(Assumptions!$D$17:$F$17,$AK$4)) | AL31: =IF($AL$5="UpfrontShare",$AL$6,INDEX(Assumptions!$D$17:$F$17,$AL$4)) | AM31: =IF($AM$5="UpfrontShare",$AM$6,INDEX(Assumptions!$D$17:$F$17,$AM$4)) | AN31: =IF($AN$5="UpfrontShare",$AN$6,INDEX(Assumptions!$D$17:$F$17,$AN$4)) | AO31: =IF($AO$5="UpfrontShare",$AO$6,INDEX(Assumptions!$D$17:$F$17,$AO$4)) | AP31: =IF($AP$5="UpfrontShare",$AP$6,INDEX(Assumptions!$D$17:$F$17,$AP$4)) | AQ31: =IF($AQ$5="UpfrontShare",$AQ$6,INDEX(Assumptions!$D$17:$F$17,$AQ$4)) | AR31: =IF($AR$5="UpfrontShare",$AR$6,INDEX(Assumptions!$D$17:$F$17,$AR$4)) | AS31: =IF($AS$5="UpfrontShare",$AS$6,INDEX(Assumptions!$D$17:$F$17,$AS$4)) | AT31: =IF($AT$5="UpfrontShare",$AT$6,INDEX(Assumptions!$D$17:$F$17,$AT$4)) | AU31: =IF($AU$5="UpfrontShare",$AU$6,INDEX(Assumptions!$D$17:$F$17,$AU$4)) | AV31: =IF($AV$5="UpfrontShare",$AV$6,INDEX(Assumptions!$D$17:$F$17,$AV$4))
B32: NInstalments | D32: =IF($D$5="NInstalments",$D$6,INDEX(Assumptions!$D$18:$F$18,$D$4)) | E32: =IF($E$5="NInstalments",$E$6,INDEX(Assumptions!$D$18:$F$18,$E$4)) | F32: =IF($F$5="NInstalments",$F$6,INDEX(Assumptions!$D$18:$F$18,$F$4)) | G32: =IF($G$5="NInstalments",$G$6,INDEX(Assumptions!$D$18:$F$18,$G$4)) | H32: =IF($H$5="NInstalments",$H$6,INDEX(Assumptions!$D$18:$F$18,$H$4)) | I32: =IF($I$5="NInstalments",$I$6,INDEX(Assumptions!$D$18:$F$18,$I$4)) | J32: =IF($J$5="NInstalments",$J$6,INDEX(Assumptions!$D$18:$F$18,$J$4)) | K32: =IF($K$5="NInstalments",$K$6,INDEX(Assumptions!$D$18:$F$18,$K$4)) | L32: =IF($L$5="NInstalments",$L$6,INDEX(Assumptions!$D$18:$F$18,$L$4)) | M32: =IF($M$5="NInstalments",$M$6,INDEX(Assumptions!$D$18:$F$18,$M$4)) | N32: =IF($N$5="NInstalments",$N$6,INDEX(Assumptions!$D$18:$F$18,$N$4)) | O32: =IF($O$5="NInstalments",$O$6,INDEX(Assumptions!$D$18:$F$18,$O$4)) | P32: =IF($P$5="NInstalments",$P$6,INDEX(Assumptions!$D$18:$F$18,$P$4)) | Q32: =IF($Q$5="NInstalments",$Q$6,INDEX(Assumptions!$D$18:$F$18,$Q$4)) | R32: =IF($R$5="NInstalments",$R$6,INDEX(Assumptions!$D$18:$F$18,$R$4)) | S32: =IF($S$5="NInstalments",$S$6,INDEX(Assumptions!$D$18:$F$18,$S$4)) | T32: =IF($T$5="NInstalments",$T$6,INDEX(Assumptions!$D$18:$F$18,$T$4)) | U32: =IF($U$5="NInstalments",$U$6,INDEX(Assumptions!$D$18:$F$18,$U$4)) | V32: =IF($V$5="NInstalments",$V$6,INDEX(Assumptions!$D$18:$F$18,$V$4)) | W32: =IF($W$5="NInstalments",$W$6,INDEX(Assumptions!$D$18:$F$18,$W$4)) | X32: =IF($X$5="NInstalments",$X$6,INDEX(Assumptions!$D$18:$F$18,$X$4)) | Y32: =IF($Y$5="NInstalments",$Y$6,INDEX(Assumptions!$D$18:$F$18,$Y$4)) | Z32: =IF($Z$5="NInstalments",$Z$6,INDEX(Assumptions!$D$18:$F$18,$Z$4)) | AA32: =IF($AA$5="NInstalments",$AA$6,INDEX(Assumptions!$D$18:$F$18,$AA$4)) | AB32: =IF($AB$5="NInstalments",$AB$6,INDEX(Assumptions!$D$18:$F$18,$AB$4)) | AC32: =IF($AC$5="NInstalments",$AC$6,INDEX(Assumptions!$D$18:$F$18,$AC$4)) | AD32: =IF($AD$5="NInstalments",$AD$6,INDEX(Assumptions!$D$18:$F$18,$AD$4)) | AE32: =IF($AE$5="NInstalments",$AE$6,INDEX(Assumptions!$D$18:$F$18,$AE$4)) | AF32: =IF($AF$5="NInstalments",$AF$6,INDEX(Assumptions!$D$18:$F$18,$AF$4)) | AG32: =IF($AG$5="NInstalments",$AG$6,INDEX(Assumptions!$D$18:$F$18,$AG$4)) | AH32: =IF($AH$5="NInstalments",$AH$6,INDEX(Assumptions!$D$18:$F$18,$AH$4)) | AI32: =IF($AI$5="NInstalments",$AI$6,INDEX(Assumptions!$D$18:$F$18,$AI$4)) | AJ32: =IF($AJ$5="NInstalments",$AJ$6,INDEX(Assumptions!$D$18:$F$18,$AJ$4)) | AK32: =IF($AK$5="NInstalments",$AK$6,INDEX(Assumptions!$D$18:$F$18,$AK$4)) | AL32: =IF($AL$5="NInstalments",$AL$6,INDEX(Assumptions!$D$18:$F$18,$AL$4)) | AM32: =IF($AM$5="NInstalments",$AM$6,INDEX(Assumptions!$D$18:$F$18,$AM$4)) | AN32: =IF($AN$5="NInstalments",$AN$6,INDEX(Assumptions!$D$18:$F$18,$AN$4)) | AO32: =IF($AO$5="NInstalments",$AO$6,INDEX(Assumptions!$D$18:$F$18,$AO$4)) | AP32: =IF($AP$5="NInstalments",$AP$6,INDEX(Assumptions!$D$18:$F$18,$AP$4)) | AQ32: =IF($AQ$5="NInstalments",$AQ$6,INDEX(Assumptions!$D$18:$F$18,$AQ$4)) | AR32: =IF($AR$5="NInstalments",$AR$6,INDEX(Assumptions!$D$18:$F$18,$AR$4)) | AS32: =IF($AS$5="NInstalments",$AS$6,INDEX(Assumptions!$D$18:$F$18,$AS$4)) | AT32: =IF($AT$5="NInstalments",$AT$6,INDEX(Assumptions!$D$18:$F$18,$AT$4)) | AU32: =IF($AU$5="NInstalments",$AU$6,INDEX(Assumptions!$D$18:$F$18,$AU$4)) | AV32: =IF($AV$5="NInstalments",$AV$6,INDEX(Assumptions!$D$18:$F$18,$AV$4))
B33: RefundEnforced | D33: =IF($D$5="RefundEnforced",$D$6,INDEX(Assumptions!$D$19:$F$19,$D$4)) | E33: =IF($E$5="RefundEnforced",$E$6,INDEX(Assumptions!$D$19:$F$19,$E$4)) | F33: =IF($F$5="RefundEnforced",$F$6,INDEX(Assumptions!$D$19:$F$19,$F$4)) | G33: =IF($G$5="RefundEnforced",$G$6,INDEX(Assumptions!$D$19:$F$19,$G$4)) | H33: =IF($H$5="RefundEnforced",$H$6,INDEX(Assumptions!$D$19:$F$19,$H$4)) | I33: =IF($I$5="RefundEnforced",$I$6,INDEX(Assumptions!$D$19:$F$19,$I$4)) | J33: =IF($J$5="RefundEnforced",$J$6,INDEX(Assumptions!$D$19:$F$19,$J$4)) | K33: =IF($K$5="RefundEnforced",$K$6,INDEX(Assumptions!$D$19:$F$19,$K$4)) | L33: =IF($L$5="RefundEnforced",$L$6,INDEX(Assumptions!$D$19:$F$19,$L$4)) | M33: =IF($M$5="RefundEnforced",$M$6,INDEX(Assumptions!$D$19:$F$19,$M$4)) | N33: =IF($N$5="RefundEnforced",$N$6,INDEX(Assumptions!$D$19:$F$19,$N$4)) | O33: =IF($O$5="RefundEnforced",$O$6,INDEX(Assumptions!$D$19:$F$19,$O$4)) | P33: =IF($P$5="RefundEnforced",$P$6,INDEX(Assumptions!$D$19:$F$19,$P$4)) | Q33: =IF($Q$5="RefundEnforced",$Q$6,INDEX(Assumptions!$D$19:$F$19,$Q$4)) | R33: =IF($R$5="RefundEnforced",$R$6,INDEX(Assumptions!$D$19:$F$19,$R$4)) | S33: =IF($S$5="RefundEnforced",$S$6,INDEX(Assumptions!$D$19:$F$19,$S$4)) | T33: =IF($T$5="RefundEnforced",$T$6,INDEX(Assumptions!$D$19:$F$19,$T$4)) | U33: =IF($U$5="RefundEnforced",$U$6,INDEX(Assumptions!$D$19:$F$19,$U$4)) | V33: =IF($V$5="RefundEnforced",$V$6,INDEX(Assumptions!$D$19:$F$19,$V$4)) | W33: =IF($W$5="RefundEnforced",$W$6,INDEX(Assumptions!$D$19:$F$19,$W$4)) | X33: =IF($X$5="RefundEnforced",$X$6,INDEX(Assumptions!$D$19:$F$19,$X$4)) | Y33: =IF($Y$5="RefundEnforced",$Y$6,INDEX(Assumptions!$D$19:$F$19,$Y$4)) | Z33: =IF($Z$5="RefundEnforced",$Z$6,INDEX(Assumptions!$D$19:$F$19,$Z$4)) | AA33: =IF($AA$5="RefundEnforced",$AA$6,INDEX(Assumptions!$D$19:$F$19,$AA$4)) | AB33: =IF($AB$5="RefundEnforced",$AB$6,INDEX(Assumptions!$D$19:$F$19,$AB$4)) | AC33: =IF($AC$5="RefundEnforced",$AC$6,INDEX(Assumptions!$D$19:$F$19,$AC$4)) | AD33: =IF($AD$5="RefundEnforced",$AD$6,INDEX(Assumptions!$D$19:$F$19,$AD$4)) | AE33: =IF($AE$5="RefundEnforced",$AE$6,INDEX(Assumptions!$D$19:$F$19,$AE$4)) | AF33: =IF($AF$5="RefundEnforced",$AF$6,INDEX(Assumptions!$D$19:$F$19,$AF$4)) | AG33: =IF($AG$5="RefundEnforced",$AG$6,INDEX(Assumptions!$D$19:$F$19,$AG$4)) | AH33: =IF($AH$5="RefundEnforced",$AH$6,INDEX(Assumptions!$D$19:$F$19,$AH$4)) | AI33: =IF($AI$5="RefundEnforced",$AI$6,INDEX(Assumptions!$D$19:$F$19,$AI$4)) | AJ33: =IF($AJ$5="RefundEnforced",$AJ$6,INDEX(Assumptions!$D$19:$F$19,$AJ$4)) | AK33: =IF($AK$5="RefundEnforced",$AK$6,INDEX(Assumptions!$D$19:$F$19,$AK$4)) | AL33: =IF($AL$5="RefundEnforced",$AL$6,INDEX(Assumptions!$D$19:$F$19,$AL$4)) | AM33: =IF($AM$5="RefundEnforced",$AM$6,INDEX(Assumptions!$D$19:$F$19,$AM$4)) | AN33: =IF($AN$5="RefundEnforced",$AN$6,INDEX(Assumptions!$D$19:$F$19,$AN$4)) | AO33: =IF($AO$5="RefundEnforced",$AO$6,INDEX(Assumptions!$D$19:$F$19,$AO$4)) | AP33: =IF($AP$5="RefundEnforced",$AP$6,INDEX(Assumptions!$D$19:$F$19,$AP$4)) | AQ33: =IF($AQ$5="RefundEnforced",$AQ$6,INDEX(Assumptions!$D$19:$F$19,$AQ$4)) | AR33: =IF($AR$5="RefundEnforced",$AR$6,INDEX(Assumptions!$D$19:$F$19,$AR$4)) | AS33: =IF($AS$5="RefundEnforced",$AS$6,INDEX(Assumptions!$D$19:$F$19,$AS$4)) | AT33: =IF($AT$5="RefundEnforced",$AT$6,INDEX(Assumptions!$D$19:$F$19,$AT$4)) | AU33: =IF($AU$5="RefundEnforced",$AU$6,INDEX(Assumptions!$D$19:$F$19,$AU$4)) | AV33: =IF($AV$5="RefundEnforced",$AV$6,INDEX(Assumptions!$D$19:$F$19,$AV$4))
