Workbook
Name Scenario: Cover!$C$6
Name Students_S: Assumptions!$G$6
Name Students_M: Assumptions!$G$7
Name Students_L: Assumptions!$G$8
Name Fee_S: Assumptions!$G$9
Name Fee_M: Assumptions!$G$10
Name Fee_L: Assumptions!$G$11
Name OnboardMult_S: Assumptions!$G$12
Name OnboardMult_M: Assumptions!$G$13
Name OnboardMult_L: Assumptions!$G$14
Name DropoutRate: Assumptions!$G$16
Name UpfrontShare: Assumptions!$G$17
Name NInstalments: Assumptions!$G$18
Name RefundEnforced: Assumptions!$G$19
Name CourseMonths: Assumptions!$G$20
Name BlindMonths: Assumptions!$G$21
Name Preventable: Assumptions!$G$22
Name MinorShare: Assumptions!$G$23
Name Recall_Minor: Assumptions!$G$24
Name Recall_Adult: Assumptions!$G$25
Name Precision: Assumptions!$G$26
Name ActionRate: Assumptions!$G$27
Name InterventionSuccess: Assumptions!$G$28
Name AdmissionUplift: Assumptions!$G$29
Name MarginExtraAdmission: Assumptions!$G$30
Name StaffHoursSaved: Assumptions!$G$31
Name StaffHourCost: Assumptions!$G$32
Name InterventionMinutes: Assumptions!$G$33
Name MentorHourCost: Assumptions!$G$34
Name GST: Assumptions!$G$35
Name ITCShare: Assumptions!$G$36
Name ListPrice: Assumptions!$G$38
Name CompetitorAnchor: Assumptions!$G$39
Name CompetitorAnchorHigh: Assumptions!$G$40
Name MinFee: Assumptions!$G$41
Name NegotiationDisc: Assumptions!$G$42
Name PrepayUptake: Assumptions!$G$43
Name PrepayDisc: Assumptions!$G$44
Name BadDebt: Assumptions!$G$45
Name GatewayFee: Assumptions!$G$46
Name ReportsPerStudentMonth: Assumptions!$G$48
Name TokensInPerReport: Assumptions!$G$49
Name TokensOutPerReport: Assumptions!$G$50
Name LLMPriceIn: Assumptions!$G$51
Name LLMPriceOut: Assumptions!$G$52
Name WAMsgsPerStudentMonth: Assumptions!$G$53
Name WAPricePerMsg: Assumptions!$G$54
Name ComputePerStudentMonth: Assumptions!$G$55
Name ConsentCostPerStudentYear: Assumptions!$G$56
Name ServerCostMonth: Assumptions!$G$57
Name BSPFeeMonth: Assumptions!$G$58
Name InstPerStack: Assumptions!$G$59
Name CompliancePerInstMonth: Assumptions!$G$60
Name CSM_CTC: Assumptions!$G$62
Name InstPerCSM: Assumptions!$G$63
Name RepCTC: Assumptions!$G$64
Name RepTravel: Assumptions!$G$65
Name SalesOverheadPct: Assumptions!$G$66
Name PilotsPerRepMonth: Assumptions!$G$67
Name PilotConv: Assumptions!$G$68

Sheet Cover
A1: The Data Moat — Financial Model
A2: Institute Intelligence Platform · Nextute × Finance Club IIT Patna, Case B · v1.1 CFO audit · 2026-10-22
B6: SCENARIO (1 = Bear, 2 = Base, 3 = Bull) → | C6: 2 | D6: =CHOOSE(Scenario,"Bear","Base","Bull")
B7: Model checks | C7: =IF(ErrorCount=0,"ALL CHECKS PASS","ERRORS: "&ErrorCount) | D7: ="Warnings to discuss: "&WarningCount
B9: Headline (Mid institute, 400 students, live scenario) | C9: Our model | D9: Guide (naive)
B10: Effective dropout reduction | C10: =Institute_ROI!E37 | D10: =G_Prevent
B11: Dropouts prevented per year | C11: =Institute_ROI!E38 | D11: =Institute_ROI!$E$67
B12: Institute ROI (all benefits) | C12: =Institute_ROI!E54 | D12: =Institute_ROI!$E$70
B13: Institute ROI (hard benefits: fees + staff time) | C13: =Institute_ROI!E56 | D13: =Institute_ROI!$E$70
B14: Institute ROI (fees only) | C14: =Institute_ROI!E55 | D14: =Institute_ROI!$E$70
B15: Break-even: students to save per year | C15: =Institute_ROI!E57 | D15: =Institute_ROI!$E$71
B16: Extra admissions needed to break even (after fees + staff time) | C16: =Institute_ROI!E60 | D16: n/a
B17: Platform cost as % of a student's fee | C17: =Institute_ROI!E62 | D17: =G_Price*G_Months/G_Fee
B18: Avg monthly revenue per institute | C18: =Unit_Econ!E33 | D18: =Unit_Econ!$I$5
B19: Contribution margin | C19: =Unit_Econ!E38 | D19: =Unit_Econ!$I$6/Unit_Econ!$I$5
B20: CAC: sales + marketing per paying institute | C20: =Unit_Econ!E43 | D20: =G_CAC
B21: Fully loaded acquisition cost | C21: =Unit_Econ!E44 | D21: =Unit_Econ!$I$7
B22: LTV (discounted) | C22: =Unit_Econ!E51 | D22: =Unit_Econ!$I$9
B23: LTV ÷ acquisition cost (discounted) | C23: =Unit_Econ!E52 | D23: =Unit_Econ!$I$10
B24: LTV ÷ acquisition cost (undiscounted, peer convention) | C24: =Unit_Econ!E56 | D24: =Unit_Econ!$I$10
B25: Payback, survival-weighted (months) | C25: =Unit_Econ!E53 | D25: =Unit_Econ!$I$8
B26: Payback, simple (months) | C26: =Unit_Econ!E54 | D26: =Unit_Econ!$I$8
B27: Institutes needed to cover fixed team cost (steady state) | C27: =Unit_Econ!I16 | D27: n/a
B28: 3-year: revenue in year 3 | C28: =Projection!$F$87 | D28: n/a
B29: 3-year: EBITDA in year 3 | C29: =Projection!$F$93 | D29: n/a
B30: 3-year: paying institutes at the end of year 3 | C30: =Projection!$F$96 | D30: n/a
B31: 3-year: funding the model says we need | C31: =Projection!$D$103 | D31: n/a
B32: 3-year: break-even month (3 positive months in a row) | C32: =Projection!$D$105 | D32: n/a
B34: Colour code
B35: Blue text | C35: Input — edit only these (Assumptions D:F and N, Seasonality, grid points, Scenario)
B36: Black text | C36: Formula
B37: Green text | C37: Link from another sheet
B38: Yellow fill | C38: Key lever / live value
B39: Green fill | C39: Key output
B41: How to use
B42: 1 | C42: Pick a scenario in C6. Bear / Base / Bull flex only the scenario drivers (Assumptions column N).
B43: 2 | C43: Change an input on Assumptions (Bear/Base/Bull) — never type over a formula.
B44: 3 | C44: Cover C7 must say ALL CHECKS PASS before you quote any number.
B45: 4 | C45: To rebuild from the CSVs: python build_model.py (Financial_Model folder).
B47: Evidence labels | C47: Researched/Public = sourced (see Sources) · Guide = case brief · Assumption = unverified · Structural = modelling convention
B48: Scope | C48: Pricing, COGS, Institute ROI, Unit economics, 3-year Projection (sales capacity, cohorts, P&L, cash, funding ask), Scenarios, Sensitivity, Checks, Sources. Not modelled: upsell/expansion revenue (so no NRR) and the other PS revenue models (outcome-linked, parent, marketplace, benchmarks).

Sheet Assumptions
A1: Assumptions — every input in the model lives here
A2: Blue = input you may edit (Bear / Base / Bull). LIVE = the value the model uses: rows marked Y in 'Scenario driver' follow the Cover switch, CHOOSE(Scenario, Bear, Base, Bull); rows marked N always use Base. Bear = worse for OUR business. Type: Researched/Public = sourced · Guide = case brief · Assumption = unverified · Structural = convention.
A4: Name (named range → Live) | B4: Input | C4: Unit | D4: Bear | E4: Base | F4: Bull | G4: LIVE | H4: Type | I4: Confidence | J4: Source | K4: Note | L4: Pct out of [0,1] | M4: Live outside Bear–Bull | N4: Scenario driver (Y/N)
A5: Segments
A6: Students_S | B6: Students per institute - Small | C6: students | D6: 180 | E6: 180 | F6: 180 | G6: =IF(N6="Y",CHOOSE(Scenario,D6,E6,F6),E6) | H6: Assumption | I6: M | J6: Case brief range 150-2000; our cut <250 | K6: Segment midpoint | L6: 0 | M6: =IF(AND(G6>=MIN(D6,F6),G6<=MAX(D6,F6)),0,1) | N6: N
A7: Students_M | B7: Students per institute - Mid | C7: students | D7: 400 | E7: 400 | F7: 400 | G7: =IF(N7="Y",CHOOSE(Scenario,D7,E7,F7),E7) | H7: Guide | I7: M | J7: Case brief baseline 400 | L7: 0 | M7: =IF(AND(G7>=MIN(D7,F7),G7<=MAX(D7,F7)),0,1) | N7: N
A8: Students_L | B8: Students per institute - Large | C8: students | D8: 1200 | E8: 1200 | F8: 1200 | G8: =IF(N8="Y",CHOOSE(Scenario,D8,E8,F8),E8) | H8: Assumption | I8: M | J8: Case brief range 150-2000; our cut >800 | L8: 0 | M8: =IF(AND(G8>=MIN(D8,F8),G8<=MAX(D8,F8)),0,1) | N8: N
A9: Fee_S | B9: Annual fee per student - Small | C9: Rs/yr | D9: 50000 | E9: 60000 | F9: 75000 | G9: =IF(N9="Y",CHOOSE(Scenario,D9,E9,F9),E9) | H9: Researched | I9: L | J9: R2 local-institute evidence: Vedantu Gaya Rs50-56k, Rupantri Muzaffarpur Rs55-60k, GOAL Patna Rs51-99k; PS baseline Rs60k | K9: Audit 2026-10-22: re-based to local evidence (was Rs65k Base) | L9: 0 | M9: =IF(AND(G9>=MIN(D9,F9),G9<=MAX(D9,F9)),0,1) | N9: N
A10: Fee_M | B10: Annual fee per student - Mid | C10: Rs/yr | D10: 60000 | E10: 75000 | F10: 95000 | G10: =IF(N10="Y",CHOOSE(Scenario,D10,E10,F10),E10) | H10: Researched | I10: L | J10: R2: PS baseline Rs60k = Bear; local Tier-2 evidence Rs50k-1.2L (Patna independents); chain fees (Vedantu Patna Rs95k) = Bull | K10: Audit 2026-10-22: was Rs95k Base (chain pricing); our customers are local independents | L10: 0 | M10: =IF(AND(G10>=MIN(D10,F10),G10<=MAX(D10,F10)),0,1) | N10: N
A11: Fee_L | B11: Annual fee per student - Large | C11: Rs/yr | D11: 85000 | E11: 100000 | F11: 125000 | G11: =IF(N11="Y",CHOOSE(Scenario,D11,E11,F11),E11) | H11: Researched | I11: M | J11: R2: Udaan Patna Rs1.15-1.25L/yr (own site, 2025-27); chains Rs1.1-1.4L (Motion, Allen Indore, Vedantu Lucknow) | K11: Audit 2026-10-22: was Rs125k Base | L11: 0 | M11: =IF(AND(G11>=MIN(D11,F11),G11<=MAX(D11,F11)),0,1) | N11: N
A12: OnboardMult_S | B12: Onboarding cost multiplier - Small | C12: x | D12: 0.8 | E12: 0.8 | F12: 0.8 | G12: =IF(N12="Y",CHOOSE(Scenario,D12,E12,F12),E12) | H12: Assumption | I12: L | J12: Fewer batches to migrate | L12: 0 | M12: =IF(AND(G12>=MIN(D12,F12),G12<=MAX(D12,F12)),0,1) | N12: N
A13: OnboardMult_M | B13: Onboarding cost multiplier - Mid | C13: x | D13: 1 | E13: 1 | F13: 1 | G13: =IF(N13="Y",CHOOSE(Scenario,D13,E13,F13),E13) | H13: Structural | I13: H | J13: Reference segment | L13: 0 | M13: =IF(AND(G13>=MIN(D13,F13),G13<=MAX(D13,F13)),0,1) | N13: N
A14: OnboardMult_L | B14: Onboarding cost multiplier - Large | C14: x | D14: 1.6 | E14: 1.6 | F14: 1.6 | G14: =IF(N14="Y",CHOOSE(Scenario,D14,E14,F14),E14) | H14: Assumption | I14: L | J14: More batches and staff to train | L14: 0 | M14: =IF(AND(G14>=MIN(D14,F14),G14<=MAX(D14,F14)),0,1) | N14: N
A15: Institute
A16: DropoutRate | B16: Mid-session dropout/default rate | C16: % of students/yr | D16: 0.08 | E16: 0.12 | F16: 0.18 | G16: =IF(N16="Y",CHOOSE(Scenario,D16,E16,F16),E16) | H16: Researched | I16: L | J16: PS Section 7 baseline 8-15% (12% used); CFI 'at least 10 per cent of students in every batch' (ThePrint 2025) is a floor; tech generator uses 18% (knob 12-25%) | K16: Audit 2026-10-22: Base back to the PS's 12% (was 10%). Tech's 18% is a stress calibration that gives enough validation events | L16: =IF(OR(G16<0,G16>1),1,0) | M16: =IF(AND(G16>=MIN(D16,F16),G16<=MAX(D16,F16)),0,1) | N16: Y
A17: UpfrontShare | B17: Share of students paying full fee upfront | C17: % | D17: 0.4 | E17: 0.25 | F17: 0.15 | G17: =IF(N17="Y",CHOOSE(Scenario,D17,E17,F17),E17) | H17: Assumption | I17: L | J17: R2: not found. Instalments are the norm (Allen 2; PW 3; Aakash several; Rajasthan Act s.6(2)(d) >=4 option) | K17: TECH_PLAN's 35% had no source | L17: =IF(OR(G17<0,G17>1),1,0) | M17: =IF(AND(G17>=MIN(D17,F17),G17<=MAX(D17,F17)),0,1) | N17: N
A18: NInstalments | B18: Instalments per year for non-upfront payers | C18: count | D18: 2 | E18: 3 | F18: 4 | G18: =IF(N18="Y",CHOOSE(Scenario,D18,E18,F18),E18) | H18: Researched | I18: M | J18: R2: Allen 2 (2nd within 45 days); PW 3; Rajasthan Act 16/2025 s.6(2)(d) min. 4 equal | K18: Fewer instalments = cash collected early = less at risk | L18: 0 | M18: =IF(AND(G18>=MIN(D18,F18),G18<=MAX(D18,F18)),0,1) | N18: N
A19: RefundEnforced | B19: Share of upfront leavers actually refunded pro-rata | C19: % | D19: 0.1 | E19: 0.3 | F19: 0.6 | G19: =IF(N19="Y",CHOOSE(Scenario,D19,E19,F19),E19) | H19: Assumption | I19: L | J19: R2: MoE Guidelines 2024 cl.8(iv) and Rajasthan s.13(4) require pro-rata refund within 10 days; MoE is advisory and Allen/Aakash/PW practice is cut-off or no refund | K19: Refunded upfront leavers = fee at risk | L19: =IF(OR(G19<0,G19>1),1,0) | M19: =IF(AND(G19>=MIN(D19,F19),G19<=MAX(D19,F19)),0,1) | N19: N
A20: CourseMonths | B20: Course length | C20: months | D20: 10 | E20: 10 | F20: 10 | G20: =IF(N20="Y",CHOOSE(Scenario,D20,E20,F20),E20) | H20: Guide | I20: H | J20: Case brief ~10 months | L20: 0 | M20: =IF(AND(G20>=MIN(D20,F20),G20<=MAX(D20,F20)),0,1) | N20: N
A21: BlindMonths | B21: Months before the model can flag (no test data yet) | C21: months | D21: 3 | E21: 2 | F21: 1 | G21: =IF(N21="Y",CHOOSE(Scenario,D21,E21,F21),E21) | H21: Assumption | I21: M | J21: The model needs 1-2 cumulative tests before it can flag (tech generator: a full mock every 14 days) | K21: Audit: Base 2 (was 1). Dropouts in these months cannot be caught | L21: 0 | M21: =IF(AND(G21>=MIN(D21,F21),G21<=MAX(D21,F21)),0,1) | N21: N
A22: Preventable | B22: Share of dropouts that are preventable (check only) | C22: % | D22: 0.35 | E22: 0.55 | F22: 0.65 | G22: =IF(N22="Y",CHOOSE(Scenario,D22,E22,F22),E22) | H22: Assumption | I22: L | J22: Tech generator reasons_mix: academic gap 35% + financial 20% are addressable; relocation 20%, switched institute 15%, health 10% are not | K22: Audit: aligned with the tech team; used only as a sanity check on the trial effect | L22: =IF(OR(G22<0,G22>1),1,0) | M22: =IF(AND(G22>=MIN(D22,F22),G22<=MAX(D22,F22)),0,1) | N22: N
A23: MinorShare | B23: Share of students under 18 | C23: % | D23: 0.85 | E23: 0.78 | F23: 0.65 | G23: =IF(N23="Y",CHOOSE(Scenario,D23,E23,F23),E23) | H23: Public | I23: M | J23: Tech generator: 78% of students are minors at join (FEASIBILITY_CHECK s.6); JEE/NEET Class 11-12 are 16-17 | K23: Audit: aligned with the tech team's synthetic data | L23: =IF(OR(G23<0,G23>1),1,0) | M23: =IF(AND(G23>=MIN(D23,F23),G23<=MAX(D23,F23)),0,1) | N23: N
A24: Recall_Minor | B24: Model recall on minors (academic-support + rules) | C24: % | D24: 0.25 | E24: 0.32 | F24: 0.45 | G24: =IF(N24="Y",CHOOSE(Scenario,D24,E24,F24),E24) | H24: Assumption | I24: M | J24: Tech FEASIBILITY_CHECK s.2 and s.6: recall 0.31 on the actual generator; 0.49-0.55 of gradual dropouts x 75% gradual = 0.37-0.41 of all dropouts; minors get the academic-support model + rules only. Replace with metrics.json | K24: Audit 2026-10-22: was 0.55 Base (above anything the tech team measured). 25% of dropouts are sudden and unpredictable | L24: =IF(OR(G24<0,G24>1),1,0) | M24: =IF(AND(G24>=MIN(D24,F24),G24<=MAX(D24,F24)),0,1) | N24: Y
A25: Recall_Adult | B25: Model recall on 18+ (full ML) | C25: % | D25: 0.3 | E25: 0.42 | F25: 0.6 | G25: =IF(N25="Y",CHOOSE(Scenario,D25,E25,F25),E25) | H25: Assumption | I25: M | J25: Tech FEASIBILITY_CHECK s.2: 0.37-0.41 of all dropouts at fixed workload; adults (18+) can use full ML incl. engagement. Replace with metrics.json | K25: Audit 2026-10-22: was 0.65 Base. OULAD AUC 0.706-0.794 (public) is ranking quality, not recall at a workload | L25: =IF(OR(G25<0,G25>1),1,0) | M25: =IF(AND(G25>=MIN(D25,F25),G25<=MAX(D25,F25)),0,1) | N25: Y
A26: Precision | B26: Precision of at-risk flag | C26: % | D26: 0.1 | E26: 0.15 | F26: 0.25 | G26: =IF(N26="Y",CHOOSE(Scenario,D26,E26,F26),E26) | H26: Researched | I26: M | J26: Tech FEASIBILITY_CHECK s.6: precision@top-4%/wk 0.136; with 38% of students flagged at least once and recall 0.31, student-level precision is about 0.15 (derived) | K26: Audit 2026-10-22: was 0.35. Low precision means most mentor calls go to students who would not have left | L26: =IF(OR(G26<0,G26>1),1,0) | M26: =IF(AND(G26>=MIN(D26,F26),G26<=MAX(D26,F26)),0,1) | N26: Y
A27: ActionRate | B27: Share of flags the institute assigns to outreach | C27: % | D27: 0.7 | E27: 0.9 | F27: 1 | G27: =IF(N27="Y",CHOOSE(Scenario,D27,E27,F27),E27) | H27: Assumption | I27: L | J27: Mentor capacity; the RCT effect below is already intention-to-treat | K27: Primary research needed | L27: =IF(OR(G27<0,G27>1),1,0) | M27: =IF(AND(G27>=MIN(D27,F27),G27<=MAX(D27,F27)),0,1) | N27: N
A28: InterventionSuccess | B28: Dropout reduction among flagged students given outreach (RCT) | C28: relative % | D28: 0.05 | E28: 0.15 | F28: 0.3 | G28: =IF(N28="Y",CHOOSE(Scenario,D28,E28,F28),E28) | H28: Researched | I28: M | J28: R4: mean 15.8% / median 12.5% over 8 RCTs - OU outreach RCT 2020 -19%/-35%; Room to Read India -30%; Bergman parent texts; MAAPS/Samata/Oreopoulos nulls (research/R4_R5) | K28: Borrowed from other settings - not our measured effect | L28: =IF(OR(G28<0,G28>1),1,0) | M28: =IF(AND(G28>=MIN(D28,F28),G28<=MAX(D28,F28)),0,1) | N28: Y
A29: AdmissionUplift | B29: Admissions uplift next session from results/parent trust | C29: % of students | D29: 0 | E29: 0.01 | F29: 0.03 | G29: =IF(N29="Y",CHOOSE(Scenario,D29,E29,F29),E29) | H29: Assumption | I29: L | J29: No evidence - Bear = 0 | L29: =IF(OR(G29<0,G29>1),1,0) | M29: =IF(AND(G29>=MIN(D29,F29),G29<=MAX(D29,F29)),0,1) | N29: Y
A30: MarginExtraAdmission | B30: Institute margin on one extra admission | C30: % | D30: 0.4 | E30: 0.6 | F30: 0.8 | G30: =IF(N30="Y",CHOOSE(Scenario,D30,E30,F30),E30) | H30: Assumption | I30: L | J30: Marginal seat in an existing batch | L30: =IF(OR(G30<0,G30>1),1,0) | M30: =IF(AND(G30>=MIN(D30,F30),G30<=MAX(D30,F30)),0,1) | N30: N
A31: StaffHoursSaved | B31: Staff hours saved per month | C31: hours/month | D31: 10 | E31: 25 | F31: 50 | G31: =IF(N31="Y",CHOOSE(Scenario,D31,E31,F31),E31) | H31: Guide | I31: L | J31: Case brief value lever; primary research needed | L31: 0 | M31: =IF(AND(G31>=MIN(D31,F31),G31<=MAX(D31,F31)),0,1) | N31: N
A32: StaffHourCost | B32: Cost of one admin staff hour | C32: Rs/hour | D32: 75 | E32: 100 | F32: 150 | G32: =IF(N32="Y",CHOOSE(Scenario,D32,E32,F32),E32) | H32: Researched | I32: M | J32: R5: Tier-2 executive pay Rs18-25k/month (Payscale/Indeed Patna) / ~200 h | L32: 0 | M32: =IF(AND(G32>=MIN(D32,F32),G32<=MAX(D32,F32)),0,1) | N32: N
A33: InterventionMinutes | B33: Mentor minutes per intervention | C33: minutes | D33: 240 | E33: 120 | F33: 60 | G33: =IF(N33="Y",CHOOSE(Scenario,D33,E33,F33),E33) | H33: Assumption | I33: L | J33: Assumption: the trials behind the 15% effect used multi-touch outreach (call + parent meeting + follow-ups), about 2 hours per flagged student | K33: Audit 2026-10-22: was 30 minutes Base, too thin to deliver the trial effect | L33: 0 | M33: =IF(AND(G33>=MIN(D33,F33),G33<=MAX(D33,F33)),0,1) | N33: N
A34: MentorHourCost | B34: Cost of one mentor hour | C34: Rs/hour | D34: 250 | E34: 200 | F34: 150 | G34: =IF(N34="Y",CHOOSE(Scenario,D34,E34,F34),E34) | H34: Assumption | I34: M | J34: Teacher pay ~Rs30-50k/month / ~200 h | L34: 0 | M34: =IF(AND(G34>=MIN(D34,F34),G34<=MAX(D34,F34)),0,1) | N34: N
A35: GST | B35: GST on SaaS | C35: % | D35: 0.18 | E35: 0.18 | F35: 0.18 | G35: =IF(N35="Y",CHOOSE(Scenario,D35,E35,F35),E35) | H35: Researched | I35: M | J35: R6: 18% (heading 9983 residual entry; Notif. 11/2017-CTR as amended by 15/2025-CTR) | K35: SAC code 9983 vs 9984 unconfirmed - ask a CA | L35: =IF(OR(G35<0,G35>1),1,0) | M35: =IF(AND(G35>=MIN(D35,F35),G35<=MAX(D35,F35)),0,1) | N35: N
A36: ITCShare | B36: Share of institutes that reclaim our GST as input credit | C36: % | D36: 0.3 | E36: 0.6 | F36: 0.9 | G36: =IF(N36="Y",CHOOSE(Scenario,D36,E36,F36),E36) | H36: Assumption | I36: L | J36: R6: coaching is taxable at 18%; registration mandatory above Rs20L turnover; CGST s.16(1) gives ITC to registered persons. A 180-student institute turns over ~Rs1 Cr, so legally registered - but cash/informal practice in Tier-3 | K36: Was 'all unregistered' in the naive view | L36: =IF(OR(G36<0,G36>1),1,0) | M36: =IF(AND(G36>=MIN(D36,F36),G36<=MAX(D36,F36)),0,1) | N36: N
A37: Pricing
A38: ListPrice | B38: List price per active student per month | C38: Rs/student/month | D38: 20 | E38: 30 | F38: 40 | G38: =IF(N38="Y",CHOOSE(Scenario,D38,E38,F38),E38) | H38: Assumption | I38: L | J38: R1: ERP/LMS anchors Rs4-21/student/month at 400 students (Classplus/Fedena/Graphy); no competitor bundles OMR + topic analytics + Hindi WhatsApp | K38: Decision lever - test in interviews (Van Westendorp) | L38: 0 | M38: =IF(AND(G38>=MIN(D38,F38),G38<=MAX(D38,F38)),0,1) | N38: Y
A39: CompetitorAnchor | B39: What institutes already pay for an ERP/LMS | C39: Rs/student/month | D39: 4.17 | E39: 10.42 | F39: 20.83 | G39: =IF(N39="Y",CHOOSE(Scenario,D39,E39,F39),E39) | H39: Researched | I39: M | J39: R1: Classplus Starter Rs19999/yr (Capterra); Fedena Standard / Graphy Grow Rs50k/yr; Fedena Ultimate Rs1L/yr - all at 400 students | K39: Reference only - not used in revenue | L39: 0 | M39: =IF(AND(G39>=MIN(D39,F39),G39<=MAX(D39,F39)),0,1) | N39: N
A40: CompetitorAnchorHigh | B40: Highest priced ERP/LMS anchor found | C40: Rs/student/month | D40: 20.83 | E40: 20.83 | F40: 20.83 | G40: =IF(N40="Y",CHOOSE(Scenario,D40,E40,F40),E40) | H40: Researched | I40: M | J40: R1: Fedena Ultimate / Graphy Rise Rs1L/yr at 400 students | K40: Used in a warning check | L40: 0 | M40: =IF(AND(G40>=MIN(D40,F40),G40<=MAX(D40,F40)),0,1) | N40: N
A41: MinFee | B41: Minimum monthly fee per institute | C41: Rs/month | D41: 2000 | E41: 3000 | F41: 4000 | G41: =IF(N41="Y",CHOOSE(Scenario,D41,E41,F41),E41) | H41: Assumption | I41: L | J41: FINANCE_PLAN s.3.2 | L41: 0 | M41: =IF(AND(G41>=MIN(D41,F41),G41<=MAX(D41,F41)),0,1) | N41: N
A42: NegotiationDisc | B42: Average negotiated discount off list | C42: % | D42: 0.2 | E42: 0.1 | F42: 0.05 | G42: =IF(N42="Y",CHOOSE(Scenario,D42,E42,F42),E42) | H42: Assumption | I42: L | J42: Primary research needed | L42: =IF(OR(G42<0,G42>1),1,0) | M42: =IF(AND(G42>=MIN(D42,F42),G42<=MAX(D42,F42)),0,1) | N42: N
A43: PrepayUptake | B43: Share of institutes choosing annual prepay | C43: % | D43: 0.2 | E43: 0.4 | F43: 0.6 | G43: =IF(N43="Y",CHOOSE(Scenario,D43,E43,F43),E43) | H43: Assumption | I43: L | J43: Coaching institutes are cash-rich in Apr-Jun (admission season) | K43: Prepaid institutes cannot churn mid-session | L43: =IF(OR(G43<0,G43>1),1,0) | M43: =IF(AND(G43>=MIN(D43,F43),G43<=MAX(D43,F43)),0,1) | N43: N
A44: PrepayDisc | B44: Annual prepay discount | C44: % | D44: 0.15 | E44: 0.15 | F44: 0.15 | G44: =IF(N44="Y",CHOOSE(Scenario,D44,E44,F44),E44) | H44: Assumption | I44: M | J44: FINANCE_PLAN s.3.2; R2 shows institutes give 4-6% for upfront fees | L44: =IF(OR(G44<0,G44>1),1,0) | M44: =IF(AND(G44>=MIN(D44,F44),G44<=MAX(D44,F44)),0,1) | N44: N
A45: BadDebt | B45: Bad debt / uncollected billing | C45: % | D45: 0.08 | E45: 0.03 | F45: 0.01 | G45: =IF(N45="Y",CHOOSE(Scenario,D45,E45,F45),E45) | H45: Assumption | I45: M | J45: FINANCE_PLAN s.3.2 | L45: =IF(OR(G45<0,G45>1),1,0) | M45: =IF(AND(G45>=MIN(D45,F45),G45<=MAX(D45,F45)),0,1) | N45: N
A46: GatewayFee | B46: Payment collection cost (blended) | C46: % of revenue | D46: 0.0236 | E46: 0.012 | F46: 0.004 | G46: =IF(N46="Y",CHOOSE(Scenario,D46,E46,F46),E46) | H46: Researched | I46: M | J46: R6: Razorpay 2% + 18% GST = 2.36%; UPI MDR 0.4% on P2M >Rs2000 from 15-Oct-2026; NEFT ~0 | K46: Base assumes half paid by bank transfer | L46: =IF(OR(G46<0,G46>1),1,0) | M46: =IF(AND(G46>=MIN(D46,F46),G46<=MAX(D46,F46)),0,1) | N46: N
A47: COGS
A48: ReportsPerStudentMonth | B48: AI parent reports per student per month | C48: reports | D48: 6 | E48: 4 | F48: 4 | G48: =IF(N48="Y",CHOOSE(Scenario,D48,E48,F48),E48) | H48: Assumption | I48: M | J48: TECH_PLAN s.11 weekly report; Bear adds alerts | L48: 0 | M48: =IF(AND(G48>=MIN(D48,F48),G48<=MAX(D48,F48)),0,1) | N48: N
A49: TokensInPerReport | B49: LLM input tokens per report | C49: tokens | D49: 2500 | E49: 1500 | F49: 1000 | G49: =IF(N49="Y",CHOOSE(Scenario,D49,E49,F49),E49) | H49: Assumption | I49: M | J49: TECH_PLAN GenAI design (numbers_json + template) | L49: 0 | M49: =IF(AND(G49>=MIN(D49,F49),G49<=MAX(D49,F49)),0,1) | N49: N
A50: TokensOutPerReport | B50: LLM output tokens per report | C50: tokens | D50: 1200 | E50: 1000 | F50: 600 | G50: =IF(N50="Y",CHOOSE(Scenario,D50,E50,F50),E50) | H50: Assumption | I50: M | J50: Bilingual report ~400-600 words | L50: 0 | M50: =IF(AND(G50>=MIN(D50,F50),G50<=MAX(D50,F50)),0,1) | N50: N
A51: LLMPriceIn | B51: LLM input price (hosted) | C51: Rs per 1M tokens | D51: 142.58 | E51: 23.76 | F51: 9.51 | G51: =IF(N51="Y",CHOOSE(Scenario,D51,E51,F51),E51) | H51: Researched | I51: H | J51: R6: Gemini 3.8 Flash from 1-Jan-2027 / Gemini 3.1 Flash-Lite / Claude Haiku 5.5 at Rs95.05/USD (official pricing pages 20-Oct-2026) | K51: Local Ollama = ~0 (prototype) | L51: 0 | M51: =IF(AND(G51>=MIN(D51,F51),G51<=MAX(D51,F51)),0,1) | N51: N
A52: LLMPriceOut | B52: LLM output price (hosted) | C52: Rs per 1M tokens | D52: 712.88 | E52: 142.58 | F52: 47.53 | G52: =IF(N52="Y",CHOOSE(Scenario,D52,E52,F52),E52) | H52: Researched | I52: H | J52: R6: same models as input price | L52: 0 | M52: =IF(AND(G52>=MIN(D52,F52),G52<=MAX(D52,F52)),0,1) | N52: N
A53: WAMsgsPerStudentMonth | B53: WhatsApp utility messages per student per month | C53: messages | D53: 10 | E53: 6 | F53: 4 | G53: =IF(N53="Y",CHOOSE(Scenario,D53,E53,F53),E53) | H53: Assumption | I53: M | J53: Weekly report + alerts + fee reminders | L53: 0 | M53: =IF(AND(G53>=MIN(D53,F53),G53<=MAX(D53,F53)),0,1) | N53: N
A54: WAPricePerMsg | B54: WhatsApp utility message price (India) | C54: Rs/message | D54: 0.145 | E54: 0.1323 | F54: 0.115 | G54: =IF(N54="Y",CHOOSE(Scenario,D54,E54,F54),E54) | H54: Researched | I54: H | J54: R6: Meta list Rs0.115 (eff. 1-Oct-2026); Gallabox Rs0.1323; AiSensy Rs0.145. Utility replies in window charged again from 1-Oct-2026 | L54: 0 | M54: =IF(AND(G54>=MIN(D54,F54),G54<=MAX(D54,F54)),0,1) | N54: N
A55: ComputePerStudentMonth | B55: Compute + storage + backups per student | C55: Rs/student/month | D55: 1.5 | E55: 0.8 | F55: 0.4 | G55: =IF(N55="Y",CHOOSE(Scenario,D55,E55,F55),E55) | H55: Assumption | I55: L | J55: TECH_PLAN s.16 cost model (NB09 pending); OMR images auto-deleted after 7 days | L55: 0 | M55: =IF(AND(G55>=MIN(D55,F55),G55<=MAX(D55,F55)),0,1) | N55: N
A56: ConsentCostPerStudentYear | B56: Consent OTP + verification per student | C56: Rs/student/yr | D56: 3 | E56: 1.5 | F56: 0.5 | G56: =IF(N56="Y",CHOOSE(Scenario,D56,E56,F56),E56) | H56: Assumption | I56: L | J56: TECH_PLAN consent design (OTP) | L56: 0 | M56: =IF(AND(G56>=MIN(D56,F56),G56<=MAX(D56,F56)),0,1) | N56: N
A57: ServerCostMonth | B57: App server + managed Postgres + backups per stack | C57: Rs/month | D57: 9000 | E57: 4000 | F57: 3000 | G57: =IF(N57="Y",CHOOSE(Scenario,D57,E57,F57),E57) | H57: Researched | I57: M | J57: R6: AWS t3.medium Rs3108 + DO PG 2vCPU Rs5789 / Lightsail-DO Rs2281 + DO PG Rs1440 / t4g Rs1554 + Lightsail DB Rs1426 | K57: Base adds ~Rs300 backups | L57: 0 | M57: =IF(AND(G57>=MIN(D57,F57),G57<=MAX(D57,F57)),0,1) | N57: N
A58: BSPFeeMonth | B58: WhatsApp BSP platform fee per stack | C58: Rs/month | D58: 3200 | E58: 1500 | F58: 0 | G58: =IF(N58="Y",CHOOSE(Scenario,D58,E58,F58),E58) | H58: Researched | I58: M | J58: R6: AiSensy Pro Rs3200 / Basic Rs1500 / Gupshup self-serve Rs0 + per-msg | L58: 0 | M58: =IF(AND(G58>=MIN(D58,F58),G58<=MAX(D58,F58)),0,1) | N58: N
A59: InstPerStack | B59: Institutes sharing one server stack | C59: institutes | D59: 10 | E59: 20 | F59: 40 | G59: =IF(N59="Y",CHOOSE(Scenario,D59,E59,F59),E59) | H59: Assumption | I59: L | J59: Depends on load test (NB09) | L59: 0 | M59: =IF(AND(G59>=MIN(D59,F59),G59<=MAX(D59,F59)),0,1) | N59: N
A60: CompliancePerInstMonth | B60: DPDP compliance cost per institute | C60: Rs/month | D60: 400 | E60: 200 | F60: 100 | G60: =IF(N60="Y",CHOOSE(Scenario,D60,E60,F60),E60) | H60: Assumption | I60: L | J60: Audits / consent management / DPO time | L60: 0 | M60: =IF(AND(G60>=MIN(D60,F60),G60<=MAX(D60,F60)),0,1) | N60: N
A61: GTM
A62: CSM_CTC | B62: Customer-success / onboarding exec monthly CTC | C62: Rs/month | D62: 45000 | E62: 35000 | F62: 25000 | G62: =IF(N62="Y",CHOOSE(Scenario,D62,E62,F62),E62) | H62: Researched | I62: L | J62: R5: Tier-2 remote CS median Rs33-42k (Frontlines 2026); Payscale Jaipur CSM-manager Rs58k | L62: 0 | M62: =IF(AND(G62>=MIN(D62,F62),G62<=MAX(D62,F62)),0,1) | N62: N
A63: InstPerCSM | B63: Institutes per CSM | C63: institutes | D63: 40 | E63: 80 | F63: 120 | G63: =IF(N63="Y",CHOOSE(Scenario,D63,E63,F63),E63) | H63: Researched | I63: L | J63: R5: Gainsight SMB 100-250 accounts per CSM - cut for high-touch Tier-2 onboarding | L63: 0 | M63: =IF(AND(G63>=MIN(D63,F63),G63<=MAX(D63,F63)),0,1) | N63: N
A64: RepCTC | B64: Field sales rep monthly CTC (incl. fuel) | C64: Rs/month | D64: 30000 | E64: 24000 | F64: 19000 | G64: =IF(N64="Y",CHOOSE(Scenario,D64,E64,F64),E64) | H64: Researched | I64: M | J64: R5: Payscale Patna field sales ~Rs20k base; PhonePe postings Rs18-25k + Rs4-4.5k fuel | L64: 0 | M64: =IF(AND(G64>=MIN(D64,F64),G64<=MAX(D64,F64)),0,1) | N64: N
A65: RepTravel | B65: Rep intercity travel + demo material per month | C65: Rs/month | D65: 8000 | E65: 5000 | F65: 3000 | G65: =IF(N65="Y",CHOOSE(Scenario,D65,E65,F65),E65) | H65: Assumption | I65: L | J65: R5: per-km allowance not found | L65: 0 | M65: =IF(AND(G65>=MIN(D65,F65),G65<=MAX(D65,F65)),0,1) | N65: N
A66: SalesOverheadPct | B66: Sales overhead loading on rep cost (manager, incentives, recruiting, tools) | C66: % of rep cost | D66: 0.4 | E66: 0.3 | F66: 0.2 | G66: =IF(N66="Y",CHOOSE(Scenario,D66,E66,F66),E66) | H66: Assumption | I66: L | J66: R5: bottom-up CAC adds x1.3 / x1.2 / x1.0 for manager overhead plus an incentive; peers load CAC with 25-40% | K66: Audit 2026-10-22: new. Puts CAC inside the PS's Rs15-30k range | L66: =IF(OR(G66<0,G66>1),1,0) | M66: =IF(AND(G66>=MIN(D66,F66),G66<=MAX(D66,F66)),0,1) | N66: N
A67: PilotsPerRepMonth | B67: Pilots started per rep per month (yearly avg) | C67: pilots | D67: 6 | E67: 10 | F67: 14 | G67: =IF(N67="Y",CHOOSE(Scenario,D67,E67,F67),E67) | H67: Assumption | I67: L | J67: R5: SaaStr 20-50 deals/month is inside sales; cut for in-person Tier-2 demos; peak Mar-Jun | L67: 0 | M67: =IF(AND(G67>=MIN(D67,F67),G67<=MAX(D67,F67)),0,1) | N67: Y
A68: PilotConv | B68: Pilot-to-paid conversion | C68: % | D68: 0.15 | E68: 0.3 | F68: 0.5 | G68: =IF(N68="Y",CHOOSE(Scenario,D68,E68,F68),E68) | H68: Researched | I68: L | J68: R5: trial-to-paid 8% median / 18.2% opt-in / 48.8% opt-out (Userpilot 2026); assisted-pilot benchmark not found | L68: =IF(OR(G68<0,G68>1),1,0) | M68: =IF(AND(G68>=MIN(D68,F68),G68<=MAX(D68,F68)),0,1) | N68: Y
A69: PilotMonths | B69: Free pilot length | C69: months | D69: 2 | E69: 1 | F69: 1 | G69: =IF(N69="Y",CHOOSE(Scenario,D69,E69,F69),E69) | H69: Assumption | I69: M | J69: FINANCE_PLAN s.3.2 | L69: 0 | M69: =IF(AND(G69>=MIN(D69,F69),G69<=MAX(D69,F69)),0,1) | N69: N
A70: PilotSetupCost | B70: Retro-pilot setup (import last year's Excel; show who left) | C70: Rs per pilot | D70: 5000 | E70: 3000 | F70: 1500 | G70: =IF(N70="Y",CHOOSE(Scenario,D70,E70,F70),E70) | H70: Assumption | I70: L | J70: GTM design: light pilot; full onboarding only after conversion | K70: Primary research needed | L70: 0 | M70: =IF(AND(G70>=MIN(D70,F70),G70<=MAX(D70,F70)),0,1) | N70: N
A71: OnboardBase | B71: Onboarding cost per institute (mid) | C71: Rs | D71: 15000 | E71: 8000 | F71: 5000 | G71: =IF(N71="Y",CHOOSE(Scenario,D71,E71,F71),E71) | H71: Guide | I71: L | J71: Case brief Rs5-10k; low-tech institutes higher | L71: 0 | M71: =IF(AND(G71>=MIN(D71,F71),G71<=MAX(D71,F71)),0,1) | N71: N
A72: MarketingPerPaid | B72: Marketing spend per paid institute | C72: Rs | D72: 6000 | E72: 3000 | F72: 1000 | G72: =IF(N72="Y",CHOOSE(Scenario,D72,E72,F72),E72) | H72: Assumption | I72: L | L72: 0 | M72: =IF(AND(G72>=MIN(D72,F72),G72<=MAX(D72,F72)),0,1) | N72: N
A73: ChannelCommission | B73: Channel-partner commission (share of year-1 revenue) | C73: % of year-1 revenue | D73: 0.3 | E73: 0.2 | F73: 0.15 | G73: =IF(N73="Y",CHOOSE(Scenario,D73,E73,F73),E73) | H73: Assumption | I73: L | J73: FINANCE_PLAN s.3.2: 15-20% of year-1 revenue, 30% upper bound | K73: Used for the channel-vs-field comparison in Unit_Econ | L73: =IF(OR(G73<0,G73>1),1,0) | M73: =IF(AND(G73>=MIN(D73,F73),G73<=MAX(D73,F73)),0,1) | N73: N
A74: ChurnInSeason | B74: Monthly logo churn for monthly payers | C74: %/month | D74: 0.05 | E74: 0.03 | F74: 0.015 | G74: =IF(N74="Y",CHOOSE(Scenario,D74,E74,F74),E74) | H74: Researched | I74: L | J74: R5: ChartMogul 6.1%/month at ARPA <$25 (2022); eChai India SMB 3-5%; SaaS Capital 2025 GRR 90%/yr | K74: Applied only to institutes not on annual prepay | L74: =IF(OR(G74<0,G74>1),1,0) | M74: =IF(AND(G74>=MIN(D74,F74),G74<=MAX(D74,F74)),0,1) | N74: Y
A75: RenewalSpike | B75: Non-renewal at session end (annual) | C75: % of logos | D75: 0.3 | E75: 0.2 | F75: 0.1 | G75: =IF(N75="Y",CHOOSE(Scenario,D75,E75,F75),E75) | H75: Assumption | I75: L | J75: R5: no benchmark found - answers the judges' post-exam churn question | K75: Spread over renewal months | L75: =IF(OR(G75<0,G75>1),1,0) | M75: =IF(AND(G75>=MIN(D75,F75),G75<=MAX(D75,F75)),0,1) | N75: Y
A76: MinRenewTenure | B76: Months a customer must have paid before the first renewal decision | C76: months | D76: 9 | E76: 9 | F76: 9 | G76: =IF(N76="Y",CHOOSE(Scenario,D76,E76,F76),E76) | H76: Structural | I76: M | J76: A customer signed in May cannot fail to renew in June; the first renewal is at the next session start | K76: Audit 2026-10-22: new. Fixes the renewal timing in Unit_Econ | L76: 0 | M76: =IF(AND(G76>=MIN(D76,F76),G76<=MAX(D76,F76)),0,1) | N76: N
A77: DiscountRate | B77: Discount rate for LTV | C77: %/yr | D77: 0.2 | E77: 0.2 | F77: 0.2 | G77: =IF(N77="Y",CHOOSE(Scenario,D77,E77,F77),E77) | H77: Structural | I77: M | J77: Early-stage cost of capital convention | L77: =IF(OR(G77<0,G77>1),1,0) | M77: =IF(AND(G77>=MIN(D77,F77),G77<=MAX(D77,F77)),0,1) | N77: N
A78: StartMonth | B78: Paid start month (1 = April) | C78: month # | D78: 2 | E78: 2 | F78: 2 | G78: =IF(N78="Y",CHOOSE(Scenario,D78,E78,F78),E78) | H78: Structural | I78: M | J78: Sales peak Mar-Jun; paid from May after a 1-month pilot | L78: 0 | M78: =IF(AND(G78>=MIN(D78,F78),G78<=MAX(D78,F78)),0,1) | N78: N
A79: Team
A80: Founders | B80: Founders drawing a stipend | C80: people | D80: 3 | E80: 3 | F80: 3 | G80: =IF(N80="Y",CHOOSE(Scenario,D80,E80,F80),E80) | H80: Assumption | I80: M | J80: Owner decision | L80: 0 | M80: =IF(AND(G80>=MIN(D80,F80),G80<=MAX(D80,F80)),0,1) | N80: N
A81: FounderStipend | B81: Founder stipend per month | C81: Rs/month | D81: 30000 | E81: 20000 | F81: 15000 | G81: =IF(N81="Y",CHOOSE(Scenario,D81,E81,F81),E81) | H81: Assumption | I81: M | J81: Owner decision | L81: 0 | M81: =IF(AND(G81>=MIN(D81,F81),G81<=MAX(D81,F81)),0,1) | N81: N
A82: EngineersY1 | B82: Engineers in year 1 | C82: people | D82: 1 | E82: 1 | F82: 1 | G82: =IF(N82="Y",CHOOSE(Scenario,D82,E82,F82),E82) | H82: Assumption | I82: M | K82: Hiring plan is a decision, so Bear = Base = Bull | L82: 0 | M82: =IF(AND(G82>=MIN(D82,F82),G82<=MAX(D82,F82)),0,1) | N82: N
A83: EngineerCTC | B83: Engineer monthly CTC | C83: Rs/month | D83: 67000 | E83: 50000 | F83: 35000 | G83: =IF(N83="Y",CHOOSE(Scenario,D83,E83,F83),E83) | H83: Researched | I83: L | J83: R5: Glassdoor Jaipur Rs6L/yr; Indore Rs6-8L/yr (1-3 yrs) | L83: 0 | M83: =IF(AND(G83>=MIN(D83,F83),G83<=MAX(D83,F83)),0,1) | N83: N
A84: ToolsOpex | B84: Tools / office / legal per month | C84: Rs/month | D84: 20000 | E84: 12000 | F84: 8000 | G84: =IF(N84="Y",CHOOSE(Scenario,D84,E84,F84),E84) | H84: Assumption | I84: L | L84: 0 | M84: =IF(AND(G84>=MIN(D84,F84),G84<=MAX(D84,F84)),0,1) | N84: N
A85: Guide
A86: G_Students | B86: Guide: students | C86: students | D86: 400 | E86: 400 | F86: 400 | G86: =IF(N86="Y",CHOOSE(Scenario,D86,E86,F86),E86) | H86: Guide | I86: H | J86: Case brief | L86: 0 | M86: =IF(AND(G86>=MIN(D86,F86),G86<=MAX(D86,F86)),0,1) | N86: N
A87: G_Fee | B87: Guide: annual fee per student | C87: Rs/yr | D87: 60000 | E87: 60000 | F87: 60000 | G87: =IF(N87="Y",CHOOSE(Scenario,D87,E87,F87),E87) | H87: Guide | I87: H | J87: Case brief | K87: Used for the PS's own platform-cost-as-%-of-fee figure | L87: 0 | M87: =IF(AND(G87>=MIN(D87,F87),G87<=MAX(D87,F87)),0,1) | N87: N
A88: G_Dropout | B88: Guide: dropout rate | C88: % | D88: 0.12 | E88: 0.12 | F88: 0.12 | G88: =IF(N88="Y",CHOOSE(Scenario,D88,E88,F88),E88) | H88: Guide | I88: H | J88: Case brief | L88: =IF(OR(G88<0,G88>1),1,0) | M88: =IF(AND(G88>=MIN(D88,F88),G88<=MAX(D88,F88)),0,1) | N88: N
A89: G_RemainingFee | B89: Guide: remaining fee per dropout | C89: Rs | D89: 36000 | E89: 36000 | F89: 36000 | G89: =IF(N89="Y",CHOOSE(Scenario,D89,E89,F89),E89) | H89: Guide | I89: H | J89: Case brief | L89: 0 | M89: =IF(AND(G89>=MIN(D89,F89),G89<=MAX(D89,F89)),0,1) | N89: N
A90: G_Prevent | B90: Guide: share of dropouts prevented | C90: % | D90: 0.25 | E90: 0.25 | F90: 0.25 | G90: =IF(N90="Y",CHOOSE(Scenario,D90,E90,F90),E90) | H90: Guide | I90: H | J90: Case brief | L90: =IF(OR(G90<0,G90>1),1,0) | M90: =IF(AND(G90>=MIN(D90,F90),G90<=MAX(D90,F90)),0,1) | N90: N
A91: G_Price | B91: Guide: price per student per month | C91: Rs | D91: 40 | E91: 40 | F91: 40 | G91: =IF(N91="Y",CHOOSE(Scenario,D91,E91,F91),E91) | H91: Guide | I91: H | J91: Case brief | L91: 0 | M91: =IF(AND(G91>=MIN(D91,F91),G91<=MAX(D91,F91)),0,1) | N91: N
A92: G_Months | B92: Guide: billing months per year | C92: months | D92: 12 | E92: 12 | F92: 12 | G92: =IF(N92="Y",CHOOSE(Scenario,D92,E92,F92),E92) | H92: Guide | I92: H | J92: Case brief | L92: 0 | M92: =IF(AND(G92>=MIN(D92,F92),G92<=MAX(D92,F92)),0,1) | N92: N
A93: G_Infra | B93: Guide: infra + AI per student per month | C93: Rs | D93: 6 | E93: 6 | F93: 6 | G93: =IF(N93="Y",CHOOSE(Scenario,D93,E93,F93),E93) | H93: Guide | I93: H | J93: Case brief | L93: 0 | M93: =IF(AND(G93>=MIN(D93,F93),G93<=MAX(D93,F93)),0,1) | N93: N
A94: G_Support | B94: Guide: support per institute per month | C94: Rs | D94: 3000 | E94: 3000 | F94: 3000 | G94: =IF(N94="Y",CHOOSE(Scenario,D94,E94,F94),E94) | H94: Guide | I94: H | J94: Case brief | L94: 0 | M94: =IF(AND(G94>=MIN(D94,F94),G94<=MAX(D94,F94)),0,1) | N94: N
A95: G_CAC | B95: Guide: CAC | C95: Rs | D95: 25000 | E95: 25000 | F95: 25000 | G95: =IF(N95="Y",CHOOSE(Scenario,D95,E95,F95),E95) | H95: Guide | I95: H | J95: Case brief | L95: 0 | M95: =IF(AND(G95>=MIN(D95,F95),G95<=MAX(D95,F95)),0,1) | N95: N
A96: G_Onboard | B96: Guide: onboarding | C96: Rs | D96: 8000 | E96: 8000 | F96: 8000 | G96: =IF(N96="Y",CHOOSE(Scenario,D96,E96,F96),E96) | H96: Guide | I96: H | J96: Case brief | L96: 0 | M96: =IF(AND(G96>=MIN(D96,F96),G96<=MAX(D96,F96)),0,1) | N96: N
A97: G_Churn | B97: Guide: monthly churn | C97: % | D97: 0.03 | E97: 0.03 | F97: 0.03 | G97: =IF(N97="Y",CHOOSE(Scenario,D97,E97,F97),E97) | H97: Guide | I97: H | J97: Case brief | L97: =IF(OR(G97<0,G97>1),1,0) | M97: =IF(AND(G97>=MIN(D97,F97),G97<=MAX(D97,F97)),0,1) | N97: N
A98: Projection
A99: SegMix_S | B99: Share of new institutes that are Small | C99: % of new logos | D99: 0.55 | E99: 0.45 | F99: 0.35 | G99: =IF(N99="Y",CHOOSE(Scenario,D99,E99,F99),E99) | H99: Assumption | I99: L | J99: Size distribution of Tier-2/3 institutes not found (R7 gap); skewed to small | K99: Bear = more small institutes | L99: =IF(OR(G99<0,G99>1),1,0) | M99: =IF(AND(G99>=MIN(D99,F99),G99<=MAX(D99,F99)),0,1) | N99: N
A100: SegMix_M | B100: Share of new institutes that are Mid | C100: % of new logos | D100: 0.35 | E100: 0.4 | F100: 0.45 | G100: =IF(N100="Y",CHOOSE(Scenario,D100,E100,F100),E100) | H100: Assumption | I100: L | J100: As above | K100: The three shares must sum to 100% | L100: =IF(OR(G100<0,G100>1),1,0) | M100: =IF(AND(G100>=MIN(D100,F100),G100<=MAX(D100,F100)),0,1) | N100: N
A101: SegMix_L | B101: Share of new institutes that are Large | C101: % of new logos | D101: 0.1 | E101: 0.15 | F101: 0.2 | G101: =IF(N101="Y",CHOOSE(Scenario,D101,E101,F101),E101) | H101: Assumption | I101: L | J101: As above | K101: The three shares must sum to 100% | L101: =IF(OR(G101<0,G101>1),1,0) | M101: =IF(AND(G101>=MIN(D101,F101),G101<=MAX(D101,F101)),0,1) | N101: N
...

Sheet Seasonality
A1: Seasonality, dropout timing and the 60-month timeline
A2: Session month 1 = April. Blue cells are inputs (currently assumptions, see Source).
A3: A. Active-student index and renewal (churn) months
A4: No. | B4: Month | C4: Active-student index | D4: Renewal month (1/0) | E4: Sales intensity index | F4: Source
A5: 1 | B5: Apr | C5: 0.85 | D5: 1 | E5: 1.6 | F5: Assumption (L): new session starts; admissions still coming in | flag: Assumption: renewal decision for the new session | sales index: Assumption: PS Section 7 'sales cycle peaks before the new session (March-June)'; mean 1.0
A6: 2 | B6: May | C6: 0.95 | D6: 1 | E6: 2 | F6: Assumption (L) | flag: Assumption
A7: 3 | B7: Jun | C7: 1 | D7: 0 | E7: 1.7 | F7: Assumption (L)
A8: 4 | B8: Jul | C8: 1 | D8: 0 | E8: 1 | F8: Assumption (L)
A9: 5 | B9: Aug | C9: 1 | D9: 0 | E9: 0.7 | F9: Assumption (L)
A10: 6 | B10: Sep | C10: 1 | D10: 0 | E10: 0.6 | F10: Assumption (L)
A11: 7 | B11: Oct | C11: 0.98 | D11: 0 | E11: 0.5 | F11: Assumption (L): dropouts start reducing roster
A12: 8 | B12: Nov | C12: 0.96 | D12: 0 | E12: 0.5 | F12: Assumption (L)
A13: 9 | B13: Dec | C13: 0.93 | D13: 0 | E13: 0.4 | F13: Assumption (L)
A14: 10 | B14: Jan | C14: 0.85 | D14: 0 | E14: 0.5 | F14: Assumption (L): JEE Main Jan; 12th students thin out
A15: 11 | B15: Feb | C15: 0.6 | D15: 0 | E15: 0.8 | F15: Assumption (L): board exams
A16: 12 | B16: Mar | C16: 0.45 | D16: 1 | E16: 1.7 | F16: Assumption (L): boards end; session over for 12th | flag: Assumption: post-exam churn window
B18: Renewal months per year | C18: =SUM(Season_Flag)
A20: B. When in the course students drop out
A21: Course month | C21: Share of dropouts | D21: Share of course left | E21: Source
A22: 1 | B22: Course month 1 | C22: 0.03 | D22: =MAX(0,(CourseMonths-A22)/CourseMonths) | E22: Assumption (L): PS Section 7 'highest in first 4-5 months'; tech generator peak months 3-4 (43% of dropouts there, FEASIBILITY_CHECK s.6). Audit 2026-10-22: was front-loaded (30% in months 1-2)
A23: 2 | B23: Course month 2 | C23: 0.1 | D23: =MAX(0,(CourseMonths-A23)/CourseMonths) | E23: Assumption (L): same curve
A24: 3 | B24: Course month 3 | C24: 0.2 | D24: =MAX(0,(CourseMonths-A24)/CourseMonths) | E24: Assumption (L): same curve
A25: 4 | B25: Course month 4 | C25: 0.23 | D25: =MAX(0,(CourseMonths-A25)/CourseMonths) | E25: Assumption (L): same curve
A26: 5 | B26: Course month 5 | C26: 0.15 | D26: =MAX(0,(CourseMonths-A26)/CourseMonths) | E26: Assumption (L): same curve
A27: 6 | B27: Course month 6 | C27: 0.09 | D27: =MAX(0,(CourseMonths-A27)/CourseMonths) | E27: Assumption (L): same curve
A28: 7 | B28: Course month 7 | C28: 0.07 | D28: =MAX(0,(CourseMonths-A28)/CourseMonths) | E28: Assumption (L): same curve
A29: 8 | B29: Course month 8 | C29: 0.05 | D29: =MAX(0,(CourseMonths-A29)/CourseMonths) | E29: Assumption (L): same curve
A30: 9 | B30: Course month 9 | C30: 0.04 | D30: =MAX(0,(CourseMonths-A30)/CourseMonths) | E30: Assumption (L): same curve
A31: 10 | B31: Course month 10 | C31: 0.04 | D31: =MAX(0,(CourseMonths-A31)/CourseMonths) | E31: Assumption (L): same curve
B32: Total (must be 100%) | C32: =SUM(DropTiming)
A34: C. Timeline for LTV: paid month t → calendar month, student index, renewal flag, discount factor
A36: t (paid month) | B36: Calendar month # | C36: Active-student index | D36: Renewal flag | E36: Discount factor
A37: 1 | B37: =MOD(StartMonth+A37-2,12)+1 | C37: =INDEX(Season_Idx,B37) | D37: =INDEX(Season_Flag,B37) | E37: =1/(1+DiscountRate)^(A37/12)
A38: 2 | B38: =MOD(StartMonth+A38-2,12)+1 | C38: =INDEX(Season_Idx,B38) | D38: =INDEX(Season_Flag,B38) | E38: =1/(1+DiscountRate)^(A38/12)
A39: 3 | B39: =MOD(StartMonth+A39-2,12)+1 | C39: =INDEX(Season_Idx,B39) | D39: =INDEX(Season_Flag,B39) | E39: =1/(1+DiscountRate)^(A39/12)
A40: 4 | B40: =MOD(StartMonth+A40-2,12)+1 | C40: =INDEX(Season_Idx,B40) | D40: =INDEX(Season_Flag,B40) | E40: =1/(1+DiscountRate)^(A40/12)
A41: 5 | B41: =MOD(StartMonth+A41-2,12)+1 | C41: =INDEX(Season_Idx,B41) | D41: =INDEX(Season_Flag,B41) | E41: =1/(1+DiscountRate)^(A41/12)
A42: 6 | B42: =MOD(StartMonth+A42-2,12)+1 | C42: =INDEX(Season_Idx,B42) | D42: =INDEX(Season_Flag,B42) | E42: =1/(1+DiscountRate)^(A42/12)
A43: 7 | B43: =MOD(StartMonth+A43-2,12)+1 | C43: =INDEX(Season_Idx,B43) | D43: =INDEX(Season_Flag,B43) | E43: =1/(1+DiscountRate)^(A43/12)
A44: 8 | B44: =MOD(StartMonth+A44-2,12)+1 | C44: =INDEX(Season_Idx,B44) | D44: =INDEX(Season_Flag,B44) | E44: =1/(1+DiscountRate)^(A44/12)
A45: 9 | B45: =MOD(StartMonth+A45-2,12)+1 | C45: =INDEX(Season_Idx,B45) | D45: =INDEX(Season_Flag,B45) | E45: =1/(1+DiscountRate)^(A45/12)
A46: 10 | B46: =MOD(StartMonth+A46-2,12)+1 | C46: =INDEX(Season_Idx,B46) | D46: =INDEX(Season_Flag,B46) | E46: =1/(1+DiscountRate)^(A46/12)
A47: 11 | B47: =MOD(StartMonth+A47-2,12)+1 | C47: =INDEX(Season_Idx,B47) | D47: =INDEX(Season_Flag,B47) | E47: =1/(1+DiscountRate)^(A47/12)
A48: 12 | B48: =MOD(StartMonth+A48-2,12)+1 | C48: =INDEX(Season_Idx,B48) | D48: =INDEX(Season_Flag,B48) | E48: =1/(1+DiscountRate)^(A48/12)
... A96: 60 | B96: =MOD(StartMonth+A96-2,12)+1 | C96: =INDEX(Season_Idx,B96) | D96: =INDEX(Season_Flag,B96) | E96: =1/(1+DiscountRate)^(A96/12)

Sheet Pricing
A1: Pricing — list price, discounts, realised price
A2: Green = linked input · black = formula · green fill = output used elsewhere
B4: Item | C4: Unit | D4: LIVE
B5: Inputs (from Assumptions)
B6: List price per active student per month | C6: Rs/student/month | D6: =ListPrice
B7: Minimum monthly fee per institute | C7: Rs/month | D7: =MinFee
B8: Average negotiated discount off list | C8: % | D8: =NegotiationDisc
B9: Share of institutes choosing annual prepay | C9: % | D9: =PrepayUptake
B10: Annual prepay discount | C10: % | D10: =PrepayDisc
B11: GST on SaaS | C11: % | D11: =GST
B12: Realised price
B13: Effective discount = negotiation + prepay uptake × prepay discount | C13: % | D13: =D8+D9*D10
B14: Realised price per student-month (ex-GST) | C14: ₹/student/month | D14: =D6*(1-D13)
B15: Price the owner feels (incl. GST) | C15: ₹/student/month | D15: =D14*(1+D11)
B16: What institutes already pay for an ERP/LMS | C16: Rs/student/month | D16: =CompetitorAnchor
B17: Our realised price ÷ what institutes already pay for an ERP/LMS | C17: x | D17: =IF(D16>0,D14/D16,0)
A20: Packaging (for the deck; Pro price is the model's list price)
A21: Tier | B21: Contents | C21: Price | D21: Role
A22: Starter | B22: CSV / OMR upload, test-level reports, 1 batch | C22: 0 | D22: Free — lead generation, data on-ramp
A23: Pro (core) | B23: Topic heatmap, at-risk list with reasons, template parent reports | C23: =ListPrice | D23: Core paid plan, ₹/active student/month, min fee applies
A24: Premium (AI) | B24: GenAI Hindi/English parent reports on WhatsApp, percentile band, study plans | C24: Pro + add-on | D24: Upsell — NOT in base revenue until priced by research
A25: Annual plan | B25: Pro billed yearly upfront | C25: =ListPrice*(1-PrepayDisc) | D25: Cash up front, lower churn at renewal

Sheet COGS_Build
A1: COGS build-up — cost to serve one student (must match TECH_PLAN §16 / NB09)
A2: Mid-segment size used for the all-in figure. Tech plan target band: ₹3–10 per student-month.
B4: Item | C4: Unit | D4: LIVE
B5: Inputs (from Assumptions)
B6: AI parent reports per student per month | C6: reports | D6: =ReportsPerStudentMonth
B7: LLM input tokens per report | C7: tokens | D7: =TokensInPerReport
B8: LLM output tokens per report | C8: tokens | D8: =TokensOutPerReport
B9: LLM input price (hosted) | C9: Rs per 1M tokens | D9: =LLMPriceIn
B10: LLM output price (hosted) | C10: Rs per 1M tokens | D10: =LLMPriceOut
B11: WhatsApp utility messages per student per month | C11: messages | D11: =WAMsgsPerStudentMonth
B12: WhatsApp utility message price (India) | C12: Rs/message | D12: =WAPricePerMsg
B13: Compute + storage + backups per student | C13: Rs/student/month | D13: =ComputePerStudentMonth
B14: Consent OTP + verification per student | C14: Rs/student/yr | D14: =ConsentCostPerStudentYear
B15: App server + managed Postgres + backups per stack | C15: Rs/month | D15: =ServerCostMonth
B16: WhatsApp BSP platform fee per stack | C16: Rs/month | D16: =BSPFeeMonth
B17: Institutes sharing one server stack | C17: institutes | D17: =InstPerStack
B18: DPDP compliance cost per institute | C18: Rs/month | D18: =CompliancePerInstMonth
B19: Students per institute | C19: students | D19: =Students_M
B20: Variable cost per active student per month
B21: LLM (AI parent reports, hosted model) | C21: ₹/student/month | D21: =D6*(D7*D9+D8*D10)/1000000
B22: WhatsApp utility messages | C22: ₹/student/month | D22: =D11*D12
B23: Compute + storage + backups | C23: ₹/student/month | D23: =D13
B24: Consent OTP / verification (annual ÷ 12) | C24: ₹/student/month | D24: =D14/12
B25: Total variable COGS per student-month | C25: ₹/student/month | D25: =SUM(D21:D24)
B26: Fixed cost per institute per month
B27: Hosting share = (server + DB + WhatsApp BSP fee) ÷ institutes per stack | C27: ₹/institute/month | D27: =(D15+D16)/D17
B28: Hosting share + DPDP compliance | C28: ₹/institute/month | D28: =D27+D18
B29: All-in COGS per student-month at this size | C29: ₹/student/month | D29: =D25+D28/D19

Sheet Institute_ROI
A1: Institute ROI — does it pay for the owner? (per segment, live scenario)
A2: Same price and same dropout funnel as Unit_Econ. Green fill = key outputs.
B4: Line | C4: Unit | D4: Small (<250) | E4: Mid (250-800) | F4: Large (>800)
B5: Inputs (from Assumptions / Pricing)
B6: Students per institute | C6: students | D6: =Students_S | E6: =Students_M | F6: =Students_L
B7: Annual fee per student | C7: Rs/yr | D7: =Fee_S | E7: =Fee_M | F7: =Fee_L
B8: Mid-session dropout/default rate | C8: % of students/yr | D8: =DropoutRate | E8: =DropoutRate | F8: =DropoutRate
B9: Share of students paying full fee upfront | C9: % | D9: =UpfrontShare | E9: =UpfrontShare | F9: =UpfrontShare
B10: Instalments per year for non-upfront payers | C10: count | D10: =NInstalments | E10: =NInstalments | F10: =NInstalments
B11: Share of upfront leavers actually refunded pro-rata | C11: % | D11: =RefundEnforced | E11: =RefundEnforced | F11: =RefundEnforced
B12: Months before the model can flag (no test data yet) | C12: months | D12: =BlindMonths | E12: =BlindMonths | F12: =BlindMonths
B13: Share of students under 18 | C13: % | D13: =MinorShare | E13: =MinorShare | F13: =MinorShare
B14: Model recall on minors (academic-support + rules) | C14: % | D14: =Recall_Minor | E14: =Recall_Minor | F14: =Recall_Minor
B15: Model recall on 18+ (full ML) | C15: % | D15: =Recall_Adult | E15: =Recall_Adult | F15: =Recall_Adult
B16: Precision of at-risk flag | C16: % | D16: =Precision | E16: =Precision | F16: =Precision
B17: Share of flags the institute assigns to outreach | C17: % | D17: =ActionRate | E17: =ActionRate | F17: =ActionRate
B18: Dropout reduction among flagged students given outreach (RCT) | C18: relative % | D18: =InterventionSuccess | E18: =InterventionSuccess | F18: =InterventionSuccess
B19: Admissions uplift next session from results/parent trust | C19: % of students | D19: =AdmissionUplift | E19: =AdmissionUplift | F19: =AdmissionUplift
B20: Institute margin on one extra admission | C20: % | D20: =MarginExtraAdmission | E20: =MarginExtraAdmission | F20: =MarginExtraAdmission
B21: Staff hours saved per month | C21: hours/month | D21: =StaffHoursSaved | E21: =StaffHoursSaved | F21: =StaffHoursSaved
B22: Cost of one admin staff hour | C22: Rs/hour | D22: =StaffHourCost | E22: =StaffHourCost | F22: =StaffHourCost
B23: Mentor minutes per intervention | C23: minutes | D23: =InterventionMinutes | E23: =InterventionMinutes | F23: =InterventionMinutes
B24: Cost of one mentor hour | C24: Rs/hour | D24: =MentorHourCost | E24: =MentorHourCost | F24: =MentorHourCost
B25: List price per active student per month | C25: Rs/student/month | D25: =ListPrice | E25: =ListPrice | F25: =ListPrice
B26: Minimum monthly fee per institute | C26: Rs/month | D26: =MinFee | E26: =MinFee | F26: =MinFee
B27: GST on SaaS | C27: % | D27: =GST | E27: =GST | F27: =GST
B28: Share of institutes that reclaim our GST as input credit | C28: % | D28: =ITCShare | E28: =ITCShare | F28: =ITCShare
B29: Effective discount (Pricing) | C29: % | D29: =EffDisc | E29: =EffDisc | F29: =EffDisc
B30: 1. What a dropout actually costs (unpaid instalments + refunds to full payers)
B31: Dropouts per year | C31: students/yr | D31: =D6*D8 | E31: =E6*E8 | F31: =F6*F8
B32: Avg fee lost per dropout (timing curve × unpaid instalments / pro-rata refund) | C32: ₹/dropout | D32: =SUMPRODUCT(DropTiming,D7*((1-D9)*(1-(INT((DropMonth-1)*D10/CourseMonths)+1)/D10)+D9*D11*DropRemain)) | E32: =SUMPRODUCT(DropTiming,E7*((1-E9)*(1-(INT((DropMonth-1)*E10/CourseMonths)+1)/E10)+E9*E11*DropRemain)) | F32: =SUMPRODUCT(DropTiming,F7*((1-F9)*(1-(INT((DropMonth-1)*F10/CourseMonths)+1)/F10)+F9*F11*DropRemain))
B33: Fee lost to dropouts per year (no platform) | C33: ₹/yr | D33: =D31*D32 | E33: =E31*E32 | F33: =F31*F32
B34: 2. Prevention funnel (replaces the guide's flat 25%)
B35: Blended recall (minors: academic model + rules; 18+: full ML) | C35: % | D35: =D13*D14+(1-D13)*D15 | E35: =E13*E14+(1-E13)*E15 | F35: =F13*F14+(1-F13)*F15
B36: Share of dropouts after the 'blind' months (enough test data to flag) | C36: % | D36: =SUMPRODUCT(DropTiming*(DropMonth>D12)) | E36: =SUMPRODUCT(DropTiming*(DropMonth>E12)) | F36: =SUMPRODUCT(DropTiming*(DropMonth>F12))
B37: Effective dropout reduction = recall × action × RCT effect × catchable | C37: % | D37: =D35*D17*D18*D36 | E37: =E35*E17*E18*E36 | F37: =F35*F17*F18*F36
B38: Dropouts prevented per year | C38: students/yr | D38: =D31*D37 | E38: =E31*E37 | F38: =F31*F37
B39: Fee saved per prevented dropout (catchable months only) | C39: ₹/student | D39: =IF(D36>0,SUMPRODUCT(DropTiming*(DropMonth>D12)*D7*((1-D9)*(1-(INT((DropMonth-1)*D10/CourseMonths)+1)/D10)+D9*D11*DropRemain))/D36,0) | E39: =IF(E36>0,SUMPRODUCT(DropTiming*(DropMonth>E12)*E7*((1-E9)*(1-(INT((DropMonth-1)*E10/CourseMonths)+1)/E10)+E9*E11*DropRemain))/E36,0) | F39: =IF(F36>0,SUMPRODUCT(DropTiming*(DropMonth>F12)*F7*((1-F9)*(1-(INT((DropMonth-1)*F10/CourseMonths)+1)/F10)+F9*F11*DropRemain))/F36,0)
B40: 3. Value to the institute (₹/yr)
B41: Fees retained | C41: ₹/yr | D41: =D38*D39 | E41: =E38*E39 | F41: =F38*F39
B42: Margin on extra admissions (results / parent trust) | C42: ₹/yr | D42: =D6*D19*D7*D20 | E42: =E6*E19*E7*E20 | F42: =F6*F19*F7*F20
B43: Staff time saved | C43: ₹/yr | D43: =D21*D22*12 | E43: =E21*E22*12 | F43: =F21*F22*12
B44: Total value | C44: ₹/yr | D44: =D41+D42+D43 | E44: =E41+E42+E43 | F44: =F41+F42+F43
B45: 4. Cost to the institute (₹/yr)
B46: Platform fee (seasonal active students, min fee, discounts; ex-GST) | C46: ₹/yr | D46: =SUMPRODUCT((D6*Season_Idx*D25>D26)*(D6*Season_Idx*D25)+(D6*Season_Idx*D25<=D26)*D26)*(1-D29) | E46: =SUMPRODUCT((E6*Season_Idx*E25>E26)*(E6*Season_Idx*E25)+(E6*Season_Idx*E25<=E26)*E26)*(1-E29) | F46: =SUMPRODUCT((F6*Season_Idx*F25>F26)*(F6*Season_Idx*F25)+(F6*Season_Idx*F25<=F26)*F26)*(1-F29)
B47: GST the institute cannot reclaim | C47: ₹/yr | D47: =D46*D27*(1-D28) | E47: =E46*E27*(1-E28) | F47: =F46*F27*(1-F28)
B48: Students flagged per year (true + false alarms) | C48: students/yr | D48: =IF(D16>0,D31*D35/D16,0) | E48: =IF(E16>0,E31*E35/E16,0) | F48: =IF(F16>0,F31*F35/F16,0)
B49: Share of the roll flagged per year (alert load) | C49: % | D49: =IF(D6>0,D48/D6,0) | E49: =IF(E6>0,E48/E6,0) | F49: =IF(F6>0,F48/F6,0)
B50: Mentor time spent acting on flags | C50: ₹/yr | D50: =D48*D17*D23/60*D24 | E50: =E48*E17*E23/60*E24 | F50: =F48*F17*F23/60*F24
B51: Total cost | C51: ₹/yr | D51: =D46+D47+D50 | E51: =E46+E47+E50 | F51: =F46+F47+F50
B52: 5. Result
B53: Net benefit to institute | C53: ₹/yr | D53: =D44-D51 | E53: =E44-E51 | F53: =F44-F51
B54: Institute ROI (value ÷ cost) | C54: x | D54: =IF(D51>0,D44/D51,0) | E54: =IF(E51>0,E44/E51,0) | F54: =IF(F51>0,F44/F51,0)
B55: Fees-only ROI (no soft benefits) | C55: x | D55: =IF(D51>0,D41/D51,0) | E55: =IF(E51>0,E41/E51,0) | F55: =IF(F51>0,F41/F51,0)
B56: Hard-benefit ROI (fees retained + staff time, no admissions) | C56: x | D56: =IF(D51>0,(D41+D43)/D51,0) | E56: =IF(E51>0,(E41+E43)/E51,0) | F56: =IF(F51>0,(F41+F43)/F51,0)
B57: Break-even: students to save per year (fees only) | C57: students/yr | D57: =IF(D39>0,D51/D39,0) | E57: =IF(E39>0,E51/E39,0) | F57: =IF(F39>0,F51/F39,0)
B58: Break-even dropout reduction needed | C58: % | D58: =IF(D31>0,D57/D31,0) | E58: =IF(E31>0,E57/E31,0) | F58: =IF(F31>0,F57/F31,0)
B59: Admissions uplift needed to break even, after fees + staff time | C59: % of students | D59: =IF(D6*D7*D20>0,MAX(0,D51-D41-D43)/(D6*D7*D20),0) | E59: =IF(E6*E7*E20>0,MAX(0,E51-E41-E43)/(E6*E7*E20),0) | F59: =IF(F6*F7*F20>0,MAX(0,F51-F41-F43)/(F6*F7*F20),0)
B60: …in extra admissions per year | C60: students/yr | D60: =D59*D6 | E60: =E59*E6 | F60: =F59*F6
B61: Platform cost per student per year (incl. unreclaimed GST) | C61: ₹/student/yr | D61: =(D46+D47)/D6 | E61: =(E46+E47)/E6 | F61: =(F46+F47)/F6
B62: Platform cost as % of the student's fee | C62: % | D62: =D61/D7 | E62: =E61/E7 | F62: =F61/F7
A65: The guide's naive model (for contrast — all inputs from the Guide block on Assumptions)
B66: Dropouts per year | E66: =G_Students*G_Dropout
B67: Dropouts prevented (flat 25%) | E67: =G_Students*G_Dropout*G_Prevent
B68: Fees saved | E68: =G_Students*G_Dropout*G_Prevent*G_RemainingFee
B69: Platform cost (12 months, no GST, no seasonality) | E69: =G_Students*G_Price*G_Months
B70: Guide ROI | E70: =IF(ROUND(G_Students*G_Price*G_Months,6)>0,G_Students*G_Dropout*G_Prevent*G_RemainingFee/(G_Students*G_Price*G_Months),0)
B71: Guide break-even students | E71: =G_Students*G_Price*G_Months/G_RemainingFee

Sheet Unit_Econ
A1: Unit economics per institute (live scenario)
A2: LTV uses a seasonal survival curve (monthly churn + a renewal spike that applies only after the customer has paid MinRenewTenure months), discounted, capped at 60 months. Payback = 61 means 'not within 60 months'. Undiscounted LTV and simple payback are shown too, because peers quote those.
B4: Line | C4: Unit | D4: Small (<250) | E4: Mid (250-800) | F4: Large (>800) | H4: Guide's naive unit economics | I4: Value
B5: Inputs (from Assumptions / Pricing / COGS_Build) | H5: Revenue per institute per month | I5: =G_Students*G_Price
B6: Students per institute | C6: students | D6: =Students_S | E6: =Students_M | F6: =Students_L | H6: Contribution per month | I6: =G_Students*G_Price-G_Students*G_Infra-G_Support
B7: List price per active student per month | C7: Rs/student/month | D7: =ListPrice | E7: =ListPrice | F7: =ListPrice | H7: CAC + onboarding | I7: =G_CAC+G_Onboard
B8: Minimum monthly fee per institute | C8: Rs/month | D8: =MinFee | E8: =MinFee | F8: =MinFee | H8: Payback (months) | I8: =(G_CAC+G_Onboard)/(G_Students*G_Price-G_Students*G_Infra-G_Support)
B9: Bad debt / uncollected billing | C9: % | D9: =BadDebt | E9: =BadDebt | F9: =BadDebt | H9: LTV = contribution ÷ churn | I9: =(G_Students*G_Price-G_Students*G_Infra-G_Support)/G_Churn
B10: Payment collection cost (blended) | C10: % of revenue | D10: =GatewayFee | E10: =GatewayFee | F10: =GatewayFee | H10: LTV ÷ (CAC + onboarding) | I10: =((G_Students*G_Price-G_Students*G_Infra-G_Support)/G_Churn)/(G_CAC+G_Onboard)
B11: Monthly logo churn for monthly payers | C11: %/month | D11: =ChurnInSeason | E11: =ChurnInSeason | F11: =ChurnInSeason
B12: Share of institutes choosing annual prepay | C12: % | D12: =PrepayUptake | E12: =PrepayUptake | F12: =PrepayUptake
B13: Non-renewal at session end (annual) | C13: % of logos | D13: =RenewalSpike | E13: =RenewalSpike | F13: =RenewalSpike | H13: Break-even scale, steady state (no new sales; fixed team ÷ Mid contribution) | I13: Value
B14: Customer-success / onboarding exec monthly CTC | C14: Rs/month | D14: =CSM_CTC | E14: =CSM_CTC | F14: =CSM_CTC | H14: Fixed team + tools cost per month | I14: =Founders*FounderStipend+EngineersY1*EngineerCTC+ToolsOpex
B15: Institutes per CSM | C15: institutes | D15: =InstPerCSM | E15: =InstPerCSM | F15: =InstPerCSM | H15: Mid-institute avg monthly contribution | I15: =E37
B16: Field sales rep monthly CTC (incl. fuel) | C16: Rs/month | D16: =RepCTC | E16: =RepCTC | F16: =RepCTC | H16: Institutes needed to cover fixed cost | I16: =IF(I15>0,I14/I15,0)
B17: Rep intercity travel + demo material per month | C17: Rs/month | D17: =RepTravel | E17: =RepTravel | F17: =RepTravel | H17: …equivalent active students | I17: =I16*Students_M
B18: Pilots started per rep per month (yearly avg) | C18: pilots | D18: =PilotsPerRepMonth | E18: =PilotsPerRepMonth | F18: =PilotsPerRepMonth | H18: Paid institutes one rep adds per month | I18: =PilotsPerRepMonth*PilotConv
B19: Pilot-to-paid conversion | C19: % | D19: =PilotConv | E19: =PilotConv | F19: =PilotConv
B20: Free pilot length | C20: months | D20: =PilotMonths | E20: =PilotMonths | F20: =PilotMonths | H20: Hiring plan, cohorts, P&L, cash and funding need: see the Projection tab.
B21: Retro-pilot setup (import last year's Excel; show who left) | C21: Rs per pilot | D21: =PilotSetupCost | E21: =PilotSetupCost | F21: =PilotSetupCost
B22: Onboarding cost per institute (mid) | C22: Rs | D22: =OnboardBase | E22: =OnboardBase | F22: =OnboardBase
B23: Onboarding cost multiplier | C23: x | D23: =OnboardMult_S | E23: =OnboardMult_M | F23: =OnboardMult_L
B24: Marketing spend per paid institute | C24: Rs | D24: =MarketingPerPaid | E24: =MarketingPerPaid | F24: =MarketingPerPaid
B25: Sales overhead loading on rep cost (manager, incentives, recruiting, tools) | C25: % of rep cost | D25: =SalesOverheadPct | E25: =SalesOverheadPct | F25: =SalesOverheadPct
B26: Months a customer must have paid before the first renewal decision | C26: months | D26: =MinRenewTenure | E26: =MinRenewTenure | F26: =MinRenewTenure
B27: Channel-partner commission (share of year-1 revenue) | C27: % of year-1 revenue | D27: =ChannelCommission | E27: =ChannelCommission | F27: =ChannelCommission
B28: Effective discount (Pricing) | C28: % | D28: =EffDisc | E28: =EffDisc | F28: =EffDisc
B29: Variable COGS per student-month (COGS_Build) | C29: ₹/student/month | D29: =COGS_PerStudent | E29: =COGS_PerStudent | F29: =COGS_PerStudent
B30: Fixed COGS per institute-month (COGS_Build) | C30: ₹/month | D30: =COGS_FixedInst | E30: =COGS_FixedInst | F30: =COGS_FixedInst
B31: 1. Year-1 economics per institute (before churn)
B32: Collected revenue, first 12 paid months (ex-GST, after bad debt) | C32: ₹/yr | D32: =SUM(D61:D72) | E32: =SUM(E61:E72) | F32: =SUM(F61:F72)
B33: Average monthly revenue | C33: ₹/month | D33: =D32/12 | E33: =E32/12 | F33: =F32/12
B34: COGS, first 12 months (students × seasonality × COGS + fixed + gateway) | C34: ₹/yr | D34: =D6*D29*SUM(Seasonality!$C$37:$C$48)+12*D30+D10*D32 | E34: =E6*E29*SUM(Seasonality!$C$37:$C$48)+12*E30+E10*E32 | F34: =F6*F29*SUM(Seasonality!$C$37:$C$48)+12*F30+F10*F32
B35: Product gross margin (before customer-success staff) | C35: % | D35: =IF(D32>0,(D32-D34)/D32,0) | E35: =IF(E32>0,(E32-E34)/E32,0) | F35: =IF(F32>0,(F32-F34)/F32,0)
B36: Customer-success cost per institute | C36: ₹/month | D36: =D14/D15 | E36: =E14/E15 | F36: =F14/F15
B37: Average monthly contribution (after COGS + support) | C37: ₹/month | D37: =SUM(D121:D132)/12 | E37: =SUM(E121:E132)/12 | F37: =SUM(F121:F132)/12
B38: Contribution margin (after support: the PS's definition, a peer's 'gross margin') | C38: % | D38: =IF(D33>0,D37/D33,0) | E38: =IF(E33>0,E37/E33,0) | F38: =IF(F33>0,F37/F33,0)
B39: 2. Cost to acquire one paying institute
B40: Sales cost per pilot started (rep CTC + travel, loaded with overhead, ÷ pilots) | C40: ₹ | D40: =(D16+D17)*(1+D25)/D18 | E40: =(E16+E17)*(1+E25)/E18 | F40: =(F16+F17)*(1+F25)/F18
B41: Onboarding cost (data migration + training) | C41: ₹ | D41: =D22*D23 | E41: =E22*E23 | F41: =F22*F23
B42: Cost of serving the free pilot | C42: ₹ | D42: =D20*(D6*D29+D30) | E42: =E20*(E6*E29+E30) | F42: =F20*(F6*F29+F30)
B43: CAC (PS definition): sales + marketing per paying institute (failed pilots included) | C43: ₹ | D43: =D40/D19+D24 | E43: =E40/E19+E24 | F43: =F40/F19+F24
B44: Fully loaded acquisition cost = (sales + pilot setup + pilot COGS) ÷ conversion + onboarding (paid only) + marketing | C44: ₹ | D44: =(D40+D21+D42)/D19+D41+D24 | E44: =(E40+E21+E42)/E19+E41+E24 | F44: =(F40+F21+F42)/F19+F41+F24
B45: 3. Retention (seasonal, not 1/churn)
B46: In-season churn, monthly payers only (prepaid annual plans cannot leave mid-year) | C46: %/month | D46: =D11*(1-D12) | E46: =E11*(1-E12) | F46: =F11*(1-F12)
B47: Extra churn per renewal month | C47: %/month | D47: =1-(1-D13)^(1/NRenew) | E47: =1-(1-E13)^(1/NRenew) | F47: =1-(1-F13)^(1/NRenew)
B48: Annual logo retention | C48: % | D48: =(1-D46)^12*(1-D13) | E48: =(1-E46)^12*(1-E13) | F48: =(1-F46)^12*(1-F13)
B49: Expected paid lifetime within horizon | C49: months | D49: =SUM(D181:D240) | E49: =SUM(E181:E240) | F49: =SUM(F181:F240)
B50: 4. Lifetime value (60-month horizon, survival-weighted, discounted)
B51: LTV (contribution) | C51: ₹ | D51: =D300 | E51: =E300 | F51: =F300
B52: LTV ÷ fully loaded acquisition cost | C52: x | D52: =IF(D44>0,D51/D44,0) | E52: =IF(E44>0,E51/E44,0) | F52: =IF(F44>0,F51/F44,0)
B53: Payback (months of paid life, discounted) | C53: months | D53: =IF(D300<D44,61,COUNTIF(D241:D300,"<"&D44)+1) | E53: =IF(E300<E44,61,COUNTIF(E241:E300,"<"&E44)+1) | F53: =IF(F300<F44,61,COUNTIF(F241:F300,"<"&F44)+1)
B54: Payback, simple (acquisition cost ÷ average monthly contribution) | C54: months | D54: =IF(D37>0,D44/D37,99) | E54: =IF(E37>0,E44/E37,99) | F54: =IF(F37>0,F44/F37,99)
B55: LTV, undiscounted (survival-weighted) | C55: ₹ | D55: =SUMPRODUCT(D181:D240,D121:D180) | E55: =SUMPRODUCT(E181:E240,E121:E180) | F55: =SUMPRODUCT(F181:F240,F121:F180)
B56: LTV ÷ acquisition cost, undiscounted (the peer convention) | C56: x | D56: =IF(D44>0,D55/D44,0) | E56: =IF(E44>0,E55/E44,0) | F56: =IF(F44>0,F55/F44,0)
B57: 4b. Field sales versus a channel partner
B58: Acquisition cost via a channel partner (commission on year-1 revenue + our onboarding) | C58: ₹ | D58: =D27*D32+D41 | E58: =E27*E32+E41 | F58: =F27*F32+F41
B59: LTV ÷ channel acquisition cost | C59: x | D59: =IF(D58>0,D51/D58,0) | E59: =IF(E58>0,E51/E58,0) | F59: =IF(F58>0,F51/F58,0)
B60: 5. Month-by-month engine (t = paid month; calendar from Seasonality timeline)
B61: Revenue collected · month 1 | C61: ₹ | D61: =MAX(D8,D6*Seasonality!$C$37*D7)*(1-D28)*(1-D9) | E61: =MAX(E8,E6*Seasonality!$C$37*E7)*(1-E28)*(1-E9) | F61: =MAX(F8,F6*Seasonality!$C$37*F7)*(1-F28)*(1-F9)
B62: Revenue collected · month 2 | C62: ₹ | D62: =MAX(D8,D6*Seasonality!$C$38*D7)*(1-D28)*(1-D9) | E62: =MAX(E8,E6*Seasonality!$C$38*E7)*(1-E28)*(1-E9) | F62: =MAX(F8,F6*Seasonality!$C$38*F7)*(1-F28)*(1-F9)
B63: Revenue collected · month 3 | C63: ₹ | D63: =MAX(D8,D6*Seasonality!$C$39*D7)*(1-D28)*(1-D9) | E63: =MAX(E8,E6*Seasonality!$C$39*E7)*(1-E28)*(1-E9) | F63: =MAX(F8,F6*Seasonality!$C$39*F7)*(1-F28)*(1-F9)
B64: Revenue collected · month 4 | C64: ₹ | D64: =MAX(D8,D6*Seasonality!$C$40*D7)*(1-D28)*(1-D9) | E64: =MAX(E8,E6*Seasonality!$C$40*E7)*(1-E28)*(1-E9) | F64: =MAX(F8,F6*Seasonality!$C$40*F7)*(1-F28)*(1-F9)
B65: Revenue collected · month 5 | C65: ₹ | D65: =MAX(D8,D6*Seasonality!$C$41*D7)*(1-D28)*(1-D9) | E65: =MAX(E8,E6*Seasonality!$C$41*E7)*(1-E28)*(1-E9) | F65: =MAX(F8,F6*Seasonality!$C$41*F7)*(1-F28)*(1-F9)
B66: Revenue collected · month 6 | C66: ₹ | D66: =MAX(D8,D6*Seasonality!$C$42*D7)*(1-D28)*(1-D9) | E66: =MAX(E8,E6*Seasonality!$C$42*E7)*(1-E28)*(1-E9) | F66: =MAX(F8,F6*Seasonality!$C$42*F7)*(1-F28)*(1-F9)
B67: Revenue collected · month 7 | C67: ₹ | D67: =MAX(D8,D6*Seasonality!$C$43*D7)*(1-D28)*(1-D9) | E67: =MAX(E8,E6*Seasonality!$C$43*E7)*(1-E28)*(1-E9) | F67: =MAX(F8,F6*Seasonality!$C$43*F7)*(1-F28)*(1-F9)
B68: Revenue collected · month 8 | C68: ₹ | D68: =MAX(D8,D6*Seasonality!$C$44*D7)*(1-D28)*(1-D9) | E68: =MAX(E8,E6*Seasonality!$C$44*E7)*(1-E28)*(1-E9) | F68: =MAX(F8,F6*Seasonality!$C$44*F7)*(1-F28)*(1-F9)
B69: Revenue collected · month 9 | C69: ₹ | D69: =MAX(D8,D6*Seasonality!$C$45*D7)*(1-D28)*(1-D9) | E69: =MAX(E8,E6*Seasonality!$C$45*E7)*(1-E28)*(1-E9) | F69: =MAX(F8,F6*Seasonality!$C$45*F7)*(1-F28)*(1-F9)
B70: Revenue collected · month 10 | C70: ₹ | D70: =MAX(D8,D6*Seasonality!$C$46*D7)*(1-D28)*(1-D9) | E70: =MAX(E8,E6*Seasonality!$C$46*E7)*(1-E28)*(1-E9) | F70: =MAX(F8,F6*Seasonality!$C$46*F7)*(1-F28)*(1-F9)
B71: Revenue collected · month 11 | C71: ₹ | D71: =MAX(D8,D6*Seasonality!$C$47*D7)*(1-D28)*(1-D9) | E71: =MAX(E8,E6*Seasonality!$C$47*E7)*(1-E28)*(1-E9) | F71: =MAX(F8,F6*Seasonality!$C$47*F7)*(1-F28)*(1-F9)
B72: Revenue collected · month 12 | C72: ₹ | D72: =MAX(D8,D6*Seasonality!$C$48*D7)*(1-D28)*(1-D9) | E72: =MAX(E8,E6*Seasonality!$C$48*E7)*(1-E28)*(1-E9) | F72: =MAX(F8,F6*Seasonality!$C$48*F7)*(1-F28)*(1-F9)
B73: Revenue collected · month 13 | C73: ₹ | D73: =MAX(D8,D6*Seasonality!$C$49*D7)*(1-D28)*(1-D9) | E73: =MAX(E8,E6*Seasonality!$C$49*E7)*(1-E28)*(1-E9) | F73: =MAX(F8,F6*Seasonality!$C$49*F7)*(1-F28)*(1-F9)
B74: Revenue collected · month 14 | C74: ₹ | D74: =MAX(D8,D6*Seasonality!$C$50*D7)*(1-D28)*(1-D9) | E74: =MAX(E8,E6*Seasonality!$C$50*E7)*(1-E28)*(1-E9) | F74: =MAX(F8,F6*Seasonality!$C$50*F7)*(1-F28)*(1-F9)
B75: Revenue collected · month 15 | C75: ₹ | D75: =MAX(D8,D6*Seasonality!$C$51*D7)*(1-D28)*(1-D9) | E75: =MAX(E8,E6*Seasonality!$C$51*E7)*(1-E28)*(1-E9) | F75: =MAX(F8,F6*Seasonality!$C$51*F7)*(1-F28)*(1-F9)
B76: Revenue collected · month 16 | C76: ₹ | D76: =MAX(D8,D6*Seasonality!$C$52*D7)*(1-D28)*(1-D9) | E76: =MAX(E8,E6*Seasonality!$C$52*E7)*(1-E28)*(1-E9) | F76: =MAX(F8,F6*Seasonality!$C$52*F7)*(1-F28)*(1-F9)
B77: Revenue collected · month 17 | C77: ₹ | D77: =MAX(D8,D6*Seasonality!$C$53*D7)*(1-D28)*(1-D9) | E77: =MAX(E8,E6*Seasonality!$C$53*E7)*(1-E28)*(1-E9) | F77: =MAX(F8,F6*Seasonality!$C$53*F7)*(1-F28)*(1-F9)
B78: Revenue collected · month 18 | C78: ₹ | D78: =MAX(D8,D6*Seasonality!$C$54*D7)*(1-D28)*(1-D9) | E78: =MAX(E8,E6*Seasonality!$C$54*E7)*(1-E28)*(1-E9) | F78: =MAX(F8,F6*Seasonality!$C$54*F7)*(1-F28)*(1-F9)
B79: Revenue collected · month 19 | C79: ₹ | D79: =MAX(D8,D6*Seasonality!$C$55*D7)*(1-D28)*(1-D9) | E79: =MAX(E8,E6*Seasonality!$C$55*E7)*(1-E28)*(1-E9) | F79: =MAX(F8,F6*Seasonality!$C$55*F7)*(1-F28)*(1-F9)
B80: Revenue collected · month 20 | C80: ₹ | D80: =MAX(D8,D6*Seasonality!$C$56*D7)*(1-D28)*(1-D9) | E80: =MAX(E8,E6*Seasonality!$C$56*E7)*(1-E28)*(1-E9) | F80: =MAX(F8,F6*Seasonality!$C$56*F7)*(1-F28)*(1-F9)
B81: Revenue collected · month 21 | C81: ₹ | D81: =MAX(D8,D6*Seasonality!$C$57*D7)*(1-D28)*(1-D9) | E81: =MAX(E8,E6*Seasonality!$C$57*E7)*(1-E28)*(1-E9) | F81: =MAX(F8,F6*Seasonality!$C$57*F7)*(1-F28)*(1-F9)
B82: Revenue collected · month 22 | C82: ₹ | D82: =MAX(D8,D6*Seasonality!$C$58*D7)*(1-D28)*(1-D9) | E82: =MAX(E8,E6*Seasonality!$C$58*E7)*(1-E28)*(1-E9) | F82: =MAX(F8,F6*Seasonality!$C$58*F7)*(1-F28)*(1-F9)
B83: Revenue collected · month 23 | C83: ₹ | D83: =MAX(D8,D6*Seasonality!$C$59*D7)*(1-D28)*(1-D9) | E83: =MAX(E8,E6*Seasonality!$C$59*E7)*(1-E28)*(1-E9) | F83: =MAX(F8,F6*Seasonality!$C$59*F7)*(1-F28)*(1-F9)
B84: Revenue collected · month 24 | C84: ₹ | D84: =MAX(D8,D6*Seasonality!$C$60*D7)*(1-D28)*(1-D9) | E84: =MAX(E8,E6*Seasonality!$C$60*E7)*(1-E28)*(1-E9) | F84: =MAX(F8,F6*Seasonality!$C$60*F7)*(1-F28)*(1-F9)
B85: Revenue collected · month 25 | C85: ₹ | D85: =MAX(D8,D6*Seasonality!$C$61*D7)*(1-D28)*(1-D9) | E85: =MAX(E8,E6*Seasonality!$C$61*E7)*(1-E28)*(1-E9) | F85: =MAX(F8,F6*Seasonality!$C$61*F7)*(1-F28)*(1-F9)
B86: Revenue collected · month 26 | C86: ₹ | D86: =MAX(D8,D6*Seasonality!$C$62*D7)*(1-D28)*(1-D9) | E86: =MAX(E8,E6*Seasonality!$C$62*E7)*(1-E28)*(1-E9) | F86: =MAX(F8,F6*Seasonality!$C$62*F7)*(1-F28)*(1-F9)
B87: Revenue collected · month 27 | C87: ₹ | D87: =MAX(D8,D6*Seasonality!$C$63*D7)*(1-D28)*(1-D9) | E87: =MAX(E8,E6*Seasonality!$C$63*E7)*(1-E28)*(1-E9) | F87: =MAX(F8,F6*Seasonality!$C$63*F7)*(1-F28)*(1-F9)
B88: Revenue collected · month 28 | C88: ₹ | D88: =MAX(D8,D6*Seasonality!$C$64*D7)*(1-D28)*(1-D9) | E88: =MAX(E8,E6*Seasonality!$C$64*E7)*(1-E28)*(1-E9) | F88: =MAX(F8,F6*Seasonality!$C$64*F7)*(1-F28)*(1-F9)
B89: Revenue collected · month 29 | C89: ₹ | D89: =MAX(D8,D6*Seasonality!$C$65*D7)*(1-D28)*(1-D9) | E89: =MAX(E8,E6*Seasonality!$C$65*E7)*(1-E28)*(1-E9) | F89: =MAX(F8,F6*Seasonality!$C$65*F7)*(1-F28)*(1-F9)
B90: Revenue collected · month 30 | C90: ₹ | D90: =MAX(D8,D6*Seasonality!$C$66*D7)*(1-D28)*(1-D9) | E90: =MAX(E8,E6*Seasonality!$C$66*E7)*(1-E28)*(1-E9) | F90: =MAX(F8,F6*Seasonality!$C$66*F7)*(1-F28)*(1-F9)
B91: Revenue collected · month 31 | C91: ₹ | D91: =MAX(D8,D6*Seasonality!$C$67*D7)*(1-D28)*(1-D9) | E91: =MAX(E8,E6*Seasonality!$C$67*E7)*(1-E28)*(1-E9) | F91: =MAX(F8,F6*Seasonality!$C$67*F7)*(1-F28)*(1-F9)
B92: Revenue collected · month 32 | C92: ₹ | D92: =MAX(D8,D6*Seasonality!$C$68*D7)*(1-D28)*(1-D9) | E92: =MAX(E8,E6*Seasonality!$C$68*E7)*(1-E28)*(1-E9) | F92: =MAX(F8,F6*Seasonality!$C$68*F7)*(1-F28)*(1-F9)
B93: Revenue collected · month 33 | C93: ₹ | D93: =MAX(D8,D6*Seasonality!$C$69*D7)*(1-D28)*(1-D9) | E93: =MAX(E8,E6*Seasonality!$C$69*E7)*(1-E28)*(1-E9) | F93: =MAX(F8,F6*Seasonality!$C$69*F7)*(1-F28)*(1-F9)
B94: Revenue collected · month 34 | C94: ₹ | D94: =MAX(D8,D6*Seasonality!$C$70*D7)*(1-D28)*(1-D9) | E94: =MAX(E8,E6*Seasonality!$C$70*E7)*(1-E28)*(1-E9) | F94: =MAX(F8,F6*Seasonality!$C$70*F7)*(1-F28)*(1-F9)
B95: Revenue collected · month 35 | C95: ₹ | D95: =MAX(D8,D6*Seasonality!$C$71*D7)*(1-D28)*(1-D9) | E95: =MAX(E8,E6*Seasonality!$C$71*E7)*(1-E28)*(1-E9) | F95: =MAX(F8,F6*Seasonality!$C$71*F7)*(1-F28)*(1-F9)
B96: Revenue collected · month 36 | C96: ₹ | D96: =MAX(D8,D6*Seasonality!$C$72*D7)*(1-D28)*(1-D9) | E96: =MAX(E8,E6*Seasonality!$C$72*E7)*(1-E28)*(1-E9) | F96: =MAX(F8,F6*Seasonality!$C$72*F7)*(1-F28)*(1-F9)
B97: Revenue collected · month 37 | C97: ₹ | D97: =MAX(D8,D6*Seasonality!$C$73*D7)*(1-D28)*(1-D9) | E97: =MAX(E8,E6*Seasonality!$C$73*E7)*(1-E28)*(1-E9) | F97: =MAX(F8,F6*Seasonality!$C$73*F7)*(1-F28)*(1-F9)
B98: Revenue collected · month 38 | C98: ₹ | D98: =MAX(D8,D6*Seasonality!$C$74*D7)*(1-D28)*(1-D9) | E98: =MAX(E8,E6*Seasonality!$C$74*E7)*(1-E28)*(1-E9) | F98: =MAX(F8,F6*Seasonality!$C$74*F7)*(1-F28)*(1-F9)
B99: Revenue collected · month 39 | C99: ₹ | D99: =MAX(D8,D6*Seasonality!$C$75*D7)*(1-D28)*(1-D9) | E99: =MAX(E8,E6*Seasonality!$C$75*E7)*(1-E28)*(1-E9) | F99: =MAX(F8,F6*Seasonality!$C$75*F7)*(1-F28)*(1-F9)
B100: Revenue collected · month 40 | C100: ₹ | D100: =MAX(D8,D6*Seasonality!$C$76*D7)*(1-D28)*(1-D9) | E100: =MAX(E8,E6*Seasonality!$C$76*E7)*(1-E28)*(1-E9) | F100: =MAX(F8,F6*Seasonality!$C$76*F7)*(1-F28)*(1-F9)
B101: Revenue collected · month 41 | C101: ₹ | D101: =MAX(D8,D6*Seasonality!$C$77*D7)*(1-D28)*(1-D9) | E101: =MAX(E8,E6*Seasonality!$C$77*E7)*(1-E28)*(1-E9) | F101: =MAX(F8,F6*Seasonality!$C$77*F7)*(1-F28)*(1-F9)
...

Sheet Projection
A1: 3-year projection — live scenario: sales capacity → cohorts → P&L → cash → funding ask
A2: Months run April to March. Revenue starts after the free pilot. New institutes are capped by the addressable market. Rows 6-80 (inputs and per-institute vectors) are grouped: use the +/- in the left margin.
B3: Scenario (1 = Bear, 2 = Base, 3 = Bull) | D3: =Scenario
B5: Inputs used (linked from Assumptions; Bear / Base / Bull chosen by the scenario)
B6: Students per institute - Small | C6: students | D6: =Students_S
B7: Students per institute - Mid | C7: students | D7: =Students_M
B8: Students per institute - Large | C8: students | D8: =Students_L
B9: Onboarding cost multiplier - Small | C9: x | D9: =OnboardMult_S
B10: Onboarding cost multiplier - Mid | C10: x | D10: =OnboardMult_M
B11: Onboarding cost multiplier - Large | C11: x | D11: =OnboardMult_L
B12: Share of new institutes that are Small | C12: % of new logos | D12: =SegMix_S
B13: Share of new institutes that are Mid | C13: % of new logos | D13: =SegMix_M
B14: Share of new institutes that are Large | C14: % of new logos | D14: =SegMix_L
B15: List price per active student per month | C15: Rs/student/month | D15: =ListPrice
B16: Minimum monthly fee per institute | C16: Rs/month | D16: =MinFee
B17: Average negotiated discount off list | C17: % | D17: =NegotiationDisc
B18: Share of institutes choosing annual prepay | C18: % | D18: =PrepayUptake
B19: Annual prepay discount | C19: % | D19: =PrepayDisc
B20: Bad debt / uncollected billing | C20: % | D20: =BadDebt
B21: Payment collection cost (blended) | C21: % of revenue | D21: =GatewayFee
B22: AI parent reports per student per month | C22: reports | D22: =ReportsPerStudentMonth
B23: LLM input tokens per report | C23: tokens | D23: =TokensInPerReport
B24: LLM output tokens per report | C24: tokens | D24: =TokensOutPerReport
B25: LLM input price (hosted) | C25: Rs per 1M tokens | D25: =LLMPriceIn
B26: LLM output price (hosted) | C26: Rs per 1M tokens | D26: =LLMPriceOut
B27: WhatsApp utility messages per student per month | C27: messages | D27: =WAMsgsPerStudentMonth
B28: WhatsApp utility message price (India) | C28: Rs/message | D28: =WAPricePerMsg
B29: Compute + storage + backups per student | C29: Rs/student/month | D29: =ComputePerStudentMonth
B30: Consent OTP + verification per student | C30: Rs/student/yr | D30: =ConsentCostPerStudentYear
B31: App server + managed Postgres + backups per stack | C31: Rs/month | D31: =ServerCostMonth
B32: WhatsApp BSP platform fee per stack | C32: Rs/month | D32: =BSPFeeMonth
B33: Institutes sharing one server stack | C33: institutes | D33: =InstPerStack
B34: DPDP compliance cost per institute | C34: Rs/month | D34: =CompliancePerInstMonth
B35: Customer-success / onboarding exec monthly CTC | C35: Rs/month | D35: =CSM_CTC
B36: Institutes per CSM | C36: institutes | D36: =InstPerCSM
B37: Field sales rep monthly CTC (incl. fuel) | C37: Rs/month | D37: =RepCTC
B38: Rep intercity travel + demo material per month | C38: Rs/month | D38: =RepTravel
B39: Sales overhead loading on rep cost (manager, incentives, recruiting, tools) | C39: % of rep cost | D39: =SalesOverheadPct
B40: Pilots started per rep per month (yearly avg) | C40: pilots | D40: =PilotsPerRepMonth
B41: Pilot-to-paid conversion | C41: % | D41: =PilotConv
B42: Free pilot length | C42: months | D42: =PilotMonths
B43: Retro-pilot setup (import last year's Excel; show who left) | C43: Rs per pilot | D43: =PilotSetupCost
B44: Onboarding cost per institute (mid) | C44: Rs | D44: =OnboardBase
B45: Marketing spend per paid institute | C45: Rs | D45: =MarketingPerPaid
B46: Monthly logo churn for monthly payers | C46: %/month | D46: =ChurnInSeason
B47: Non-renewal at session end (annual) | C47: % of logos | D47: =RenewalSpike
B48: Months a customer must have paid before the first renewal decision | C48: months | D48: =MinRenewTenure
B49: Founders drawing a stipend | C49: people | D49: =Founders
B50: Founder stipend per month | C50: Rs/month | D50: =FounderStipend
B51: Engineers in year 1 | C51: people | D51: =EngineersY1
B52: Engineers in year 2 | C52: people | D52: =EngineersY2
B53: Engineers in year 3 | C53: people | D53: =EngineersY3
B54: Engineer monthly CTC | C54: Rs/month | D54: =EngineerCTC
B55: Tools / office / legal per month | C55: Rs/month | D55: =ToolsOpex
B56: Field sales reps in year 1 | C56: people | D56: =RepsY1
B57: Field sales reps in year 2 | C57: people | D57: =RepsY2
B58: Field sales reps in year 3 | C58: people | D58: =RepsY3
B59: Minimum product and engineering spend as a share of revenue | C59: % of revenue | D59: =RDFloorPct
B60: Minimum founders' and general costs as a share of revenue | C60: % of revenue | D60: =GAFloorPct
B61: Annual salary and cost inflation | C61: %/yr | D61: =SalaryInflation
B62: Days to collect an invoice (receivables) | C62: days | D62: =DaysToCollect
B63: Laptop and set-up cost per new hire | C63: Rs/hire | D63: =HireEquipment
B64: Minimum cash buffer, in months of costs | C64: months | D64: =CashBufferMonths
B65: Addressable institutes (SAM): independent, 150-2,000 students, five states | C65: institutes | D65: =AddressableInstitutes
B66: Maximum share of SAM won in 3 years (cumulative new logos) | C66: % of SAM | D66: =MaxPenetration
B67: Derived values
B68: Effective discount (negotiation + prepay uptake × prepay discount) | C68: % | D68: =$D$17+$D$18*$D$19
B69: Variable cost per active student per month | C69: ₹/student/month | D69: =$D$22*($D$23*$D$25+$D$24*$D$26)/1000000+$D$27*$D$28+$D$29+$D$30/12
B70: In-season churn, monthly payers only | C70: %/month | D70: =$D$46*(1-$D$18)
B71: Extra churn per renewal month | C71: %/month | D71: =1-(1-$D$47)^(1/NRenew)
B72: Average students per new institute (customer mix) | C72: students | D72: =$D$12*$D$6+$D$13*$D$7+$D$14*$D$8
B73: Average onboarding-cost multiplier (customer mix) | C73: x | D73: =$D$12*$D$9+$D$13*$D$10+$D$14*$D$11
B74: Cost of one free pilot (setup + serving the free months) | C74: ₹ | D74: =$D$43+$D$42*($D$72*$D$69+$D$34)
B75: Market cap: addressable institutes × max penetration | C75: institutes | D75: =$D$65*$D$66
B76: Average monthly revenue per institute over a year | C76: ₹ | D76: =AVERAGE(E82:P82)
B77: Per-institute revenue and cost by calendar month (April = 1), same formulas as Unit_Econ
B78: Calendar month number | E78: 1 | F78: 2 | G78: 3 | H78: 4 | I78: 5 | J78: 6 | K78: 7 | L78: 8 | M78: 9 | N78: 10 | O78: 11 | P78: 12
B79: Revenue per Small institute (ex-GST, after discounts and bad debt) | C79: ₹ | E79: =MAX($D$16,$D$6*INDEX(Season_Idx,E$78)*$D$15)*(1-$D$68)*(1-$D$20) | F79: =MAX($D$16,$D$6*INDEX(Season_Idx,F$78)*$D$15)*(1-$D$68)*(1-$D$20) | G79: =MAX($D$16,$D$6*INDEX(Season_Idx,G$78)*$D$15)*(1-$D$68)*(1-$D$20) | H79: =MAX($D$16,$D$6*INDEX(Season_Idx,H$78)*$D$15)*(1-$D$68)*(1-$D$20) | I79: =MAX($D$16,$D$6*INDEX(Season_Idx,I$78)*$D$15)*(1-$D$68)*(1-$D$20) | J79: =MAX($D$16,$D$6*INDEX(Season_Idx,J$78)*$D$15)*(1-$D$68)*(1-$D$20) | K79: =MAX($D$16,$D$6*INDEX(Season_Idx,K$78)*$D$15)*(1-$D$68)*(1-$D$20) | L79: =MAX($D$16,$D$6*INDEX(Season_Idx,L$78)*$D$15)*(1-$D$68)*(1-$D$20) | ... P79: =MAX($D$16,$D$6*INDEX(Season_Idx,P$78)*$D$15)*(1-$D$68)*(1-$D$20)
B80: Revenue per Mid institute (ex-GST, after discounts and bad debt) | C80: ₹ | E80: =MAX($D$16,$D$7*INDEX(Season_Idx,E$78)*$D$15)*(1-$D$68)*(1-$D$20) | F80: =MAX($D$16,$D$7*INDEX(Season_Idx,F$78)*$D$15)*(1-$D$68)*(1-$D$20) | G80: =MAX($D$16,$D$7*INDEX(Season_Idx,G$78)*$D$15)*(1-$D$68)*(1-$D$20) | H80: =MAX($D$16,$D$7*INDEX(Season_Idx,H$78)*$D$15)*(1-$D$68)*(1-$D$20) | I80: =MAX($D$16,$D$7*INDEX(Season_Idx,I$78)*$D$15)*(1-$D$68)*(1-$D$20) | J80: =MAX($D$16,$D$7*INDEX(Season_Idx,J$78)*$D$15)*(1-$D$68)*(1-$D$20) | K80: =MAX($D$16,$D$7*INDEX(Season_Idx,K$78)*$D$15)*(1-$D$68)*(1-$D$20) | L80: =MAX($D$16,$D$7*INDEX(Season_Idx,L$78)*$D$15)*(1-$D$68)*(1-$D$20) | ... P80: =MAX($D$16,$D$7*INDEX(Season_Idx,P$78)*$D$15)*(1-$D$68)*(1-$D$20)
B81: Revenue per Large institute (ex-GST, after discounts and bad debt) | C81: ₹ | E81: =MAX($D$16,$D$8*INDEX(Season_Idx,E$78)*$D$15)*(1-$D$68)*(1-$D$20) | F81: =MAX($D$16,$D$8*INDEX(Season_Idx,F$78)*$D$15)*(1-$D$68)*(1-$D$20) | G81: =MAX($D$16,$D$8*INDEX(Season_Idx,G$78)*$D$15)*(1-$D$68)*(1-$D$20) | H81: =MAX($D$16,$D$8*INDEX(Season_Idx,H$78)*$D$15)*(1-$D$68)*(1-$D$20) | I81: =MAX($D$16,$D$8*INDEX(Season_Idx,I$78)*$D$15)*(1-$D$68)*(1-$D$20) | J81: =MAX($D$16,$D$8*INDEX(Season_Idx,J$78)*$D$15)*(1-$D$68)*(1-$D$20) | K81: =MAX($D$16,$D$8*INDEX(Season_Idx,K$78)*$D$15)*(1-$D$68)*(1-$D$20) | L81: =MAX($D$16,$D$8*INDEX(Season_Idx,L$78)*$D$15)*(1-$D$68)*(1-$D$20) | ... P81: =MAX($D$16,$D$8*INDEX(Season_Idx,P$78)*$D$15)*(1-$D$68)*(1-$D$20)
B82: Revenue per institute, weighted by customer mix | C82: ₹ | E82: =$D$12*E79+$D$13*E80+$D$14*E81 | F82: =$D$12*F79+$D$13*F80+$D$14*F81 | G82: =$D$12*G79+$D$13*G80+$D$14*G81 | H82: =$D$12*H79+$D$13*H80+$D$14*H81 | I82: =$D$12*I79+$D$13*I80+$D$14*I81 | J82: =$D$12*J79+$D$13*J80+$D$14*J81 | K82: =$D$12*K79+$D$13*K80+$D$14*K81 | L82: =$D$12*L79+$D$13*L80+$D$14*L81 | ... P82: =$D$12*P79+$D$13*P80+$D$14*P81
B83: Variable cost per institute, weighted by customer mix | C83: ₹ | E83: =$D$69*$D$72*INDEX(Season_Idx,E$78)+$D$21*E82+$D$34 | F83: =$D$69*$D$72*INDEX(Season_Idx,F$78)+$D$21*F82+$D$34 | G83: =$D$69*$D$72*INDEX(Season_Idx,G$78)+$D$21*G82+$D$34 | H83: =$D$69*$D$72*INDEX(Season_Idx,H$78)+$D$21*H82+$D$34 | I83: =$D$69*$D$72*INDEX(Season_Idx,I$78)+$D$21*I82+$D$34 | J83: =$D$69*$D$72*INDEX(Season_Idx,J$78)+$D$21*J82+$D$34 | K83: =$D$69*$D$72*INDEX(Season_Idx,K$78)+$D$21*K82+$D$34 | L83: =$D$69*$D$72*INDEX(Season_Idx,L$78)+$D$21*L82+$D$34 | ... P83: =$D$69*$D$72*INDEX(Season_Idx,P$78)+$D$21*P82+$D$34
B85: Annual summary
B86: Financial year (April to March) | D86: 1 | E86: 2 | F86: 3 | G86: 3-year total
B87: Revenue | D87: =SUMIF($E$114:$AN$114,D$86,$E$128:$AN$128) | E87: =SUMIF($E$114:$AN$114,E$86,$E$128:$AN$128) | F87: =SUMIF($E$114:$AN$114,F$86,$E$128:$AN$128) | G87: =SUM(D87:F87)
B88: Gross profit (after support) | D88: =SUMIF($E$114:$AN$114,D$86,$E$135:$AN$135) | E88: =SUMIF($E$114:$AN$114,E$86,$E$135:$AN$135) | F88: =SUMIF($E$114:$AN$114,F$86,$E$135:$AN$135) | G88: =SUM(D88:F88)
B89: Gross margin | D89: =IF(D87<>0,D88/D87,0) | E89: =IF(E87<>0,E88/E87,0) | F89: =IF(F87<>0,F88/F87,0) | G89: =IF(G87<>0,G88/G87,0)
B90: Sales and marketing | D90: =SUMIF($E$114:$AN$114,D$86,$E$141:$AN$141) | E90: =SUMIF($E$114:$AN$114,E$86,$E$141:$AN$141) | F90: =SUMIF($E$114:$AN$114,F$86,$E$141:$AN$141) | G90: =SUM(D90:F90)
B91: Product and engineering | D91: =SUMIF($E$114:$AN$114,D$86,$E$143:$AN$143) | E91: =SUMIF($E$114:$AN$114,E$86,$E$143:$AN$143) | F91: =SUMIF($E$114:$AN$114,F$86,$E$143:$AN$143) | G91: =SUM(D91:F91)
B92: Founders' stipends and general costs | D92: =SUMIF($E$114:$AN$114,D$86,$E$144:$AN$144) | E92: =SUMIF($E$114:$AN$114,E$86,$E$144:$AN$144) | F92: =SUMIF($E$114:$AN$114,F$86,$E$144:$AN$144) | G92: =SUM(D92:F92)
B93: EBITDA | D93: =SUMIF($E$114:$AN$114,D$86,$E$146:$AN$146) | E93: =SUMIF($E$114:$AN$114,E$86,$E$146:$AN$146) | F93: =SUMIF($E$114:$AN$114,F$86,$E$146:$AN$146) | G93: =SUM(D93:F93)
B94: EBITDA margin | D94: =IF(D87<>0,D93/D87,0) | E94: =IF(E87<>0,E93/E87,0) | F94: =IF(F87<>0,F93/F87,0) | G94: =IF(G87<>0,G93/G87,0)
B95: New paying institutes | D95: =SUMIF($E$114:$AN$114,D$86,$E$123:$AN$123) | E95: =SUMIF($E$114:$AN$114,E$86,$E$123:$AN$123) | F95: =SUMIF($E$114:$AN$114,F$86,$E$123:$AN$123) | G95: =SUM(D95:F95)
B96: Paying institutes at year end | D96: =INDEX($E$126:$AN$126,1,12*D$86) | E96: =INDEX($E$126:$AN$126,1,12*E$86) | F96: =INDEX($E$126:$AN$126,1,12*F$86)
B97: Run-rate annual revenue at year end (institutes × average yearly revenue per institute) | D97: =D96*$D$76*12 | E97: =E96*$D$76*12 | F97: =F96*$D$76*12
B98: Headcount at year end | D98: =INDEX($E$150:$AN$150,1,12*D$86) | E98: =INDEX($E$150:$AN$150,1,12*E$86) | F98: =INDEX($E$150:$AN$150,1,12*F$86)
B100: Funding, break-even and market checks
B101: Peak cash deficit before any funding | C101: ₹ | D101: =-MIN(0,MIN($E$154:$AN$154))
B102: Cash buffer: months of costs at the point of the deepest deficit | C102: ₹ | D102: =$D$64*INDEX($E$155:$AN$155,1,MATCH(MIN($E$154:$AN$154),$E$154:$AN$154,0))
B103: FUNDING THE MODEL SAYS WE NEED (peak deficit + buffer, rounded up to ₹5 lakh) | C103: ₹ | D103: =CEILING($D$101+$D$102,500000)
...

Sheet Scenarios
A1: Scenarios — honest model vs the guide's naive model
A2: Bear / Base / Bull flex only the 13 scenario drivers (Assumptions column N); every other input stays at Base. Stress flexes ALL inputs to their worst at once: a survival test, not a forecast. Mid institute = 400 students. Always shown side by side, whatever the Cover selector says.
A4: Metric (Mid institute) | B4: Unit | C4: Guide (naive) | D4: Bear | E4: Base | F4: Bull | G4: Stress (all inputs worst)
A5: Effective dropout reduction | B5: % | C5: =Assumptions!$E$90 | D5: =Engine!$H$84 | E5: =Engine!$K$84 | F5: =Engine!$N$84 | G5: =Engine!$Q$84
A6: Dropouts prevented per year | B6: students | C6: =Institute_ROI!$E$67 | D6: =Engine!$H$85 | E6: =Engine!$K$85 | F6: =Engine!$N$85 | G6: =Engine!$Q$85
A7: Fee lost per dropout | B7: ₹ | C7: =G_RemainingFee | D7: =Engine!$H$80 | E7: =Engine!$K$80 | F7: =Engine!$N$80 | G7: =Engine!$Q$80
A8: Fees retained per year | B8: ₹/yr | C8: =Institute_ROI!$E$68 | D8: =Engine!$H$87 | E8: =Engine!$K$87 | F8: =Engine!$N$87 | G8: =Engine!$Q$87
A9: Total value to institute | B9: ₹/yr | C9: =Institute_ROI!$E$68 | D9: =Engine!$H$90 | E9: =Engine!$K$90 | F9: =Engine!$N$90 | G9: =Engine!$Q$90
A10: Total cost to institute (fee + GST + mentor time) | B10: ₹/yr | C10: =Institute_ROI!$E$69 | D10: =Engine!$H$96 | E10: =Engine!$K$96 | F10: =Engine!$N$96 | G10: =Engine!$Q$96
A11: Institute ROI, all benefits | B11: x | C11: =Institute_ROI!$E$70 | D11: =Engine!$H$98 | E11: =Engine!$K$98 | F11: =Engine!$N$98 | G11: =Engine!$Q$98
A12: Institute ROI, hard benefits (fees + staff time) | B12: x | C12: =Institute_ROI!$E$70 | D12: =Engine!$H$100 | E12: =Engine!$K$100 | F12: =Engine!$N$100 | G12: =Engine!$Q$100
A13: Institute ROI, fees only | B13: x | C13: =Institute_ROI!$E$70 | D13: =Engine!$H$99 | E13: =Engine!$K$99 | F13: =Engine!$N$99 | G13: =Engine!$Q$99
A14: Break-even students saved per year | B14: students | C14: =Institute_ROI!$E$71 | D14: =Engine!$H$101 | E14: =Engine!$K$101 | F14: =Engine!$N$101 | G14: =Engine!$Q$101
A15: Avg monthly revenue per institute | B15: ₹/month | C15: =Unit_Econ!$I$5 | D15: =Engine!$H$108 | E15: =Engine!$K$108 | F15: =Engine!$N$108 | G15: =Engine!$Q$108
A16: Avg monthly contribution | B16: ₹/month | C16: =Unit_Econ!$I$6 | D16: =Engine!$H$112 | E16: =Engine!$K$112 | F16: =Engine!$N$112 | G16: =Engine!$Q$112
A17: CAC: sales + marketing per paying institute | B17: ₹ | C17: =G_CAC | D17: =Engine!$H$117 | E17: =Engine!$K$117 | F17: =Engine!$N$117 | G17: =Engine!$Q$117
A18: Fully loaded acquisition cost | B18: ₹ | C18: =Unit_Econ!$I$7 | D18: =Engine!$H$118 | E18: =Engine!$K$118 | F18: =Engine!$N$118 | G18: =Engine!$Q$118
A19: Annual logo retention | B19: % | C19: =(1-G_Churn)^12 | D19: =Engine!$H$121 | E19: =Engine!$K$121 | F19: =Engine!$N$121 | G19: =Engine!$Q$121
A20: LTV, discounted | B20: ₹ | C20: =Unit_Econ!$I$9 | D20: =Engine!$H$123 | E20: =Engine!$K$123 | F20: =Engine!$N$123 | G20: =Engine!$Q$123
A21: LTV ÷ acquisition cost, discounted | B21: x | C21: =Unit_Econ!$I$10 | D21: =Engine!$H$124 | E21: =Engine!$K$124 | F21: =Engine!$N$124 | G21: =Engine!$Q$124
A22: LTV ÷ acquisition cost, undiscounted (peer convention) | B22: x | C22: =Unit_Econ!$I$10 | D22: =Engine!$H$128 | E22: =Engine!$K$128 | F22: =Engine!$N$128 | G22: =Engine!$Q$128
A23: Payback, survival-weighted and discounted | B23: months | C23: =Unit_Econ!$I$8 | D23: =Engine!$H$125 | E23: =Engine!$K$125 | F23: =Engine!$N$125 | G23: =Engine!$Q$125
A24: Payback, simple | B24: months | C24: =Unit_Econ!$I$8 | D24: =Engine!$H$126 | E24: =Engine!$K$126 | F24: =Engine!$N$126 | G24: =Engine!$Q$126
A27: By segment
A28: Institute ROI, all benefits | D28: Bear | E28: Base | F28: Bull
A29: Small (<250) | D29: =Engine!$G$98 | E29: =Engine!$J$98 | F29: =Engine!$M$98
A30: Mid (250-800) | D30: =Engine!$H$98 | E30: =Engine!$K$98 | F30: =Engine!$N$98
A31: Large (>800) | D31: =Engine!$I$98 | E31: =Engine!$L$98 | F31: =Engine!$O$98
A34: LTV ÷ acquisition cost (field sales) | D34: Bear | E34: Base | F34: Bull
A35: Small (<250) | D35: =Engine!$G$124 | E35: =Engine!$J$124 | F35: =Engine!$M$124
A36: Mid (250-800) | D36: =Engine!$H$124 | E36: =Engine!$K$124 | F36: =Engine!$N$124
A37: Large (>800) | D37: =Engine!$I$124 | E37: =Engine!$L$124 | F37: =Engine!$O$124
A40: LTV ÷ acquisition cost (channel partner) | D40: Bear | E40: Base | F40: Bull
A41: Small (<250) | D41: =Engine!$G$130 | E41: =Engine!$J$130 | F41: =Engine!$M$130
A42: Mid (250-800) | D42: =Engine!$H$130 | E42: =Engine!$K$130 | F42: =Engine!$N$130
A43: Large (>800) | D43: =Engine!$I$130 | E43: =Engine!$L$130 | F43: =Engine!$O$130
A46: Payback (months) | D46: Bear | E46: Base | F46: Bull
A47: Small (<250) | D47: =Engine!$G$125 | E47: =Engine!$J$125 | F47: =Engine!$M$125
A48: Mid (250-800) | D48: =Engine!$H$125 | E48: =Engine!$K$125 | F48: =Engine!$N$125
A49: Large (>800) | D49: =Engine!$I$125 | E49: =Engine!$L$125 | F49: =Engine!$O$125
A52: 3-year projection (36 months) | B52: Unit | D52: Bear | E52: Base | F52: Bull
A53: Revenue in year 3 | B53: ₹ | D53: =Proj_Bear!$F$87 | E53: =Proj_Base!$F$87 | F53: =Proj_Bull!$F$87
A54: EBITDA in year 3 | B54: ₹ | D54: =Proj_Bear!$F$93 | E54: =Proj_Base!$F$93 | F54: =Proj_Bull!$F$93
A55: Paying institutes at the end of year 3 | B55: institutes | D55: =Proj_Bear!$F$96 | E55: =Proj_Base!$F$96 | F55: =Proj_Bull!$F$96
A56: Run-rate annual revenue at the end of year 3 | B56: ₹ | D56: =Proj_Bear!$F$97 | E56: =Proj_Base!$F$97 | F56: =Proj_Bull!$F$97
A57: Funding the model says we need | B57: ₹ | D57: =Proj_Bear!$D$103 | E57: =Proj_Base!$D$103 | F57: =Proj_Bull!$D$103
A58: Break-even month (3 positive months in a row) | B58: month # | D58: =Proj_Bear!$D$105 | E58: =Proj_Base!$D$105 | F58: =Proj_Bull!$D$105
A59: Months in which the market cap limited sales | B59: months | D59: =Proj_Bear!$D$109 | E59: =Proj_Base!$D$109 | F59: =Proj_Bull!$D$109

Sheet Sensitivity
A1: Sensitivity — what actually moves the answer
A2: Tornado: one input at a time moved to its Bear / Bull value, all else Base (Mid institute). Grids follow the live scenario.
A4: Input | B4: Bear value | C4: Bull value | D4: ROI @ Bear | E4: ROI @ Bull | F4: ROI swing | G4: LTV/CAC @ Bear | H4: LTV/CAC @ Bull | I4: LTV/CAC swing
A5: BASE (all inputs Base) | D5: =Engine!$K$98 | E5: =Engine!$K$98 | G5: =Engine!$K$124 | H5: =Engine!$K$124
A6: List price per active student per month | B6: =Assumptions!$D$38 | C6: =Assumptions!$F$38 | D6: =Engine!$S$98 | E6: =Engine!$T$98 | F6: =ABS(E6-D6) | G6: =Engine!$S$124 | H6: =Engine!$T$124 | I6: =ABS(H6-G6)
A7: Annual fee per student - Mid | B7: =Assumptions!$D$10 | C7: =Assumptions!$F$10 | D7: =Engine!$U$98 | E7: =Engine!$V$98 | F7: =ABS(E7-D7) | G7: =Engine!$U$124 | H7: =Engine!$V$124 | I7: =ABS(H7-G7)
A8: Mid-session dropout/default rate | B8: =Assumptions!$D$16 | C8: =Assumptions!$F$16 | D8: =Engine!$W$98 | E8: =Engine!$X$98 | F8: =ABS(E8-D8) | G8: =Engine!$W$124 | H8: =Engine!$X$124 | I8: =ABS(H8-G8)
A9: Share of students paying full fee upfront | B9: =Assumptions!$D$17 | C9: =Assumptions!$F$17 | D9: =Engine!$Y$98 | E9: =Engine!$Z$98 | F9: =ABS(E9-D9) | G9: =Engine!$Y$124 | H9: =Engine!$Z$124 | I9: =ABS(H9-G9)
A10: Instalments per year for non-upfront payers | B10: =Assumptions!$D$18 | C10: =Assumptions!$F$18 | D10: =Engine!$AA$98 | E10: =Engine!$AB$98 | F10: =ABS(E10-D10) | G10: =Engine!$AA$124 | H10: =Engine!$AB$124 | I10: =ABS(H10-G10)
A11: Dropout reduction among flagged students given outreach (RCT) | B11: =Assumptions!$D$28 | C11: =Assumptions!$F$28 | D11: =Engine!$AC$98 | E11: =Engine!$AD$98 | F11: =ABS(E11-D11) | G11: =Engine!$AC$124 | H11: =Engine!$AD$124 | I11: =ABS(H11-G11)
A12: Model recall on minors (academic-support + rules) | B12: =Assumptions!$D$24 | C12: =Assumptions!$F$24 | D12: =Engine!$AE$98 | E12: =Engine!$AF$98 | F12: =ABS(E12-D12) | G12: =Engine!$AE$124 | H12: =Engine!$AF$124 | I12: =ABS(H12-G12)
A13: Precision of at-risk flag | B13: =Assumptions!$D$26 | C13: =Assumptions!$F$26 | D13: =Engine!$AG$98 | E13: =Engine!$AH$98 | F13: =ABS(E13-D13) | G13: =Engine!$AG$124 | H13: =Engine!$AH$124 | I13: =ABS(H13-G13)
A14: Mentor minutes per intervention | B14: =Assumptions!$D$33 | C14: =Assumptions!$F$33 | D14: =Engine!$AI$98 | E14: =Engine!$AJ$98 | F14: =ABS(E14-D14) | G14: =Engine!$AI$124 | H14: =Engine!$AJ$124 | I14: =ABS(H14-G14)
A15: Months before the model can flag (no test data yet) | B15: =Assumptions!$D$21 | C15: =Assumptions!$F$21 | D15: =Engine!$AK$98 | E15: =Engine!$AL$98 | F15: =ABS(E15-D15) | G15: =Engine!$AK$124 | H15: =Engine!$AL$124 | I15: =ABS(H15-G15)
A16: Admissions uplift next session from results/parent trust | B16: =Assumptions!$D$29 | C16: =Assumptions!$F$29 | D16: =Engine!$AM$98 | E16: =Engine!$AN$98 | F16: =ABS(E16-D16) | G16: =Engine!$AM$124 | H16: =Engine!$AN$124 | I16: =ABS(H16-G16)
A17: Share of institutes that reclaim our GST as input credit | B17: =Assumptions!$D$36 | C17: =Assumptions!$F$36 | D17: =Engine!$AO$98 | E17: =Engine!$AP$98 | F17: =ABS(E17-D17) | G17: =Engine!$AO$124 | H17: =Engine!$AP$124 | I17: =ABS(H17-G17)
A18: Monthly logo churn for monthly payers | B18: =Assumptions!$D$74 | C18: =Assumptions!$F$74 | D18: =Engine!$AQ$98 | E18: =Engine!$AR$98 | F18: =ABS(E18-D18) | G18: =Engine!$AQ$124 | H18: =Engine!$AR$124 | I18: =ABS(H18-G18)
A19: Non-renewal at session end (annual) | B19: =Assumptions!$D$75 | C19: =Assumptions!$F$75 | D19: =Engine!$AS$98 | E19: =Engine!$AT$98 | F19: =ABS(E19-D19) | G19: =Engine!$AS$124 | H19: =Engine!$AT$124 | I19: =ABS(H19-G19)
A20: Pilot-to-paid conversion | B20: =Assumptions!$D$68 | C20: =Assumptions!$F$68 | D20: =Engine!$AU$98 | E20: =Engine!$AV$98 | F20: =ABS(E20-D20) | G20: =Engine!$AU$124 | H20: =Engine!$AV$124 | I20: =ABS(H20-G20)
A21: Pilots started per rep per month (yearly avg) | B21: =Assumptions!$D$67 | C21: =Assumptions!$F$67 | D21: =Engine!$AW$98 | E21: =Engine!$AX$98 | F21: =ABS(E21-D21) | G21: =Engine!$AW$124 | H21: =Engine!$AX$124 | I21: =ABS(H21-G21)
A22: Institutes per CSM | B22: =Assumptions!$D$63 | C22: =Assumptions!$F$63 | D22: =Engine!$AY$98 | E22: =Engine!$AZ$98 | F22: =ABS(E22-D22) | G22: =Engine!$AY$124 | H22: =Engine!$AZ$124 | I22: =ABS(H22-G22)
A25: Grid 1 — Institute ROI (Mid, live scenario): list price × effective dropout reduction
A26: Rows: effective reduction · Columns: list price ₹/student/month (blue = grid points)
B27: 20 | C27: 30 | D27: 40 | E27: 50 | F27: 60 | G27: 80
A28: 0.05 | B28: =(Institute_ROI!$E$31*Institute_ROI!$E$39*$A28+Institute_ROI!$E$42+Institute_ROI!$E$43)/(SUMPRODUCT((Institute_ROI!$E$6*Season_Idx*B$27>Institute_ROI!$E$26)*(Institute_ROI!$E$6*Season_Idx*B$27)+(Institute_ROI!$E$6*Season_Idx*B$27<=Institute_ROI!$E$26)*Institute_ROI!$E$26)*(1-Institute_ROI!$E$29)*(1+GST*(1-ITCShare))+Institute_ROI!$E$50) | C28: =(Institute_ROI!$E$31*Institute_ROI!$E$39*$A28+Institute_ROI!$E$42+Institute_ROI!$E$43)/(SUMPRODUCT((Institute_ROI!$E$6*Season_Idx*C$27>Institute_ROI!$E$26)*(Institute_ROI!$E$6*Season_Idx*C$27)+(Institute_ROI!$E$6*Season_Idx*C$27<=Institute_ROI!$E$26)*Institute_ROI!$E$26)*(1-Institute_ROI!$E$29)*(1+GST*(1-ITCShare))+Institute_ROI!$E$50) | D28: =(Institute_ROI!$E$31*Institute_ROI!$E$39*$A28+Institute_ROI!$E$42+Institute_ROI!$E$43)/(SUMPRODUCT((Institute_ROI!$E$6*Season_Idx*D$27>Institute_ROI!$E$26)*(Institute_ROI!$E$6*Season_Idx*D$27)+(Institute_ROI!$E$6*Season_Idx*D$27<=Institute_ROI!$E$26)*Institute_ROI!$E$26)*(1-Institute_ROI!$E$29)*(1+GST*(1-ITCShare))+Institute_ROI!$E$50) | E28: =(Institute_ROI!$E$31*Institute_ROI!$E$39*$A28+Institute_ROI!$E$42+Institute_ROI!$E$43)/(SUMPRODUCT((Institute_ROI!$E$6*Season_Idx*E$27>Institute_ROI!$E$26)*(Institute_ROI!$E$6*Season_Idx*E$27)+(Institute_ROI!$E$6*Season_Idx*E$27<=Institute_ROI!$E$26)*Institute_ROI!$E$26)*(1-Institute_ROI!$E$29)*(1+GST*(1-ITCShare))+Institute_ROI!$E$50) | F28: =(Institute_ROI!$E$31*Institute_ROI!$E$39*$A28+Institute_ROI!$E$42+Institute_ROI!$E$43)/(SUMPRODUCT((Institute_ROI!$E$6*Season_Idx*F$27>Institute_ROI!$E$26)*(Institute_ROI!$E$6*Season_Idx*F$27)+(Institute_ROI!$E$6*Season_Idx*F$27<=Institute_ROI!$E$26)*Institute_ROI!$E$26)*(1-Institute_ROI!$E$29)*(1+GST*(1-ITCShare))+Institute_ROI!$E$50) | G28: =(Institute_ROI!$E$31*Institute_ROI!$E$39*$A28+Institute_ROI!$E$42+Institute_ROI!$E$43)/(SUMPRODUCT((Institute_ROI!$E$6*Season_Idx*G$27>Institute_ROI!$E$26)*(Institute_ROI!$E$6*Season_Idx*G$27)+(Institute_ROI!$E$6*Season_Idx*G$27<=Institute_ROI!$E$26)*Institute_ROI!$E$26)*(1-Institute_ROI!$E$29)*(1+GST*(1-ITCShare))+Institute_ROI!$E$50)
A29: 0.08 | B29: =(Institute_ROI!$E$31*Institute_ROI!$E$39*$A29+Institute_ROI!$E$42+Institute_ROI!$E$43)/(SUMPRODUCT((Institute_ROI!$E$6*Season_Idx*B$27>Institute_ROI!$E$26)*(Institute_ROI!$E$6*Season_Idx*B$27)+(Institute_ROI!$E$6*Season_Idx*B$27<=Institute_ROI!$E$26)*Institute_ROI!$E$26)*(1-Institute_ROI!$E$29)*(1+GST*(1-ITCShare))+Institute_ROI!$E$50) | C29: =(Institute_ROI!$E$31*Institute_ROI!$E$39*$A29+Institute_ROI!$E$42+Institute_ROI!$E$43)/(SUMPRODUCT((Institute_ROI!$E$6*Season_Idx*C$27>Institute_ROI!$E$26)*(Institute_ROI!$E$6*Season_Idx*C$27)+(Institute_ROI!$E$6*Season_Idx*C$27<=Institute_ROI!$E$26)*Institute_ROI!$E$26)*(1-Institute_ROI!$E$29)*(1+GST*(1-ITCShare))+Institute_ROI!$E$50) | D29: =(Institute_ROI!$E$31*Institute_ROI!$E$39*$A29+Institute_ROI!$E$42+Institute_ROI!$E$43)/(SUMPRODUCT((Institute_ROI!$E$6*Season_Idx*D$27>Institute_ROI!$E$26)*(Institute_ROI!$E$6*Season_Idx*D$27)+(Institute_ROI!$E$6*Season_Idx*D$27<=Institute_ROI!$E$26)*Institute_ROI!$E$26)*(1-Institute_ROI!$E$29)*(1+GST*(1-ITCShare))+Institute_ROI!$E$50) | E29: =(Institute_ROI!$E$31*Institute_ROI!$E$39*$A29+Institute_ROI!$E$42+Institute_ROI!$E$43)/(SUMPRODUCT((Institute_ROI!$E$6*Season_Idx*E$27>Institute_ROI!$E$26)*(Institute_ROI!$E$6*Season_Idx*E$27)+(Institute_ROI!$E$6*Season_Idx*E$27<=Institute_ROI!$E$26)*Institute_ROI!$E$26)*(1-Institute_ROI!$E$29)*(1+GST*(1-ITCShare))+Institute_ROI!$E$50) | F29: =(Institute_ROI!$E$31*Institute_ROI!$E$39*$A29+Institute_ROI!$E$42+Institute_ROI!$E$43)/(SUMPRODUCT((Institute_ROI!$E$6*Season_Idx*F$27>Institute_ROI!$E$26)*(Institute_ROI!$E$6*Season_Idx*F$27)+(Institute_ROI!$E$6*Season_Idx*F$27<=Institute_ROI!$E$26)*Institute_ROI!$E$26)*(1-Institute_ROI!$E$29)*(1+GST*(1-ITCShare))+Institute_ROI!$E$50) | G29: =(Institute_ROI!$E$31*Institute_ROI!$E$39*$A29+Institute_ROI!$E$42+Institute_ROI!$E$43)/(SUMPRODUCT((Institute_ROI!$E$6*Season_Idx*G$27>Institute_ROI!$E$26)*(Institute_ROI!$E$6*Season_Idx*G$27)+(Institute_ROI!$E$6*Season_Idx*G$27<=Institute_ROI!$E$26)*Institute_ROI!$E$26)*(1-Institute_ROI!$E$29)*(1+GST*(1-ITCShare))+Institute_ROI!$E$50)
A30: 0.11 | B30: =(Institute_ROI!$E$31*Institute_ROI!$E$39*$A30+Institute_ROI!$E$42+Institute_ROI!$E$43)/(SUMPRODUCT((Institute_ROI!$E$6*Season_Idx*B$27>Institute_ROI!$E$26)*(Institute_ROI!$E$6*Season_Idx*B$27)+(Institute_ROI!$E$6*Season_Idx*B$27<=Institute_ROI!$E$26)*Institute_ROI!$E$26)*(1-Institute_ROI!$E$29)*(1+GST*(1-ITCShare))+Institute_ROI!$E$50) | C30: =(Institute_ROI!$E$31*Institute_ROI!$E$39*$A30+Institute_ROI!$E$42+Institute_ROI!$E$43)/(SUMPRODUCT((Institute_ROI!$E$6*Season_Idx*C$27>Institute_ROI!$E$26)*(Institute_ROI!$E$6*Season_Idx*C$27)+(Institute_ROI!$E$6*Season_Idx*C$27<=Institute_ROI!$E$26)*Institute_ROI!$E$26)*(1-Institute_ROI!$E$29)*(1+GST*(1-ITCShare))+Institute_ROI!$E$50) | D30: =(Institute_ROI!$E$31*Institute_ROI!$E$39*$A30+Institute_ROI!$E$42+Institute_ROI!$E$43)/(SUMPRODUCT((Institute_ROI!$E$6*Season_Idx*D$27>Institute_ROI!$E$26)*(Institute_ROI!$E$6*Season_Idx*D$27)+(Institute_ROI!$E$6*Season_Idx*D$27<=Institute_ROI!$E$26)*Institute_ROI!$E$26)*(1-Institute_ROI!$E$29)*(1+GST*(1-ITCShare))+Institute_ROI!$E$50) | E30: =(Institute_ROI!$E$31*Institute_ROI!$E$39*$A30+Institute_ROI!$E$42+Institute_ROI!$E$43)/(SUMPRODUCT((Institute_ROI!$E$6*Season_Idx*E$27>Institute_ROI!$E$26)*(Institute_ROI!$E$6*Season_Idx*E$27)+(Institute_ROI!$E$6*Season_Idx*E$27<=Institute_ROI!$E$26)*Institute_ROI!$E$26)*(1-Institute_ROI!$E$29)*(1+GST*(1-ITCShare))+Institute_ROI!$E$50) | F30: =(Institute_ROI!$E$31*Institute_ROI!$E$39*$A30+Institute_ROI!$E$42+Institute_ROI!$E$43)/(SUMPRODUCT((Institute_ROI!$E$6*Season_Idx*F$27>Institute_ROI!$E$26)*(Institute_ROI!$E$6*Season_Idx*F$27)+(Institute_ROI!$E$6*Season_Idx*F$27<=Institute_ROI!$E$26)*Institute_ROI!$E$26)*(1-Institute_ROI!$E$29)*(1+GST*(1-ITCShare))+Institute_ROI!$E$50) | G30: =(Institute_ROI!$E$31*Institute_ROI!$E$39*$A30+Institute_ROI!$E$42+Institute_ROI!$E$43)/(SUMPRODUCT((Institute_ROI!$E$6*Season_Idx*G$27>Institute_ROI!$E$26)*(Institute_ROI!$E$6*Season_Idx*G$27)+(Institute_ROI!$E$6*Season_Idx*G$27<=Institute_ROI!$E$26)*Institute_ROI!$E$26)*(1-Institute_ROI!$E$29)*(1+GST*(1-ITCShare))+Institute_ROI!$E$50)
A31: 0.15 | B31: =(Institute_ROI!$E$31*Institute_ROI!$E$39*$A31+Institute_ROI!$E$42+Institute_ROI!$E$43)/(SUMPRODUCT((Institute_ROI!$E$6*Season_Idx*B$27>Institute_ROI!$E$26)*(Institute_ROI!$E$6*Season_Idx*B$27)+(Institute_ROI!$E$6*Season_Idx*B$27<=Institute_ROI!$E$26)*Institute_ROI!$E$26)*(1-Institute_ROI!$E$29)*(1+GST*(1-ITCShare))+Institute_ROI!$E$50) | C31: =(Institute_ROI!$E$31*Institute_ROI!$E$39*$A31+Institute_ROI!$E$42+Institute_ROI!$E$43)/(SUMPRODUCT((Institute_ROI!$E$6*Season_Idx*C$27>Institute_ROI!$E$26)*(Institute_ROI!$E$6*Season_Idx*C$27)+(Institute_ROI!$E$6*Season_Idx*C$27<=Institute_ROI!$E$26)*Institute_ROI!$E$26)*(1-Institute_ROI!$E$29)*(1+GST*(1-ITCShare))+Institute_ROI!$E$50) | D31: =(Institute_ROI!$E$31*Institute_ROI!$E$39*$A31+Institute_ROI!$E$42+Institute_ROI!$E$43)/(SUMPRODUCT((Institute_ROI!$E$6*Season_Idx*D$27>Institute_ROI!$E$26)*(Institute_ROI!$E$6*Season_Idx*D$27)+(Institute_ROI!$E$6*Season_Idx*D$27<=Institute_ROI!$E$26)*Institute_ROI!$E$26)*(1-Institute_ROI!$E$29)*(1+GST*(1-ITCShare))+Institute_ROI!$E$50) | E31: =(Institute_ROI!$E$31*Institute_ROI!$E$39*$A31+Institute_ROI!$E$42+Institute_ROI!$E$43)/(SUMPRODUCT((Institute_ROI!$E$6*Season_Idx*E$27>Institute_ROI!$E$26)*(Institute_ROI!$E$6*Season_Idx*E$27)+(Institute_ROI!$E$6*Season_Idx*E$27<=Institute_ROI!$E$26)*Institute_ROI!$E$26)*(1-Institute_ROI!$E$29)*(1+GST*(1-ITCShare))+Institute_ROI!$E$50) | F31: =(Institute_ROI!$E$31*Institute_ROI!$E$39*$A31+Institute_ROI!$E$42+Institute_ROI!$E$43)/(SUMPRODUCT((Institute_ROI!$E$6*Season_Idx*F$27>Institute_ROI!$E$26)*(Institute_ROI!$E$6*Season_Idx*F$27)+(Institute_ROI!$E$6*Season_Idx*F$27<=Institute_ROI!$E$26)*Institute_ROI!$E$26)*(1-Institute_ROI!$E$29)*(1+GST*(1-ITCShare))+Institute_ROI!$E$50) | G31: =(Institute_ROI!$E$31*Institute_ROI!$E$39*$A31+Institute_ROI!$E$42+Institute_ROI!$E$43)/(SUMPRODUCT((Institute_ROI!$E$6*Season_Idx*G$27>Institute_ROI!$E$26)*(Institute_ROI!$E$6*Season_Idx*G$27)+(Institute_ROI!$E$6*Season_Idx*G$27<=Institute_ROI!$E$26)*Institute_ROI!$E$26)*(1-Institute_ROI!$E$29)*(1+GST*(1-ITCShare))+Institute_ROI!$E$50)
A32: 0.2 | B32: =(Institute_ROI!$E$31*Institute_ROI!$E$39*$A32+Institute_ROI!$E$42+Institute_ROI!$E$43)/(SUMPRODUCT((Institute_ROI!$E$6*Season_Idx*B$27>Institute_ROI!$E$26)*(Institute_ROI!$E$6*Season_Idx*B$27)+(Institute_ROI!$E$6*Season_Idx*B$27<=Institute_ROI!$E$26)*Institute_ROI!$E$26)*(1-Institute_ROI!$E$29)*(1+GST*(1-ITCShare))+Institute_ROI!$E$50) | C32: =(Institute_ROI!$E$31*Institute_ROI!$E$39*$A32+Institute_ROI!$E$42+Institute_ROI!$E$43)/(SUMPRODUCT((Institute_ROI!$E$6*Season_Idx*C$27>Institute_ROI!$E$26)*(Institute_ROI!$E$6*Season_Idx*C$27)+(Institute_ROI!$E$6*Season_Idx*C$27<=Institute_ROI!$E$26)*Institute_ROI!$E$26)*(1-Institute_ROI!$E$29)*(1+GST*(1-ITCShare))+Institute_ROI!$E$50) | D32: =(Institute_ROI!$E$31*Institute_ROI!$E$39*$A32+Institute_ROI!$E$42+Institute_ROI!$E$43)/(SUMPRODUCT((Institute_ROI!$E$6*Season_Idx*D$27>Institute_ROI!$E$26)*(Institute_ROI!$E$6*Season_Idx*D$27)+(Institute_ROI!$E$6*Season_Idx*D$27<=Institute_ROI!$E$26)*Institute_ROI!$E$26)*(1-Institute_ROI!$E$29)*(1+GST*(1-ITCShare))+Institute_ROI!$E$50) | E32: =(Institute_ROI!$E$31*Institute_ROI!$E$39*$A32+Institute_ROI!$E$42+Institute_ROI!$E$43)/(SUMPRODUCT((Institute_ROI!$E$6*Season_Idx*E$27>Institute_ROI!$E$26)*(Institute_ROI!$E$6*Season_Idx*E$27)+(Institute_ROI!$E$6*Season_Idx*E$27<=Institute_ROI!$E$26)*Institute_ROI!$E$26)*(1-Institute_ROI!$E$29)*(1+GST*(1-ITCShare))+Institute_ROI!$E$50) | F32: =(Institute_ROI!$E$31*Institute_ROI!$E$39*$A32+Institute_ROI!$E$42+Institute_ROI!$E$43)/(SUMPRODUCT((Institute_ROI!$E$6*Season_Idx*F$27>Institute_ROI!$E$26)*(Institute_ROI!$E$6*Season_Idx*F$27)+(Institute_ROI!$E$6*Season_Idx*F$27<=Institute_ROI!$E$26)*Institute_ROI!$E$26)*(1-Institute_ROI!$E$29)*(1+GST*(1-ITCShare))+Institute_ROI!$E$50) | G32: =(Institute_ROI!$E$31*Institute_ROI!$E$39*$A32+Institute_ROI!$E$42+Institute_ROI!$E$43)/(SUMPRODUCT((Institute_ROI!$E$6*Season_Idx*G$27>Institute_ROI!$E$26)*(Institute_ROI!$E$6*Season_Idx*G$27)+(Institute_ROI!$E$6*Season_Idx*G$27<=Institute_ROI!$E$26)*Institute_ROI!$E$26)*(1-Institute_ROI!$E$29)*(1+GST*(1-ITCShare))+Institute_ROI!$E$50)
A33: 0.25 | B33: =(Institute_ROI!$E$31*Institute_ROI!$E$39*$A33+Institute_ROI!$E$42+Institute_ROI!$E$43)/(SUMPRODUCT((Institute_ROI!$E$6*Season_Idx*B$27>Institute_ROI!$E$26)*(Institute_ROI!$E$6*Season_Idx*B$27)+(Institute_ROI!$E$6*Season_Idx*B$27<=Institute_ROI!$E$26)*Institute_ROI!$E$26)*(1-Institute_ROI!$E$29)*(1+GST*(1-ITCShare))+Institute_ROI!$E$50) | C33: =(Institute_ROI!$E$31*Institute_ROI!$E$39*$A33+Institute_ROI!$E$42+Institute_ROI!$E$43)/(SUMPRODUCT((Institute_ROI!$E$6*Season_Idx*C$27>Institute_ROI!$E$26)*(Institute_ROI!$E$6*Season_Idx*C$27)+(Institute_ROI!$E$6*Season_Idx*C$27<=Institute_ROI!$E$26)*Institute_ROI!$E$26)*(1-Institute_ROI!$E$29)*(1+GST*(1-ITCShare))+Institute_ROI!$E$50) | D33: =(Institute_ROI!$E$31*Institute_ROI!$E$39*$A33+Institute_ROI!$E$42+Institute_ROI!$E$43)/(SUMPRODUCT((Institute_ROI!$E$6*Season_Idx*D$27>Institute_ROI!$E$26)*(Institute_ROI!$E$6*Season_Idx*D$27)+(Institute_ROI!$E$6*Season_Idx*D$27<=Institute_ROI!$E$26)*Institute_ROI!$E$26)*(1-Institute_ROI!$E$29)*(1+GST*(1-ITCShare))+Institute_ROI!$E$50) | E33: =(Institute_ROI!$E$31*Institute_ROI!$E$39*$A33+Institute_ROI!$E$42+Institute_ROI!$E$43)/(SUMPRODUCT((Institute_ROI!$E$6*Season_Idx*E$27>Institute_ROI!$E$26)*(Institute_ROI!$E$6*Season_Idx*E$27)+(Institute_ROI!$E$6*Season_Idx*E$27<=Institute_ROI!$E$26)*Institute_ROI!$E$26)*(1-Institute_ROI!$E$29)*(1+GST*(1-ITCShare))+Institute_ROI!$E$50) | F33: =(Institute_ROI!$E$31*Institute_ROI!$E$39*$A33+Institute_ROI!$E$42+Institute_ROI!$E$43)/(SUMPRODUCT((Institute_ROI!$E$6*Season_Idx*F$27>Institute_ROI!$E$26)*(Institute_ROI!$E$6*Season_Idx*F$27)+(Institute_ROI!$E$6*Season_Idx*F$27<=Institute_ROI!$E$26)*Institute_ROI!$E$26)*(1-Institute_ROI!$E$29)*(1+GST*(1-ITCShare))+Institute_ROI!$E$50) | G33: =(Institute_ROI!$E$31*Institute_ROI!$E$39*$A33+Institute_ROI!$E$42+Institute_ROI!$E$43)/(SUMPRODUCT((Institute_ROI!$E$6*Season_Idx*G$27>Institute_ROI!$E$26)*(Institute_ROI!$E$6*Season_Idx*G$27)+(Institute_ROI!$E$6*Season_Idx*G$27<=Institute_ROI!$E$26)*Institute_ROI!$E$26)*(1-Institute_ROI!$E$29)*(1+GST*(1-ITCShare))+Institute_ROI!$E$50)
A36: Grid 2 — LTV ÷ acquisition cost (Mid, live scenario): monthly churn × acquisition cost
A37: Monthly in-season churn (blue) → LTV from Engine | B37: 0.01 | C37: 0.02 | D37: 0.03 | E37: 0.04 | F37: 0.05
A38: LTV at that churn (₹) | B38: =Engine!$BA$123 | C38: =Engine!$BB$123 | D38: =Engine!$BC$123 | E38: =Engine!$BD$123 | F38: =Engine!$BE$123
A39: Acquisition cost ₹ ↓
A40: 15000 | B40: =B$38/$A40 | C40: =C$38/$A40 | D40: =D$38/$A40 | E40: =E$38/$A40 | F40: =F$38/$A40
A41: 25000 | B41: =B$38/$A41 | C41: =C$38/$A41 | D41: =D$38/$A41 | E41: =E$38/$A41 | F41: =F$38/$A41
A42: 35000 | B42: =B$38/$A42 | C42: =C$38/$A42 | D42: =D$38/$A42 | E42: =E$38/$A42 | F42: =F$38/$A42
A43: 50000 | B43: =B$38/$A43 | C43: =C$38/$A43 | D43: =D$38/$A43 | E43: =E$38/$A43 | F43: =F$38/$A43
A44: 75000 | B44: =B$38/$A44 | C44: =C$38/$A44 | D44: =D$38/$A44 | E44: =E$38/$A44 | F44: =F$38/$A44
A46: Reading: ROI < 1.0x red, 1–2x amber, ≥ 2x green. LTV/CAC < 3x red.

Sheet Checks
A1: Checks — any red flag means the model is not safe to quote
A3: Check | B3: Type | C3: Value | D3: Flag (1 = fail)
A4: Scenario selector is 1, 2 or 3 | B4: Error | C4: =Scenario | D4: =IF(OR(Scenario=1,Scenario=2,Scenario=3),0,1)
A5: Dropout timing curve sums to 100% | B5: Error | C5: =SUM(DropTiming) | D5: =IF(ABS(C5-1)<0.0001,0,1)
A6: Percent inputs within 0–100% | B6: Error | C6: =SUM(Assumptions!L5:L114) | D6: =IF(C6=0,0,1)
A7: Live values within Bear–Bull range | B7: Error | C7: =SUM(Assumptions!M5:M114) | D7: =IF(C7=0,0,1)
A8: At least one renewal month (avoids ÷0) | B8: Error | C8: =NRenew | D8: =IF(C8>=1,0,1)
A9: Active-student index between 0 and 1.2 | B9: Error | C9: =SUMPRODUCT((Season_Idx<0)+(Season_Idx>1.2)) | D9: =IF(C9=0,0,1)
A10: Effective reduction ≤ RCT effect (Mid) | B10: Error | C10: =Institute_ROI!E37-InterventionSuccess | D10: =IF(C10<=0.000001,0,1)
A11: Instalments ≥ 1 and ≤ course months | B11: Error | C11: =NInstalments | D11: =IF(AND(C11>=1,C11<=CourseMonths,C11=INT(C11)),0,1)
A12: Customer mix (Small + Mid + Large) sums to 100% | B12: Error | C12: =ABS(SegMix_S+SegMix_M+SegMix_L-1) | D12: =IF(C12<0.0001,0,1)
A13: Sales intensity index averages 1.0 | B13: Error | C13: =ABS(AVERAGE(Sales_Idx)-1) | D13: =IF(C13<0.02,0,1)
A14: First renewal tenure is between 0 and 24 months | B14: Error | C14: =MinRenewTenure | D14: =IF(AND(C14>=0,C14<=24),0,1)
A15: Engine reproduces Institute_ROI ROI (S) | B15: Error | C15: =ABS(Institute_ROI!D54-Engine!$D$98) | D15: =IF(C15<0.000001,0,1)
A16: Engine reproduces Unit_Econ LTV (S) | B16: Error | C16: =ABS(Unit_Econ!D51-Engine!$D$123) | D16: =IF(C16<0.000001,0,1)
A17: Engine reproduces Institute_ROI ROI (M) | B17: Error | C17: =ABS(Institute_ROI!E54-Engine!$E$98) | D17: =IF(C17<0.000001,0,1)
A18: Engine reproduces Unit_Econ LTV (M) | B18: Error | C18: =ABS(Unit_Econ!E51-Engine!$E$123) | D18: =IF(C18<0.000001,0,1)
A19: Engine reproduces Institute_ROI ROI (L) | B19: Error | C19: =ABS(Institute_ROI!F54-Engine!$F$98) | D19: =IF(C19<0.000001,0,1)
A20: Engine reproduces Unit_Econ LTV (L) | B20: Error | C20: =ABS(Unit_Econ!F51-Engine!$F$123) | D20: =IF(C20<0.000001,0,1)
A21: Survival curve stays within 0–1 (Mid) | B21: Error | C21: =IF(AND(MIN(Unit_Econ!E181:E240)>=0,MAX(Unit_Econ!E181:E240)<=1),0,1) | D21: =C21
A22: Guide ROI reproduces the brief's 2.25x | B22: Error | C22: =Institute_ROI!$E$70 | D22: =IF(ABS(C22-2.25)<0.01,0,1)
A23: Projection: never more paying institutes than institutes won | B23: Error | C23: =SUMPRODUCT((Projection!$E$126:$AN$126>Projection!$E$124:$AN$124+0.000001)*1) | D23: =IF(C23=0,0,1)
A24: Projection: institutes won never exceed the market cap | B24: Error | C24: =MAX(0,Projection!$AN$124-Projection!$D$75) | D24: =IF(C24<0.001,0,1)
A25: Projection: cash never negative once the funding ask arrives | B25: Error | C25: =MIN(Projection!$E$156:$AN$156) | D25: =IF(C25>=-1,0,1)
A26: Projection (live) equals the fixed-scenario sheet for the chosen scenario | B26: Error | C26: =ABS(Projection!$F$87-CHOOSE(Scenario,Proj_Bear!$F$87,Proj_Base!$F$87,Proj_Bull!$F$87))+ABS(Projection!$D$103-CHOOSE(Scenario,Proj_Bear!$D$103,Proj_Base!$D$103,Proj_Bull!$D$103)) | D26: =IF(C26<0.01,0,1)
A27: WARNING: RCT effect exceeds share of dropouts that are preventable | B27: Warning | C27: =InterventionSuccess-Preventable | D27: =IF(C27<=0,0,1)
A28: WARNING: list price above the highest ERP/LMS anchor found (₹21/student/month) | B28: Warning | C28: =ListPrice | D28: =IF(C28<=CompetitorAnchorHigh,0,1)
A29: WARNING: months with negative contribution (Mid) | B29: Warning | C29: =COUNTIF(Unit_Econ!E121:E180,"<0") | D29: =IF(C29=0,0,1)
A30: WARNING: all-in COGS outside tech band ₹3–10 per student-month | B30: Warning | C30: =COGS_AllIn | D30: =IF(AND(C30>=3,C30<=10),0,1)
A31: WARNING: Mid institute ROI (all benefits) below 1.0x | B31: Warning | C31: =Institute_ROI!E54 | D31: =IF(C31>=1,0,1)
A32: WARNING: Mid hard-benefit ROI (fees + staff time) below 1.0x | B32: Warning | C32: =Institute_ROI!E56 | D32: =IF(C32>=1,0,1)
A33: WARNING: more than 30% of the roll flagged per year (alert fatigue) | B33: Warning | C33: =Institute_ROI!E49 | D33: =IF(C33<=0.3,0,1)
A34: WARNING: Mid LTV/CAC (discounted) below 3x | B34: Warning | C34: =Unit_Econ!E52 | D34: =IF(C34>=3,0,1)
A35: WARNING: Mid payback above 24 months | B35: Warning | C35: =Unit_Econ!E53 | D35: =IF(C35<=24,0,1)
A36: WARNING: 3-year projection never reaches 3 positive EBITDA months in a row | B36: Warning | C36: =IF(ISNUMBER(Projection!$D$105),0,1) | D36: =C36
A37: WARNING: EBITDA in year 3 is negative | B37: Warning | C37: =Projection!$F$93 | D37: =IF(C37>=0,0,1)
A38: WARNING: the market cap limited sales in the live projection | B38: Warning | C38: =Projection!$D$109 | D38: =IF(C38=0,0,1)
A40: ERRORS | D40: =SUMIF(B4:B38,"Error",D4:D38)
A41: WARNINGS (honest red flags to discuss, not bugs) | D41: =SUMIF(B4:B38,"Warning",D4:D38)

Sheet Sources
A1: Sources & evidence register
A2: Raw research is in Financial_Model/research/*.md. Anything typed 'Assumption' is unverified — say so on the slide.
A4: Name | B4: Input | C4: Type | D4: Confidence | E4: Source | F4: Note
A5: Students_S | B5: Students per institute - Small | C5: Assumption | D5: M | E5: Case brief range 150-2000; our cut <250 | F5: Segment midpoint
A6: Students_M | B6: Students per institute - Mid | C6: Guide | D6: M | E6: Case brief baseline 400
A7: Students_L | B7: Students per institute - Large | C7: Assumption | D7: M | E7: Case brief range 150-2000; our cut >800
A8: Fee_S | B8: Annual fee per student - Small | C8: Researched | D8: L | E8: R2 local-institute evidence: Vedantu Gaya Rs50-56k, Rupantri Muzaffarpur Rs55-60k, GOAL Patna Rs51-99k; PS baseline Rs60k | F8: Audit 2026-10-22: re-based to local evidence (was Rs65k Base)
A9: Fee_M | B9: Annual fee per student - Mid | C9: Researched | D9: L | E9: R2: PS baseline Rs60k = Bear; local Tier-2 evidence Rs50k-1.2L (Patna independents); chain fees (Vedantu Patna Rs95k) = Bull | F9: Audit 2026-10-22: was Rs95k Base (chain pricing); our customers are local independents
A10: Fee_L | B10: Annual fee per student - Large | C10: Researched | D10: M | E10: R2: Udaan Patna Rs1.15-1.25L/yr (own site, 2025-27); chains Rs1.1-1.4L (Motion, Allen Indore, Vedantu Lucknow) | F10: Audit 2026-10-22: was Rs125k Base
A11: OnboardMult_S | B11: Onboarding cost multiplier - Small | C11: Assumption | D11: L | E11: Fewer batches to migrate
A12: OnboardMult_M | B12: Onboarding cost multiplier - Mid | C12: Structural | D12: H | E12: Reference segment
A13: OnboardMult_L | B13: Onboarding cost multiplier - Large | C13: Assumption | D13: L | E13: More batches and staff to train
A14: DropoutRate | B14: Mid-session dropout/default rate | C14: Researched | D14: L | E14: PS Section 7 baseline 8-15% (12% used); CFI 'at least 10 per cent of students in every batch' (ThePrint 2025) is a floor; tech generator uses 18% (knob 12-25%) | F14: Audit 2026-10-22: Base back to the PS's 12% (was 10%). Tech's 18% is a stress calibration that gives enough validation events
A15: UpfrontShare | B15: Share of students paying full fee upfront | C15: Assumption | D15: L | E15: R2: not found. Instalments are the norm (Allen 2; PW 3; Aakash several; Rajasthan Act s.6(2)(d) >=4 option) | F15: TECH_PLAN's 35% had no source
A16: NInstalments | B16: Instalments per year for non-upfront payers | C16: Researched | D16: M | E16: R2: Allen 2 (2nd within 45 days); PW 3; Rajasthan Act 16/2025 s.6(2)(d) min. 4 equal | F16: Fewer instalments = cash collected early = less at risk
A17: RefundEnforced | B17: Share of upfront leavers actually refunded pro-rata | C17: Assumption | D17: L | E17: R2: MoE Guidelines 2024 cl.8(iv) and Rajasthan s.13(4) require pro-rata refund within 10 days; MoE is advisory and Allen/Aakash/PW practice is cut-off or no refund | F17: Refunded upfront leavers = fee at risk
A18: CourseMonths | B18: Course length | C18: Guide | D18: H | E18: Case brief ~10 months
A19: BlindMonths | B19: Months before the model can flag (no test data yet) | C19: Assumption | D19: M | E19: The model needs 1-2 cumulative tests before it can flag (tech generator: a full mock every 14 days) | F19: Audit: Base 2 (was 1). Dropouts in these months cannot be caught
A20: Preventable | B20: Share of dropouts that are preventable (check only) | C20: Assumption | D20: L | E20: Tech generator reasons_mix: academic gap 35% + financial 20% are addressable; relocation 20%, switched institute 15%, health 10% are not | F20: Audit: aligned with the tech team; used only as a sanity check on the trial effect
A21: MinorShare | B21: Share of students under 18 | C21: Public | D21: M | E21: Tech generator: 78% of students are minors at join (FEASIBILITY_CHECK s.6); JEE/NEET Class 11-12 are 16-17 | F21: Audit: aligned with the tech team's synthetic data
A22: Recall_Minor | B22: Model recall on minors (academic-support + rules) | C22: Assumption | D22: M | E22: Tech FEASIBILITY_CHECK s.2 and s.6: recall 0.31 on the actual generator; 0.49-0.55 of gradual dropouts x 75% gradual = 0.37-0.41 of all dropouts; minors get the academic-support model + rules only. Replace with metrics.json | F22: Audit 2026-10-22: was 0.55 Base (above anything the tech team measured). 25% of dropouts are sudden and unpredictable
A23: Recall_Adult | B23: Model recall on 18+ (full ML) | C23: Assumption | D23: M | E23: Tech FEASIBILITY_CHECK s.2: 0.37-0.41 of all dropouts at fixed workload; adults (18+) can use full ML incl. engagement. Replace with metrics.json | F23: Audit 2026-10-22: was 0.65 Base. OULAD AUC 0.706-0.794 (public) is ranking quality, not recall at a workload
A24: Precision | B24: Precision of at-risk flag | C24: Researched | D24: M | E24: Tech FEASIBILITY_CHECK s.6: precision@top-4%/wk 0.136; with 38% of students flagged at least once and recall 0.31, student-level precision is about 0.15 (derived) | F24: Audit 2026-10-22: was 0.35. Low precision means most mentor calls go to students who would not have left
A25: ActionRate | B25: Share of flags the institute assigns to outreach | C25: Assumption | D25: L | E25: Mentor capacity; the RCT effect below is already intention-to-treat | F25: Primary research needed
A26: InterventionSuccess | B26: Dropout reduction among flagged students given outreach (RCT) | C26: Researched | D26: M | E26: R4: mean 15.8% / median 12.5% over 8 RCTs - OU outreach RCT 2020 -19%/-35%; Room to Read India -30%; Bergman parent texts; MAAPS/Samata/Oreopoulos nulls (research/R4_R5) | F26: Borrowed from other settings - not our measured effect
A27: AdmissionUplift | B27: Admissions uplift next session from results/parent trust | C27: Assumption | D27: L | E27: No evidence - Bear = 0
A28: MarginExtraAdmission | B28: Institute margin on one extra admission | C28: Assumption | D28: L | E28: Marginal seat in an existing batch
A29: StaffHoursSaved | B29: Staff hours saved per month | C29: Guide | D29: L | E29: Case brief value lever; primary research needed
A30: StaffHourCost | B30: Cost of one admin staff hour | C30: Researched | D30: M | E30: R5: Tier-2 executive pay Rs18-25k/month (Payscale/Indeed Patna) / ~200 h
A31: InterventionMinutes | B31: Mentor minutes per intervention | C31: Assumption | D31: L | E31: Assumption: the trials behind the 15% effect used multi-touch outreach (call + parent meeting + follow-ups), about 2 hours per flagged student | F31: Audit 2026-10-22: was 30 minutes Base, too thin to deliver the trial effect
A32: MentorHourCost | B32: Cost of one mentor hour | C32: Assumption | D32: M | E32: Teacher pay ~Rs30-50k/month / ~200 h
A33: GST | B33: GST on SaaS | C33: Researched | D33: M | E33: R6: 18% (heading 9983 residual entry; Notif. 11/2017-CTR as amended by 15/2025-CTR) | F33: SAC code 9983 vs 9984 unconfirmed - ask a CA
A34: ITCShare | B34: Share of institutes that reclaim our GST as input credit | C34: Assumption | D34: L | E34: R6: coaching is taxable at 18%; registration mandatory above Rs20L turnover; CGST s.16(1) gives ITC to registered persons. A 180-student institute turns over ~Rs1 Cr, so legally registered - but cash/informal practice in Tier-3 | F34: Was 'all unregistered' in the naive view
A35: ListPrice | B35: List price per active student per month | C35: Assumption | D35: L | E35: R1: ERP/LMS anchors Rs4-21/student/month at 400 students (Classplus/Fedena/Graphy); no competitor bundles OMR + topic analytics + Hindi WhatsApp | F35: Decision lever - test in interviews (Van Westendorp)
A36: CompetitorAnchor | B36: What institutes already pay for an ERP/LMS | C36: Researched | D36: M | E36: R1: Classplus Starter Rs19999/yr (Capterra); Fedena Standard / Graphy Grow Rs50k/yr; Fedena Ultimate Rs1L/yr - all at 400 students | F36: Reference only - not used in revenue
A37: CompetitorAnchorHigh | B37: Highest priced ERP/LMS anchor found | C37: Researched | D37: M | E37: R1: Fedena Ultimate / Graphy Rise Rs1L/yr at 400 students | F37: Used in a warning check
A38: MinFee | B38: Minimum monthly fee per institute | C38: Assumption | D38: L | E38: FINANCE_PLAN s.3.2
A39: NegotiationDisc | B39: Average negotiated discount off list | C39: Assumption | D39: L | E39: Primary research needed
A40: PrepayUptake | B40: Share of institutes choosing annual prepay | C40: Assumption | D40: L | E40: Coaching institutes are cash-rich in Apr-Jun (admission season) | F40: Prepaid institutes cannot churn mid-session
A41: PrepayDisc | B41: Annual prepay discount | C41: Assumption | D41: M | E41: FINANCE_PLAN s.3.2; R2 shows institutes give 4-6% for upfront fees
A42: BadDebt | B42: Bad debt / uncollected billing | C42: Assumption | D42: M | E42: FINANCE_PLAN s.3.2
A43: GatewayFee | B43: Payment collection cost (blended) | C43: Researched | D43: M | E43: R6: Razorpay 2% + 18% GST = 2.36%; UPI MDR 0.4% on P2M >Rs2000 from 15-Oct-2026; NEFT ~0 | F43: Base assumes half paid by bank transfer
A44: ReportsPerStudentMonth | B44: AI parent reports per student per month | C44: Assumption | D44: M | E44: TECH_PLAN s.11 weekly report; Bear adds alerts
A45: TokensInPerReport | B45: LLM input tokens per report | C45: Assumption | D45: M | E45: TECH_PLAN GenAI design (numbers_json + template)
A46: TokensOutPerReport | B46: LLM output tokens per report | C46: Assumption | D46: M | E46: Bilingual report ~400-600 words
A47: LLMPriceIn | B47: LLM input price (hosted) | C47: Researched | D47: H | E47: R6: Gemini 3.8 Flash from 1-Jan-2027 / Gemini 3.1 Flash-Lite / Claude Haiku 5.5 at Rs95.05/USD (official pricing pages 20-Oct-2026) | F47: Local Ollama = ~0 (prototype)
A48: LLMPriceOut | B48: LLM output price (hosted) | C48: Researched | D48: H | E48: R6: same models as input price
A49: WAMsgsPerStudentMonth | B49: WhatsApp utility messages per student per month | C49: Assumption | D49: M | E49: Weekly report + alerts + fee reminders
A50: WAPricePerMsg | B50: WhatsApp utility message price (India) | C50: Researched | D50: H | E50: R6: Meta list Rs0.115 (eff. 1-Oct-2026); Gallabox Rs0.1323; AiSensy Rs0.145. Utility replies in window charged again from 1-Oct-2026
A51: ComputePerStudentMonth | B51: Compute + storage + backups per student | C51: Assumption | D51: L | E51: TECH_PLAN s.16 cost model (NB09 pending); OMR images auto-deleted after 7 days
A52: ConsentCostPerStudentYear | B52: Consent OTP + verification per student | C52: Assumption | D52: L | E52: TECH_PLAN consent design (OTP)
A53: ServerCostMonth | B53: App server + managed Postgres + backups per stack | C53: Researched | D53: M | E53: R6: AWS t3.medium Rs3108 + DO PG 2vCPU Rs5789 / Lightsail-DO Rs2281 + DO PG Rs1440 / t4g Rs1554 + Lightsail DB Rs1426 | F53: Base adds ~Rs300 backups
A54: BSPFeeMonth | B54: WhatsApp BSP platform fee per stack | C54: Researched | D54: M | E54: R6: AiSensy Pro Rs3200 / Basic Rs1500 / Gupshup self-serve Rs0 + per-msg
A55: InstPerStack | B55: Institutes sharing one server stack | C55: Assumption | D55: L | E55: Depends on load test (NB09)
A56: CompliancePerInstMonth | B56: DPDP compliance cost per institute | C56: Assumption | D56: L | E56: Audits / consent management / DPO time
A57: CSM_CTC | B57: Customer-success / onboarding exec monthly CTC | C57: Researched | D57: L | E57: R5: Tier-2 remote CS median Rs33-42k (Frontlines 2026); Payscale Jaipur CSM-manager Rs58k
A58: InstPerCSM | B58: Institutes per CSM | C58: Researched | D58: L | E58: R5: Gainsight SMB 100-250 accounts per CSM - cut for high-touch Tier-2 onboarding
A59: RepCTC | B59: Field sales rep monthly CTC (incl. fuel) | C59: Researched | D59: M | E59: R5: Payscale Patna field sales ~Rs20k base; PhonePe postings Rs18-25k + Rs4-4.5k fuel
A60: RepTravel | B60: Rep intercity travel + demo material per month | C60: Assumption | D60: L | E60: R5: per-km allowance not found
A61: SalesOverheadPct | B61: Sales overhead loading on rep cost (manager, incentives, recruiting, tools) | C61: Assumption | D61: L | E61: R5: bottom-up CAC adds x1.3 / x1.2 / x1.0 for manager overhead plus an incentive; peers load CAC with 25-40% | F61: Audit 2026-10-22: new. Puts CAC inside the PS's Rs15-30k range
A62: PilotsPerRepMonth | B62: Pilots started per rep per month (yearly avg) | C62: Assumption | D62: L | E62: R5: SaaStr 20-50 deals/month is inside sales; cut for in-person Tier-2 demos; peak Mar-Jun
A63: PilotConv | B63: Pilot-to-paid conversion | C63: Researched | D63: L | E63: R5: trial-to-paid 8% median / 18.2% opt-in / 48.8% opt-out (Userpilot 2026); assisted-pilot benchmark not found
A64: PilotMonths | B64: Free pilot length | C64: Assumption | D64: M | E64: FINANCE_PLAN s.3.2
A65: PilotSetupCost | B65: Retro-pilot setup (import last year's Excel; show who left) | C65: Assumption | D65: L | E65: GTM design: light pilot; full onboarding only after conversion | F65: Primary research needed
A66: OnboardBase | B66: Onboarding cost per institute (mid) | C66: Guide | D66: L | E66: Case brief Rs5-10k; low-tech institutes higher
A67: MarketingPerPaid | B67: Marketing spend per paid institute | C67: Assumption | D67: L
A68: ChannelCommission | B68: Channel-partner commission (share of year-1 revenue) | C68: Assumption | D68: L | E68: FINANCE_PLAN s.3.2: 15-20% of year-1 revenue, 30% upper bound | F68: Used for the channel-vs-field comparison in Unit_Econ
A69: ChurnInSeason | B69: Monthly logo churn for monthly payers | C69: Researched | D69: L | E69: R5: ChartMogul 6.1%/month at ARPA <$25 (2022); eChai India SMB 3-5%; SaaS Capital 2025 GRR 90%/yr | F69: Applied only to institutes not on annual prepay
A70: RenewalSpike | B70: Non-renewal at session end (annual) | C70: Assumption | D70: L | E70: R5: no benchmark found - answers the judges' post-exam churn question | F70: Spread over renewal months
A71: MinRenewTenure | B71: Months a customer must have paid before the first renewal decision | C71: Structural | D71: M | E71: A customer signed in May cannot fail to renew in June; the first renewal is at the next session start | F71: Audit 2026-10-22: new. Fixes the renewal timing in Unit_Econ
A72: DiscountRate | B72: Discount rate for LTV | C72: Structural | D72: M | E72: Early-stage cost of capital convention
A73: StartMonth | B73: Paid start month (1 = April) | C73: Structural | D73: M | E73: Sales peak Mar-Jun; paid from May after a 1-month pilot
A74: Founders | B74: Founders drawing a stipend | C74: Assumption | D74: M | E74: Owner decision
A75: FounderStipend | B75: Founder stipend per month | C75: Assumption | D75: M | E75: Owner decision
A76: EngineersY1 | B76: Engineers in year 1 | C76: Assumption | D76: M | F76: Hiring plan is a decision, so Bear = Base = Bull
A77: EngineerCTC | B77: Engineer monthly CTC | C77: Researched | D77: L | E77: R5: Glassdoor Jaipur Rs6L/yr; Indore Rs6-8L/yr (1-3 yrs)
A78: ToolsOpex | B78: Tools / office / legal per month | C78: Assumption | D78: L
A79: G_Students | B79: Guide: students | C79: Guide | D79: H | E79: Case brief
A80: G_Fee | B80: Guide: annual fee per student | C80: Guide | D80: H | E80: Case brief | F80: Used for the PS's own platform-cost-as-%-of-fee figure
A81: G_Dropout | B81: Guide: dropout rate | C81: Guide | D81: H | E81: Case brief
A82: G_RemainingFee | B82: Guide: remaining fee per dropout | C82: Guide | D82: H | E82: Case brief
A83: G_Prevent | B83: Guide: share of dropouts prevented | C83: Guide | D83: H | E83: Case brief
A84: G_Price | B84: Guide: price per student per month | C84: Guide | D84: H | E84: Case brief
A85: G_Months | B85: Guide: billing months per year | C85: Guide | D85: H | E85: Case brief
A86: G_Infra | B86: Guide: infra + AI per student per month | C86: Guide | D86: H | E86: Case brief
A87: G_Support | B87: Guide: support per institute per month | C87: Guide | D87: H | E87: Case brief
A88: G_CAC | B88: Guide: CAC | C88: Guide | D88: H | E88: Case brief
A89: G_Onboard | B89: Guide: onboarding | C89: Guide | D89: H | E89: Case brief
A90: G_Churn | B90: Guide: monthly churn | C90: Guide | D90: H | E90: Case brief
A91: SegMix_S | B91: Share of new institutes that are Small | C91: Assumption | D91: L | E91: Size distribution of Tier-2/3 institutes not found (R7 gap); skewed to small | F91: Bear = more small institutes
A92: SegMix_M | B92: Share of new institutes that are Mid | C92: Assumption | D92: L | E92: As above | F92: The three shares must sum to 100%
A93: SegMix_L | B93: Share of new institutes that are Large | C93: Assumption | D93: L | E93: As above | F93: The three shares must sum to 100%
A94: RepsY1 | B94: Field sales reps in year 1 | C94: Assumption | D94: M | E94: Owner decision; the founders also sell | F94: Decision: Bear = Base = Bull
A95: RepsY2 | B95: Field sales reps in year 2 | C95: Assumption | D95: M | E95: Owner decision | F95: Audit: held at 1. At 8% of the market one rep exhausts the cap in about 3 years; a second rep only helps after the territory grows
A96: RepsY3 | B96: Field sales reps in year 3 | C96: Assumption | D96: M | E96: Owner decision; capped by the addressable market, see Projection | F96: Audit: held at 1 for the same reason. Growth beyond this needs new territory or exams, not more reps
A97: EngineersY2 | B97: Engineers in year 2 | C97: Assumption | D97: M | E97: Owner decision | F97: Decision
A98: EngineersY3 | B98: Engineers in year 3 | C98: Assumption | D98: M | E98: Owner decision | F98: Decision
A99: RDFloorPct | B99: Minimum product and engineering spend as a share of revenue | C99: Assumption | D99: L | E99: CFO convention: a SaaS business spends well over 10% of revenue on product and about 8% on overheads as it scales | F99: Costs must scale with revenue: planned engineers are the floor, this share of revenue is the other floor
A100: GAFloorPct | B100: Minimum founders' and general costs as a share of revenue | C100: Assumption | D100: L | E100: CFO convention: a SaaS business spends well over 10% of revenue on product and about 8% on overheads as it scales | F100: Audit 2026-10-22: stops a fast-growth case from showing an unrealistic margin
A101: SalaryInflation | B101: Annual salary and cost inflation | C101: Assumption | D101: M | E101: Indian wage inflation convention | F101: Applied from year 2
...

Sheet Engine
A1: Engine — re-runs the full chain for scenarios, the stress test, the tornado and the churn grid. Do not edit.
B2: Case | D2: Live S | E2: Live M | F2: Live L | G2: Bear S | H2: Bear M | I2: Bear L | J2: Base S | K2: Base M | L2: Base L | M2: Bull S | N2: Bull M | O2: Bull L | P2: Stress S | Q2: Stress M | R2: Stress L | S2: T ListPrice bear | T2: T ListPrice bull | U2: T Fee bear | V2: T Fee bull | W2: T DropoutRate bear | X2: T DropoutRate bull | Y2: T UpfrontShare bear | Z2: T UpfrontShare bull | AA2: T NInstalments bear | AB2: T NInstalments bull | AC2: T InterventionSuccess bear | AD2: T InterventionSuccess bull | AE2: T Recall_Minor bear | AF2: T Recall_Minor bull | AG2: T Precision bear | AH2: T Precision bull | AI2: T InterventionMinutes bear | AJ2: T InterventionMinutes bull | AK2: T BlindMonths bear | AL2: T BlindMonths bull | AM2: T AdmissionUplift bear | AN2: T AdmissionUplift bull | AO2: T ITCShare bear | AP2: T ITCShare bull | AQ2: T ChurnInSeason bear | AR2: T ChurnInSeason bull | AS2: T RenewalSpike bear | AT2: T RenewalSpike bull | AU2: T PilotConv bear | AV2: T PilotConv bull | AW2: T PilotsPerRepMonth bear | AX2: T PilotsPerRepMonth bull | AY2: T InstPerCSM bear | AZ2: T InstPerCSM bull | BA2: Churn grid 1 | BB2: Churn grid 2 | BC2: Churn grid 3 | BD2: Churn grid 4 | BE2: Churn grid 5
B3: Segment | D3: S | E3: M | F3: L | G3: S | H3: M | I3: L | J3: S | K3: M | L3: L | M3: S | N3: M | O3: L | P3: S | Q3: M | R3: L | S3: M | T3: M | U3: M | V3: M | W3: M | X3: M | Y3: M | Z3: M | AA3: M | AB3: M | AC3: M | AD3: M | AE3: M | AF3: M | AG3: M | AH3: M | AI3: M | AJ3: M | AK3: M | AL3: M | AM3: M | AN3: M | AO3: M | AP3: M | AQ3: M | AR3: M | AS3: M | AT3: M | AU3: M | AV3: M | AW3: M | AX3: M | AY3: M | AZ3: M | BA3: M | BB3: M | BC3: M | BD3: M | BE3: M
B4: Scenario (1-3) | D4: =Scenario | E4: =Scenario | F4: =Scenario | G4: 1 | H4: 1 | I4: 1 | J4: 2 | K4: 2 | L4: 2 | M4: 3 | N4: 3 | O4: 3 | P4: 1 | Q4: 1 | R4: 1 | S4: 2 | T4: 2 | U4: 2 | V4: 2 | W4: 2 | X4: 2 | Y4: 2 | Z4: 2 | AA4: 2 | AB4: 2 | AC4: 2 | AD4: 2 | AE4: 2 | AF4: 2 | AG4: 2 | AH4: 2 | AI4: 2 | AJ4: 2 | AK4: 2 | AL4: 2 | AM4: 2 | AN4: 2 | AO4: 2 | AP4: 2 | AQ4: 2 | AR4: 2 | AS4: 2 | AT4: 2 | AU4: 2 | AV4: 2 | AW4: 2 | AX4: 2 | AY4: 2 | AZ4: 2 | BA4: =Scenario | BB4: =Scenario | BC4: =Scenario | BD4: =Scenario | BE4: =Scenario
B5: Override input | S5: ListPrice | T5: ListPrice | U5: Fee | V5: Fee | W5: DropoutRate | X5: DropoutRate | Y5: UpfrontShare | Z5: UpfrontShare | AA5: NInstalments | AB5: NInstalments | AC5: InterventionSuccess | AD5: InterventionSuccess | AE5: Recall_Minor | AF5: Recall_Minor | AG5: Precision | AH5: Precision | AI5: InterventionMinutes | AJ5: InterventionMinutes | AK5: BlindMonths | AL5: BlindMonths | AM5: AdmissionUplift | AN5: AdmissionUplift | AO5: ITCShare | AP5: ITCShare | AQ5: ChurnInSeason | AR5: ChurnInSeason | AS5: RenewalSpike | AT5: RenewalSpike | AU5: PilotConv | AV5: PilotConv | AW5: PilotsPerRepMonth | AX5: PilotsPerRepMonth | AY5: InstPerCSM | AZ5: InstPerCSM | BA5: ChurnInSeason | BB5: ChurnInSeason | BC5: ChurnInSeason | BD5: ChurnInSeason | BE5: ChurnInSeason
B6: Override value | S6: =Assumptions!$D$38 | T6: =Assumptions!$F$38 | U6: =Assumptions!$D$10 | V6: =Assumptions!$F$10 | W6: =Assumptions!$D$16 | X6: =Assumptions!$F$16 | Y6: =Assumptions!$D$17 | Z6: =Assumptions!$F$17 | AA6: =Assumptions!$D$18 | AB6: =Assumptions!$F$18 | AC6: =Assumptions!$D$28 | AD6: =Assumptions!$F$28 | AE6: =Assumptions!$D$24 | AF6: =Assumptions!$F$24 | AG6: =Assumptions!$D$26 | AH6: =Assumptions!$F$26 | AI6: =Assumptions!$D$33 | AJ6: =Assumptions!$F$33 | AK6: =Assumptions!$D$21 | AL6: =Assumptions!$F$21 | AM6: =Assumptions!$D$29 | AN6: =Assumptions!$F$29 | AO6: =Assumptions!$D$36 | AP6: =Assumptions!$F$36 | AQ6: =Assumptions!$D$74 | AR6: =Assumptions!$F$74 | AS6: =Assumptions!$D$75 | AT6: =Assumptions!$F$75 | AU6: =Assumptions!$D$68 | AV6: =Assumptions!$F$68 | AW6: =Assumptions!$D$67 | AX6: =Assumptions!$F$67 | AY6: =Assumptions!$D$63 | AZ6: =Assumptions!$F$63 | BA6: =Sensitivity!B$37 | BB6: =Sensitivity!C$37 | BC6: =Sensitivity!D$37 | BD6: =Sensitivity!E$37 | BE6: =Sensitivity!F$37
B7: Inputs flexed: DRIVERS or ALL | D7: DRIVERS | E7: DRIVERS | F7: DRIVERS | G7: DRIVERS | H7: DRIVERS | I7: DRIVERS | J7: DRIVERS | K7: DRIVERS | L7: DRIVERS | M7: DRIVERS | N7: DRIVERS | O7: DRIVERS | P7: ALL | Q7: ALL | R7: ALL | S7: DRIVERS | T7: DRIVERS | U7: DRIVERS | V7: DRIVERS | W7: DRIVERS | X7: DRIVERS | Y7: DRIVERS | Z7: DRIVERS | AA7: DRIVERS | AB7: DRIVERS | AC7: DRIVERS | AD7: DRIVERS | AE7: DRIVERS | AF7: DRIVERS | AG7: DRIVERS | AH7: DRIVERS | AI7: DRIVERS | AJ7: DRIVERS | AK7: DRIVERS | AL7: DRIVERS | AM7: DRIVERS | AN7: DRIVERS | AO7: DRIVERS | AP7: DRIVERS | AQ7: DRIVERS | AR7: DRIVERS | AS7: DRIVERS | AT7: DRIVERS | AU7: DRIVERS | AV7: DRIVERS | AW7: DRIVERS | AX7: DRIVERS | AY7: DRIVERS | AZ7: DRIVERS | BA7: DRIVERS | BB7: DRIVERS | BC7: DRIVERS | BD7: DRIVERS | BE7: DRIVERS
B8: ReportsPerStudentMonth | D8: =IF($D$5="ReportsPerStudentMonth",$D$6,IF(OR($D$7="ALL",Assumptions!$N$48="Y"),INDEX(Assumptions!$D$48:$F$48,$D$4),Assumptions!$E$48)) | E8: =IF($E$5="ReportsPerStudentMonth",$E$6,IF(OR($E$7="ALL",Assumptions!$N$48="Y"),INDEX(Assumptions!$D$48:$F$48,$E$4),Assumptions!$E$48)) | F8: =IF($F$5="ReportsPerStudentMonth",$F$6,IF(OR($F$7="ALL",Assumptions!$N$48="Y"),INDEX(Assumptions!$D$48:$F$48,$F$4),Assumptions!$E$48)) | G8: =IF($G$5="ReportsPerStudentMonth",$G$6,IF(OR($G$7="ALL",Assumptions!$N$48="Y"),INDEX(Assumptions!$D$48:$F$48,$G$4),Assumptions!$E$48)) | H8: =IF($H$5="ReportsPerStudentMonth",$H$6,IF(OR($H$7="ALL",Assumptions!$N$48="Y"),INDEX(Assumptions!$D$48:$F$48,$H$4),Assumptions!$E$48)) | I8: =IF($I$5="ReportsPerStudentMonth",$I$6,IF(OR($I$7="ALL",Assumptions!$N$48="Y"),INDEX(Assumptions!$D$48:$F$48,$I$4),Assumptions!$E$48)) | J8: =IF($J$5="ReportsPerStudentMonth",$J$6,IF(OR($J$7="ALL",Assumptions!$N$48="Y"),INDEX(Assumptions!$D$48:$F$48,$J$4),Assumptions!$E$48)) | K8: =IF($K$5="ReportsPerStudentMonth",$K$6,IF(OR($K$7="ALL",Assumptions!$N$48="Y"),INDEX(Assumptions!$D$48:$F$48,$K$4),Assumptions!$E$48)) | L8: =IF($L$5="ReportsPerStudentMonth",$L$6,IF(OR($L$7="ALL",Assumptions!$N$48="Y"),INDEX(Assumptions!$D$48:$F$48,$L$4),Assumptions!$E$48)) | M8: =IF($M$5="ReportsPerStudentMonth",$M$6,IF(OR($M$7="ALL",Assumptions!$N$48="Y"),INDEX(Assumptions!$D$48:$F$48,$M$4),Assumptions!$E$48)) | N8: =IF($N$5="ReportsPerStudentMonth",$N$6,IF(OR($N$7="ALL",Assumptions!$N$48="Y"),INDEX(Assumptions!$D$48:$F$48,$N$4),Assumptions!$E$48)) | O8: =IF($O$5="ReportsPerStudentMonth",$O$6,IF(OR($O$7="ALL",Assumptions!$N$48="Y"),INDEX(Assumptions!$D$48:$F$48,$O$4),Assumptions!$E$48)) | P8: =IF($P$5="ReportsPerStudentMonth",$P$6,IF(OR($P$7="ALL",Assumptions!$N$48="Y"),INDEX(Assumptions!$D$48:$F$48,$P$4),Assumptions!$E$48)) | Q8: =IF($Q$5="ReportsPerStudentMonth",$Q$6,IF(OR($Q$7="ALL",Assumptions!$N$48="Y"),INDEX(Assumptions!$D$48:$F$48,$Q$4),Assumptions!$E$48)) | R8: =IF($R$5="ReportsPerStudentMonth",$R$6,IF(OR($R$7="ALL",Assumptions!$N$48="Y"),INDEX(Assumptions!$D$48:$F$48,$R$4),Assumptions!$E$48)) | S8: =IF($S$5="ReportsPerStudentMonth",$S$6,IF(OR($S$7="ALL",Assumptions!$N$48="Y"),INDEX(Assumptions!$D$48:$F$48,$S$4),Assumptions!$E$48)) | T8: =IF($T$5="ReportsPerStudentMonth",$T$6,IF(OR($T$7="ALL",Assumptions!$N$48="Y"),INDEX(Assumptions!$D$48:$F$48,$T$4),Assumptions!$E$48)) | U8: =IF($U$5="ReportsPerStudentMonth",$U$6,IF(OR($U$7="ALL",Assumptions!$N$48="Y"),INDEX(Assumptions!$D$48:$F$48,$U$4),Assumptions!$E$48)) | V8: =IF($V$5="ReportsPerStudentMonth",$V$6,IF(OR($V$7="ALL",Assumptions!$N$48="Y"),INDEX(Assumptions!$D$48:$F$48,$V$4),Assumptions!$E$48)) | W8: =IF($W$5="ReportsPerStudentMonth",$W$6,IF(OR($W$7="ALL",Assumptions!$N$48="Y"),INDEX(Assumptions!$D$48:$F$48,$W$4),Assumptions!$E$48)) | X8: =IF($X$5="ReportsPerStudentMonth",$X$6,IF(OR($X$7="ALL",Assumptions!$N$48="Y"),INDEX(Assumptions!$D$48:$F$48,$X$4),Assumptions!$E$48)) | Y8: =IF($Y$5="ReportsPerStudentMonth",$Y$6,IF(OR($Y$7="ALL",Assumptions!$N$48="Y"),INDEX(Assumptions!$D$48:$F$48,$Y$4),Assumptions!$E$48)) | Z8: =IF($Z$5="ReportsPerStudentMonth",$Z$6,IF(OR($Z$7="ALL",Assumptions!$N$48="Y"),INDEX(Assumptions!$D$48:$F$48,$Z$4),Assumptions!$E$48)) | AA8: =IF($AA$5="ReportsPerStudentMonth",$AA$6,IF(OR($AA$7="ALL",Assumptions!$N$48="Y"),INDEX(Assumptions!$D$48:$F$48,$AA$4),Assumptions!$E$48)) | AB8: =IF($AB$5="ReportsPerStudentMonth",$AB$6,IF(OR($AB$7="ALL",Assumptions!$N$48="Y"),INDEX(Assumptions!$D$48:$F$48,$AB$4),Assumptions!$E$48)) | AC8: =IF($AC$5="ReportsPerStudentMonth",$AC$6,IF(OR($AC$7="ALL",Assumptions!$N$48="Y"),INDEX(Assumptions!$D$48:$F$48,$AC$4),Assumptions!$E$48)) | AD8: =IF($AD$5="ReportsPerStudentMonth",$AD$6,IF(OR($AD$7="ALL",Assumptions!$N$48="Y"),INDEX(Assumptions!$D$48:$F$48,$AD$4),Assumptions!$E$48)) | AE8: =IF($AE$5="ReportsPerStudentMonth",$AE$6,IF(OR($AE$7="ALL",Assumptions!$N$48="Y"),INDEX(Assumptions!$D$48:$F$48,$AE$4),Assumptions!$E$48)) | AF8: =IF($AF$5="ReportsPerStudentMonth",$AF$6,IF(OR($AF$7="ALL",Assumptions!$N$48="Y"),INDEX(Assumptions!$D$48:$F$48,$AF$4),Assumptions!$E$48)) | AG8: =IF($AG$5="ReportsPerStudentMonth",$AG$6,IF(OR($AG$7="ALL",Assumptions!$N$48="Y"),INDEX(Assumptions!$D$48:$F$48,$AG$4),Assumptions!$E$48)) | AH8: =IF($AH$5="ReportsPerStudentMonth",$AH$6,IF(OR($AH$7="ALL",Assumptions!$N$48="Y"),INDEX(Assumptions!$D$48:$F$48,$AH$4),Assumptions!$E$48)) | AI8: =IF($AI$5="ReportsPerStudentMonth",$AI$6,IF(OR($AI$7="ALL",Assumptions!$N$48="Y"),INDEX(Assumptions!$D$48:$F$48,$AI$4),Assumptions!$E$48)) | AJ8: =IF($AJ$5="ReportsPerStudentMonth",$AJ$6,IF(OR($AJ$7="ALL",Assumptions!$N$48="Y"),INDEX(Assumptions!$D$48:$F$48,$AJ$4),Assumptions!$E$48)) | AK8: =IF($AK$5="ReportsPerStudentMonth",$AK$6,IF(OR($AK$7="ALL",Assumptions!$N$48="Y"),INDEX(Assumptions!$D$48:$F$48,$AK$4),Assumptions!$E$48)) | AL8: =IF($AL$5="ReportsPerStudentMonth",$AL$6,IF(OR($AL$7="ALL",Assumptions!$N$48="Y"),INDEX(Assumptions!$D$48:$F$48,$AL$4),Assumptions!$E$48)) | AM8: =IF($AM$5="ReportsPerStudentMonth",$AM$6,IF(OR($AM$7="ALL",Assumptions!$N$48="Y"),INDEX(Assumptions!$D$48:$F$48,$AM$4),Assumptions!$E$48)) | AN8: =IF($AN$5="ReportsPerStudentMonth",$AN$6,IF(OR($AN$7="ALL",Assumptions!$N$48="Y"),INDEX(Assumptions!$D$48:$F$48,$AN$4),Assumptions!$E$48)) | AO8: =IF($AO$5="ReportsPerStudentMonth",$AO$6,IF(OR($AO$7="ALL",Assumptions!$N$48="Y"),INDEX(Assumptions!$D$48:$F$48,$AO$4),Assumptions!$E$48)) | AP8: =IF($AP$5="ReportsPerStudentMonth",$AP$6,IF(OR($AP$7="ALL",Assumptions!$N$48="Y"),INDEX(Assumptions!$D$48:$F$48,$AP$4),Assumptions!$E$48)) | AQ8: =IF($AQ$5="ReportsPerStudentMonth",$AQ$6,IF(OR($AQ$7="ALL",Assumptions!$N$48="Y"),INDEX(Assumptions!$D$48:$F$48,$AQ$4),Assumptions!$E$48)) | AR8: =IF($AR$5="ReportsPerStudentMonth",$AR$6,IF(OR($AR$7="ALL",Assumptions!$N$48="Y"),INDEX(Assumptions!$D$48:$F$48,$AR$4),Assumptions!$E$48)) | AS8: =IF($AS$5="ReportsPerStudentMonth",$AS$6,IF(OR($AS$7="ALL",Assumptions!$N$48="Y"),INDEX(Assumptions!$D$48:$F$48,$AS$4),Assumptions!$E$48)) | AT8: =IF($AT$5="ReportsPerStudentMonth",$AT$6,IF(OR($AT$7="ALL",Assumptions!$N$48="Y"),INDEX(Assumptions!$D$48:$F$48,$AT$4),Assumptions!$E$48)) | AU8: =IF($AU$5="ReportsPerStudentMonth",$AU$6,IF(OR($AU$7="ALL",Assumptions!$N$48="Y"),INDEX(Assumptions!$D$48:$F$48,$AU$4),Assumptions!$E$48)) | AV8: =IF($AV$5="ReportsPerStudentMonth",$AV$6,IF(OR($AV$7="ALL",Assumptions!$N$48="Y"),INDEX(Assumptions!$D$48:$F$48,$AV$4),Assumptions!$E$48)) | AW8: =IF($AW$5="ReportsPerStudentMonth",$AW$6,IF(OR($AW$7="ALL",Assumptions!$N$48="Y"),INDEX(Assumptions!$D$48:$F$48,$AW$4),Assumptions!$E$48)) | AX8: =IF($AX$5="ReportsPerStudentMonth",$AX$6,IF(OR($AX$7="ALL",Assumptions!$N$48="Y"),INDEX(Assumptions!$D$48:$F$48,$AX$4),Assumptions!$E$48)) | AY8: =IF($AY$5="ReportsPerStudentMonth",$AY$6,IF(OR($AY$7="ALL",Assumptions!$N$48="Y"),INDEX(Assumptions!$D$48:$F$48,$AY$4),Assumptions!$E$48)) | AZ8: =IF($AZ$5="ReportsPerStudentMonth",$AZ$6,IF(OR($AZ$7="ALL",Assumptions!$N$48="Y"),INDEX(Assumptions!$D$48:$F$48,$AZ$4),Assumptions!$E$48)) | BA8: =IF($BA$5="ReportsPerStudentMonth",$BA$6,IF(OR($BA$7="ALL",Assumptions!$N$48="Y"),INDEX(Assumptions!$D$48:$F$48,$BA$4),Assumptions!$E$48)) | BB8: =IF($BB$5="ReportsPerStudentMonth",$BB$6,IF(OR($BB$7="ALL",Assumptions!$N$48="Y"),INDEX(Assumptions!$D$48:$F$48,$BB$4),Assumptions!$E$48)) | BC8: =IF($BC$5="ReportsPerStudentMonth",$BC$6,IF(OR($BC$7="ALL",Assumptions!$N$48="Y"),INDEX(Assumptions!$D$48:$F$48,$BC$4),Assumptions!$E$48)) | BD8: =IF($BD$5="ReportsPerStudentMonth",$BD$6,IF(OR($BD$7="ALL",Assumptions!$N$48="Y"),INDEX(Assumptions!$D$48:$F$48,$BD$4),Assumptions!$E$48)) | BE8: =IF($BE$5="ReportsPerStudentMonth",$BE$6,IF(OR($BE$7="ALL",Assumptions!$N$48="Y"),INDEX(Assumptions!$D$48:$F$48,$BE$4),Assumptions!$E$48))
B9: TokensInPerReport | D9: =IF($D$5="TokensInPerReport",$D$6,IF(OR($D$7="ALL",Assumptions!$N$49="Y"),INDEX(Assumptions!$D$49:$F$49,$D$4),Assumptions!$E$49)) | E9: =IF($E$5="TokensInPerReport",$E$6,IF(OR($E$7="ALL",Assumptions!$N$49="Y"),INDEX(Assumptions!$D$49:$F$49,$E$4),Assumptions!$E$49)) | F9: =IF($F$5="TokensInPerReport",$F$6,IF(OR($F$7="ALL",Assumptions!$N$49="Y"),INDEX(Assumptions!$D$49:$F$49,$F$4),Assumptions!$E$49)) | G9: =IF($G$5="TokensInPerReport",$G$6,IF(OR($G$7="ALL",Assumptions!$N$49="Y"),INDEX(Assumptions!$D$49:$F$49,$G$4),Assumptions!$E$49)) | H9: =IF($H$5="TokensInPerReport",$H$6,IF(OR($H$7="ALL",Assumptions!$N$49="Y"),INDEX(Assumptions!$D$49:$F$49,$H$4),Assumptions!$E$49)) | I9: =IF($I$5="TokensInPerReport",$I$6,IF(OR($I$7="ALL",Assumptions!$N$49="Y"),INDEX(Assumptions!$D$49:$F$49,$I$4),Assumptions!$E$49)) | J9: =IF($J$5="TokensInPerReport",$J$6,IF(OR($J$7="ALL",Assumptions!$N$49="Y"),INDEX(Assumptions!$D$49:$F$49,$J$4),Assumptions!$E$49)) | K9: =IF($K$5="TokensInPerReport",$K$6,IF(OR($K$7="ALL",Assumptions!$N$49="Y"),INDEX(Assumptions!$D$49:$F$49,$K$4),Assumptions!$E$49)) | L9: =IF($L$5="TokensInPerReport",$L$6,IF(OR($L$7="ALL",Assumptions!$N$49="Y"),INDEX(Assumptions!$D$49:$F$49,$L$4),Assumptions!$E$49)) | M9: =IF($M$5="TokensInPerReport",$M$6,IF(OR($M$7="ALL",Assumptions!$N$49="Y"),INDEX(Assumptions!$D$49:$F$49,$M$4),Assumptions!$E$49)) | N9: =IF($N$5="TokensInPerReport",$N$6,IF(OR($N$7="ALL",Assumptions!$N$49="Y"),INDEX(Assumptions!$D$49:$F$49,$N$4),Assumptions!$E$49)) | O9: =IF($O$5="TokensInPerReport",$O$6,IF(OR($O$7="ALL",Assumptions!$N$49="Y"),INDEX(Assumptions!$D$49:$F$49,$O$4),Assumptions!$E$49)) | P9: =IF($P$5="TokensInPerReport",$P$6,IF(OR($P$7="ALL",Assumptions!$N$49="Y"),INDEX(Assumptions!$D$49:$F$49,$P$4),Assumptions!$E$49)) | Q9: =IF($Q$5="TokensInPerReport",$Q$6,IF(OR($Q$7="ALL",Assumptions!$N$49="Y"),INDEX(Assumptions!$D$49:$F$49,$Q$4),Assumptions!$E$49)) | R9: =IF($R$5="TokensInPerReport",$R$6,IF(OR($R$7="ALL",Assumptions!$N$49="Y"),INDEX(Assumptions!$D$49:$F$49,$R$4),Assumptions!$E$49)) | S9: =IF($S$5="TokensInPerReport",$S$6,IF(OR($S$7="ALL",Assumptions!$N$49="Y"),INDEX(Assumptions!$D$49:$F$49,$S$4),Assumptions!$E$49)) | T9: =IF($T$5="TokensInPerReport",$T$6,IF(OR($T$7="ALL",Assumptions!$N$49="Y"),INDEX(Assumptions!$D$49:$F$49,$T$4),Assumptions!$E$49)) | U9: =IF($U$5="TokensInPerReport",$U$6,IF(OR($U$7="ALL",Assumptions!$N$49="Y"),INDEX(Assumptions!$D$49:$F$49,$U$4),Assumptions!$E$49)) | V9: =IF($V$5="TokensInPerReport",$V$6,IF(OR($V$7="ALL",Assumptions!$N$49="Y"),INDEX(Assumptions!$D$49:$F$49,$V$4),Assumptions!$E$49)) | W9: =IF($W$5="TokensInPerReport",$W$6,IF(OR($W$7="ALL",Assumptions!$N$49="Y"),INDEX(Assumptions!$D$49:$F$49,$W$4),Assumptions!$E$49)) | X9: =IF($X$5="TokensInPerReport",$X$6,IF(OR($X$7="ALL",Assumptions!$N$49="Y"),INDEX(Assumptions!$D$49:$F$49,$X$4),Assumptions!$E$49)) | Y9: =IF($Y$5="TokensInPerReport",$Y$6,IF(OR($Y$7="ALL",Assumptions!$N$49="Y"),INDEX(Assumptions!$D$49:$F$49,$Y$4),Assumptions!$E$49)) | Z9: =IF($Z$5="TokensInPerReport",$Z$6,IF(OR($Z$7="ALL",Assumptions!$N$49="Y"),INDEX(Assumptions!$D$49:$F$49,$Z$4),Assumptions!$E$49)) | AA9: =IF($AA$5="TokensInPerReport",$AA$6,IF(OR($AA$7="ALL",Assumptions!$N$49="Y"),INDEX(Assumptions!$D$49:$F$49,$AA$4),Assumptions!$E$49)) | AB9: =IF($AB$5="TokensInPerReport",$AB$6,IF(OR($AB$7="ALL",Assumptions!$N$49="Y"),INDEX(Assumptions!$D$49:$F$49,$AB$4),Assumptions!$E$49)) | AC9: =IF($AC$5="TokensInPerReport",$AC$6,IF(OR($AC$7="ALL",Assumptions!$N$49="Y"),INDEX(Assumptions!$D$49:$F$49,$AC$4),Assumptions!$E$49)) | AD9: =IF($AD$5="TokensInPerReport",$AD$6,IF(OR($AD$7="ALL",Assumptions!$N$49="Y"),INDEX(Assumptions!$D$49:$F$49,$AD$4),Assumptions!$E$49)) | AE9: =IF($AE$5="TokensInPerReport",$AE$6,IF(OR($AE$7="ALL",Assumptions!$N$49="Y"),INDEX(Assumptions!$D$49:$F$49,$AE$4),Assumptions!$E$49)) | AF9: =IF($AF$5="TokensInPerReport",$AF$6,IF(OR($AF$7="ALL",Assumptions!$N$49="Y"),INDEX(Assumptions!$D$49:$F$49,$AF$4),Assumptions!$E$49)) | AG9: =IF($AG$5="TokensInPerReport",$AG$6,IF(OR($AG$7="ALL",Assumptions!$N$49="Y"),INDEX(Assumptions!$D$49:$F$49,$AG$4),Assumptions!$E$49)) | AH9: =IF($AH$5="TokensInPerReport",$AH$6,IF(OR($AH$7="ALL",Assumptions!$N$49="Y"),INDEX(Assumptions!$D$49:$F$49,$AH$4),Assumptions!$E$49)) | AI9: =IF($AI$5="TokensInPerReport",$AI$6,IF(OR($AI$7="ALL",Assumptions!$N$49="Y"),INDEX(Assumptions!$D$49:$F$49,$AI$4),Assumptions!$E$49)) | AJ9: =IF($AJ$5="TokensInPerReport",$AJ$6,IF(OR($AJ$7="ALL",Assumptions!$N$49="Y"),INDEX(Assumptions!$D$49:$F$49,$AJ$4),Assumptions!$E$49)) | AK9: =IF($AK$5="TokensInPerReport",$AK$6,IF(OR($AK$7="ALL",Assumptions!$N$49="Y"),INDEX(Assumptions!$D$49:$F$49,$AK$4),Assumptions!$E$49)) | AL9: =IF($AL$5="TokensInPerReport",$AL$6,IF(OR($AL$7="ALL",Assumptions!$N$49="Y"),INDEX(Assumptions!$D$49:$F$49,$AL$4),Assumptions!$E$49)) | AM9: =IF($AM$5="TokensInPerReport",$AM$6,IF(OR($AM$7="ALL",Assumptions!$N$49="Y"),INDEX(Assumptions!$D$49:$F$49,$AM$4),Assumptions!$E$49)) | AN9: =IF($AN$5="TokensInPerReport",$AN$6,IF(OR($AN$7="ALL",Assumptions!$N$49="Y"),INDEX(Assumptions!$D$49:$F$49,$AN$4),Assumptions!$E$49)) | AO9: =IF($AO$5="TokensInPerReport",$AO$6,IF(OR($AO$7="ALL",Assumptions!$N$49="Y"),INDEX(Assumptions!$D$49:$F$49,$AO$4),Assumptions!$E$49)) | AP9: =IF($AP$5="TokensInPerReport",$AP$6,IF(OR($AP$7="ALL",Assumptions!$N$49="Y"),INDEX(Assumptions!$D$49:$F$49,$AP$4),Assumptions!$E$49)) | AQ9: =IF($AQ$5="TokensInPerReport",$AQ$6,IF(OR($AQ$7="ALL",Assumptions!$N$49="Y"),INDEX(Assumptions!$D$49:$F$49,$AQ$4),Assumptions!$E$49)) | AR9: =IF($AR$5="TokensInPerReport",$AR$6,IF(OR($AR$7="ALL",Assumptions!$N$49="Y"),INDEX(Assumptions!$D$49:$F$49,$AR$4),Assumptions!$E$49)) | AS9: =IF($AS$5="TokensInPerReport",$AS$6,IF(OR($AS$7="ALL",Assumptions!$N$49="Y"),INDEX(Assumptions!$D$49:$F$49,$AS$4),Assumptions!$E$49)) | AT9: =IF($AT$5="TokensInPerReport",$AT$6,IF(OR($AT$7="ALL",Assumptions!$N$49="Y"),INDEX(Assumptions!$D$49:$F$49,$AT$4),Assumptions!$E$49)) | AU9: =IF($AU$5="TokensInPerReport",$AU$6,IF(OR($AU$7="ALL",Assumptions!$N$49="Y"),INDEX(Assumptions!$D$49:$F$49,$AU$4),Assumptions!$E$49)) | AV9: =IF($AV$5="TokensInPerReport",$AV$6,IF(OR($AV$7="ALL",Assumptions!$N$49="Y"),INDEX(Assumptions!$D$49:$F$49,$AV$4),Assumptions!$E$49)) | AW9: =IF($AW$5="TokensInPerReport",$AW$6,IF(OR($AW$7="ALL",Assumptions!$N$49="Y"),INDEX(Assumptions!$D$49:$F$49,$AW$4),Assumptions!$E$49)) | AX9: =IF($AX$5="TokensInPerReport",$AX$6,IF(OR($AX$7="ALL",Assumptions!$N$49="Y"),INDEX(Assumptions!$D$49:$F$49,$AX$4),Assumptions!$E$49)) | AY9: =IF($AY$5="TokensInPerReport",$AY$6,IF(OR($AY$7="ALL",Assumptions!$N$49="Y"),INDEX(Assumptions!$D$49:$F$49,$AY$4),Assumptions!$E$49)) | AZ9: =IF($AZ$5="TokensInPerReport",$AZ$6,IF(OR($AZ$7="ALL",Assumptions!$N$49="Y"),INDEX(Assumptions!$D$49:$F$49,$AZ$4),Assumptions!$E$49)) | BA9: =IF($BA$5="TokensInPerReport",$BA$6,IF(OR($BA$7="ALL",Assumptions!$N$49="Y"),INDEX(Assumptions!$D$49:$F$49,$BA$4),Assumptions!$E$49)) | BB9: =IF($BB$5="TokensInPerReport",$BB$6,IF(OR($BB$7="ALL",Assumptions!$N$49="Y"),INDEX(Assumptions!$D$49:$F$49,$BB$4),Assumptions!$E$49)) | BC9: =IF($BC$5="TokensInPerReport",$BC$6,IF(OR($BC$7="ALL",Assumptions!$N$49="Y"),INDEX(Assumptions!$D$49:$F$49,$BC$4),Assumptions!$E$49)) | BD9: =IF($BD$5="TokensInPerReport",$BD$6,IF(OR($BD$7="ALL",Assumptions!$N$49="Y"),INDEX(Assumptions!$D$49:$F$49,$BD$4),Assumptions!$E$49)) | BE9: =IF($BE$5="TokensInPerReport",$BE$6,IF(OR($BE$7="ALL",Assumptions!$N$49="Y"),INDEX(Assumptions!$D$49:$F$49,$BE$4),Assumptions!$E$49))
B10: TokensOutPerReport | D10: =IF($D$5="TokensOutPerReport",$D$6,IF(OR($D$7="ALL",Assumptions!$N$50="Y"),INDEX(Assumptions!$D$50:$F$50,$D$4),Assumptions!$E$50)) | E10: =IF($E$5="TokensOutPerReport",$E$6,IF(OR($E$7="ALL",Assumptions!$N$50="Y"),INDEX(Assumptions!$D$50:$F$50,$E$4),Assumptions!$E$50)) | F10: =IF($F$5="TokensOutPerReport",$F$6,IF(OR($F$7="ALL",Assumptions!$N$50="Y"),INDEX(Assumptions!$D$50:$F$50,$F$4),Assumptions!$E$50)) | G10: =IF($G$5="TokensOutPerReport",$G$6,IF(OR($G$7="ALL",Assumptions!$N$50="Y"),INDEX(Assumptions!$D$50:$F$50,$G$4),Assumptions!$E$50)) | H10: =IF($H$5="TokensOutPerReport",$H$6,IF(OR($H$7="ALL",Assumptions!$N$50="Y"),INDEX(Assumptions!$D$50:$F$50,$H$4),Assumptions!$E$50)) | I10: =IF($I$5="TokensOutPerReport",$I$6,IF(OR($I$7="ALL",Assumptions!$N$50="Y"),INDEX(Assumptions!$D$50:$F$50,$I$4),Assumptions!$E$50)) | J10: =IF($J$5="TokensOutPerReport",$J$6,IF(OR($J$7="ALL",Assumptions!$N$50="Y"),INDEX(Assumptions!$D$50:$F$50,$J$4),Assumptions!$E$50)) | K10: =IF($K$5="TokensOutPerReport",$K$6,IF(OR($K$7="ALL",Assumptions!$N$50="Y"),INDEX(Assumptions!$D$50:$F$50,$K$4),Assumptions!$E$50)) | L10: =IF($L$5="TokensOutPerReport",$L$6,IF(OR($L$7="ALL",Assumptions!$N$50="Y"),INDEX(Assumptions!$D$50:$F$50,$L$4),Assumptions!$E$50)) | M10: =IF($M$5="TokensOutPerReport",$M$6,IF(OR($M$7="ALL",Assumptions!$N$50="Y"),INDEX(Assumptions!$D$50:$F$50,$M$4),Assumptions!$E$50)) | N10: =IF($N$5="TokensOutPerReport",$N$6,IF(OR($N$7="ALL",Assumptions!$N$50="Y"),INDEX(Assumptions!$D$50:$F$50,$N$4),Assumptions!$E$50)) | O10: =IF($O$5="TokensOutPerReport",$O$6,IF(OR($O$7="ALL",Assumptions!$N$50="Y"),INDEX(Assumptions!$D$50:$F$50,$O$4),Assumptions!$E$50)) | P10: =IF($P$5="TokensOutPerReport",$P$6,IF(OR($P$7="ALL",Assumptions!$N$50="Y"),INDEX(Assumptions!$D$50:$F$50,$P$4),Assumptions!$E$50)) | Q10: =IF($Q$5="TokensOutPerReport",$Q$6,IF(OR($Q$7="ALL",Assumptions!$N$50="Y"),INDEX(Assumptions!$D$50:$F$50,$Q$4),Assumptions!$E$50)) | R10: =IF($R$5="TokensOutPerReport",$R$6,IF(OR($R$7="ALL",Assumptions!$N$50="Y"),INDEX(Assumptions!$D$50:$F$50,$R$4),Assumptions!$E$50)) | S10: =IF($S$5="TokensOutPerReport",$S$6,IF(OR($S$7="ALL",Assumptions!$N$50="Y"),INDEX(Assumptions!$D$50:$F$50,$S$4),Assumptions!$E$50)) | T10: =IF($T$5="TokensOutPerReport",$T$6,IF(OR($T$7="ALL",Assumptions!$N$50="Y"),INDEX(Assumptions!$D$50:$F$50,$T$4),Assumptions!$E$50)) | U10: =IF($U$5="TokensOutPerReport",$U$6,IF(OR($U$7="ALL",Assumptions!$N$50="Y"),INDEX(Assumptions!$D$50:$F$50,$U$4),Assumptions!$E$50)) | V10: =IF($V$5="TokensOutPerReport",$V$6,IF(OR($V$7="ALL",Assumptions!$N$50="Y"),INDEX(Assumptions!$D$50:$F$50,$V$4),Assumptions!$E$50)) | W10: =IF($W$5="TokensOutPerReport",$W$6,IF(OR($W$7="ALL",Assumptions!$N$50="Y"),INDEX(Assumptions!$D$50:$F$50,$W$4),Assumptions!$E$50)) | X10: =IF($X$5="TokensOutPerReport",$X$6,IF(OR($X$7="ALL",Assumptions!$N$50="Y"),INDEX(Assumptions!$D$50:$F$50,$X$4),Assumptions!$E$50)) | Y10: =IF($Y$5="TokensOutPerReport",$Y$6,IF(OR($Y$7="ALL",Assumptions!$N$50="Y"),INDEX(Assumptions!$D$50:$F$50,$Y$4),Assumptions!$E$50)) | Z10: =IF($Z$5="TokensOutPerReport",$Z$6,IF(OR($Z$7="ALL",Assumptions!$N$50="Y"),INDEX(Assumptions!$D$50:$F$50,$Z$4),Assumptions!$E$50)) | AA10: =IF($AA$5="TokensOutPerReport",$AA$6,IF(OR($AA$7="ALL",Assumptions!$N$50="Y"),INDEX(Assumptions!$D$50:$F$50,$AA$4),Assumptions!$E$50)) | AB10: =IF($AB$5="TokensOutPerReport",$AB$6,IF(OR($AB$7="ALL",Assumptions!$N$50="Y"),INDEX(Assumptions!$D$50:$F$50,$AB$4),Assumptions!$E$50)) | AC10: =IF($AC$5="TokensOutPerReport",$AC$6,IF(OR($AC$7="ALL",Assumptions!$N$50="Y"),INDEX(Assumptions!$D$50:$F$50,$AC$4),Assumptions!$E$50)) | AD10: =IF($AD$5="TokensOutPerReport",$AD$6,IF(OR($AD$7="ALL",Assumptions!$N$50="Y"),INDEX(Assumptions!$D$50:$F$50,$AD$4),Assumptions!$E$50)) | AE10: =IF($AE$5="TokensOutPerReport",$AE$6,IF(OR($AE$7="ALL",Assumptions!$N$50="Y"),INDEX(Assumptions!$D$50:$F$50,$AE$4),Assumptions!$E$50)) | AF10: =IF($AF$5="TokensOutPerReport",$AF$6,IF(OR($AF$7="ALL",Assumptions!$N$50="Y"),INDEX(Assumptions!$D$50:$F$50,$AF$4),Assumptions!$E$50)) | AG10: =IF($AG$5="TokensOutPerReport",$AG$6,IF(OR($AG$7="ALL",Assumptions!$N$50="Y"),INDEX(Assumptions!$D$50:$F$50,$AG$4),Assumptions!$E$50)) | AH10: =IF($AH$5="TokensOutPerReport",$AH$6,IF(OR($AH$7="ALL",Assumptions!$N$50="Y"),INDEX(Assumptions!$D$50:$F$50,$AH$4),Assumptions!$E$50)) | AI10: =IF($AI$5="TokensOutPerReport",$AI$6,IF(OR($AI$7="ALL",Assumptions!$N$50="Y"),INDEX(Assumptions!$D$50:$F$50,$AI$4),Assumptions!$E$50)) | AJ10: =IF($AJ$5="TokensOutPerReport",$AJ$6,IF(OR($AJ$7="ALL",Assumptions!$N$50="Y"),INDEX(Assumptions!$D$50:$F$50,$AJ$4),Assumptions!$E$50)) | AK10: =IF($AK$5="TokensOutPerReport",$AK$6,IF(OR($AK$7="ALL",Assumptions!$N$50="Y"),INDEX(Assumptions!$D$50:$F$50,$AK$4),Assumptions!$E$50)) | AL10: =IF($AL$5="TokensOutPerReport",$AL$6,IF(OR($AL$7="ALL",Assumptions!$N$50="Y"),INDEX(Assumptions!$D$50:$F$50,$AL$4),Assumptions!$E$50)) | AM10: =IF($AM$5="TokensOutPerReport",$AM$6,IF(OR($AM$7="ALL",Assumptions!$N$50="Y"),INDEX(Assumptions!$D$50:$F$50,$AM$4),Assumptions!$E$50)) | AN10: =IF($AN$5="TokensOutPerReport",$AN$6,IF(OR($AN$7="ALL",Assumptions!$N$50="Y"),INDEX(Assumptions!$D$50:$F$50,$AN$4),Assumptions!$E$50)) | AO10: =IF($AO$5="TokensOutPerReport",$AO$6,IF(OR($AO$7="ALL",Assumptions!$N$50="Y"),INDEX(Assumptions!$D$50:$F$50,$AO$4),Assumptions!$E$50)) | AP10: =IF($AP$5="TokensOutPerReport",$AP$6,IF(OR($AP$7="ALL",Assumptions!$N$50="Y"),INDEX(Assumptions!$D$50:$F$50,$AP$4),Assumptions!$E$50)) | AQ10: =IF($AQ$5="TokensOutPerReport",$AQ$6,IF(OR($AQ$7="ALL",Assumptions!$N$50="Y"),INDEX(Assumptions!$D$50:$F$50,$AQ$4),Assumptions!$E$50)) | AR10: =IF($AR$5="TokensOutPerReport",$AR$6,IF(OR($AR$7="ALL",Assumptions!$N$50="Y"),INDEX(Assumptions!$D$50:$F$50,$AR$4),Assumptions!$E$50)) | AS10: =IF($AS$5="TokensOutPerReport",$AS$6,IF(OR($AS$7="ALL",Assumptions!$N$50="Y"),INDEX(Assumptions!$D$50:$F$50,$AS$4),Assumptions!$E$50)) | AT10: =IF($AT$5="TokensOutPerReport",$AT$6,IF(OR($AT$7="ALL",Assumptions!$N$50="Y"),INDEX(Assumptions!$D$50:$F$50,$AT$4),Assumptions!$E$50)) | AU10: =IF($AU$5="TokensOutPerReport",$AU$6,IF(OR($AU$7="ALL",Assumptions!$N$50="Y"),INDEX(Assumptions!$D$50:$F$50,$AU$4),Assumptions!$E$50)) | AV10: =IF($AV$5="TokensOutPerReport",$AV$6,IF(OR($AV$7="ALL",Assumptions!$N$50="Y"),INDEX(Assumptions!$D$50:$F$50,$AV$4),Assumptions!$E$50)) | AW10: =IF($AW$5="TokensOutPerReport",$AW$6,IF(OR($AW$7="ALL",Assumptions!$N$50="Y"),INDEX(Assumptions!$D$50:$F$50,$AW$4),Assumptions!$E$50)) | AX10: =IF($AX$5="TokensOutPerReport",$AX$6,IF(OR($AX$7="ALL",Assumptions!$N$50="Y"),INDEX(Assumptions!$D$50:$F$50,$AX$4),Assumptions!$E$50)) | AY10: =IF($AY$5="TokensOutPerReport",$AY$6,IF(OR($AY$7="ALL",Assumptions!$N$50="Y"),INDEX(Assumptions!$D$50:$F$50,$AY$4),Assumptions!$E$50)) | AZ10: =IF($AZ$5="TokensOutPerReport",$AZ$6,IF(OR($AZ$7="ALL",Assumptions!$N$50="Y"),INDEX(Assumptions!$D$50:$F$50,$AZ$4),Assumptions!$E$50)) | BA10: =IF($BA$5="TokensOutPerReport",$BA$6,IF(OR($BA$7="ALL",Assumptions!$N$50="Y"),INDEX(Assumptions!$D$50:$F$50,$BA$4),Assumptions!$E$50)) | BB10: =IF($BB$5="TokensOutPerReport",$BB$6,IF(OR($BB$7="ALL",Assumptions!$N$50="Y"),INDEX(Assumptions!$D$50:$F$50,$BB$4),Assumptions!$E$50)) | BC10: =IF($BC$5="TokensOutPerReport",$BC$6,IF(OR($BC$7="ALL",Assumptions!$N$50="Y"),INDEX(Assumptions!$D$50:$F$50,$BC$4),Assumptions!$E$50)) | BD10: =IF($BD$5="TokensOutPerReport",$BD$6,IF(OR($BD$7="ALL",Assumptions!$N$50="Y"),INDEX(Assumptions!$D$50:$F$50,$BD$4),Assumptions!$E$50)) | BE10: =IF($BE$5="TokensOutPerReport",$BE$6,IF(OR($BE$7="ALL",Assumptions!$N$50="Y"),INDEX(Assumptions!$D$50:$F$50,$BE$4),Assumptions!$E$50))
B11: LLMPriceIn | D11: =IF($D$5="LLMPriceIn",$D$6,IF(OR($D$7="ALL",Assumptions!$N$51="Y"),INDEX(Assumptions!$D$51:$F$51,$D$4),Assumptions!$E$51)) | E11: =IF($E$5="LLMPriceIn",$E$6,IF(OR($E$7="ALL",Assumptions!$N$51="Y"),INDEX(Assumptions!$D$51:$F$51,$E$4),Assumptions!$E$51)) | F11: =IF($F$5="LLMPriceIn",$F$6,IF(OR($F$7="ALL",Assumptions!$N$51="Y"),INDEX(Assumptions!$D$51:$F$51,$F$4),Assumptions!$E$51)) | G11: =IF($G$5="LLMPriceIn",$G$6,IF(OR($G$7="ALL",Assumptions!$N$51="Y"),INDEX(Assumptions!$D$51:$F$51,$G$4),Assumptions!$E$51)) | H11: =IF($H$5="LLMPriceIn",$H$6,IF(OR($H$7="ALL",Assumptions!$N$51="Y"),INDEX(Assumptions!$D$51:$F$51,$H$4),Assumptions!$E$51)) | I11: =IF($I$5="LLMPriceIn",$I$6,IF(OR($I$7="ALL",Assumptions!$N$51="Y"),INDEX(Assumptions!$D$51:$F$51,$I$4),Assumptions!$E$51)) | J11: =IF($J$5="LLMPriceIn",$J$6,IF(OR($J$7="ALL",Assumptions!$N$51="Y"),INDEX(Assumptions!$D$51:$F$51,$J$4),Assumptions!$E$51)) | K11: =IF($K$5="LLMPriceIn",$K$6,IF(OR($K$7="ALL",Assumptions!$N$51="Y"),INDEX(Assumptions!$D$51:$F$51,$K$4),Assumptions!$E$51)) | L11: =IF($L$5="LLMPriceIn",$L$6,IF(OR($L$7="ALL",Assumptions!$N$51="Y"),INDEX(Assumptions!$D$51:$F$51,$L$4),Assumptions!$E$51)) | M11: =IF($M$5="LLMPriceIn",$M$6,IF(OR($M$7="ALL",Assumptions!$N$51="Y"),INDEX(Assumptions!$D$51:$F$51,$M$4),Assumptions!$E$51)) | N11: =IF($N$5="LLMPriceIn",$N$6,IF(OR($N$7="ALL",Assumptions!$N$51="Y"),INDEX(Assumptions!$D$51:$F$51,$N$4),Assumptions!$E$51)) | O11: =IF($O$5="LLMPriceIn",$O$6,IF(OR($O$7="ALL",Assumptions!$N$51="Y"),INDEX(Assumptions!$D$51:$F$51,$O$4),Assumptions!$E$51)) | P11: =IF($P$5="LLMPriceIn",$P$6,IF(OR($P$7="ALL",Assumptions!$N$51="Y"),INDEX(Assumptions!$D$51:$F$51,$P$4),Assumptions!$E$51)) | Q11: =IF($Q$5="LLMPriceIn",$Q$6,IF(OR($Q$7="ALL",Assumptions!$N$51="Y"),INDEX(Assumptions!$D$51:$F$51,$Q$4),Assumptions!$E$51)) | R11: =IF($R$5="LLMPriceIn",$R$6,IF(OR($R$7="ALL",Assumptions!$N$51="Y"),INDEX(Assumptions!$D$51:$F$51,$R$4),Assumptions!$E$51)) | S11: =IF($S$5="LLMPriceIn",$S$6,IF(OR($S$7="ALL",Assumptions!$N$51="Y"),INDEX(Assumptions!$D$51:$F$51,$S$4),Assumptions!$E$51)) | T11: =IF($T$5="LLMPriceIn",$T$6,IF(OR($T$7="ALL",Assumptions!$N$51="Y"),INDEX(Assumptions!$D$51:$F$51,$T$4),Assumptions!$E$51)) | U11: =IF($U$5="LLMPriceIn",$U$6,IF(OR($U$7="ALL",Assumptions!$N$51="Y"),INDEX(Assumptions!$D$51:$F$51,$U$4),Assumptions!$E$51)) | V11: =IF($V$5="LLMPriceIn",$V$6,IF(OR($V$7="ALL",Assumptions!$N$51="Y"),INDEX(Assumptions!$D$51:$F$51,$V$4),Assumptions!$E$51)) | W11: =IF($W$5="LLMPriceIn",$W$6,IF(OR($W$7="ALL",Assumptions!$N$51="Y"),INDEX(Assumptions!$D$51:$F$51,$W$4),Assumptions!$E$51)) | X11: =IF($X$5="LLMPriceIn",$X$6,IF(OR($X$7="ALL",Assumptions!$N$51="Y"),INDEX(Assumptions!$D$51:$F$51,$X$4),Assumptions!$E$51)) | Y11: =IF($Y$5="LLMPriceIn",$Y$6,IF(OR($Y$7="ALL",Assumptions!$N$51="Y"),INDEX(Assumptions!$D$51:$F$51,$Y$4),Assumptions!$E$51)) | Z11: =IF($Z$5="LLMPriceIn",$Z$6,IF(OR($Z$7="ALL",Assumptions!$N$51="Y"),INDEX(Assumptions!$D$51:$F$51,$Z$4),Assumptions!$E$51)) | AA11: =IF($AA$5="LLMPriceIn",$AA$6,IF(OR($AA$7="ALL",Assumptions!$N$51="Y"),INDEX(Assumptions!$D$51:$F$51,$AA$4),Assumptions!$E$51)) | AB11: =IF($AB$5="LLMPriceIn",$AB$6,IF(OR($AB$7="ALL",Assumptions!$N$51="Y"),INDEX(Assumptions!$D$51:$F$51,$AB$4),Assumptions!$E$51)) | AC11: =IF($AC$5="LLMPriceIn",$AC$6,IF(OR($AC$7="ALL",Assumptions!$N$51="Y"),INDEX(Assumptions!$D$51:$F$51,$AC$4),Assumptions!$E$51)) | AD11: =IF($AD$5="LLMPriceIn",$AD$6,IF(OR($AD$7="ALL",Assumptions!$N$51="Y"),INDEX(Assumptions!$D$51:$F$51,$AD$4),Assumptions!$E$51)) | AE11: =IF($AE$5="LLMPriceIn",$AE$6,IF(OR($AE$7="ALL",Assumptions!$N$51="Y"),INDEX(Assumptions!$D$51:$F$51,$AE$4),Assumptions!$E$51)) | AF11: =IF($AF$5="LLMPriceIn",$AF$6,IF(OR($AF$7="ALL",Assumptions!$N$51="Y"),INDEX(Assumptions!$D$51:$F$51,$AF$4),Assumptions!$E$51)) | AG11: =IF($AG$5="LLMPriceIn",$AG$6,IF(OR($AG$7="ALL",Assumptions!$N$51="Y"),INDEX(Assumptions!$D$51:$F$51,$AG$4),Assumptions!$E$51)) | AH11: =IF($AH$5="LLMPriceIn",$AH$6,IF(OR($AH$7="ALL",Assumptions!$N$51="Y"),INDEX(Assumptions!$D$51:$F$51,$AH$4),Assumptions!$E$51)) | AI11: =IF($AI$5="LLMPriceIn",$AI$6,IF(OR($AI$7="ALL",Assumptions!$N$51="Y"),INDEX(Assumptions!$D$51:$F$51,$AI$4),Assumptions!$E$51)) | AJ11: =IF($AJ$5="LLMPriceIn",$AJ$6,IF(OR($AJ$7="ALL",Assumptions!$N$51="Y"),INDEX(Assumptions!$D$51:$F$51,$AJ$4),Assumptions!$E$51)) | AK11: =IF($AK$5="LLMPriceIn",$AK$6,IF(OR($AK$7="ALL",Assumptions!$N$51="Y"),INDEX(Assumptions!$D$51:$F$51,$AK$4),Assumptions!$E$51)) | AL11: =IF($AL$5="LLMPriceIn",$AL$6,IF(OR($AL$7="ALL",Assumptions!$N$51="Y"),INDEX(Assumptions!$D$51:$F$51,$AL$4),Assumptions!$E$51)) | AM11: =IF($AM$5="LLMPriceIn",$AM$6,IF(OR($AM$7="ALL",Assumptions!$N$51="Y"),INDEX(Assumptions!$D$51:$F$51,$AM$4),Assumptions!$E$51)) | AN11: =IF($AN$5="LLMPriceIn",$AN$6,IF(OR($AN$7="ALL",Assumptions!$N$51="Y"),INDEX(Assumptions!$D$51:$F$51,$AN$4),Assumptions!$E$51)) | AO11: =IF($AO$5="LLMPriceIn",$AO$6,IF(OR($AO$7="ALL",Assumptions!$N$51="Y"),INDEX(Assumptions!$D$51:$F$51,$AO$4),Assumptions!$E$51)) | AP11: =IF($AP$5="LLMPriceIn",$AP$6,IF(OR($AP$7="ALL",Assumptions!$N$51="Y"),INDEX(Assumptions!$D$51:$F$51,$AP$4),Assumptions!$E$51)) | AQ11: =IF($AQ$5="LLMPriceIn",$AQ$6,IF(OR($AQ$7="ALL",Assumptions!$N$51="Y"),INDEX(Assumptions!$D$51:$F$51,$AQ$4),Assumptions!$E$51)) | AR11: =IF($AR$5="LLMPriceIn",$AR$6,IF(OR($AR$7="ALL",Assumptions!$N$51="Y"),INDEX(Assumptions!$D$51:$F$51,$AR$4),Assumptions!$E$51)) | AS11: =IF($AS$5="LLMPriceIn",$AS$6,IF(OR($AS$7="ALL",Assumptions!$N$51="Y"),INDEX(Assumptions!$D$51:$F$51,$AS$4),Assumptions!$E$51)) | AT11: =IF($AT$5="LLMPriceIn",$AT$6,IF(OR($AT$7="ALL",Assumptions!$N$51="Y"),INDEX(Assumptions!$D$51:$F$51,$AT$4),Assumptions!$E$51)) | AU11: =IF($AU$5="LLMPriceIn",$AU$6,IF(OR($AU$7="ALL",Assumptions!$N$51="Y"),INDEX(Assumptions!$D$51:$F$51,$AU$4),Assumptions!$E$51)) | AV11: =IF($AV$5="LLMPriceIn",$AV$6,IF(OR($AV$7="ALL",Assumptions!$N$51="Y"),INDEX(Assumptions!$D$51:$F$51,$AV$4),Assumptions!$E$51)) | AW11: =IF($AW$5="LLMPriceIn",$AW$6,IF(OR($AW$7="ALL",Assumptions!$N$51="Y"),INDEX(Assumptions!$D$51:$F$51,$AW$4),Assumptions!$E$51)) | AX11: =IF($AX$5="LLMPriceIn",$AX$6,IF(OR($AX$7="ALL",Assumptions!$N$51="Y"),INDEX(Assumptions!$D$51:$F$51,$AX$4),Assumptions!$E$51)) | AY11: =IF($AY$5="LLMPriceIn",$AY$6,IF(OR($AY$7="ALL",Assumptions!$N$51="Y"),INDEX(Assumptions!$D$51:$F$51,$AY$4),Assumptions!$E$51)) | AZ11: =IF($AZ$5="LLMPriceIn",$AZ$6,IF(OR($AZ$7="ALL",Assumptions!$N$51="Y"),INDEX(Assumptions!$D$51:$F$51,$AZ$4),Assumptions!$E$51)) | BA11: =IF($BA$5="LLMPriceIn",$BA$6,IF(OR($BA$7="ALL",Assumptions!$N$51="Y"),INDEX(Assumptions!$D$51:$F$51,$BA$4),Assumptions!$E$51)) | BB11: =IF($BB$5="LLMPriceIn",$BB$6,IF(OR($BB$7="ALL",Assumptions!$N$51="Y"),INDEX(Assumptions!$D$51:$F$51,$BB$4),Assumptions!$E$51)) | BC11: =IF($BC$5="LLMPriceIn",$BC$6,IF(OR($BC$7="ALL",Assumptions!$N$51="Y"),INDEX(Assumptions!$D$51:$F$51,$BC$4),Assumptions!$E$51)) | BD11: =IF($BD$5="LLMPriceIn",$BD$6,IF(OR($BD$7="ALL",Assumptions!$N$51="Y"),INDEX(Assumptions!$D$51:$F$51,$BD$4),Assumptions!$E$51)) | BE11: =IF($BE$5="LLMPriceIn",$BE$6,IF(OR($BE$7="ALL",Assumptions!$N$51="Y"),INDEX(Assumptions!$D$51:$F$51,$BE$4),Assumptions!$E$51))
B12: LLMPriceOut | D12: =IF($D$5="LLMPriceOut",$D$6,IF(OR($D$7="ALL",Assumptions!$N$52="Y"),INDEX(Assumptions!$D$52:$F$52,$D$4),Assumptions!$E$52)) | E12: =IF($E$5="LLMPriceOut",$E$6,IF(OR($E$7="ALL",Assumptions!$N$52="Y"),INDEX(Assumptions!$D$52:$F$52,$E$4),Assumptions!$E$52)) | F12: =IF($F$5="LLMPriceOut",$F$6,IF(OR($F$7="ALL",Assumptions!$N$52="Y"),INDEX(Assumptions!$D$52:$F$52,$F$4),Assumptions!$E$52)) | G12: =IF($G$5="LLMPriceOut",$G$6,IF(OR($G$7="ALL",Assumptions!$N$52="Y"),INDEX(Assumptions!$D$52:$F$52,$G$4),Assumptions!$E$52)) | H12: =IF($H$5="LLMPriceOut",$H$6,IF(OR($H$7="ALL",Assumptions!$N$52="Y"),INDEX(Assumptions!$D$52:$F$52,$H$4),Assumptions!$E$52)) | I12: =IF($I$5="LLMPriceOut",$I$6,IF(OR($I$7="ALL",Assumptions!$N$52="Y"),INDEX(Assumptions!$D$52:$F$52,$I$4),Assumptions!$E$52)) | J12: =IF($J$5="LLMPriceOut",$J$6,IF(OR($J$7="ALL",Assumptions!$N$52="Y"),INDEX(Assumptions!$D$52:$F$52,$J$4),Assumptions!$E$52)) | K12: =IF($K$5="LLMPriceOut",$K$6,IF(OR($K$7="ALL",Assumptions!$N$52="Y"),INDEX(Assumptions!$D$52:$F$52,$K$4),Assumptions!$E$52)) | L12: =IF($L$5="LLMPriceOut",$L$6,IF(OR($L$7="ALL",Assumptions!$N$52="Y"),INDEX(Assumptions!$D$52:$F$52,$L$4),Assumptions!$E$52)) | M12: =IF($M$5="LLMPriceOut",$M$6,IF(OR($M$7="ALL",Assumptions!$N$52="Y"),INDEX(Assumptions!$D$52:$F$52,$M$4),Assumptions!$E$52)) | N12: =IF($N$5="LLMPriceOut",$N$6,IF(OR($N$7="ALL",Assumptions!$N$52="Y"),INDEX(Assumptions!$D$52:$F$52,$N$4),Assumptions!$E$52)) | O12: =IF($O$5="LLMPriceOut",$O$6,IF(OR($O$7="ALL",Assumptions!$N$52="Y"),INDEX(Assumptions!$D$52:$F$52,$O$4),Assumptions!$E$52)) | P12: =IF($P$5="LLMPriceOut",$P$6,IF(OR($P$7="ALL",Assumptions!$N$52="Y"),INDEX(Assumptions!$D$52:$F$52,$P$4),Assumptions!$E$52)) | Q12: =IF($Q$5="LLMPriceOut",$Q$6,IF(OR($Q$7="ALL",Assumptions!$N$52="Y"),INDEX(Assumptions!$D$52:$F$52,$Q$4),Assumptions!$E$52)) | R12: =IF($R$5="LLMPriceOut",$R$6,IF(OR($R$7="ALL",Assumptions!$N$52="Y"),INDEX(Assumptions!$D$52:$F$52,$R$4),Assumptions!$E$52)) | S12: =IF($S$5="LLMPriceOut",$S$6,IF(OR($S$7="ALL",Assumptions!$N$52="Y"),INDEX(Assumptions!$D$52:$F$52,$S$4),Assumptions!$E$52)) | T12: =IF($T$5="LLMPriceOut",$T$6,IF(OR($T$7="ALL",Assumptions!$N$52="Y"),INDEX(Assumptions!$D$52:$F$52,$T$4),Assumptions!$E$52)) | U12: =IF($U$5="LLMPriceOut",$U$6,IF(OR($U$7="ALL",Assumptions!$N$52="Y"),INDEX(Assumptions!$D$52:$F$52,$U$4),Assumptions!$E$52)) | V12: =IF($V$5="LLMPriceOut",$V$6,IF(OR($V$7="ALL",Assumptions!$N$52="Y"),INDEX(Assumptions!$D$52:$F$52,$V$4),Assumptions!$E$52)) | W12: =IF($W$5="LLMPriceOut",$W$6,IF(OR($W$7="ALL",Assumptions!$N$52="Y"),INDEX(Assumptions!$D$52:$F$52,$W$4),Assumptions!$E$52)) | X12: =IF($X$5="LLMPriceOut",$X$6,IF(OR($X$7="ALL",Assumptions!$N$52="Y"),INDEX(Assumptions!$D$52:$F$52,$X$4),Assumptions!$E$52)) | Y12: =IF($Y$5="LLMPriceOut",$Y$6,IF(OR($Y$7="ALL",Assumptions!$N$52="Y"),INDEX(Assumptions!$D$52:$F$52,$Y$4),Assumptions!$E$52)) | Z12: =IF($Z$5="LLMPriceOut",$Z$6,IF(OR($Z$7="ALL",Assumptions!$N$52="Y"),INDEX(Assumptions!$D$52:$F$52,$Z$4),Assumptions!$E$52)) | AA12: =IF($AA$5="LLMPriceOut",$AA$6,IF(OR($AA$7="ALL",Assumptions!$N$52="Y"),INDEX(Assumptions!$D$52:$F$52,$AA$4),Assumptions!$E$52)) | AB12: =IF($AB$5="LLMPriceOut",$AB$6,IF(OR($AB$7="ALL",Assumptions!$N$52="Y"),INDEX(Assumptions!$D$52:$F$52,$AB$4),Assumptions!$E$52)) | AC12: =IF($AC$5="LLMPriceOut",$AC$6,IF(OR($AC$7="ALL",Assumptions!$N$52="Y"),INDEX(Assumptions!$D$52:$F$52,$AC$4),Assumptions!$E$52)) | AD12: =IF($AD$5="LLMPriceOut",$AD$6,IF(OR($AD$7="ALL",Assumptions!$N$52="Y"),INDEX(Assumptions!$D$52:$F$52,$AD$4),Assumptions!$E$52)) | AE12: =IF($AE$5="LLMPriceOut",$AE$6,IF(OR($AE$7="ALL",Assumptions!$N$52="Y"),INDEX(Assumptions!$D$52:$F$52,$AE$4),Assumptions!$E$52)) | AF12: =IF($AF$5="LLMPriceOut",$AF$6,IF(OR($AF$7="ALL",Assumptions!$N$52="Y"),INDEX(Assumptions!$D$52:$F$52,$AF$4),Assumptions!$E$52)) | AG12: =IF($AG$5="LLMPriceOut",$AG$6,IF(OR($AG$7="ALL",Assumptions!$N$52="Y"),INDEX(Assumptions!$D$52:$F$52,$AG$4),Assumptions!$E$52)) | AH12: =IF($AH$5="LLMPriceOut",$AH$6,IF(OR($AH$7="ALL",Assumptions!$N$52="Y"),INDEX(Assumptions!$D$52:$F$52,$AH$4),Assumptions!$E$52)) | AI12: =IF($AI$5="LLMPriceOut",$AI$6,IF(OR($AI$7="ALL",Assumptions!$N$52="Y"),INDEX(Assumptions!$D$52:$F$52,$AI$4),Assumptions!$E$52)) | AJ12: =IF($AJ$5="LLMPriceOut",$AJ$6,IF(OR($AJ$7="ALL",Assumptions!$N$52="Y"),INDEX(Assumptions!$D$52:$F$52,$AJ$4),Assumptions!$E$52)) | AK12: =IF($AK$5="LLMPriceOut",$AK$6,IF(OR($AK$7="ALL",Assumptions!$N$52="Y"),INDEX(Assumptions!$D$52:$F$52,$AK$4),Assumptions!$E$52)) | AL12: =IF($AL$5="LLMPriceOut",$AL$6,IF(OR($AL$7="ALL",Assumptions!$N$52="Y"),INDEX(Assumptions!$D$52:$F$52,$AL$4),Assumptions!$E$52)) | AM12: =IF($AM$5="LLMPriceOut",$AM$6,IF(OR($AM$7="ALL",Assumptions!$N$52="Y"),INDEX(Assumptions!$D$52:$F$52,$AM$4),Assumptions!$E$52)) | AN12: =IF($AN$5="LLMPriceOut",$AN$6,IF(OR($AN$7="ALL",Assumptions!$N$52="Y"),INDEX(Assumptions!$D$52:$F$52,$AN$4),Assumptions!$E$52)) | AO12: =IF($AO$5="LLMPriceOut",$AO$6,IF(OR($AO$7="ALL",Assumptions!$N$52="Y"),INDEX(Assumptions!$D$52:$F$52,$AO$4),Assumptions!$E$52)) | AP12: =IF($AP$5="LLMPriceOut",$AP$6,IF(OR($AP$7="ALL",Assumptions!$N$52="Y"),INDEX(Assumptions!$D$52:$F$52,$AP$4),Assumptions!$E$52)) | AQ12: =IF($AQ$5="LLMPriceOut",$AQ$6,IF(OR($AQ$7="ALL",Assumptions!$N$52="Y"),INDEX(Assumptions!$D$52:$F$52,$AQ$4),Assumptions!$E$52)) | AR12: =IF($AR$5="LLMPriceOut",$AR$6,IF(OR($AR$7="ALL",Assumptions!$N$52="Y"),INDEX(Assumptions!$D$52:$F$52,$AR$4),Assumptions!$E$52)) | AS12: =IF($AS$5="LLMPriceOut",$AS$6,IF(OR($AS$7="ALL",Assumptions!$N$52="Y"),INDEX(Assumptions!$D$52:$F$52,$AS$4),Assumptions!$E$52)) | AT12: =IF($AT$5="LLMPriceOut",$AT$6,IF(OR($AT$7="ALL",Assumptions!$N$52="Y"),INDEX(Assumptions!$D$52:$F$52,$AT$4),Assumptions!$E$52)) | AU12: =IF($AU$5="LLMPriceOut",$AU$6,IF(OR($AU$7="ALL",Assumptions!$N$52="Y"),INDEX(Assumptions!$D$52:$F$52,$AU$4),Assumptions!$E$52)) | AV12: =IF($AV$5="LLMPriceOut",$AV$6,IF(OR($AV$7="ALL",Assumptions!$N$52="Y"),INDEX(Assumptions!$D$52:$F$52,$AV$4),Assumptions!$E$52)) | AW12: =IF($AW$5="LLMPriceOut",$AW$6,IF(OR($AW$7="ALL",Assumptions!$N$52="Y"),INDEX(Assumptions!$D$52:$F$52,$AW$4),Assumptions!$E$52)) | AX12: =IF($AX$5="LLMPriceOut",$AX$6,IF(OR($AX$7="ALL",Assumptions!$N$52="Y"),INDEX(Assumptions!$D$52:$F$52,$AX$4),Assumptions!$E$52)) | AY12: =IF($AY$5="LLMPriceOut",$AY$6,IF(OR($AY$7="ALL",Assumptions!$N$52="Y"),INDEX(Assumptions!$D$52:$F$52,$AY$4),Assumptions!$E$52)) | AZ12: =IF($AZ$5="LLMPriceOut",$AZ$6,IF(OR($AZ$7="ALL",Assumptions!$N$52="Y"),INDEX(Assumptions!$D$52:$F$52,$AZ$4),Assumptions!$E$52)) | BA12: =IF($BA$5="LLMPriceOut",$BA$6,IF(OR($BA$7="ALL",Assumptions!$N$52="Y"),INDEX(Assumptions!$D$52:$F$52,$BA$4),Assumptions!$E$52)) | BB12: =IF($BB$5="LLMPriceOut",$BB$6,IF(OR($BB$7="ALL",Assumptions!$N$52="Y"),INDEX(Assumptions!$D$52:$F$52,$BB$4),Assumptions!$E$52)) | BC12: =IF($BC$5="LLMPriceOut",$BC$6,IF(OR($BC$7="ALL",Assumptions!$N$52="Y"),INDEX(Assumptions!$D$52:$F$52,$BC$4),Assumptions!$E$52)) | BD12: =IF($BD$5="LLMPriceOut",$BD$6,IF(OR($BD$7="ALL",Assumptions!$N$52="Y"),INDEX(Assumptions!$D$52:$F$52,$BD$4),Assumptions!$E$52)) | BE12: =IF($BE$5="LLMPriceOut",$BE$6,IF(OR($BE$7="ALL",Assumptions!$N$52="Y"),INDEX(Assumptions!$D$52:$F$52,$BE$4),Assumptions!$E$52))
B13: WAMsgsPerStudentMonth | D13: =IF($D$5="WAMsgsPerStudentMonth",$D$6,IF(OR($D$7="ALL",Assumptions!$N$53="Y"),INDEX(Assumptions!$D$53:$F$53,$D$4),Assumptions!$E$53)) | E13: =IF($E$5="WAMsgsPerStudentMonth",$E$6,IF(OR($E$7="ALL",Assumptions!$N$53="Y"),INDEX(Assumptions!$D$53:$F$53,$E$4),Assumptions!$E$53)) | F13: =IF($F$5="WAMsgsPerStudentMonth",$F$6,IF(OR($F$7="ALL",Assumptions!$N$53="Y"),INDEX(Assumptions!$D$53:$F$53,$F$4),Assumptions!$E$53)) | G13: =IF($G$5="WAMsgsPerStudentMonth",$G$6,IF(OR($G$7="ALL",Assumptions!$N$53="Y"),INDEX(Assumptions!$D$53:$F$53,$G$4),Assumptions!$E$53)) | H13: =IF($H$5="WAMsgsPerStudentMonth",$H$6,IF(OR($H$7="ALL",Assumptions!$N$53="Y"),INDEX(Assumptions!$D$53:$F$53,$H$4),Assumptions!$E$53)) | I13: =IF($I$5="WAMsgsPerStudentMonth",$I$6,IF(OR($I$7="ALL",Assumptions!$N$53="Y"),INDEX(Assumptions!$D$53:$F$53,$I$4),Assumptions!$E$53)) | J13: =IF($J$5="WAMsgsPerStudentMonth",$J$6,IF(OR($J$7="ALL",Assumptions!$N$53="Y"),INDEX(Assumptions!$D$53:$F$53,$J$4),Assumptions!$E$53)) | K13: =IF($K$5="WAMsgsPerStudentMonth",$K$6,IF(OR($K$7="ALL",Assumptions!$N$53="Y"),INDEX(Assumptions!$D$53:$F$53,$K$4),Assumptions!$E$53)) | L13: =IF($L$5="WAMsgsPerStudentMonth",$L$6,IF(OR($L$7="ALL",Assumptions!$N$53="Y"),INDEX(Assumptions!$D$53:$F$53,$L$4),Assumptions!$E$53)) | M13: =IF($M$5="WAMsgsPerStudentMonth",$M$6,IF(OR($M$7="ALL",Assumptions!$N$53="Y"),INDEX(Assumptions!$D$53:$F$53,$M$4),Assumptions!$E$53)) | N13: =IF($N$5="WAMsgsPerStudentMonth",$N$6,IF(OR($N$7="ALL",Assumptions!$N$53="Y"),INDEX(Assumptions!$D$53:$F$53,$N$4),Assumptions!$E$53)) | O13: =IF($O$5="WAMsgsPerStudentMonth",$O$6,IF(OR($O$7="ALL",Assumptions!$N$53="Y"),INDEX(Assumptions!$D$53:$F$53,$O$4),Assumptions!$E$53)) | P13: =IF($P$5="WAMsgsPerStudentMonth",$P$6,IF(OR($P$7="ALL",Assumptions!$N$53="Y"),INDEX(Assumptions!$D$53:$F$53,$P$4),Assumptions!$E$53)) | Q13: =IF($Q$5="WAMsgsPerStudentMonth",$Q$6,IF(OR($Q$7="ALL",Assumptions!$N$53="Y"),INDEX(Assumptions!$D$53:$F$53,$Q$4),Assumptions!$E$53)) | R13: =IF($R$5="WAMsgsPerStudentMonth",$R$6,IF(OR($R$7="ALL",Assumptions!$N$53="Y"),INDEX(Assumptions!$D$53:$F$53,$R$4),Assumptions!$E$53)) | S13: =IF($S$5="WAMsgsPerStudentMonth",$S$6,IF(OR($S$7="ALL",Assumptions!$N$53="Y"),INDEX(Assumptions!$D$53:$F$53,$S$4),Assumptions!$E$53)) | T13: =IF($T$5="WAMsgsPerStudentMonth",$T$6,IF(OR($T$7="ALL",Assumptions!$N$53="Y"),INDEX(Assumptions!$D$53:$F$53,$T$4),Assumptions!$E$53)) | U13: =IF($U$5="WAMsgsPerStudentMonth",$U$6,IF(OR($U$7="ALL",Assumptions!$N$53="Y"),INDEX(Assumptions!$D$53:$F$53,$U$4),Assumptions!$E$53)) | V13: =IF($V$5="WAMsgsPerStudentMonth",$V$6,IF(OR($V$7="ALL",Assumptions!$N$53="Y"),INDEX(Assumptions!$D$53:$F$53,$V$4),Assumptions!$E$53)) | W13: =IF($W$5="WAMsgsPerStudentMonth",$W$6,IF(OR($W$7="ALL",Assumptions!$N$53="Y"),INDEX(Assumptions!$D$53:$F$53,$W$4),Assumptions!$E$53)) | X13: =IF($X$5="WAMsgsPerStudentMonth",$X$6,IF(OR($X$7="ALL",Assumptions!$N$53="Y"),INDEX(Assumptions!$D$53:$F$53,$X$4),Assumptions!$E$53)) | Y13: =IF($Y$5="WAMsgsPerStudentMonth",$Y$6,IF(OR($Y$7="ALL",Assumptions!$N$53="Y"),INDEX(Assumptions!$D$53:$F$53,$Y$4),Assumptions!$E$53)) | Z13: =IF($Z$5="WAMsgsPerStudentMonth",$Z$6,IF(OR($Z$7="ALL",Assumptions!$N$53="Y"),INDEX(Assumptions!$D$53:$F$53,$Z$4),Assumptions!$E$53)) | AA13: =IF($AA$5="WAMsgsPerStudentMonth",$AA$6,IF(OR($AA$7="ALL",Assumptions!$N$53="Y"),INDEX(Assumptions!$D$53:$F$53,$AA$4),Assumptions!$E$53)) | AB13: =IF($AB$5="WAMsgsPerStudentMonth",$AB$6,IF(OR($AB$7="ALL",Assumptions!$N$53="Y"),INDEX(Assumptions!$D$53:$F$53,$AB$4),Assumptions!$E$53)) | AC13: =IF($AC$5="WAMsgsPerStudentMonth",$AC$6,IF(OR($AC$7="ALL",Assumptions!$N$53="Y"),INDEX(Assumptions!$D$53:$F$53,$AC$4),Assumptions!$E$53)) | AD13: =IF($AD$5="WAMsgsPerStudentMonth",$AD$6,IF(OR($AD$7="ALL",Assumptions!$N$53="Y"),INDEX(Assumptions!$D$53:$F$53,$AD$4),Assumptions!$E$53)) | AE13: =IF($AE$5="WAMsgsPerStudentMonth",$AE$6,IF(OR($AE$7="ALL",Assumptions!$N$53="Y"),INDEX(Assumptions!$D$53:$F$53,$AE$4),Assumptions!$E$53)) | AF13: =IF($AF$5="WAMsgsPerStudentMonth",$AF$6,IF(OR($AF$7="ALL",Assumptions!$N$53="Y"),INDEX(Assumptions!$D$53:$F$53,$AF$4),Assumptions!$E$53)) | AG13: =IF($AG$5="WAMsgsPerStudentMonth",$AG$6,IF(OR($AG$7="ALL",Assumptions!$N$53="Y"),INDEX(Assumptions!$D$53:$F$53,$AG$4),Assumptions!$E$53)) | AH13: =IF($AH$5="WAMsgsPerStudentMonth",$AH$6,IF(OR($AH$7="ALL",Assumptions!$N$53="Y"),INDEX(Assumptions!$D$53:$F$53,$AH$4),Assumptions!$E$53)) | AI13: =IF($AI$5="WAMsgsPerStudentMonth",$AI$6,IF(OR($AI$7="ALL",Assumptions!$N$53="Y"),INDEX(Assumptions!$D$53:$F$53,$AI$4),Assumptions!$E$53)) | AJ13: =IF($AJ$5="WAMsgsPerStudentMonth",$AJ$6,IF(OR($AJ$7="ALL",Assumptions!$N$53="Y"),INDEX(Assumptions!$D$53:$F$53,$AJ$4),Assumptions!$E$53)) | AK13: =IF($AK$5="WAMsgsPerStudentMonth",$AK$6,IF(OR($AK$7="ALL",Assumptions!$N$53="Y"),INDEX(Assumptions!$D$53:$F$53,$AK$4),Assumptions!$E$53)) | AL13: =IF($AL$5="WAMsgsPerStudentMonth",$AL$6,IF(OR($AL$7="ALL",Assumptions!$N$53="Y"),INDEX(Assumptions!$D$53:$F$53,$AL$4),Assumptions!$E$53)) | AM13: =IF($AM$5="WAMsgsPerStudentMonth",$AM$6,IF(OR($AM$7="ALL",Assumptions!$N$53="Y"),INDEX(Assumptions!$D$53:$F$53,$AM$4),Assumptions!$E$53)) | AN13: =IF($AN$5="WAMsgsPerStudentMonth",$AN$6,IF(OR($AN$7="ALL",Assumptions!$N$53="Y"),INDEX(Assumptions!$D$53:$F$53,$AN$4),Assumptions!$E$53)) | AO13: =IF($AO$5="WAMsgsPerStudentMonth",$AO$6,IF(OR($AO$7="ALL",Assumptions!$N$53="Y"),INDEX(Assumptions!$D$53:$F$53,$AO$4),Assumptions!$E$53)) | AP13: =IF($AP$5="WAMsgsPerStudentMonth",$AP$6,IF(OR($AP$7="ALL",Assumptions!$N$53="Y"),INDEX(Assumptions!$D$53:$F$53,$AP$4),Assumptions!$E$53)) | AQ13: =IF($AQ$5="WAMsgsPerStudentMonth",$AQ$6,IF(OR($AQ$7="ALL",Assumptions!$N$53="Y"),INDEX(Assumptions!$D$53:$F$53,$AQ$4),Assumptions!$E$53)) | AR13: =IF($AR$5="WAMsgsPerStudentMonth",$AR$6,IF(OR($AR$7="ALL",Assumptions!$N$53="Y"),INDEX(Assumptions!$D$53:$F$53,$AR$4),Assumptions!$E$53)) | AS13: =IF($AS$5="WAMsgsPerStudentMonth",$AS$6,IF(OR($AS$7="ALL",Assumptions!$N$53="Y"),INDEX(Assumptions!$D$53:$F$53,$AS$4),Assumptions!$E$53)) | AT13: =IF($AT$5="WAMsgsPerStudentMonth",$AT$6,IF(OR($AT$7="ALL",Assumptions!$N$53="Y"),INDEX(Assumptions!$D$53:$F$53,$AT$4),Assumptions!$E$53)) | AU13: =IF($AU$5="WAMsgsPerStudentMonth",$AU$6,IF(OR($AU$7="ALL",Assumptions!$N$53="Y"),INDEX(Assumptions!$D$53:$F$53,$AU$4),Assumptions!$E$53)) | AV13: =IF($AV$5="WAMsgsPerStudentMonth",$AV$6,IF(OR($AV$7="ALL",Assumptions!$N$53="Y"),INDEX(Assumptions!$D$53:$F$53,$AV$4),Assumptions!$E$53)) | AW13: =IF($AW$5="WAMsgsPerStudentMonth",$AW$6,IF(OR($AW$7="ALL",Assumptions!$N$53="Y"),INDEX(Assumptions!$D$53:$F$53,$AW$4),Assumptions!$E$53)) | AX13: =IF($AX$5="WAMsgsPerStudentMonth",$AX$6,IF(OR($AX$7="ALL",Assumptions!$N$53="Y"),INDEX(Assumptions!$D$53:$F$53,$AX$4),Assumptions!$E$53)) | AY13: =IF($AY$5="WAMsgsPerStudentMonth",$AY$6,IF(OR($AY$7="ALL",Assumptions!$N$53="Y"),INDEX(Assumptions!$D$53:$F$53,$AY$4),Assumptions!$E$53)) | AZ13: =IF($AZ$5="WAMsgsPerStudentMonth",$AZ$6,IF(OR($AZ$7="ALL",Assumptions!$N$53="Y"),INDEX(Assumptions!$D$53:$F$53,$AZ$4),Assumptions!$E$53)) | BA13: =IF($BA$5="WAMsgsPerStudentMonth",$BA$6,IF(OR($BA$7="ALL",Assumptions!$N$53="Y"),INDEX(Assumptions!$D$53:$F$53,$BA$4),Assumptions!$E$53)) | BB13: =IF($BB$5="WAMsgsPerStudentMonth",$BB$6,IF(OR($BB$7="ALL",Assumptions!$N$53="Y"),INDEX(Assumptions!$D$53:$F$53,$BB$4),Assumptions!$E$53)) | BC13: =IF($BC$5="WAMsgsPerStudentMonth",$BC$6,IF(OR($BC$7="ALL",Assumptions!$N$53="Y"),INDEX(Assumptions!$D$53:$F$53,$BC$4),Assumptions!$E$53)) | BD13: =IF($BD$5="WAMsgsPerStudentMonth",$BD$6,IF(OR($BD$7="ALL",Assumptions!$N$53="Y"),INDEX(Assumptions!$D$53:$F$53,$BD$4),Assumptions!$E$53)) | BE13: =IF($BE$5="WAMsgsPerStudentMonth",$BE$6,IF(OR($BE$7="ALL",Assumptions!$N$53="Y"),INDEX(Assumptions!$D$53:$F$53,$BE$4),Assumptions!$E$53))
B14: WAPricePerMsg | D14: =IF($D$5="WAPricePerMsg",$D$6,IF(OR($D$7="ALL",Assumptions!$N$54="Y"),INDEX(Assumptions!$D$54:$F$54,$D$4),Assumptions!$E$54)) | E14: =IF($E$5="WAPricePerMsg",$E$6,IF(OR($E$7="ALL",Assumptions!$N$54="Y"),INDEX(Assumptions!$D$54:$F$54,$E$4),Assumptions!$E$54)) | F14: =IF($F$5="WAPricePerMsg",$F$6,IF(OR($F$7="ALL",Assumptions!$N$54="Y"),INDEX(Assumptions!$D$54:$F$54,$F$4),Assumptions!$E$54)) | G14: =IF($G$5="WAPricePerMsg",$G$6,IF(OR($G$7="ALL",Assumptions!$N$54="Y"),INDEX(Assumptions!$D$54:$F$54,$G$4),Assumptions!$E$54)) | H14: =IF($H$5="WAPricePerMsg",$H$6,IF(OR($H$7="ALL",Assumptions!$N$54="Y"),INDEX(Assumptions!$D$54:$F$54,$H$4),Assumptions!$E$54)) | I14: =IF($I$5="WAPricePerMsg",$I$6,IF(OR($I$7="ALL",Assumptions!$N$54="Y"),INDEX(Assumptions!$D$54:$F$54,$I$4),Assumptions!$E$54)) | J14: =IF($J$5="WAPricePerMsg",$J$6,IF(OR($J$7="ALL",Assumptions!$N$54="Y"),INDEX(Assumptions!$D$54:$F$54,$J$4),Assumptions!$E$54)) | K14: =IF($K$5="WAPricePerMsg",$K$6,IF(OR($K$7="ALL",Assumptions!$N$54="Y"),INDEX(Assumptions!$D$54:$F$54,$K$4),Assumptions!$E$54)) | L14: =IF($L$5="WAPricePerMsg",$L$6,IF(OR($L$7="ALL",Assumptions!$N$54="Y"),INDEX(Assumptions!$D$54:$F$54,$L$4),Assumptions!$E$54)) | M14: =IF($M$5="WAPricePerMsg",$M$6,IF(OR($M$7="ALL",Assumptions!$N$54="Y"),INDEX(Assumptions!$D$54:$F$54,$M$4),Assumptions!$E$54)) | N14: =IF($N$5="WAPricePerMsg",$N$6,IF(OR($N$7="ALL",Assumptions!$N$54="Y"),INDEX(Assumptions!$D$54:$F$54,$N$4),Assumptions!$E$54)) | O14: =IF($O$5="WAPricePerMsg",$O$6,IF(OR($O$7="ALL",Assumptions!$N$54="Y"),INDEX(Assumptions!$D$54:$F$54,$O$4),Assumptions!$E$54)) | P14: =IF($P$5="WAPricePerMsg",$P$6,IF(OR($P$7="ALL",Assumptions!$N$54="Y"),INDEX(Assumptions!$D$54:$F$54,$P$4),Assumptions!$E$54)) | Q14: =IF($Q$5="WAPricePerMsg",$Q$6,IF(OR($Q$7="ALL",Assumptions!$N$54="Y"),INDEX(Assumptions!$D$54:$F$54,$Q$4),Assumptions!$E$54)) | R14: =IF($R$5="WAPricePerMsg",$R$6,IF(OR($R$7="ALL",Assumptions!$N$54="Y"),INDEX(Assumptions!$D$54:$F$54,$R$4),Assumptions!$E$54)) | S14: =IF($S$5="WAPricePerMsg",$S$6,IF(OR($S$7="ALL",Assumptions!$N$54="Y"),INDEX(Assumptions!$D$54:$F$54,$S$4),Assumptions!$E$54)) | T14: =IF($T$5="WAPricePerMsg",$T$6,IF(OR($T$7="ALL",Assumptions!$N$54="Y"),INDEX(Assumptions!$D$54:$F$54,$T$4),Assumptions!$E$54)) | U14: =IF($U$5="WAPricePerMsg",$U$6,IF(OR($U$7="ALL",Assumptions!$N$54="Y"),INDEX(Assumptions!$D$54:$F$54,$U$4),Assumptions!$E$54)) | V14: =IF($V$5="WAPricePerMsg",$V$6,IF(OR($V$7="ALL",Assumptions!$N$54="Y"),INDEX(Assumptions!$D$54:$F$54,$V$4),Assumptions!$E$54)) | W14: =IF($W$5="WAPricePerMsg",$W$6,IF(OR($W$7="ALL",Assumptions!$N$54="Y"),INDEX(Assumptions!$D$54:$F$54,$W$4),Assumptions!$E$54)) | X14: =IF($X$5="WAPricePerMsg",$X$6,IF(OR($X$7="ALL",Assumptions!$N$54="Y"),INDEX(Assumptions!$D$54:$F$54,$X$4),Assumptions!$E$54)) | Y14: =IF($Y$5="WAPricePerMsg",$Y$6,IF(OR($Y$7="ALL",Assumptions!$N$54="Y"),INDEX(Assumptions!$D$54:$F$54,$Y$4),Assumptions!$E$54)) | Z14: =IF($Z$5="WAPricePerMsg",$Z$6,IF(OR($Z$7="ALL",Assumptions!$N$54="Y"),INDEX(Assumptions!$D$54:$F$54,$Z$4),Assumptions!$E$54)) | AA14: =IF($AA$5="WAPricePerMsg",$AA$6,IF(OR($AA$7="ALL",Assumptions!$N$54="Y"),INDEX(Assumptions!$D$54:$F$54,$AA$4),Assumptions!$E$54)) | AB14: =IF($AB$5="WAPricePerMsg",$AB$6,IF(OR($AB$7="ALL",Assumptions!$N$54="Y"),INDEX(Assumptions!$D$54:$F$54,$AB$4),Assumptions!$E$54)) | AC14: =IF($AC$5="WAPricePerMsg",$AC$6,IF(OR($AC$7="ALL",Assumptions!$N$54="Y"),INDEX(Assumptions!$D$54:$F$54,$AC$4),Assumptions!$E$54)) | AD14: =IF($AD$5="WAPricePerMsg",$AD$6,IF(OR($AD$7="ALL",Assumptions!$N$54="Y"),INDEX(Assumptions!$D$54:$F$54,$AD$4),Assumptions!$E$54)) | AE14: =IF($AE$5="WAPricePerMsg",$AE$6,IF(OR($AE$7="ALL",Assumptions!$N$54="Y"),INDEX(Assumptions!$D$54:$F$54,$AE$4),Assumptions!$E$54)) | AF14: =IF($AF$5="WAPricePerMsg",$AF$6,IF(OR($AF$7="ALL",Assumptions!$N$54="Y"),INDEX(Assumptions!$D$54:$F$54,$AF$4),Assumptions!$E$54)) | AG14: =IF($AG$5="WAPricePerMsg",$AG$6,IF(OR($AG$7="ALL",Assumptions!$N$54="Y"),INDEX(Assumptions!$D$54:$F$54,$AG$4),Assumptions!$E$54)) | AH14: =IF($AH$5="WAPricePerMsg",$AH$6,IF(OR($AH$7="ALL",Assumptions!$N$54="Y"),INDEX(Assumptions!$D$54:$F$54,$AH$4),Assumptions!$E$54)) | AI14: =IF($AI$5="WAPricePerMsg",$AI$6,IF(OR($AI$7="ALL",Assumptions!$N$54="Y"),INDEX(Assumptions!$D$54:$F$54,$AI$4),Assumptions!$E$54)) | AJ14: =IF($AJ$5="WAPricePerMsg",$AJ$6,IF(OR($AJ$7="ALL",Assumptions!$N$54="Y"),INDEX(Assumptions!$D$54:$F$54,$AJ$4),Assumptions!$E$54)) | AK14: =IF($AK$5="WAPricePerMsg",$AK$6,IF(OR($AK$7="ALL",Assumptions!$N$54="Y"),INDEX(Assumptions!$D$54:$F$54,$AK$4),Assumptions!$E$54)) | AL14: =IF($AL$5="WAPricePerMsg",$AL$6,IF(OR($AL$7="ALL",Assumptions!$N$54="Y"),INDEX(Assumptions!$D$54:$F$54,$AL$4),Assumptions!$E$54)) | AM14: =IF($AM$5="WAPricePerMsg",$AM$6,IF(OR($AM$7="ALL",Assumptions!$N$54="Y"),INDEX(Assumptions!$D$54:$F$54,$AM$4),Assumptions!$E$54)) | AN14: =IF($AN$5="WAPricePerMsg",$AN$6,IF(OR($AN$7="ALL",Assumptions!$N$54="Y"),INDEX(Assumptions!$D$54:$F$54,$AN$4),Assumptions!$E$54)) | AO14: =IF($AO$5="WAPricePerMsg",$AO$6,IF(OR($AO$7="ALL",Assumptions!$N$54="Y"),INDEX(Assumptions!$D$54:$F$54,$AO$4),Assumptions!$E$54)) | AP14: =IF($AP$5="WAPricePerMsg",$AP$6,IF(OR($AP$7="ALL",Assumptions!$N$54="Y"),INDEX(Assumptions!$D$54:$F$54,$AP$4),Assumptions!$E$54)) | AQ14: =IF($AQ$5="WAPricePerMsg",$AQ$6,IF(OR($AQ$7="ALL",Assumptions!$N$54="Y"),INDEX(Assumptions!$D$54:$F$54,$AQ$4),Assumptions!$E$54)) | AR14: =IF($AR$5="WAPricePerMsg",$AR$6,IF(OR($AR$7="ALL",Assumptions!$N$54="Y"),INDEX(Assumptions!$D$54:$F$54,$AR$4),Assumptions!$E$54)) | AS14: =IF($AS$5="WAPricePerMsg",$AS$6,IF(OR($AS$7="ALL",Assumptions!$N$54="Y"),INDEX(Assumptions!$D$54:$F$54,$AS$4),Assumptions!$E$54)) | AT14: =IF($AT$5="WAPricePerMsg",$AT$6,IF(OR($AT$7="ALL",Assumptions!$N$54="Y"),INDEX(Assumptions!$D$54:$F$54,$AT$4),Assumptions!$E$54)) | AU14: =IF($AU$5="WAPricePerMsg",$AU$6,IF(OR($AU$7="ALL",Assumptions!$N$54="Y"),INDEX(Assumptions!$D$54:$F$54,$AU$4),Assumptions!$E$54)) | AV14: =IF($AV$5="WAPricePerMsg",$AV$6,IF(OR($AV$7="ALL",Assumptions!$N$54="Y"),INDEX(Assumptions!$D$54:$F$54,$AV$4),Assumptions!$E$54)) | AW14: =IF($AW$5="WAPricePerMsg",$AW$6,IF(OR($AW$7="ALL",Assumptions!$N$54="Y"),INDEX(Assumptions!$D$54:$F$54,$AW$4),Assumptions!$E$54)) | AX14: =IF($AX$5="WAPricePerMsg",$AX$6,IF(OR($AX$7="ALL",Assumptions!$N$54="Y"),INDEX(Assumptions!$D$54:$F$54,$AX$4),Assumptions!$E$54)) | AY14: =IF($AY$5="WAPricePerMsg",$AY$6,IF(OR($AY$7="ALL",Assumptions!$N$54="Y"),INDEX(Assumptions!$D$54:$F$54,$AY$4),Assumptions!$E$54)) | AZ14: =IF($AZ$5="WAPricePerMsg",$AZ$6,IF(OR($AZ$7="ALL",Assumptions!$N$54="Y"),INDEX(Assumptions!$D$54:$F$54,$AZ$4),Assumptions!$E$54)) | BA14: =IF($BA$5="WAPricePerMsg",$BA$6,IF(OR($BA$7="ALL",Assumptions!$N$54="Y"),INDEX(Assumptions!$D$54:$F$54,$BA$4),Assumptions!$E$54)) | BB14: =IF($BB$5="WAPricePerMsg",$BB$6,IF(OR($BB$7="ALL",Assumptions!$N$54="Y"),INDEX(Assumptions!$D$54:$F$54,$BB$4),Assumptions!$E$54)) | BC14: =IF($BC$5="WAPricePerMsg",$BC$6,IF(OR($BC$7="ALL",Assumptions!$N$54="Y"),INDEX(Assumptions!$D$54:$F$54,$BC$4),Assumptions!$E$54)) | BD14: =IF($BD$5="WAPricePerMsg",$BD$6,IF(OR($BD$7="ALL",Assumptions!$N$54="Y"),INDEX(Assumptions!$D$54:$F$54,$BD$4),Assumptions!$E$54)) | BE14: =IF($BE$5="WAPricePerMsg",$BE$6,IF(OR($BE$7="ALL",Assumptions!$N$54="Y"),INDEX(Assumptions!$D$54:$F$54,$BE$4),Assumptions!$E$54))
B15: ComputePerStudentMonth | D15: =IF($D$5="ComputePerStudentMonth",$D$6,IF(OR($D$7="ALL",Assumptions!$N$55="Y"),INDEX(Assumptions!$D$55:$F$55,$D$4),Assumptions!$E$55)) | E15: =IF($E$5="ComputePerStudentMonth",$E$6,IF(OR($E$7="ALL",Assumptions!$N$55="Y"),INDEX(Assumptions!$D$55:$F$55,$E$4),Assumptions!$E$55)) | F15: =IF($F$5="ComputePerStudentMonth",$F$6,IF(OR($F$7="ALL",Assumptions!$N$55="Y"),INDEX(Assumptions!$D$55:$F$55,$F$4),Assumptions!$E$55)) | G15: =IF($G$5="ComputePerStudentMonth",$G$6,IF(OR($G$7="ALL",Assumptions!$N$55="Y"),INDEX(Assumptions!$D$55:$F$55,$G$4),Assumptions!$E$55)) | H15: =IF($H$5="ComputePerStudentMonth",$H$6,IF(OR($H$7="ALL",Assumptions!$N$55="Y"),INDEX(Assumptions!$D$55:$F$55,$H$4),Assumptions!$E$55)) | I15: =IF($I$5="ComputePerStudentMonth",$I$6,IF(OR($I$7="ALL",Assumptions!$N$55="Y"),INDEX(Assumptions!$D$55:$F$55,$I$4),Assumptions!$E$55)) | J15: =IF($J$5="ComputePerStudentMonth",$J$6,IF(OR($J$7="ALL",Assumptions!$N$55="Y"),INDEX(Assumptions!$D$55:$F$55,$J$4),Assumptions!$E$55)) | K15: =IF($K$5="ComputePerStudentMonth",$K$6,IF(OR($K$7="ALL",Assumptions!$N$55="Y"),INDEX(Assumptions!$D$55:$F$55,$K$4),Assumptions!$E$55)) | L15: =IF($L$5="ComputePerStudentMonth",$L$6,IF(OR($L$7="ALL",Assumptions!$N$55="Y"),INDEX(Assumptions!$D$55:$F$55,$L$4),Assumptions!$E$55)) | M15: =IF($M$5="ComputePerStudentMonth",$M$6,IF(OR($M$7="ALL",Assumptions!$N$55="Y"),INDEX(Assumptions!$D$55:$F$55,$M$4),Assumptions!$E$55)) | N15: =IF($N$5="ComputePerStudentMonth",$N$6,IF(OR($N$7="ALL",Assumptions!$N$55="Y"),INDEX(Assumptions!$D$55:$F$55,$N$4),Assumptions!$E$55)) | O15: =IF($O$5="ComputePerStudentMonth",$O$6,IF(OR($O$7="ALL",Assumptions!$N$55="Y"),INDEX(Assumptions!$D$55:$F$55,$O$4),Assumptions!$E$55)) | P15: =IF($P$5="ComputePerStudentMonth",$P$6,IF(OR($P$7="ALL",Assumptions!$N$55="Y"),INDEX(Assumptions!$D$55:$F$55,$P$4),Assumptions!$E$55)) | Q15: =IF($Q$5="ComputePerStudentMonth",$Q$6,IF(OR($Q$7="ALL",Assumptions!$N$55="Y"),INDEX(Assumptions!$D$55:$F$55,$Q$4),Assumptions!$E$55)) | R15: =IF($R$5="ComputePerStudentMonth",$R$6,IF(OR($R$7="ALL",Assumptions!$N$55="Y"),INDEX(Assumptions!$D$55:$F$55,$R$4),Assumptions!$E$55)) | S15: =IF($S$5="ComputePerStudentMonth",$S$6,IF(OR($S$7="ALL",Assumptions!$N$55="Y"),INDEX(Assumptions!$D$55:$F$55,$S$4),Assumptions!$E$55)) | T15: =IF($T$5="ComputePerStudentMonth",$T$6,IF(OR($T$7="ALL",Assumptions!$N$55="Y"),INDEX(Assumptions!$D$55:$F$55,$T$4),Assumptions!$E$55)) | U15: =IF($U$5="ComputePerStudentMonth",$U$6,IF(OR($U$7="ALL",Assumptions!$N$55="Y"),INDEX(Assumptions!$D$55:$F$55,$U$4),Assumptions!$E$55)) | V15: =IF($V$5="ComputePerStudentMonth",$V$6,IF(OR($V$7="ALL",Assumptions!$N$55="Y"),INDEX(Assumptions!$D$55:$F$55,$V$4),Assumptions!$E$55)) | W15: =IF($W$5="ComputePerStudentMonth",$W$6,IF(OR($W$7="ALL",Assumptions!$N$55="Y"),INDEX(Assumptions!$D$55:$F$55,$W$4),Assumptions!$E$55)) | X15: =IF($X$5="ComputePerStudentMonth",$X$6,IF(OR($X$7="ALL",Assumptions!$N$55="Y"),INDEX(Assumptions!$D$55:$F$55,$X$4),Assumptions!$E$55)) | Y15: =IF($Y$5="ComputePerStudentMonth",$Y$6,IF(OR($Y$7="ALL",Assumptions!$N$55="Y"),INDEX(Assumptions!$D$55:$F$55,$Y$4),Assumptions!$E$55)) | Z15: =IF($Z$5="ComputePerStudentMonth",$Z$6,IF(OR($Z$7="ALL",Assumptions!$N$55="Y"),INDEX(Assumptions!$D$55:$F$55,$Z$4),Assumptions!$E$55)) | AA15: =IF($AA$5="ComputePerStudentMonth",$AA$6,IF(OR($AA$7="ALL",Assumptions!$N$55="Y"),INDEX(Assumptions!$D$55:$F$55,$AA$4),Assumptions!$E$55)) | AB15: =IF($AB$5="ComputePerStudentMonth",$AB$6,IF(OR($AB$7="ALL",Assumptions!$N$55="Y"),INDEX(Assumptions!$D$55:$F$55,$AB$4),Assumptions!$E$55)) | AC15: =IF($AC$5="ComputePerStudentMonth",$AC$6,IF(OR($AC$7="ALL",Assumptions!$N$55="Y"),INDEX(Assumptions!$D$55:$F$55,$AC$4),Assumptions!$E$55)) | AD15: =IF($AD$5="ComputePerStudentMonth",$AD$6,IF(OR($AD$7="ALL",Assumptions!$N$55="Y"),INDEX(Assumptions!$D$55:$F$55,$AD$4),Assumptions!$E$55)) | AE15: =IF($AE$5="ComputePerStudentMonth",$AE$6,IF(OR($AE$7="ALL",Assumptions!$N$55="Y"),INDEX(Assumptions!$D$55:$F$55,$AE$4),Assumptions!$E$55)) | AF15: =IF($AF$5="ComputePerStudentMonth",$AF$6,IF(OR($AF$7="ALL",Assumptions!$N$55="Y"),INDEX(Assumptions!$D$55:$F$55,$AF$4),Assumptions!$E$55)) | AG15: =IF($AG$5="ComputePerStudentMonth",$AG$6,IF(OR($AG$7="ALL",Assumptions!$N$55="Y"),INDEX(Assumptions!$D$55:$F$55,$AG$4),Assumptions!$E$55)) | AH15: =IF($AH$5="ComputePerStudentMonth",$AH$6,IF(OR($AH$7="ALL",Assumptions!$N$55="Y"),INDEX(Assumptions!$D$55:$F$55,$AH$4),Assumptions!$E$55)) | AI15: =IF($AI$5="ComputePerStudentMonth",$AI$6,IF(OR($AI$7="ALL",Assumptions!$N$55="Y"),INDEX(Assumptions!$D$55:$F$55,$AI$4),Assumptions!$E$55)) | AJ15: =IF($AJ$5="ComputePerStudentMonth",$AJ$6,IF(OR($AJ$7="ALL",Assumptions!$N$55="Y"),INDEX(Assumptions!$D$55:$F$55,$AJ$4),Assumptions!$E$55)) | AK15: =IF($AK$5="ComputePerStudentMonth",$AK$6,IF(OR($AK$7="ALL",Assumptions!$N$55="Y"),INDEX(Assumptions!$D$55:$F$55,$AK$4),Assumptions!$E$55)) | AL15: =IF($AL$5="ComputePerStudentMonth",$AL$6,IF(OR($AL$7="ALL",Assumptions!$N$55="Y"),INDEX(Assumptions!$D$55:$F$55,$AL$4),Assumptions!$E$55)) | AM15: =IF($AM$5="ComputePerStudentMonth",$AM$6,IF(OR($AM$7="ALL",Assumptions!$N$55="Y"),INDEX(Assumptions!$D$55:$F$55,$AM$4),Assumptions!$E$55)) | AN15: =IF($AN$5="ComputePerStudentMonth",$AN$6,IF(OR($AN$7="ALL",Assumptions!$N$55="Y"),INDEX(Assumptions!$D$55:$F$55,$AN$4),Assumptions!$E$55)) | AO15: =IF($AO$5="ComputePerStudentMonth",$AO$6,IF(OR($AO$7="ALL",Assumptions!$N$55="Y"),INDEX(Assumptions!$D$55:$F$55,$AO$4),Assumptions!$E$55)) | AP15: =IF($AP$5="ComputePerStudentMonth",$AP$6,IF(OR($AP$7="ALL",Assumptions!$N$55="Y"),INDEX(Assumptions!$D$55:$F$55,$AP$4),Assumptions!$E$55)) | AQ15: =IF($AQ$5="ComputePerStudentMonth",$AQ$6,IF(OR($AQ$7="ALL",Assumptions!$N$55="Y"),INDEX(Assumptions!$D$55:$F$55,$AQ$4),Assumptions!$E$55)) | AR15: =IF($AR$5="ComputePerStudentMonth",$AR$6,IF(OR($AR$7="ALL",Assumptions!$N$55="Y"),INDEX(Assumptions!$D$55:$F$55,$AR$4),Assumptions!$E$55)) | AS15: =IF($AS$5="ComputePerStudentMonth",$AS$6,IF(OR($AS$7="ALL",Assumptions!$N$55="Y"),INDEX(Assumptions!$D$55:$F$55,$AS$4),Assumptions!$E$55)) | AT15: =IF($AT$5="ComputePerStudentMonth",$AT$6,IF(OR($AT$7="ALL",Assumptions!$N$55="Y"),INDEX(Assumptions!$D$55:$F$55,$AT$4),Assumptions!$E$55)) | AU15: =IF($AU$5="ComputePerStudentMonth",$AU$6,IF(OR($AU$7="ALL",Assumptions!$N$55="Y"),INDEX(Assumptions!$D$55:$F$55,$AU$4),Assumptions!$E$55)) | AV15: =IF($AV$5="ComputePerStudentMonth",$AV$6,IF(OR($AV$7="ALL",Assumptions!$N$55="Y"),INDEX(Assumptions!$D$55:$F$55,$AV$4),Assumptions!$E$55)) | AW15: =IF($AW$5="ComputePerStudentMonth",$AW$6,IF(OR($AW$7="ALL",Assumptions!$N$55="Y"),INDEX(Assumptions!$D$55:$F$55,$AW$4),Assumptions!$E$55)) | AX15: =IF($AX$5="ComputePerStudentMonth",$AX$6,IF(OR($AX$7="ALL",Assumptions!$N$55="Y"),INDEX(Assumptions!$D$55:$F$55,$AX$4),Assumptions!$E$55)) | AY15: =IF($AY$5="ComputePerStudentMonth",$AY$6,IF(OR($AY$7="ALL",Assumptions!$N$55="Y"),INDEX(Assumptions!$D$55:$F$55,$AY$4),Assumptions!$E$55)) | AZ15: =IF($AZ$5="ComputePerStudentMonth",$AZ$6,IF(OR($AZ$7="ALL",Assumptions!$N$55="Y"),INDEX(Assumptions!$D$55:$F$55,$AZ$4),Assumptions!$E$55)) | BA15: =IF($BA$5="ComputePerStudentMonth",$BA$6,IF(OR($BA$7="ALL",Assumptions!$N$55="Y"),INDEX(Assumptions!$D$55:$F$55,$BA$4),Assumptions!$E$55)) | BB15: =IF($BB$5="ComputePerStudentMonth",$BB$6,IF(OR($BB$7="ALL",Assumptions!$N$55="Y"),INDEX(Assumptions!$D$55:$F$55,$BB$4),Assumptions!$E$55)) | BC15: =IF($BC$5="ComputePerStudentMonth",$BC$6,IF(OR($BC$7="ALL",Assumptions!$N$55="Y"),INDEX(Assumptions!$D$55:$F$55,$BC$4),Assumptions!$E$55)) | BD15: =IF($BD$5="ComputePerStudentMonth",$BD$6,IF(OR($BD$7="ALL",Assumptions!$N$55="Y"),INDEX(Assumptions!$D$55:$F$55,$BD$4),Assumptions!$E$55)) | BE15: =IF($BE$5="ComputePerStudentMonth",$BE$6,IF(OR($BE$7="ALL",Assumptions!$N$55="Y"),INDEX(Assumptions!$D$55:$F$55,$BE$4),Assumptions!$E$55))
